Workbook
Name days_year: '02_Параметры'!$C$6
Name work_days: '02_Параметры'!$C$7
Name days_week: '02_Параметры'!$C$8
Name months: '02_Параметры'!$C$9
Name quarters: '02_Параметры'!$C$10
Name weeks_year: '02_Параметры'!$C$11
Name nominal_hours: '02_Параметры'!$C$12
Name work_months: '02_Параметры'!$C$13
Name vacation_cal: '02_Параметры'!$C$14
Name vacation_work: '02_Параметры'!$C$15
Name sick_cal: '02_Параметры'!$C$16
Name sick_work: '02_Параметры'!$C$17
Name eff_hours: '02_Параметры'!$C$18
Name work_time: '02_Параметры'!$C$21
Name net_days: '02_Параметры'!$C$22
Name net_time: '02_Параметры'!$C$23
Name net_weeks: '02_Параметры'!$C$24
Name promo_per_day: '02_Параметры'!$C$25
Name promo_time: '02_Параметры'!$C$26
Name acc_mode: '02_Параметры'!$C$27
Name acc_per_quarter: '02_Параметры'!$C$28
Name accounting_time: '02_Параметры'!$C$29
Name side_time: '02_Параметры'!$C$30
Name pool_gross: '02_Параметры'!$C$31
Name fm_on: '02_Параметры'!$C$32
Name fm_pct: '02_Параметры'!$C$33
Name fm_time: '02_Параметры'!$C$34
Name fm_week: '02_Параметры'!$C$35
Name project_pool: '02_Параметры'!$C$36
Name post_ratio: '02_Параметры'!$C$39
Name profile_multiplier: '02_Параметры'!$C$40
Name client_time: '02_Параметры'!$C$41
Name shoot_duration: '02_Параметры'!$C$42
Name week_target: '02_Параметры'!$C$43
Name shoot_auto: '02_Параметры'!$C$44
Name project_time: '02_Параметры'!$C$45
Name hour_pool: '02_Параметры'!$C$46
Name projects_year: '02_Параметры'!$C$47
Name projects_month: '02_Параметры'!$C$48
Name projects_week: '02_Параметры'!$C$49
Name shooting_time: '02_Параметры'!$C$50
Name shooting_month: '02_Параметры'!$C$51
Name shooting_week: '02_Параметры'!$C$52
Name post_time: '02_Параметры'!$C$53
Name core_time: '02_Параметры'!$C$54
Name client_total: '02_Параметры'!$C$55
Name ops_per_shoot: '02_Параметры'!$C$56
Name income_month: '02_Параметры'!$C$59
Name target_income: '02_Параметры'!$C$60
Name current_rate: '02_Параметры'!$C$61
Name ws_mode: '02_Параметры'!$C$64
Name own_home: '02_Параметры'!$C$65
Name home_rent: '02_Параметры'!$C$66
Name home_util: '02_Параметры'!$C$67
Name home_area: '02_Параметры'!$C$68
Name cab_area: '02_Параметры'!$C$69
Name cab_share: '02_Параметры'!$C$70
Name office_rent: '02_Параметры'!$C$71
Name office_util: '02_Параметры'!$C$72
Name var_workspace: '02_Параметры'!$C$73

Sheet 00_Читать
A1: СЧЁТИКС · калькулятор стоимости часа
A2: Расчёт юнит-экономики для фотографов и видеографов. Обновлено 5 августа 2026.
A4: ИЗ ЧЕГО СОСТОИТ ПРОДУКТ — четыре файла
A5: Файл | B5: Что это и где живёт
A6: Калькулятор_ставки_часа.xlsx | B6: ЭТА КНИГА. Вся логика, параметры, тексты и методика. Источник правды — правки начинаются здесь.
A7: web/index.html | B7: СТРАНИЦА ВХОДА. Первое, что видит человек: один экран — заголовок, три пользы, кнопка. Принимает реферальную метку и передаёт её в форму. Кто уже начинал, попадает сразу в форму.
A8: web/calc.html | B8: ФОРМА. Вопросы анкеты, кнопка расчёта и анимация расчёта. Больше ничего: краткий итог и блок оплаты вынесены. После расчёта открывается отчёт.
A9: web/report.html | B9: ПОЛНЫЙ ОТЧЁТ. 10 блоков, открывается после оплаты. Данные принимает из формы. Тоже автономный файл.
A11: КАК УСТРОЕНА КНИГА — 27 листов
A12: Лист | B12: Назначение
A13: 00_Читать | B13: Этот лист — карта проекта
A14: 01_Глоссарий | B14: Термины: что такое ставка, амортизация, юнит-экономика
A15: 02_Параметры | B15: 143 строки. Все входные величины и формулы через ID. ГЛАВНЫЙ лист для правки цифр
A16: 03_Каталоги | B16: Оборудование, ПО, реклама — построчно, с ценами и сроками службы
A17: 04_Итог / 05_Расчёт | B17: Свод и расчёт по семи налоговым режимам
A18: 06_Отчёт | B18: Все цифры отчёта: доход по ролям, расходы, сценарии
A19: 07_Интерфейс / 08_UI / 08b / 08c | B19: Структура формы и отчёта: какой блок за каким идёт
A20: 09_Тексты | B20: 514 надписей. Колонка «Где находится» — поверхность (форма, отчёт, подсказки). Есть автофильтр
A21: 09b_Методика_цифр | B21: Как посчитана каждая цифра блока 09, откуда берутся рабочие паузы, правило округления
A22: 09e_Как_считается | B22: Полная цепочка расчёта ставки часа: 10 шагов от календаря до цены, с формулами и проверкой сходимости
A23: 09c_Палитра | B23: 68 цветов. Единая система для формы и отчёта
... A25: 12_Диаграммы / 13_Сетка_скидок / 13b_Программа_лояльности / 14_Опрос | B25: Данные для графиков, скидки за объём, ФОНД И ВСЯ ПРОГРАММА ЛОЯЛЬНОСТИ, опрос в форме
A27: ЧТО ГДЕ ПРАВИТЬ
A28: Задача | B28: Куда идти
A29: Поменять текст надписи | B29: 09_Тексты → найти по ключу → колонка «Текст». Ключ виден в HTML как data-t="..."
A30: Поменять цифру или формулу | B30: 02_Параметры → колонка «Значение»
A31: Поменять цвет | B31: 09c_Палитра → HEX. Затем тот же токен в :root обоих HTML
A32: Добавить оборудование | B32: 03_Каталоги → новая строка с кодом формы
A33: Изменить скидки, фонд, сертификаты | B33: 13b_Программа_лояльности → жёлтые ячейки. Остальное пересчитается формулами
A34: Изменить порядок блоков | B34: 08c_Структура_отчёта
A35: ПЕРЕД ПУБЛИКАЦИЕЙ — обязательно
A36: Что | B36: Где в calc.html
A37: DEV_NO_BLUR = false | B37: сейчас true — отчёт не размыт, виден бесплатно
A38: YM_ID = номер счётчика | B38: сейчас 0 — Яндекс.Метрика не подключена
A39: PAY_URL = ссылка оплаты | B39: сейчас '#order' — заглушка
A40: Связка форма → отчёт | B40: форма пока не передаёт данные в отчёт, отчёт показывает демо-набор
A42: Папка _архив — старые версии и черновики. Для работы не нужны, удалять не обязательно.

Sheet 01_Глоссарий
A1: 01 · ГЛОССАРИЙ — понятия, типы, обозначения
A3: A · МАРКЕРЫ ТИПОВ
A4: Наименование | B4: ID | C4: Тип | D4: Описание | E4: Формула / значение
A5: Константа | B5: const | C5: meta | D5: Аксиома из достоверного источника: закон, производственный календарь. Пользователь не меняет | E5: 247 дня, 57 390 ₽
A6: Значение по умолчанию | B6: default | C6: meta | D6: Предзаполнено нами, пользователь может изменить | E6: доход 108 999 ₽
A7: Формула | B7: calc | C7: meta | D7: Вычисляется из других величин, ввод недоступен | E7: net_time-side_time
A8: Переключатель | B8: switch | C8: meta | D8: Выпадающий список. Меняет ВЕТКУ расчёта, а не только число | E8: «Работаю из дома» / «Арендую»
A9: Служебное понятие | B9: meta | C9: meta | D9: Описывает устройство реестра, а не предметную область | E9: block, form, section
A10: Тип поля интерфейса | B10: ui | C10: meta | D10: Способ ввода в калькуляторе | E10: input_number, dropdown
A11: B · ВРЕМЯ — иерархия по вашему определению (ГЛАВНОЕ)
A12: Наименование | B12: ID | C12: Тип | D12: Описание | E12: Формула / значение
A13: Рабочее время | B13: work_time | C13: calc | D13: Производственный календарь без выходных и праздников. Справочно, в расчёте не участвует | E13: 247 × 8 = 1 976 ч/год
A14: ЧИСТОЕ время | B14: net_time | C14: calc | D14: Рабочее минус отпуск, больничный и час в день на перерывы. ВЕРХНИЙ УРОВЕНЬ — всё доступное время | E14: (247−20−8) × 7 = 1 533 ч/год
A15: ОПЕРАЦИОННОЕ время | B15: side_time | C15: calc | D15: Второстепенные операции: продвижение и учёт. Клиенту напрямую не продаётся | E15: 438 + 12 = 450 ч/год
A16: Время на заказы до резерва | B16: pool_gross | C16: calc | D16: Чистое минус операционное. Промежуточная величина перед вычетом резерва | E16: 1 533 − 450 = 1 083 ч/год
A17: Резерв на форс-мажоры | B17: fm_time | C17: calc | D17: Перенос и отмена съёмок, срывы по вине клиента, повторные выезды. Процент от времени на заказы | E17: 5% × 1 083 = 54,15 ч/год
A18: ПРОЕКТНОЕ время за год | B18: project_pool | C18: calc | D18: Всё, что реально остаётся на выполнение проектов. После вычета резерва | E18: 1 083 − 54,15 = 1 028,85 ч/год
A19: Проектное время на 1 проект | B19: project_time | C19: calc | D19: Реализация одного заказа: S × (1+коэф.) + 1 час клиента | E19: 6×4 + 1 = 25 ч/проект
A20: ПРОФИЛЬНОЕ время | B20: core_time | C20: calc | D20: Работа по профилю: съёмка и обработка ВМЕСТЕ. Равно S × (1+коэф.). БЕЗ клиента | E20: 262,80 + 788,40 = 1 051,20 ч/год
A21: СЪЁМОЧНОЕ время (S) | B21: shooting_time | C21: calc | D21: Работа на площадке. Обозначается S. ЦЕЛЬ РАСЧЁТА и знаменатель ставки | E21: 43,80 × 6 = 262,80 ч/год
A22: Постпродакшн | B22: post_time | C22: calc | D22: Обработка материала. S × коэффициент на каждый проект | E22: 262,80 × 3 = 788,40 ч/год
A23: Работа с клиентом | B23: client_total | C23: calc | D23: Продажа, согласования, организация. 1 час НА КАЖДЫЙ проект: чем короче съёмки, тем больше проектов и тем больше суммарных клиентских часов | E23: проектов × 1 ч
... A29: Проектов в год | B29: projects_year | C29: calc | D29: Сколько проектов помещается в проектное время | E29: 1 095 / 25 = 43,80 = число недель
A30: C · ПРОВЕРКА ИЕРАРХИИ — три равенства, которые всегда верны
A31: Наименование | B31: ID | C31: Тип | D31: Описание | E31: Формула / значение
A32: Первый уровень | B32: — | C32: meta | D32: ОПЕРАЦИОННОЕ + РЕЗЕРВ + ПРОЕКТНОЕ = ЧИСТОЕ | E32: 450 + 54,15 + 1 028,85 = 1 533 ✓
A33: Второй уровень | B33: — | C33: meta | D33: ПРОФИЛЬНОЕ + работа с клиентом = ПРОЕКТНОЕ | E33: 985,05 + 43,80 = 1 028,85 ✓
A34: Третий уровень | B34: — | C34: meta | D34: СЪЁМОЧНОЕ + постпродакшн = ПРОФИЛЬНОЕ | E34: 246,26 + 738,79 = 985,05 ✓
A35: D · ПЕРЕКЛЮЧАТЕЛИ — шесть точек выбора пользователя
A36: Наименование | B36: ID | C36: Тип | D36: Описание | E36: Формула / значение
A37: Режим налогообложения | B37: regime | C37: switch | D37: Семь вариантов. По умолчанию НПД средняя 5% | E37: Form015 · Block4
A38: Час проектного времени | B38: hour_pool | C38: calc | D38: Выручка / проектное время. ПОСТОЯННАЯ величина: база для сетки объёмных скидок | E38: 2 138 693 / 1 028,85 = 2 079 ₽
A39: Рабочее место | B39: ws_mode | C39: switch | D39: Дома — аренда по доле метров плюс коммуналка целиком. Аренда — помещение целиком | E39: Form005 · Block9
A40: Живу в своём | B40: own_home | C40: switch | D40: Если жильё своё и ипотеки нет — плата за жильё обнуляется, коммуналка остаётся | E40: Form005 · Block9
A41: Учёт и планирование | B41: acc_mode | C41: switch | D41: Нанимаю специалиста — расход 120 000 ₽, время 0. Веду самостоятельно — расход 0, время 12 ч | E41: Form011 · Block14
A42: Создание сайта | B42: site_mode | C42: switch | D42: Нанимал — цена подрядчика. Делал сам — часы × полная ставка рабочего часа | E42: Form014 · Block12
A44: Период платежа | B44: — | C44: switch | D44: Год / Квартал / Месяц. Множитель платежей в год: 1 / 4 / 12 | E44: 03_Каталоги, столбец «Период»
A45: E · ДЕНЬГИ
A46: Наименование | B46: ID | C46: Тип | D46: Описание | E46: Формула / значение
A47: Желаемый доход | B47: target_income | C47: calc | D47: Сумма на руки за год. Точка отсчёта всего расчёта | E47: 108 999 × 12 = 1 307 988 ₽
A48: Выручка | B48: revenue | C48: calc | D48: Сколько выставить клиентам за год. Главный результат | E48: 04_Расчёт, строка 4
A49: Всего расходов | B49: total_costs | C49: calc | D49: Амортизация плюс переменные. Без эквайринга | E49: C = 786 026 ₽/год
A50: Амортизация | B50: investment | C50: calc | D50: Разовые покупки, распределённые по сроку службы | E50: 308 126 ₽/год
A51: Переменные расходы | B51: variable_costs | C51: calc | D51: Регулярные платежи за год | E51: 477 900 ₽/год
A52: Эквайринг | B52: acquiring | C52: calc | D52: Процент С ОБОРОТА. Не расход — идёт в знаменатель формулы выручки | E52: 2,7%
A53: База для выручки | B53: revenue_base | C53: calc | D53: Расходы плюс желаемый доход. Получить ПОСЛЕ всех платежей | E53: N + C = 2 094 014 ₽
A54: F · НАЛОГИ 2026
A55: Наименование | B55: ID | C55: Тип | D55: Описание | E55: Формула / значение
A56: НПД | B56: rate_npd_avg | C56: default | D56: Средняя ставка 5% — базовый вариант, работа и с физлицами, и с юрлицами. Взносов нет, лимит 2,4 млн | E56: 4% физлица · 6% юрлица
A57: УСН «Доходы» | B57: rate_usn_inc | C57: default | D57: Налог с выручки. Взносы ВЫЧИТАЮТСЯ из налога до нуля | E57: 6%
A58: УСН «Д−Р» | B58: rate_usn_prof | C58: default | D58: Налог с прибыли. Взносы уменьшают базу. Минимальный налог 1% | E58: 15%
A59: АУСН | B59: rate_ausn_inc | C59: const | D59: Взносы ИП за себя НЕ платятся. Лимит 60 млн | E59: 8% · 20%, мин. налог 3%
A60: Фиксированные взносы | B60: fixed_contrib | C60: const | D60: Платит каждый ИП. Срок — 28 декабря | E60: 57 390 ₽/год
A61: Дополнительный взнос | B61: extra_contrib | C61: const | D61: 1% с дохода свыше порога. Срок — 1 июля следующего года | E61: 1% × (база − 300 000)
A62: Предельная величина | B62: contrib_threshold | C62: const | D62: Порог для допвзноса. ЗА ГОД, не за месяц | E62: 300 000 ₽
A63: Вычет взносов из налога | B63: — | C63: meta | D63: На УСН «Доходы» взносы уменьшают налог до нуля. Платёж = MAX(налог; взносы), а НЕ сумма | E63: ключевая механика
A64: G · СТАВКИ ЧАСА (все на съёмочный час)
A65: Наименование | B65: ID | C65: Тип | D65: Описание | E65: Формула / значение
A66: Наивная ставка | B66: naive_rate | C66: calc | D66: Доход / съёмочные часы. Без расходов и налогов. Демонстрация ошибки | E66: 4 977 ₽/ч
A67: Базовая ставка | B67: base_rate | C67: calc | D67: Доход / чистое время. ТОЛЬКО личный доход, без налогов и расходов | E67: 1 307 988 / 1 533 = 853 ₽/ч
A68: Текущая ставка | B68: current_rate | C68: default | D68: По которой работаете сейчас. Для блока «Сколько теряете» | E68: 6 000 ₽/ч
A69: Операционная ставка | B69: ops_rate | C69: calc | D69: Покрывает доход и расходы, но БЕЗ налога | E69: (N+C) / 261,41 = 8 011 ₽/ч
A70: ПОЛНАЯ ставка | B70: real_rate | C70: calc | D70: Покрывает доход, расходы, налог и эквайринг. ЦЕНА ДЛЯ КЛИЕНТА | E70: 05_Итог, строка 5
A71: Точка безубыточности | B71: breakeven | C71: calc | D71: Минимальная выручка при нулевом личном доходе | E71: подставить N = 0
A72: H · ПОЛНЫЙ ПЕРЕЧЕНЬ ПАРАМЕТРОВ — все величины книги, автоматически из 02_Параметры
A73: Наименование | B73: ID | C73: Тип | D73: Описание | E73: Формула / значение
A74: 1 · Календарь
A75: Всего дней в году | B75: days_year | C75: const | D75: ед.: дн | E75: 365
A76: Рабочих дней в году | B76: work_days | C76: const | D76: ед.: дн | E76: 247
A77: Рабочих дней в неделю | B77: days_week | C77: const | D77: ед.: дн | E77: 5
A78: Месяцев в году | B78: months | C78: const | D78: ед.: мес | E78: 12
A79: Кварталов в году | B79: quarters | C79: const | D79: ед.: кв | E79: 4
A80: Всего недель в году | B80: weeks_year | C80: calc | D80: ед.: нед · зависит от: days_year | E80: days_year/7
A81: Номинальных часов в дне | B81: nominal_hours | C81: const | D81: ед.: ч | E81: 8
A82: Рабочих месяцев в году | B82: work_months | C82: const | D82: ед.: мес | E82: 11
A83: Отпуск, календарных дней | B83: vacation_cal | C83: const | D83: ед.: дн | E83: 28
A84: Отпуск, рабочих дней | B84: vacation_work | C84: const | D84: ед.: дн | E84: 20
A85: Больничный, календарных дней | B85: sick_cal | C85: const | D85: ед.: дн | E85: 10
A86: Больничный, рабочих дней | B86: sick_work | C86: const | D86: ед.: дн | E86: 8
A87: Чистых (эффективных) часов в дне | B87: eff_hours | C87: const | D87: ед.: ч | E87: 7
A88: 2 · Время
A89: Рабочее время по календарю | B89: work_time | C89: calc | D89: ед.: ч/год · зависит от: work_days, nominal_hours | E89: work_days*nominal_hours
A90: Чистое рабочее время, дней | B90: net_days | C90: calc | D90: ед.: дн/год · зависит от: work_days, vacation_work, sick_work | E90: work_days-vacation_work-sick_work
A91: ЧИСТОЕ время | B91: net_time | C91: calc | D91: ед.: ч/год · зависит от: net_days, eff_hours | E91: net_days*eff_hours
A92: Чистое время, недель | B92: net_weeks | C92: calc | D92: ед.: нед · зависит от: net_days, days_week | E92: net_days/days_week
A93: Продвижение, часов в день | B93: promo_per_day | C93: default | D93: ед.: ч/дн | E93: 2
A94: Продвижение за год | B94: promo_time | C94: calc | D94: ед.: ч/год · зависит от: promo_per_day, net_days | E94: promo_per_day*net_days
A95: ПЕРЕКЛЮЧАТЕЛЬ · учёт и планирование | B95: acc_mode | C95: switch | E95: Веду самостоятельно
A96: Учёт: часов в квартал, если веду сам | B96: acc_per_quarter | C96: default | D96: ед.: ч/кв | E96: 3
A97: Учёт и планирование, время | B97: accounting_time | C97: calc | D97: ед.: ч/год · зависит от: acc_mode, acc_per_quarter, quarters | E97: IF(acc_mode="Веду самостоятельно",acc_per_quarter*quarters,0)
A98: ОПЕРАЦИОННОЕ время | B98: side_time | C98: calc | D98: ед.: ч/год · зависит от: promo_time, accounting_time | E98: promo_time+accounting_time
A99: ПРОЕКТНОЕ время за год | B99: project_pool | C99: calc | D99: ед.: ч/год · зависит от: pool_gross, fm_time | E99: pool_gross-fm_time
A100: 3 · Проект
A101: Коэффициент обработки | B101: post_ratio | C101: default | D101: ед.: × | E101: 3
A102: Множитель профильного времени | B102: profile_multiplier | C102: calc | D102: ед.: × · зависит от: post_ratio | E102: 1+post_ratio
A103: Работа с клиентом на проект | B103: client_time | C103: default | D103: ед.: ч/проект | E103: 1
A104: Целевых проектов в неделю | B104: week_target | C104: default | D104: ед.: шт/нед | E104: 1
A105: Максимальная съёмка при целевом темпе | B105: shoot_auto | C105: calc | D105: ед.: ч · зависит от: project_pool, net_weeks, week_target, client_time, profile_multiplier | E105: IF(profile_multiplier*week_target=0,0,(project_pool/net_weeks/week_target-client_time)/profile_multiplier)
A106: ТИПОВАЯ продолжительность съёмки (S) | B106: shoot_duration | C106: default | D106: ед.: ч | E106: 2
A107: Стоимость часа проектного времени | B107: hour_pool | C107: calc | D107: ед.: ₽/ч · зависит от: выручка, project_pool | E107: IF(project_pool=0,0,CHOOSE(regime_no,'05_Расчёт'!B4,'05_Расчёт'!C4,'05_Расчёт'!D4,'05_Расчёт'!E4,'05_Расчёт'!F4,'05_Расчёт'!G4,'05_Расчёт'!H4)/project_pool)
...

Sheet 02_Параметры
A1: 02 · ПАРАМЕТРЫ — каждая величина объявлена один раз, формулы записаны через ID
A2: Жёлтое — ввод пользователя. Оранжевое — ПЕРЕКЛЮЧАТЕЛЬ (выпадающий список). Зелёное — вычисляется. Серое — константа.
A4: 1 · КАЛЕНДАРЬ
A5: ID | B5: Название | C5: Значение | D5: Ед. | E5: Формула / как получено | F5: Тип | G5: Зависит от | H5: Источник / форма
A6: days_year | B6: Всего дней в году | C6: 365 | D6: дн | F6: const
A7: work_days | B7: Рабочих дней в году | C7: 247 | D7: дн | F7: const | H7: Произв. календарь РФ 2026
A8: days_week | B8: Рабочих дней в неделю | C8: 5 | D8: дн | F8: const
A9: months | B9: Месяцев в году | C9: 12 | D9: мес | F9: const
A10: quarters | B10: Кварталов в году | C10: 4 | D10: кв | F10: const
A11: weeks_year | B11: Всего недель в году | C11: =days_year/7 | D11: нед | E11: days_year/7 | F11: calc | G11: days_year
A12: nominal_hours | B12: Номинальных часов в дне | C12: 8 | D12: ч | F12: const | H12: ст. 91 ТК РФ
A13: work_months | B13: Рабочих месяцев в году | C13: 11 | D13: мес | F13: const | H13: СПРАВОЧНО, в расчёте не участвует
A14: vacation_cal | B14: Отпуск, календарных дней | C14: 28 | D14: дн | F14: const | H14: ст. 115 ТК РФ
A15: vacation_work | B15: Отпуск, рабочих дней | C15: 20 | D15: дн | F15: const
A16: sick_cal | B16: Больничный, календарных дней | C16: 10 | D16: дн | F16: const | H16: среднее за год
A17: sick_work | B17: Больничный, рабочих дней | C17: 8 | D17: дн | F17: const
A18: eff_hours | B18: Чистых (эффективных) часов в дне | C18: 7 | D18: ч | F18: const | H18: 8 минус час на перерывы
A19: 2 · ВРЕМЯ — иерархия по вашему определению
A20: ID | B20: Название | C20: Значение | D20: Ед. | E20: Формула / как получено | F20: Тип | G20: Зависит от | H20: Источник / форма
A21: work_time | B21: Рабочее время по календарю | C21: =work_days*nominal_hours | D21: ч/год | E21: work_days*nominal_hours | F21: calc | G21: work_days, nominal_hours | H21: 247 × 8. Справочно
A22: net_days | B22: Чистое рабочее время, дней | C22: =work_days-vacation_work-sick_work | D22: дн/год | E22: work_days-vacation_work-sick_work | F22: calc | G22: work_days, vacation_work, sick_work
A23: net_time | B23: ЧИСТОЕ время | C23: =net_days*eff_hours | D23: ч/год | E23: net_days*eff_hours | F23: calc | G23: net_days, eff_hours | H23: Верхний уровень: всё доступное время
A24: net_weeks | B24: Чистое время, недель | C24: =net_days/days_week | D24: нед | E24: net_days/days_week | F24: calc | G24: net_days, days_week
A25: promo_per_day | B25: Продвижение, часов в день | C25: 2 | D25: ч/дн | F25: default | H25: Form009
A26: promo_time | B26: Продвижение за год | C26: =promo_per_day*net_days | D26: ч/год | E26: promo_per_day*net_days | F26: calc | G26: promo_per_day, net_days | H26: Form009
A27: acc_mode | B27: ПЕРЕКЛЮЧАТЕЛЬ · учёт и планирование | C27: Веду самостоятельно | F27: default | H27: Form011 · Block14
A28: acc_per_quarter | B28: Учёт: часов в квартал, если веду сам | C28: 3 | D28: ч/кв | F28: default | H28: Form011
A29: accounting_time | B29: Учёт и планирование, время | C29: =IF(acc_mode="Веду самостоятельно",acc_per_quarter*quarters,0) | D29: ч/год | E29: IF(acc_mode="Веду самостоятельно",acc_per_quarter*quarters,0) | F29: calc | G29: acc_mode, acc_per_quarter, quarters | H29: Если наняли — время = 0
A30: side_time | B30: ОПЕРАЦИОННОЕ время | C30: =promo_time+accounting_time | D30: ч/год | E30: promo_time+accounting_time | F30: calc | G30: promo_time, accounting_time | H30: Второстепенные операции. Клиенту не продаётся
A31: pool_gross | B31: Время на заказы до резерва | C31: =net_time-side_time | D31: ч/год | E31: net_time-side_time | F31: calc | G31: net_time, side_time | H31: Чистое минус операционное
A32: fm_on | B32: ПЕРЕКЛЮЧАТЕЛЬ · резерв на форс-мажоры | C32: Заложить резерв | F32: default | H32: Block14a | I32: Галочка «Учитывать резерв на форс-мажоры» СНЯТА по умолчанию (06.08.2026). Поле % неактивно, пока не включена
A33: fm_pct | B33: Резерв на форс-мажоры, % | C33: 0.05 | D33: % | F33: default | H33: Перенос и отмена съёмок, срывы по вине клиента, повторные выезды. Редактируется | I33: Галочка «Учитывать резерв на форс-мажоры» СНЯТА по умолчанию (06.08.2026). Поле % неактивно, пока не включена
A34: fm_time | B34: Резерв на форс-мажоры, часов | C34: =IF(fm_on="Заложить резерв",pool_gross*fm_pct,0) | D34: ч/год | E34: IF(fm_on="Заложить резерв",pool_gross*fm_pct,0) | F34: calc | G34: fm_on, fm_pct, pool_gross | H34: Вычитается из времени на заказы
A35: fm_week | B35: Резерв, часов в неделю | C35: =IF(net_weeks=0,0,fm_time/net_weeks) | D35: ч/нед | E35: IF(net_weeks=0,0,fm_time/net_weeks) | F35: calc | G35: fm_time, net_weeks | H35: Для наглядности
A36: project_pool | B36: ПРОЕКТНОЕ время за год | C36: =pool_gross-fm_time | D36: ч/год | E36: pool_gross-fm_time | F36: calc | G36: pool_gross, fm_time | H36: Всё, что остаётся на выполнение проектов
A37: 3 · ПРОЕКТ — S × (1+K) + 1. Длительность съёмки задаёт пользователь
A38: ID | B38: Название | C38: Значение | D38: Ед. | E38: Формула / как получено | F38: Тип | G38: Зависит от | H38: Источник / форма
A39: post_ratio | B39: Коэффициент обработки | C39: 3 | D39: × | F39: default | H39: Часов обработки на 1 час съёмки. МЕНЯЕТСЯ пользователем: у свадебного ретушёра больше, у репортажника меньше
A40: profile_multiplier | B40: Множитель профильного времени | C40: =1+post_ratio | D40: × | E40: 1+post_ratio | F40: calc | G40: post_ratio | H40: ПРОФИЛЬНОЕ на проект = S × (1 + коэффициент): съёмка плюс обработка
A41: client_time | B41: Работа с клиентом на проект | C41: 1 | D41: ч/проект | F41: default | H41: Form012 · Block13 · продажа, согласования, организация
A42: shoot_duration | B42: ТИПОВАЯ продолжительность съёмки (S) | C42: 2 | D42: ч | F42: default | H42: Block3 · самый частый формат заказа. ЗАДАЁТ ПОЛЬЗОВАТЕЛЬ, по умолчанию 2 ч
A43: week_target | B43: Целевых проектов в неделю | C43: 1 | D43: шт/нед | F43: default | H43: СПРАВОЧНАЯ. В расчёте ставки не участвует
A44: shoot_auto | B44: Максимальная съёмка при целевом темпе | C44: =IF(profile_multiplier*week_target=0,0,(project_pool/net_weeks/week_target-client_time)/profile_multiplier) | D44: ч | E44: IF(profile_multiplier*week_target=0,0,(project_pool/net_weeks/week_target-client_time)/profile_multiplier) | F44: calc | G44: project_pool, net_weeks, week_target, client_time, profile_multiplier | H44: СПРАВОЧНАЯ: какая съёмка влезет при таком темпе. В расчёте НЕ участвует
A45: project_time | B45: ПРОЕКТНОЕ время на 1 проект | C45: =shoot_duration*profile_multiplier+client_time | D45: ч/проект | E45: shoot_duration*profile_multiplier+client_time | F45: calc | G45: shoot_duration, profile_multiplier, client_time | H45: S × (1 + коэффициент) + час клиента — полная реализация заказа
A46: hour_pool | B46: Стоимость часа проектного времени | C46: =IF(project_pool=0,0,CHOOSE(regime_no,'05_Расчёт'!B4,'05_Расчёт'!C4,'05_Расчёт'!D4,'05_Расчёт'!E4,'05_Расчёт'!F4,'05_Расчёт'!G4,'05_Расчёт'!H4)/project_pool) | D46: ₽/ч | E46: IF(project_pool=0,0,CHOOSE(regime_no,'05_Расчёт'!B4,'05_Расчёт'!C4,'05_Расчёт'!D4,'05_Расчёт'!E4,'05_Расчёт'!F4,'05_Расчёт'!G4,'05_Расчёт'!H4)/project_pool) | F46: calc | G46: выручка, project_pool | H46: ПОСТОЯННАЯ. База для сетки объёмных скидок
A47: projects_year | B47: Проектов в год | C47: =IF(project_time=0,0,project_pool/project_time) | D47: шт/год | E47: IF(project_time=0,0,project_pool/project_time) | F47: calc | G47: project_pool, project_time
A48: projects_month | B48: Проектов в месяц | C48: =projects_year/months | D48: шт/мес | E48: projects_year/months | F48: calc | G48: projects_year, months
A49: projects_week | B49: Проектов в неделю | C49: =projects_year/net_weeks | D49: шт/нед | E49: projects_year/net_weeks | F49: calc | G49: projects_year, net_weeks | H49: При авторежиме равно week_target
A50: shooting_time | B50: СЪЁМОЧНОЕ время | C50: =projects_year*shoot_duration | D50: ч/год | E50: projects_year*shoot_duration | F50: calc | G50: projects_year, shoot_duration | H50: ЦЕЛЬ РАСЧЁТА — знаменатель ставки
A51: shooting_month | B51: Съёмочное время в месяц | C51: =shooting_time/months | D51: ч/мес | E51: shooting_time/months | F51: calc | G51: shooting_time, months
A52: shooting_week | B52: Съёмочное время в неделю | C52: =shooting_time/net_weeks | D52: ч/нед | E52: shooting_time/net_weeks | F52: calc | G52: shooting_time, net_weeks
A53: post_time | B53: Постпродакшн за год | C53: =shooting_time*post_ratio | D53: ч/год | E53: shooting_time*post_ratio | F53: calc | G53: shooting_time, post_ratio | H53: S × коэффициент на каждый проект
A54: core_time | B54: ПРОФИЛЬНОЕ время | C54: =shooting_time*profile_multiplier | D54: ч/год | E54: shooting_time*profile_multiplier | F54: calc | G54: shooting_time, profile_multiplier | H54: Съёмка + обработка = S × (1 + коэффициент). БЕЗ работы с клиентом
A55: client_total | B55: Работа с клиентом за год | C55: =projects_year*client_time | D55: ч/год | E55: projects_year*client_time | F55: calc | G55: projects_year, client_time
A56: ops_per_shoot | B56: Операционных часов на час съёмки | C56: =IF(shooting_time=0,0,side_time/shooting_time) | D56: ч | E56: IF(shooting_time=0,0,side_time/shooting_time) | F56: calc | G56: side_time, shooting_time
A57: 4 · ДОХОД
A58: ID | B58: Название | C58: Значение | D58: Ед. | E58: Формула / как получено | F58: Тип | G58: Зависит от | H58: Источник / форма
A59: income_month | B59: Желаемый доход на руки | C59: 108999 | D59: ₽/мес | F59: default | H59: Block1 · Росстат 2026
A60: target_income | B60: Желаемый доход за год | C60: =income_month*months | D60: ₽/год | E60: income_month*months | F60: calc | G60: income_month, months | H60: N — на руки после всех платежей
A61: current_rate | B61: Текущая ставка часа | C61: 6000 | D61: ₽/ч | F61: default | H61: Block2 · для сравнения
A62: 5 · РАБОЧЕЕ МЕСТО · ПЕРЕКЛЮЧАТЕЛЬ (Form005/013 · Block9)
A63: ID | B63: Название | C63: Значение | D63: Ед. | E63: Формула / как получено | F63: Тип | G63: Зависит от | H63: Источник / форма
A64: ws_mode | B64: ПЕРЕКЛЮЧАТЕЛЬ · рабочее место | C64: Работаю из дома | F64: default | H64: Form005 · A111
A65: own_home | B65: ДОМА · живу в своём, ипотеки нет | C65: нет | F65: default | H65: Контекстная галочка: показывает рекомендацию, но не обнуляет стоимость жилья
A66: home_rent | B66: ДОМА · аренда или ипотека | C66: 40000 | D66: ₽/мес | F66: default | H66: По доле метров; поле остаётся активным при own_home = да
A67: home_util | B67: ДОМА · коммунальные и связь | C67: 7000 | D67: ₽/мес | F67: default | H67: По доле метров рабочего места
A68: home_area | B68: ДОМА · общая площадь жилья | C68: 50 | D68: м² | F68: default
A69: cab_area | B69: ДОМА · площадь под кабинет | C69: 6 | D69: м² | F69: default
A70: cab_share | B70: ДОМА · доля кабинета | C70: =IF(home_area=0,0,cab_area/home_area) | D70: % | E70: IF(home_area=0,0,cab_area/home_area) | F70: calc | G70: cab_area, home_area
A71: office_rent | B71: АРЕНДА · стоимость помещения | C71: 15000 | D71: ₽/мес | F71: default | H71: ЦЕЛИКОМ
A72: office_util | B72: АРЕНДА · коммунальные и связь | C72: 7000 | D72: ₽/мес | F72: default | H72: ЦЕЛИКОМ
A73: var_workspace | B73: Содержание рабочего места | C73: =IF(ws_mode="Работаю из дома",(home_rent+home_util)*cab_share*months,(office_rent+office_util)*months) | D73: ₽/год | E73: IF(ws_mode="Работаю из дома",(home_rent+home_util)*cab_share*months,(office_rent+office_util)*months) | F73: calc | G73: ws_mode, home_rent, cab_share, home_util, office_rent, office_util
A74: 6 · ОБУЧЕНИЕ И САЙТ · ПЕРЕКЛЮЧАТЕЛИ
A75: ID | B75: Название | C75: Значение | D75: Ед. | E75: Формула / как получено | F75: Тип | G75: Зависит от | H75: Источник / форма
A76: edu_cost | B76: Обучение · стоимость курса | C76: 80000 | D76: ₽ | F76: default | H76: Form006 · Block10
A77: edu_months | B77: Обучение · месяцев без дохода | C77: 4 | D77: мес | F77: default
A78: edu_life | B78: Обучение · срок амортизации | C78: 7 | D78: лет | F78: default
A80: edu_opportunity | B80: Обучение · упущенная выгода | C80: =edu_months*income_month | D80: ₽ | E80: edu_months*income_month | F80: calc | G80: edu_months, income_month
A81: dep_education | B81: Амортизация · обучение | C81: =IF(edu_life=0,0,(edu_cost+edu_opportunity)/edu_life) | D81: ₽/год | E81: IF(edu_life=0,0,(edu_cost+edu_opportunity)/edu_life) | F81: calc | G81: edu_cost, edu_opportunity, edu_life
A82: site_mode | B82: ПЕРЕКЛЮЧАТЕЛЬ · создание сайта | C82: Нанимал (а) специалиста | F82: default | H82: Form014 · A123 · Block12
A83: site_cost | B83: Сайт · стоимость подрядчика | C83: 70000 | D83: ₽ | F83: default
A84: site_hours | B84: Сайт · часов своими руками | C84: 0 | D84: ч | F84: default | H84: при варианте «делал сам»
A85: site_life | B85: Сайт · срок амортизации | C85: 7 | D85: лет | F85: default
A86: dep_website | B86: Амортизация · сайт | C86: =IF(site_mode="Нанимал (а) специалиста",IF(site_life=0,0,site_cost/site_life),0) | D86: ₽/год | E86: IF(site_mode="Нанимал (а) специалиста",IF(site_life=0,0,site_cost/site_life),0) | F86: calc | G86: site_mode, site_cost, site_life | H86: при «делал сам» уходит в site_divisor
A87: site_divisor | B87: Сайт · поправка знаменателя | C87: =IF(site_mode="Нанимал (а) специалиста",0,IF(site_life*net_time=0,0,site_hours/(site_life*net_time))) | E87: IF(site_mode="Нанимал (а) специалиста",0,IF(site_life*net_time=0,0,site_hours/(site_life*net_time))) | F87: calc | G87: site_mode, site_hours, site_life, net_time | H87: Свой труд по ПОЛНОЙ ставке рабочего часа (выручка / чистое время), а не по съёмочной
A88: 7 · РАСХОДЫ · итоги из 03_Каталоги по КОДУ ФОРМЫ
A89: ID | B89: Название | C89: Значение | D89: Ед. | E89: Формула / как получено | F89: Тип | G89: Зависит от | H89: Источник / форма
A90: dep_shoot | B90: Амортизация · съёмочное оборудование | C90: =SUMIF(cat_form,"Form001",cat_year) | D90: ₽/год | E90: SUMIF(cat_form,"Form001",cat_year) | F90: calc | G90: Form001 | H90: Block6
A91: dep_office | B91: Амортизация · офисное оборудование | C91: =SUMIF(cat_form,"Form002",cat_year) | D91: ₽/год | E91: SUMIF(cat_form,"Form002",cat_year) | F91: calc | G91: Form002 | H91: Block7
A92: dep_software | B92: Амортизация · ПО разовые покупки | C92: =SUMIF(cat_form,"Form004",cat_year) | D92: ₽/год | E92: SUMIF(cat_form,"Form004",cat_year) | F92: calc | G92: Form004 | H92: Block8
A93: dep_workspace | B93: Амортизация · обустройство места | C93: =SUMIF(cat_form,"Form013",cat_year) | D93: ₽/год | E93: SUMIF(cat_form,"Form013",cat_year) | F93: calc | G93: Form013 | H93: Block9
A94: investment | B94: ИТОГО амортизация | C94: =dep_shoot+dep_office+dep_software+dep_workspace+dep_education+dep_website | D94: ₽/год | E94: dep_shoot+dep_office+dep_software+dep_workspace+dep_education+dep_website | F94: calc | G94: dep_*
A95: var_software | B95: Переменные · подписки ПО | C95: =SUMIF(cat_form,"Form003",cat_year) | D95: ₽/год | E95: SUMIF(cat_form,"Form003",cat_year) | F95: calc | G95: Form003 | H95: Block8
A96: var_ads | B96: Переменные · реклама и продвижение | C96: =SUMIF(cat_form,"Form010",cat_year) | D96: ₽/год | E96: SUMIF(cat_form,"Form010",cat_year) | F96: calc | G96: Form010 | H96: Block11
A97: var_bank | B97: Переменные · банк РКО и СМС | C97: =SUMIF(cat_form,"Form007",cat_year) | D97: ₽/год | E97: SUMIF(cat_form,"Form007",cat_year) | F97: calc | G97: Form007 | H97: Block15
A98: acc_cost_month | B98: Специалист по учёту · стоимость в месяц | C98: 10000 | D98: ₽/мес | F98: default | H98: Form011
A99: var_accounting | B99: Переменные · специалист по учёту | C99: =IF(acc_mode="Нанимаю специалиста",acc_cost_month*months,0) | D99: ₽/год | E99: IF(acc_mode="Нанимаю специалиста",acc_cost_month*months,0) | F99: calc | G99: acc_mode, acc_cost_month, months | H99: Если веду сам — 0, но растёт время
A100: variable_costs | B100: ИТОГО переменные | C100: =var_software+var_ads+var_bank+var_accounting+var_workspace | D100: ₽/год | E100: var_software+var_ads+var_bank+var_accounting+var_workspace | F100: calc | G100: var_*
A101: total_costs | B101: ВСЕГО РАСХОДОВ (C) | C101: =investment+variable_costs | D101: ₽/год | E101: investment+variable_costs | F101: calc | G101: investment, variable_costs | H101: Без эквайринга
A102: revenue_base | B102: База для выручки | C102: =target_income+total_costs | D102: ₽/год | E102: target_income+total_costs | F102: calc | G102: target_income, total_costs | H102: N + C
...

Sheet 03_Каталоги
A1: 03 · КАТАЛОГИ — списки значений по умолчанию для форм калькулятора
A2: Только данные, никаких строк «ИТОГО». Итог берётся формулой SUMIF по коду формы. Период: Год=1, Месяц=12, Квартал=4 — как в ваших выпадающих списках.
A4: Форма | B4: Позиция | C4: Стоимость, ₽ | D4: Срок, лет | E4: Период | F4: Платежей/год | G4: ₽/год | H4: Тип расхода
A5: Form001 | B5: Canon EOS R6 Mark II Body | C5: 166999 | D5: 3 | F5: =IF(E5="Год",1,IF(E5="Квартал",4,IF(E5="Месяц",12,0))) | G5: =IF(N(D5)>0,C5/D5,C5*F5) | H5: амортизация
A6: Form001 | B6: Canon RF 24–105mm f/4.0 L IS USM | C6: 130999 | D6: 5 | F6: =IF(E6="Год",1,IF(E6="Квартал",4,IF(E6="Месяц",12,0))) | G6: =IF(N(D6)>0,C6/D6,C6*F6) | H6: амортизация
A7: Form001 | B7: Godox V1Pro C | C7: 36990 | D7: 5 | F7: =IF(E7="Год",1,IF(E7="Квартал",4,IF(E7="Месяц",12,0))) | G7: =IF(N(D7)>0,C7/D7,C7*F7) | H7: амортизация
A8: Form001 | B8: Godox XPro II C | C8: 9355 | D8: 5 | F8: =IF(E8="Год",1,IF(E8="Квартал",4,IF(E8="Месяц",12,0))) | G8: =IF(N(D8)>0,C8/D8,C8*F8) | H8: амортизация
A9: Form001 | B9: Аккумулятор LP-E6NH | C9: 12978 | D9: 3 | F9: =IF(E9="Год",1,IF(E9="Квартал",4,IF(E9="Месяц",12,0))) | G9: =IF(N(D9)>0,C9/D9,C9*F9) | H9: амортизация
A10: Form001 | B10: SanDisk Extreme PRO 256 ГБ #1 | C10: 6990 | D10: 2 | F10: =IF(E10="Год",1,IF(E10="Квартал",4,IF(E10="Месяц",12,0))) | G10: =IF(N(D10)>0,C10/D10,C10*F10) | H10: амортизация
A11: Form001 | B11: SanDisk Extreme PRO 256 ГБ #2 | C11: 6990 | D11: 2 | F11: =IF(E11="Год",1,IF(E11="Квартал",4,IF(E11="Месяц",12,0))) | G11: =IF(N(D11)>0,C11/D11,C11*F11) | H11: амортизация
A12: Form001 | B12: Рюкзак Lowepro ProTactic | C12: 27962 | D12: 7 | F12: =IF(E12="Год",1,IF(E12="Квартал",4,IF(E12="Месяц",12,0))) | G12: =IF(N(D12)>0,C12/D12,C12*F12) | H12: амортизация
A13: Form001 | B13: Godox RFT-05 отражатель | C13: 3000 | D13: 5 | F13: =IF(E13="Год",1,IF(E13="Квартал",4,IF(E13="Месяц",12,0))) | G13: =IF(N(D13)>0,C13/D13,C13*F13) | H13: амортизация
A14: Form001 | B14: X-Rite ColorChecker | C14: 5000 | D14: 7 | F14: =IF(E14="Год",1,IF(E14="Квартал",4,IF(E14="Месяц",12,0))) | G14: =IF(N(D14)>0,C14/D14,C14*F14) | H14: амортизация
A15: Form002 | B15: Системный блок | C15: 180000 | D15: 5 | F15: =IF(E15="Год",1,IF(E15="Квартал",4,IF(E15="Месяц",12,0))) | G15: =IF(N(D15)>0,C15/D15,C15*F15) | H15: амортизация
A16: Form002 | B16: Монитор ASUS ProArt | C16: 55000 | D16: 5 | F16: =IF(E16="Год",1,IF(E16="Квартал",4,IF(E16="Месяц",12,0))) | G16: =IF(N(D16)>0,C16/D16,C16*F16) | H16: амортизация
... A30: Form013 | B30: Косметический ремонт | C30: 30000 | D30: 7 | F30: =IF(E30="Год",1,IF(E30="Квартал",4,IF(E30="Месяц",12,0))) | G30: =IF(N(D30)>0,C30/D30,C30*F30) | H30: амортизация
A31: Form003 | B31: Adobe CC Photography | C31: 2000 | E31: Месяц | F31: =IF(E31="Год",1,IF(E31="Квартал",4,IF(E31="Месяц",12,0))) | G31: =IF(N(D31)>0,C31/D31,C31*F31) | H31: регулярный платёж
A32: Form003 | B32: Яндекс Диск 1 ТБ | C32: 250 | E32: Месяц | F32: =IF(E32="Год",1,IF(E32="Квартал",4,IF(E32="Месяц",12,0))) | G32: =IF(N(D32)>0,C32/D32,C32*F32) | H32: регулярный платёж
A33: Form007 | B33: Обслуживание счёта (РКО) | C33: 0 | E33: Месяц | F33: =IF(E33="Год",1,IF(E33="Квартал",4,IF(E33="Месяц",12,0))) | G33: =IF(N(D33)>0,C33/D33,C33*F33) | H33: регулярный платёж
A34: Form007 | B34: СМС-уведомления | C34: 150 | E34: Месяц | F34: =IF(E34="Год",1,IF(E34="Квартал",4,IF(E34="Месяц",12,0))) | G34: =IF(N(D34)>0,C34/D34,C34*F34) | H34: регулярный платёж
A35: Form010 | B35: Домен сайта | C35: 1500 | E35: Год | F35: =IF(E35="Год",1,IF(E35="Квартал",4,IF(E35="Месяц",12,0))) | G35: =IF(N(D35)>0,C35/D35,C35*F35) | H35: регулярный платёж
A36: Form010 | B36: Хостинг сайта | C36: 6000 | E36: Год | F36: =IF(E36="Год",1,IF(E36="Квартал",4,IF(E36="Месяц",12,0))) | G36: =IF(N(D36)>0,C36/D36,C36*F36) | H36: регулярный платёж
A37: Form010 | B37: Яндекс Директ | C37: 15000 | E37: Месяц | F37: =IF(E37="Год",1,IF(E37="Квартал",4,IF(E37="Месяц",12,0))) | G37: =IF(N(D37)>0,C37/D37,C37*F37) | H37: регулярный платёж
A38: Form010 | B38: Авито | C38: 0 | E38: Месяц | F38: =IF(E38="Год",1,IF(E38="Квартал",4,IF(E38="Месяц",12,0))) | G38: =IF(N(D38)>0,C38/D38,C38*F38) | H38: регулярный платёж
A39: Form010 | B39: Таргетированная реклама | C39: 0 | E39: Месяц | F39: =IF(E39="Год",1,IF(E39="Квартал",4,IF(E39="Месяц",12,0))) | G39: =IF(N(D39)>0,C39/D39,C39*F39) | H39: регулярный платёж
A40: Form010 | B40: Платные размещения у блогеров | C40: 0 | E40: Месяц | F40: =IF(E40="Год",1,IF(E40="Квартал",4,IF(E40="Месяц",12,0))) | G40: =IF(N(D40)>0,C40/D40,C40*F40) | H40: регулярный платёж
A41: Form010 | B41: Отклики на Profi.ru | C41: 0 | E41: Месяц | F41: =IF(E41="Год",1,IF(E41="Квартал",4,IF(E41="Месяц",12,0))) | G41: =IF(N(D41)>0,C41/D41,C41*F41) | H41: регулярный платёж

Sheet 04_Итог
A1: 04 · ИТОГ по выбранному режиму
A3: ГЛАВНЫЙ РЕЗУЛЬТАТ
A4: Выбранный режим | B4: =regime | C4: меняется в 02_Параметры → regime
A5: ПОЛНАЯ СТАВКА ЧАСА, ₽/час | B5: =CHOOSE(regime_no,'05_Расчёт'!B19,'05_Расчёт'!C19,'05_Расчёт'!D19,'05_Расчёт'!E19,'05_Расчёт'!F19,'05_Расчёт'!G19,'05_Расчёт'!H19) | C5: цена съёмочного часа для клиента
A6: Стоимость проекта, ₽ | B6: =CHOOSE(regime_no,'05_Расчёт'!B20,'05_Расчёт'!C20,'05_Расчёт'!D20,'05_Расчёт'!E20,'05_Расчёт'!F20,'05_Расчёт'!G20,'05_Расчёт'!H20)
A7: Полная ставка РАБОЧЕГО часа, ₽/час | B7: =full_hour_rate | C7: цена любого часа: съёмка, обработка, продвижение
A8: Выручка, ₽/год | B8: =CHOOSE(regime_no,'05_Расчёт'!B4,'05_Расчёт'!C4,'05_Расчёт'!D4,'05_Расчёт'!E4,'05_Расчёт'!F4,'05_Расчёт'!G4,'05_Расчёт'!H4)
A9: Выручка, ₽/месяц | B9: =CHOOSE(regime_no,'05_Расчёт'!B5,'05_Расчёт'!C5,'05_Расчёт'!D5,'05_Расчёт'!E5,'05_Расчёт'!F5,'05_Расчёт'!G5,'05_Расчёт'!H5)
A10: Всего налогов и взносов, ₽/год | B10: =CHOOSE(regime_no,'05_Расчёт'!B15,'05_Расчёт'!C15,'05_Расчёт'!D15,'05_Расчёт'!E15,'05_Расчёт'!F15,'05_Расчёт'!G15,'05_Расчёт'!H15)
A11: Эффективная нагрузка | B11: =CHOOSE(regime_no,'05_Расчёт'!B17,'05_Расчёт'!C17,'05_Расчёт'!D17,'05_Расчёт'!E17,'05_Расчёт'!F17,'05_Расчёт'!G17,'05_Расчёт'!H17)
A12: Точка безубыточности, ₽/год | B12: =CHOOSE(regime_no,'05_Расчёт'!B22,'05_Расчёт'!C22,'05_Расчёт'!D22,'05_Расчёт'!E22,'05_Расчёт'!F22,'05_Расчёт'!G22,'05_Расчёт'!H22)
A13: ВРЕМЯ — иерархия
A14: ЧИСТОЕ время (всё доступное) | B14: =net_time | C14: производств. календарь − отпуск − больничный − час/день
A15: ├ ОПЕРАЦИОННОЕ (второстепенное) | B15: =side_time | C15: продвижение + учёт
A16: ├ РЕЗЕРВ на форс-мажоры | B16: =fm_time | C16: переносы, отмены, срывы
A17: └ ПРОЕКТНОЕ за год | B17: =project_pool | C17: на выполнение всех проектов
A18: ├ ПРОФИЛЬНОЕ (по профилю) | B18: =core_time | C18: S × (1+коэф.): площадка + обработка
A19: │ ├ СЪЁМОЧНОЕ ← ЦЕЛЬ | B19: =shooting_time | C19: S — работа на площадке
A20: │ └ постпродакшн | B20: =post_time | C20: S × коэффициент — обработка
A21: └ работа с клиентом | B21: =client_total | C21: 1 ч на проект: продажа, согласования
A22: Продолжительность съёмки (S) | B22: =shoot_duration | C22: типовой заказ, задаёт пользователь
A23: Коэффициент обработки | B23: =post_ratio | C23: часов обработки на 1 час съёмки
A24: Проектное время на 1 проект | B24: =project_time | C24: S × (1+коэф.) + 1
A25: Проектов в год | B25: =projects_year
A26: Проектов в неделю | B26: =projects_week | C26: при авторежиме = 1
A28: ПРОВЕРКА ИЕРАРХИИ ВРЕМЕНИ
A29: Операционное + резерв + проектное = чистое | B29: =IF(ABS(side_time+fm_time+project_pool-net_time)<0.01,"OK","ОШИБКА")
A30: Профильное + клиентское = проектное | B30: =IF(ABS(core_time+client_total-project_pool)<0.01,"OK","ОШИБКА")
A31: Съёмочное + постпродакшн = профильное | B31: =IF(ABS(shooting_time+post_time-core_time)<0.01,"OK","ОШИБКА")
A33: РАСХОДЫ
A34: Амортизация | B34: =investment
A35: Переменные расходы | B35: =variable_costs
A36: ВСЕГО расходов (C) | B36: =total_costs
A37: Эквайринг (% от выручки) | B37: =acquiring
A39: СКОЛЬКО ВЫ ТЕРЯЕТЕ
B41: =B38-B37
B42: =B5
A43: Разница с текущей, ₽/час
A44: Недополучено за год, ₽ | B44: =B43*shooting_time
A46: САМОПРОВЕРКИ
A47: Все режимы дают желаемый доход | B47: =IF(SUMPRODUCT(--(ABS('05_Расчёт'!B24:H24-target_income)>1))=0,"OK","ОШИБКА")
A48: Точки безубыточности сходятся в ноль | B48: =IF(SUMPRODUCT(--(ABS('05_Расчёт'!B23:H23)>1))=0,"OK","ОШИБКА")
A49: Амортизация + переменные = всего расходов | B49: =IF(ABS(investment+variable_costs-total_costs)<0.01,"OK","ОШИБКА")
A50: Проектное время положительно | B50: =IF(project_pool>0,"OK","ОШИБКА: операционное больше чистого")
A51: Съёмочных часов больше нуля | B51: =IF(shooting_time>0,"OK","ЗАПОЛНИТЕ продолжительность съёмки")
A52: Лимиты режимов не превышены | B52: =IF(COUNTIF('05_Расчёт'!B25:H25,"ок")=7,"OK","ПРОВЕРЬТЕ")
A53: Бухгалтер: либо деньги, либо время | B53: =IF(OR(AND(var_accounting>0,accounting_time=0),AND(var_accounting=0,accounting_time>0)),"OK","ПРОВЕРЬТЕ")
A54: Длительность съёмки задана | B54: =IF(shoot_duration>0,"OK","ЗАПОЛНИТЕ")
A55: Час проектного времени положителен | B55: =IF(hour_pool>0,"OK","ПРОВЕРЬТЕ")
A56: Резерв на форс-мажоры не больше 30% | B56: =IF(fm_pct<=0.3,"OK","СЛИШКОМ БОЛЬШОЙ")
A57: Сайт: либо сумма, либо часы | B57: =IF(OR(AND(dep_website>0,site_divisor=0),AND(dep_website=0,site_divisor>=0)),"OK","ПРОВЕРЬТЕ")

Sheet 05_Расчёт
A1: 05 · РАСЧЁТ — семь режимов, как в вашем выпадающем списке
A3: Показатель | B3: НПД средняя 5% | C3: НПД физлица 4% | D3: НПД юрлица 6% | E3: УСН Доходы 6% | F3: УСН Д−Р 15% | G3: АУСН Доходы 8% | H3: АУСН Д−Р 20%
A4: ВЫРУЧКА, ₽/год | B4: =(target_income+total_costs)/((1-acquiring-site_divisor)-rate_npd_avg) | C4: =(target_income+total_costs)/((1-acquiring-site_divisor)-rate_npd_fiz) | D4: =(target_income+total_costs)/((1-acquiring-site_divisor)-rate_npd_ur) | E4: =MAX(((target_income+total_costs)+fixed_contrib-threshold_credit)/((1-acquiring-site_divisor)-extra_contrib),(target_income+total_costs)/((1-acquiring-site_divisor)-rate_usn_inc)) | F4: =((target_income/(1-rate_usn_prof))+(fixed_contrib-threshold_credit+extra_contrib*(target_income/(1-rate_usn_prof)))+total_costs)/(1-acquiring-site_divisor) | G4: =((target_income+total_costs)+injury_contrib)/((1-acquiring-site_divisor)-rate_ausn_inc) | H4: =((target_income/(1-rate_ausn_prof))+total_costs+injury_contrib)/(1-acquiring-site_divisor)
A5: Выручка, ₽/месяц | B5: =B4/months | C5: =C4/months | D5: =D4/months | E5: =E4/months | F5: =F4/months | G5: =G4/months | H5: =H4/months
A7: Эквайринг, ₽/год | B7: =B4*acquiring | C7: =C4*acquiring | D7: =D4*acquiring | E7: =E4*acquiring | F7: =F4*acquiring | G7: =G4*acquiring | H7: =H4*acquiring
A8: Страховые взносы (фикс.) | B8: =0 | C8: =0 | D8: =0 | E8: =fixed_contrib | F8: =fixed_contrib | G8: =0 | H8: =0
A9: База для доначисления 1% | B9: =0 | C9: =0 | D9: =0 | E9: =MAX(0,E4-contrib_threshold) | F9: =MAX(0,(target_income/(1-rate_usn_prof))-contrib_threshold) | G9: =0 | H9: =0
A10: Доначисление 1% | B10: =0 | C10: =0 | D10: =0 | E10: =MIN(E9*extra_contrib,contrib_cap) | F10: =MIN(F9*extra_contrib,contrib_cap) | G10: =0 | H10: =0
A11: Налог | B11: =B4*rate_npd_avg | C11: =C4*rate_npd_fiz | D11: =D4*rate_npd_ur | E11: =MAX(0,E4*rate_usn_inc-(E8+E10)) | F11: =MAX((target_income/(1-rate_usn_prof))*rate_usn_prof,F4*min_tax_usn) | G11: =G4*rate_ausn_inc | H11: =MAX((target_income/(1-rate_ausn_prof))*rate_ausn_prof,H4*min_tax_ausn)
A12: Взнос на травматизм | B12: =0 | C12: =0 | D12: =0 | E12: =0 | F12: =0 | G12: =injury_contrib | H12: =injury_contrib
A13: Применён минимальный налог? | B13: ="—" | C13: ="—" | D13: ="—" | E13: ="—" | F13: =IF((target_income/(1-rate_usn_prof))*rate_usn_prof<F4*min_tax_usn,"ДА","нет") | G13: ="—" | H13: =IF((target_income/(1-rate_ausn_prof))*rate_ausn_prof<H4*min_tax_ausn,"ДА","нет")
A15: ВСЕГО налогов и взносов | B15: =B8+B10+B11+B12 | C15: =C8+C10+C11+C12 | D15: =D8+D10+D11+D12 | E15: =E8+E10+E11+E12 | F15: =F8+F10+F11+F12 | G15: =G8+G10+G11+G12 | H15: =H8+H10+H11+H12
A16: Всего налогов и взносов, ₽/мес | B16: =B15/months | C16: =C15/months | D16: =D15/months | E16: =E15/months | F16: =F15/months | G16: =G15/months | H16: =H15/months
A17: Эффективная нагрузка | B17: =IF(B4=0,0,B15/B4) | C17: =IF(C4=0,0,C15/C4) | D17: =IF(D4=0,0,D15/D4) | E17: =IF(E4=0,0,E15/E4) | F17: =IF(F4=0,0,F15/F4) | G17: =IF(G4=0,0,G15/G4) | H17: =IF(H4=0,0,H15/H4)
A19: ПОЛНАЯ СТАВКА ЧАСА, ₽/час | B19: =IF(shooting_time=0,0,B4/shooting_time) | C19: =IF(shooting_time=0,0,C4/shooting_time) | D19: =IF(shooting_time=0,0,D4/shooting_time) | E19: =IF(shooting_time=0,0,E4/shooting_time) | F19: =IF(shooting_time=0,0,F4/shooting_time) | G19: =IF(shooting_time=0,0,G4/shooting_time) | H19: =IF(shooting_time=0,0,H4/shooting_time)
A20: Стоимость проекта, ₽ | B20: =IF(projects_year=0,0,B4/projects_year) | C20: =IF(projects_year=0,0,C4/projects_year) | D20: =IF(projects_year=0,0,D4/projects_year) | E20: =IF(projects_year=0,0,E4/projects_year) | F20: =IF(projects_year=0,0,F4/projects_year) | G20: =IF(projects_year=0,0,G4/projects_year) | H20: =IF(projects_year=0,0,H4/projects_year)
A22: Точка безубыточности, ₽/год | B22: =total_costs/((1-acquiring-site_divisor)-rate_npd_avg) | C22: =total_costs/((1-acquiring-site_divisor)-rate_npd_fiz) | D22: =total_costs/((1-acquiring-site_divisor)-rate_npd_ur) | E22: =MAX((total_costs+fixed_contrib-threshold_credit)/((1-acquiring-site_divisor)-extra_contrib),total_costs/((1-acquiring-site_divisor)-rate_usn_inc)) | F22: =(total_costs+fixed_contrib)/((1-acquiring-site_divisor)-min_tax_usn) | G22: =(total_costs+injury_contrib)/((1-acquiring-site_divisor)-rate_ausn_inc) | H22: =(total_costs+injury_contrib)/((1-acquiring-site_divisor)-min_tax_ausn)
A23: ПРОВЕРКА безубыточности (=0) | B23: =B22-total_costs-B22*acquiring-B22*rate_npd_avg | C23: =C22-total_costs-C22*acquiring-C22*rate_npd_fiz | D23: =D22-total_costs-D22*acquiring-D22*rate_npd_ur | E23: =E22-total_costs-E22*acquiring-MAX(fixed_contrib+MIN(MAX(0,E22-contrib_threshold)*extra_contrib,contrib_cap),E22*rate_usn_inc) | F23: =F22-total_costs-F22*acquiring-fixed_contrib-F22*min_tax_usn | G23: =G22-total_costs-G22*acquiring-G22*rate_ausn_inc | H23: =H22-total_costs-H22*acquiring-H22*min_tax_ausn
A24: ПРОВЕРКА: остаётся на руки | B24: =B4-total_costs-B7-B15 | C24: =C4-total_costs-C7-C15 | D24: =D4-total_costs-D7-D15 | E24: =E4-total_costs-E7-E15 | F24: =F4-total_costs-F7-F15 | G24: =G4-total_costs-G7-G15 | H24: =H4-total_costs-H7-H15
A25: Контроль лимитов | B25: =IF(B4>limit_npd,"! лимит НПД","ок") | C25: =IF(C4>limit_npd,"! лимит НПД","ок") | D25: =IF(D4>limit_npd,"! лимит НПД","ок") | E25: =IF(E4>vat_threshold,"! НДС","ок") | F25: =IF(F4>vat_threshold,"! НДС","ок") | G25: =IF(G4>limit_ausn,"! лимит АУСН","ок") | H25: =IF(H4>limit_ausn,"! лимит АУСН","ок")

Sheet 06_Отчёт
A1: 06 · ОТЧЁТ — куда уходит каждый рубль с часа съёмки
A2: Личный доход разложен по ролям: фотограф, ретушёр, менеджер, маркетолог, бухгалтер. Расходы — по назначению.
A4: 1 · ВАШ ЛИЧНЫЙ ДОХОД ПО РОЛЯМ (ставка любого рабочего часа = доход / чистое время)
A5: Статья | B5: ₽/год | C5: ₽/месяц | D5: ₽/съём. час | E5: ₽/проект | F5: доля | G5: часов/год
A6: Как ФОТОГРАФ — работа на площадке | B6: =(target_income/net_time)*shooting_time | C6: =IF(months=0,0,B6/months) | D6: =IF(shooting_time=0,0,B6/shooting_time) | E6: =IF(projects_year=0,0,B6/projects_year) | F6: =IF((CHOOSE(regime_no,'05_Расчёт'!B4,'05_Расчёт'!C4,'05_Расчёт'!D4,'05_Расчёт'!E4,'05_Расчёт'!F4,'05_Расчёт'!G4,'05_Расчёт'!H4))=0,0,B6/(CHOOSE(regime_no,'05_Расчёт'!B4,'05_Расчёт'!C4,'05_Расчёт'!D4,'05_Расчёт'!E4,'05_Расчёт'!F4,'05_Расчёт'!G4,'05_Расчёт'!H4))) | G6: =shooting_time
A7: Как РЕТУШЁР — обработка материала | B7: =(target_income/net_time)*post_time | C7: =IF(months=0,0,B7/months) | D7: =IF(shooting_time=0,0,B7/shooting_time) | E7: =IF(projects_year=0,0,B7/projects_year) | F7: =IF((CHOOSE(regime_no,'05_Расчёт'!B4,'05_Расчёт'!C4,'05_Расчёт'!D4,'05_Расчёт'!E4,'05_Расчёт'!F4,'05_Расчёт'!G4,'05_Расчёт'!H4))=0,0,B7/(CHOOSE(regime_no,'05_Расчёт'!B4,'05_Расчёт'!C4,'05_Расчёт'!D4,'05_Расчёт'!E4,'05_Расчёт'!F4,'05_Расчёт'!G4,'05_Расчёт'!H4))) | G7: =post_time
A8: Как МЕНЕДЖЕР — работа с клиентом | B8: =(target_income/net_time)*client_total | C8: =IF(months=0,0,B8/months) | D8: =IF(shooting_time=0,0,B8/shooting_time) | E8: =IF(projects_year=0,0,B8/projects_year) | F8: =IF((CHOOSE(regime_no,'05_Расчёт'!B4,'05_Расчёт'!C4,'05_Расчёт'!D4,'05_Расчёт'!E4,'05_Расчёт'!F4,'05_Расчёт'!G4,'05_Расчёт'!H4))=0,0,B8/(CHOOSE(regime_no,'05_Расчёт'!B4,'05_Расчёт'!C4,'05_Расчёт'!D4,'05_Расчёт'!E4,'05_Расчёт'!F4,'05_Расчёт'!G4,'05_Расчёт'!H4))) | G8: =client_total
A9: Как МАРКЕТОЛОГ — продвижение | B9: =(target_income/net_time)*promo_time | C9: =IF(months=0,0,B9/months) | D9: =IF(shooting_time=0,0,B9/shooting_time) | E9: =IF(projects_year=0,0,B9/projects_year) | F9: =IF((CHOOSE(regime_no,'05_Расчёт'!B4,'05_Расчёт'!C4,'05_Расчёт'!D4,'05_Расчёт'!E4,'05_Расчёт'!F4,'05_Расчёт'!G4,'05_Расчёт'!H4))=0,0,B9/(CHOOSE(regime_no,'05_Расчёт'!B4,'05_Расчёт'!C4,'05_Расчёт'!D4,'05_Расчёт'!E4,'05_Расчёт'!F4,'05_Расчёт'!G4,'05_Расчёт'!H4))) | G9: =promo_time
A10: Как БУХГАЛТЕР — учёт и отчётность | B10: =(target_income/net_time)*accounting_time | C10: =IF(months=0,0,B10/months) | D10: =IF(shooting_time=0,0,B10/shooting_time) | E10: =IF(projects_year=0,0,B10/projects_year) | F10: =IF((CHOOSE(regime_no,'05_Расчёт'!B4,'05_Расчёт'!C4,'05_Расчёт'!D4,'05_Расчёт'!E4,'05_Расчёт'!F4,'05_Расчёт'!G4,'05_Расчёт'!H4))=0,0,B10/(CHOOSE(regime_no,'05_Расчёт'!B4,'05_Расчёт'!C4,'05_Расчёт'!D4,'05_Расчёт'!E4,'05_Расчёт'!F4,'05_Расчёт'!G4,'05_Расчёт'!H4))) | G10: =accounting_time
A11: Компенсация форс-мажоров | B11: =(target_income/net_time)*fm_time | C11: =IF(months=0,0,B11/months) | D11: =IF(shooting_time=0,0,B11/shooting_time) | E11: =IF(projects_year=0,0,B11/projects_year) | F11: =IF((CHOOSE(regime_no,'05_Расчёт'!B4,'05_Расчёт'!C4,'05_Расчёт'!D4,'05_Расчёт'!E4,'05_Расчёт'!F4,'05_Расчёт'!G4,'05_Расчёт'!H4))=0,0,B11/(CHOOSE(regime_no,'05_Расчёт'!B4,'05_Расчёт'!C4,'05_Расчёт'!D4,'05_Расчёт'!E4,'05_Расчёт'!F4,'05_Расчёт'!G4,'05_Расчёт'!H4))) | G11: =fm_time
A12: ИТОГО НА РУКИ | B12: =target_income | C12: =IF(months=0,0,B12/months) | D12: =IF(shooting_time=0,0,B12/shooting_time) | E12: =IF(projects_year=0,0,B12/projects_year) | F12: =IF((CHOOSE(regime_no,'05_Расчёт'!B4,'05_Расчёт'!C4,'05_Расчёт'!D4,'05_Расчёт'!E4,'05_Расчёт'!F4,'05_Расчёт'!G4,'05_Расчёт'!H4))=0,0,B12/(CHOOSE(regime_no,'05_Расчёт'!B4,'05_Расчёт'!C4,'05_Расчёт'!D4,'05_Расчёт'!E4,'05_Расчёт'!F4,'05_Расчёт'!G4,'05_Расчёт'!H4))) | G12: =net_time
A14: 2 · ОТЛОЖИТЬ НА ВОССТАНОВЛЕНИЕ ВЛОЖЕНИЙ (амортизация)
A15: Статья | B15: ₽/год | C15: ₽/месяц | D15: ₽/съём. час | E15: ₽/проект | F15: доля | G15: часов/год
A16: На съёмочное оборудование | B16: =dep_shoot | C16: =IF(months=0,0,B16/months) | D16: =IF(shooting_time=0,0,B16/shooting_time) | E16: =IF(projects_year=0,0,B16/projects_year) | F16: =IF((CHOOSE(regime_no,'05_Расчёт'!B4,'05_Расчёт'!C4,'05_Расчёт'!D4,'05_Расчёт'!E4,'05_Расчёт'!F4,'05_Расчёт'!G4,'05_Расчёт'!H4))=0,0,B16/(CHOOSE(regime_no,'05_Расчёт'!B4,'05_Расчёт'!C4,'05_Расчёт'!D4,'05_Расчёт'!E4,'05_Расчёт'!F4,'05_Расчёт'!G4,'05_Расчёт'!H4)))
A17: На офисное оборудование | B17: =dep_office | C17: =IF(months=0,0,B17/months) | D17: =IF(shooting_time=0,0,B17/shooting_time) | E17: =IF(projects_year=0,0,B17/projects_year) | F17: =IF((CHOOSE(regime_no,'05_Расчёт'!B4,'05_Расчёт'!C4,'05_Расчёт'!D4,'05_Расчёт'!E4,'05_Расчёт'!F4,'05_Расчёт'!G4,'05_Расчёт'!H4))=0,0,B17/(CHOOSE(regime_no,'05_Расчёт'!B4,'05_Расчёт'!C4,'05_Расчёт'!D4,'05_Расчёт'!E4,'05_Расчёт'!F4,'05_Расчёт'!G4,'05_Расчёт'!H4)))
A18: На ПО (разовые покупки) | B18: =dep_software | C18: =IF(months=0,0,B18/months) | D18: =IF(shooting_time=0,0,B18/shooting_time) | E18: =IF(projects_year=0,0,B18/projects_year) | F18: =IF((CHOOSE(regime_no,'05_Расчёт'!B4,'05_Расчёт'!C4,'05_Расчёт'!D4,'05_Расчёт'!E4,'05_Расчёт'!F4,'05_Расчёт'!G4,'05_Расчёт'!H4))=0,0,B18/(CHOOSE(regime_no,'05_Расчёт'!B4,'05_Расчёт'!C4,'05_Расчёт'!D4,'05_Расчёт'!E4,'05_Расчёт'!F4,'05_Расчёт'!G4,'05_Расчёт'!H4)))
A19: На обустройство рабочего места | B19: =dep_workspace | C19: =IF(months=0,0,B19/months) | D19: =IF(shooting_time=0,0,B19/shooting_time) | E19: =IF(projects_year=0,0,B19/projects_year) | F19: =IF((CHOOSE(regime_no,'05_Расчёт'!B4,'05_Расчёт'!C4,'05_Расчёт'!D4,'05_Расчёт'!E4,'05_Расчёт'!F4,'05_Расчёт'!G4,'05_Расчёт'!H4))=0,0,B19/(CHOOSE(regime_no,'05_Расчёт'!B4,'05_Расчёт'!C4,'05_Расчёт'!D4,'05_Расчёт'!E4,'05_Расчёт'!F4,'05_Расчёт'!G4,'05_Расчёт'!H4)))
A20: На обучение | B20: =dep_education | C20: =IF(months=0,0,B20/months) | D20: =IF(shooting_time=0,0,B20/shooting_time) | E20: =IF(projects_year=0,0,B20/projects_year) | F20: =IF((CHOOSE(regime_no,'05_Расчёт'!B4,'05_Расчёт'!C4,'05_Расчёт'!D4,'05_Расчёт'!E4,'05_Расчёт'!F4,'05_Расчёт'!G4,'05_Расчёт'!H4))=0,0,B20/(CHOOSE(regime_no,'05_Расчёт'!B4,'05_Расчёт'!C4,'05_Расчёт'!D4,'05_Расчёт'!E4,'05_Расчёт'!F4,'05_Расчёт'!G4,'05_Расчёт'!H4)))
A21: На сайт | B21: =dep_website | C21: =IF(months=0,0,B21/months) | D21: =IF(shooting_time=0,0,B21/shooting_time) | E21: =IF(projects_year=0,0,B21/projects_year) | F21: =IF((CHOOSE(regime_no,'05_Расчёт'!B4,'05_Расчёт'!C4,'05_Расчёт'!D4,'05_Расчёт'!E4,'05_Расчёт'!F4,'05_Расчёт'!G4,'05_Расчёт'!H4))=0,0,B21/(CHOOSE(regime_no,'05_Расчёт'!B4,'05_Расчёт'!C4,'05_Расчёт'!D4,'05_Расчёт'!E4,'05_Расчёт'!F4,'05_Расчёт'!G4,'05_Расчёт'!H4)))
A22: ИТОГО амортизация | B22: =investment | C22: =IF(months=0,0,B22/months) | D22: =IF(shooting_time=0,0,B22/shooting_time) | E22: =IF(projects_year=0,0,B22/projects_year) | F22: =IF((CHOOSE(regime_no,'05_Расчёт'!B4,'05_Расчёт'!C4,'05_Расчёт'!D4,'05_Расчёт'!E4,'05_Расчёт'!F4,'05_Расчёт'!G4,'05_Расчёт'!H4))=0,0,B22/(CHOOSE(regime_no,'05_Расчёт'!B4,'05_Расчёт'!C4,'05_Расчёт'!D4,'05_Расчёт'!E4,'05_Расчёт'!F4,'05_Расчёт'!G4,'05_Расчёт'!H4)))
A24: 3 · РЕГУЛЯРНЫЕ РАСХОДЫ
A25: Статья | B25: ₽/год | C25: ₽/месяц | D25: ₽/съём. час | E25: ₽/проект | F25: доля | G25: часов/год
A26: Подписки на ПО | B26: =var_software | C26: =IF(months=0,0,B26/months) | D26: =IF(shooting_time=0,0,B26/shooting_time) | E26: =IF(projects_year=0,0,B26/projects_year) | F26: =IF((CHOOSE(regime_no,'05_Расчёт'!B4,'05_Расчёт'!C4,'05_Расчёт'!D4,'05_Расчёт'!E4,'05_Расчёт'!F4,'05_Расчёт'!G4,'05_Расчёт'!H4))=0,0,B26/(CHOOSE(regime_no,'05_Расчёт'!B4,'05_Расчёт'!C4,'05_Расчёт'!D4,'05_Расчёт'!E4,'05_Расчёт'!F4,'05_Расчёт'!G4,'05_Расчёт'!H4)))
A27: Реклама и продвижение | B27: =var_ads | C27: =IF(months=0,0,B27/months) | D27: =IF(shooting_time=0,0,B27/shooting_time) | E27: =IF(projects_year=0,0,B27/projects_year) | F27: =IF((CHOOSE(regime_no,'05_Расчёт'!B4,'05_Расчёт'!C4,'05_Расчёт'!D4,'05_Расчёт'!E4,'05_Расчёт'!F4,'05_Расчёт'!G4,'05_Расчёт'!H4))=0,0,B27/(CHOOSE(regime_no,'05_Расчёт'!B4,'05_Расчёт'!C4,'05_Расчёт'!D4,'05_Расчёт'!E4,'05_Расчёт'!F4,'05_Расчёт'!G4,'05_Расчёт'!H4)))
A28: Банк: РКО и СМС | B28: =var_bank | C28: =IF(months=0,0,B28/months) | D28: =IF(shooting_time=0,0,B28/shooting_time) | E28: =IF(projects_year=0,0,B28/projects_year) | F28: =IF((CHOOSE(regime_no,'05_Расчёт'!B4,'05_Расчёт'!C4,'05_Расчёт'!D4,'05_Расчёт'!E4,'05_Расчёт'!F4,'05_Расчёт'!G4,'05_Расчёт'!H4))=0,0,B28/(CHOOSE(regime_no,'05_Расчёт'!B4,'05_Расчёт'!C4,'05_Расчёт'!D4,'05_Расчёт'!E4,'05_Расчёт'!F4,'05_Расчёт'!G4,'05_Расчёт'!H4)))
A29: Бухгалтер (0 = веду самостоятельно) | B29: =var_accounting | C29: =IF(months=0,0,B29/months) | D29: =IF(shooting_time=0,0,B29/shooting_time) | E29: =IF(projects_year=0,0,B29/projects_year) | F29: =IF((CHOOSE(regime_no,'05_Расчёт'!B4,'05_Расчёт'!C4,'05_Расчёт'!D4,'05_Расчёт'!E4,'05_Расчёт'!F4,'05_Расчёт'!G4,'05_Расчёт'!H4))=0,0,B29/(CHOOSE(regime_no,'05_Расчёт'!B4,'05_Расчёт'!C4,'05_Расчёт'!D4,'05_Расчёт'!E4,'05_Расчёт'!F4,'05_Расчёт'!G4,'05_Расчёт'!H4)))
A30: Аренда и коммунальные | B30: =var_workspace | C30: =IF(months=0,0,B30/months) | D30: =IF(shooting_time=0,0,B30/shooting_time) | E30: =IF(projects_year=0,0,B30/projects_year) | F30: =IF((CHOOSE(regime_no,'05_Расчёт'!B4,'05_Расчёт'!C4,'05_Расчёт'!D4,'05_Расчёт'!E4,'05_Расчёт'!F4,'05_Расчёт'!G4,'05_Расчёт'!H4))=0,0,B30/(CHOOSE(regime_no,'05_Расчёт'!B4,'05_Расчёт'!C4,'05_Расчёт'!D4,'05_Расчёт'!E4,'05_Расчёт'!F4,'05_Расчёт'!G4,'05_Расчёт'!H4)))
A31: ИТОГО переменные | B31: =variable_costs | C31: =IF(months=0,0,B31/months) | D31: =IF(shooting_time=0,0,B31/shooting_time) | E31: =IF(projects_year=0,0,B31/projects_year) | F31: =IF((CHOOSE(regime_no,'05_Расчёт'!B4,'05_Расчёт'!C4,'05_Расчёт'!D4,'05_Расчёт'!E4,'05_Расчёт'!F4,'05_Расчёт'!G4,'05_Расчёт'!H4))=0,0,B31/(CHOOSE(regime_no,'05_Расчёт'!B4,'05_Расчёт'!C4,'05_Расчёт'!D4,'05_Расчёт'!E4,'05_Расчёт'!F4,'05_Расчёт'!G4,'05_Расчёт'!H4)))
A33: 4 · ГОСУДАРСТВУ И БАНКУ
A34: Статья | B34: ₽/год | C34: ₽/месяц | D34: ₽/съём. час | E34: ₽/проект | F34: доля | G34: часов/год
A35: Налог и страховые взносы | B35: =CHOOSE(regime_no,'05_Расчёт'!B15,'05_Расчёт'!C15,'05_Расчёт'!D15,'05_Расчёт'!E15,'05_Расчёт'!F15,'05_Расчёт'!G15,'05_Расчёт'!H15) | C35: =IF(months=0,0,B35/months) | D35: =IF(shooting_time=0,0,B35/shooting_time) | E35: =IF(projects_year=0,0,B35/projects_year) | F35: =IF((CHOOSE(regime_no,'05_Расчёт'!B4,'05_Расчёт'!C4,'05_Расчёт'!D4,'05_Расчёт'!E4,'05_Расчёт'!F4,'05_Расчёт'!G4,'05_Расчёт'!H4))=0,0,B35/(CHOOSE(regime_no,'05_Расчёт'!B4,'05_Расчёт'!C4,'05_Расчёт'!D4,'05_Расчёт'!E4,'05_Расчёт'!F4,'05_Расчёт'!G4,'05_Расчёт'!H4)))
A36: Эквайринг (комиссия банка) | B36: =(CHOOSE(regime_no,'05_Расчёт'!B4,'05_Расчёт'!C4,'05_Расчёт'!D4,'05_Расчёт'!E4,'05_Расчёт'!F4,'05_Расчёт'!G4,'05_Расчёт'!H4))*acquiring | C36: =IF(months=0,0,B36/months) | D36: =IF(shooting_time=0,0,B36/shooting_time) | E36: =IF(projects_year=0,0,B36/projects_year) | F36: =IF((CHOOSE(regime_no,'05_Расчёт'!B4,'05_Расчёт'!C4,'05_Расчёт'!D4,'05_Расчёт'!E4,'05_Расчёт'!F4,'05_Расчёт'!G4,'05_Расчёт'!H4))=0,0,B36/(CHOOSE(regime_no,'05_Расчёт'!B4,'05_Расчёт'!C4,'05_Расчёт'!D4,'05_Расчёт'!E4,'05_Расчёт'!F4,'05_Расчёт'!G4,'05_Расчёт'!H4)))
A38: ВСЕГО = ВЫРУЧКА | B38: =CHOOSE(regime_no,'05_Расчёт'!B4,'05_Расчёт'!C4,'05_Расчёт'!D4,'05_Расчёт'!E4,'05_Расчёт'!F4,'05_Расчёт'!G4,'05_Расчёт'!H4) | C38: =IF(months=0,0,B38/months) | D38: =IF(shooting_time=0,0,B38/shooting_time) | E38: =IF(projects_year=0,0,B38/projects_year) | F38: =1
A39: Сверка: сумма всех статей | B39: =IF(ABS(B12+investment+variable_costs+B35+B36-B38)<1,"OK — сходится до рубля","РАСХОЖДЕНИЕ")
A41: 5 · ТРИ СЦЕНАРИЯ — сравните, где вы сейчас
A42: Сценарий | B42: Ставка часа | C42: Цена проекта | D42: Выручка/год | E42: На руки/год | F42: На руки/мес | G42: % от цели
A43: ВАША РАСЧЁТНАЯ — чтобы получать желаемое | B43: =(CHOOSE(regime_no,'05_Расчёт'!B4,'05_Расчёт'!C4,'05_Расчёт'!D4,'05_Расчёт'!E4,'05_Расчёт'!F4,'05_Расчёт'!G4,'05_Расчёт'!H4))/shooting_time | C43: =(CHOOSE(regime_no,'05_Расчёт'!B4,'05_Расчёт'!C4,'05_Расчёт'!D4,'05_Расчёт'!E4,'05_Расчёт'!F4,'05_Расчёт'!G4,'05_Расчёт'!H4))/projects_year | D43: =CHOOSE(regime_no,'05_Расчёт'!B4,'05_Расчёт'!C4,'05_Расчёт'!D4,'05_Расчёт'!E4,'05_Расчёт'!F4,'05_Расчёт'!G4,'05_Расчёт'!H4) | E43: =target_income | F43: =target_income/months | G43: =1
A44: ВАША ТЕКУЩАЯ — по ней работаете сейчас | B44: =current_rate | C44: =current_rate*shooting_time/projects_year | D44: =current_rate*shooting_time | E44: =(current_rate*shooting_time*(1-rate_current-acquiring)-total_costs) | F44: =(current_rate*shooting_time*(1-rate_current-acquiring)-total_costs)/months | G44: =(current_rate*shooting_time*(1-rate_current-acquiring)-total_costs)/target_income
A45: БЕЗУБЫТОЧНОСТЬ — работа в ноль | B45: =(CHOOSE(regime_no,'05_Расчёт'!B22,'05_Расчёт'!C22,'05_Расчёт'!D22,'05_Расчёт'!E22,'05_Расчёт'!F22,'05_Расчёт'!G22,'05_Расчёт'!H22))/shooting_time | C45: =(CHOOSE(regime_no,'05_Расчёт'!B22,'05_Расчёт'!C22,'05_Расчёт'!D22,'05_Расчёт'!E22,'05_Расчёт'!F22,'05_Расчёт'!G22,'05_Расчёт'!H22))/projects_year | D45: =CHOOSE(regime_no,'05_Расчёт'!B22,'05_Расчёт'!C22,'05_Расчёт'!D22,'05_Расчёт'!E22,'05_Расчёт'!F22,'05_Расчёт'!G22,'05_Расчёт'!H22) | E45: =0 | F45: =0 | G45: =0
A47: Недополучено за год при текущей ставке | B47: =target_income-(current_rate*shooting_time*(1-rate_current-acquiring)-total_costs) | C47: это ваш вклад в чужой бизнес
A51: 7 · ТРИ КАРТИНЫ ОДНОГО ЧАСА — куда уходят деньги клиента
A52: Слева направо: сколько НУЖНО брать · сколько берёте СЕЙЧАС · минимум, чтобы не работать в убыток.
A54: ВАША РАСЧЁТНАЯ СТАВКА | F54: ВАША ТЕКУЩАЯ СТАВКА | K54: РАБОТА В НОЛЬ
A55: Статья | B55: ₽/год | C55: ₽/час | D55: доля | F55: Статья | G55: ₽/год | H55: ₽/час | I55: доля | K55: Статья | L55: ₽/год | M55: ₽/час | N55: доля
A56: Ваш доход на руки | B56: =MAX(0,target_income) | C56: =IF(shooting_time=0,0,B56/shooting_time) | D56: =IF((CHOOSE(regime_no,'05_Расчёт'!B4,'05_Расчёт'!C4,'05_Расчёт'!D4,'05_Расчёт'!E4,'05_Расчёт'!F4,'05_Расчёт'!G4,'05_Расчёт'!H4))=0,0,B56/(CHOOSE(regime_no,'05_Расчёт'!B4,'05_Расчёт'!C4,'05_Расчёт'!D4,'05_Расчёт'!E4,'05_Расчёт'!F4,'05_Расчёт'!G4,'05_Расчёт'!H4))) | F56: Ваш доход на руки | G56: =MAX(0,((current_rate*shooting_time)*(1-rate_current-acquiring)-total_costs)) | H56: =IF(shooting_time=0,0,G56/shooting_time) | I56: =IF((current_rate*shooting_time)=0,0,G56/(current_rate*shooting_time)) | K56: Ваш доход на руки | L56: =MAX(0,0) | M56: =IF(shooting_time=0,0,L56/shooting_time) | N56: =IF((CHOOSE(regime_no,'05_Расчёт'!B22,'05_Расчёт'!C22,'05_Расчёт'!D22,'05_Расчёт'!E22,'05_Расчёт'!F22,'05_Расчёт'!G22,'05_Расчёт'!H22))=0,0,L56/(CHOOSE(regime_no,'05_Расчёт'!B22,'05_Расчёт'!C22,'05_Расчёт'!D22,'05_Расчёт'!E22,'05_Расчёт'!F22,'05_Расчёт'!G22,'05_Расчёт'!H22)))
A57: Отложить на оборудование и обучение | B57: =MAX(0,investment) | C57: =IF(shooting_time=0,0,B57/shooting_time) | D57: =IF((CHOOSE(regime_no,'05_Расчёт'!B4,'05_Расчёт'!C4,'05_Расчёт'!D4,'05_Расчёт'!E4,'05_Расчёт'!F4,'05_Расчёт'!G4,'05_Расчёт'!H4))=0,0,B57/(CHOOSE(regime_no,'05_Расчёт'!B4,'05_Расчёт'!C4,'05_Расчёт'!D4,'05_Расчёт'!E4,'05_Расчёт'!F4,'05_Расчёт'!G4,'05_Расчёт'!H4))) | F57: Отложить на оборудование и обучение | G57: =MAX(0,investment) | H57: =IF(shooting_time=0,0,G57/shooting_time) | I57: =IF((current_rate*shooting_time)=0,0,G57/(current_rate*shooting_time)) | K57: Отложить на оборудование и обучение | L57: =MAX(0,investment) | M57: =IF(shooting_time=0,0,L57/shooting_time) | N57: =IF((CHOOSE(regime_no,'05_Расчёт'!B22,'05_Расчёт'!C22,'05_Расчёт'!D22,'05_Расчёт'!E22,'05_Расчёт'!F22,'05_Расчёт'!G22,'05_Расчёт'!H22))=0,0,L57/(CHOOSE(regime_no,'05_Расчёт'!B22,'05_Расчёт'!C22,'05_Расчёт'!D22,'05_Расчёт'!E22,'05_Расчёт'!F22,'05_Расчёт'!G22,'05_Расчёт'!H22)))
A58: Регулярные расходы (реклама, аренда, ПО) | B58: =MAX(0,variable_costs) | C58: =IF(shooting_time=0,0,B58/shooting_time) | D58: =IF((CHOOSE(regime_no,'05_Расчёт'!B4,'05_Расчёт'!C4,'05_Расчёт'!D4,'05_Расчёт'!E4,'05_Расчёт'!F4,'05_Расчёт'!G4,'05_Расчёт'!H4))=0,0,B58/(CHOOSE(regime_no,'05_Расчёт'!B4,'05_Расчёт'!C4,'05_Расчёт'!D4,'05_Расчёт'!E4,'05_Расчёт'!F4,'05_Расчёт'!G4,'05_Расчёт'!H4))) | F58: Регулярные расходы (реклама, аренда, ПО) | G58: =MAX(0,variable_costs) | H58: =IF(shooting_time=0,0,G58/shooting_time) | I58: =IF((current_rate*shooting_time)=0,0,G58/(current_rate*shooting_time)) | K58: Регулярные расходы (реклама, аренда, ПО) | L58: =MAX(0,variable_costs) | M58: =IF(shooting_time=0,0,L58/shooting_time) | N58: =IF((CHOOSE(regime_no,'05_Расчёт'!B22,'05_Расчёт'!C22,'05_Расчёт'!D22,'05_Расчёт'!E22,'05_Расчёт'!F22,'05_Расчёт'!G22,'05_Расчёт'!H22))=0,0,L58/(CHOOSE(regime_no,'05_Расчёт'!B22,'05_Расчёт'!C22,'05_Расчёт'!D22,'05_Расчёт'!E22,'05_Расчёт'!F22,'05_Расчёт'!G22,'05_Расчёт'!H22)))
A59: Налог и страховые взносы | B59: =MAX(0,(CHOOSE(regime_no,'05_Расчёт'!B4,'05_Расчёт'!C4,'05_Расчёт'!D4,'05_Расчёт'!E4,'05_Расчёт'!F4,'05_Расчёт'!G4,'05_Расчёт'!H4))*rate_current) | C59: =IF(shooting_time=0,0,B59/shooting_time) | D59: =IF((CHOOSE(regime_no,'05_Расчёт'!B4,'05_Расчёт'!C4,'05_Расчёт'!D4,'05_Расчёт'!E4,'05_Расчёт'!F4,'05_Расчёт'!G4,'05_Расчёт'!H4))=0,0,B59/(CHOOSE(regime_no,'05_Расчёт'!B4,'05_Расчёт'!C4,'05_Расчёт'!D4,'05_Расчёт'!E4,'05_Расчёт'!F4,'05_Расчёт'!G4,'05_Расчёт'!H4))) | F59: Налог и страховые взносы | G59: =MAX(0,(current_rate*shooting_time)*rate_current) | H59: =IF(shooting_time=0,0,G59/shooting_time) | I59: =IF((current_rate*shooting_time)=0,0,G59/(current_rate*shooting_time)) | K59: Налог и страховые взносы | L59: =MAX(0,(CHOOSE(regime_no,'05_Расчёт'!B22,'05_Расчёт'!C22,'05_Расчёт'!D22,'05_Расчёт'!E22,'05_Расчёт'!F22,'05_Расчёт'!G22,'05_Расчёт'!H22))*rate_current) | M59: =IF(shooting_time=0,0,L59/shooting_time) | N59: =IF((CHOOSE(regime_no,'05_Расчёт'!B22,'05_Расчёт'!C22,'05_Расчёт'!D22,'05_Расчёт'!E22,'05_Расчёт'!F22,'05_Расчёт'!G22,'05_Расчёт'!H22))=0,0,L59/(CHOOSE(regime_no,'05_Расчёт'!B22,'05_Расчёт'!C22,'05_Расчёт'!D22,'05_Расчёт'!E22,'05_Расчёт'!F22,'05_Расчёт'!G22,'05_Расчёт'!H22)))
A60: Банку за эквайринг | B60: =MAX(0,(CHOOSE(regime_no,'05_Расчёт'!B4,'05_Расчёт'!C4,'05_Расчёт'!D4,'05_Расчёт'!E4,'05_Расчёт'!F4,'05_Расчёт'!G4,'05_Расчёт'!H4))*acquiring) | C60: =IF(shooting_time=0,0,B60/shooting_time) | D60: =IF((CHOOSE(regime_no,'05_Расчёт'!B4,'05_Расчёт'!C4,'05_Расчёт'!D4,'05_Расчёт'!E4,'05_Расчёт'!F4,'05_Расчёт'!G4,'05_Расчёт'!H4))=0,0,B60/(CHOOSE(regime_no,'05_Расчёт'!B4,'05_Расчёт'!C4,'05_Расчёт'!D4,'05_Расчёт'!E4,'05_Расчёт'!F4,'05_Расчёт'!G4,'05_Расчёт'!H4))) | F60: Банку за эквайринг | G60: =MAX(0,(current_rate*shooting_time)*acquiring) | H60: =IF(shooting_time=0,0,G60/shooting_time) | I60: =IF((current_rate*shooting_time)=0,0,G60/(current_rate*shooting_time)) | K60: Банку за эквайринг | L60: =MAX(0,(CHOOSE(regime_no,'05_Расчёт'!B22,'05_Расчёт'!C22,'05_Расчёт'!D22,'05_Расчёт'!E22,'05_Расчёт'!F22,'05_Расчёт'!G22,'05_Расчёт'!H22))*acquiring) | M60: =IF(shooting_time=0,0,L60/shooting_time) | N60: =IF((CHOOSE(regime_no,'05_Расчёт'!B22,'05_Расчёт'!C22,'05_Расчёт'!D22,'05_Расчёт'!E22,'05_Расчёт'!F22,'05_Расчёт'!G22,'05_Расчёт'!H22))=0,0,L60/(CHOOSE(regime_no,'05_Расчёт'!B22,'05_Расчёт'!C22,'05_Расчёт'!D22,'05_Расчёт'!E22,'05_Расчёт'!F22,'05_Расчёт'!G22,'05_Расчёт'!H22)))
A61: ИТОГО берёте с клиента | B61: =(CHOOSE(regime_no,'05_Расчёт'!B4,'05_Расчёт'!C4,'05_Расчёт'!D4,'05_Расчёт'!E4,'05_Расчёт'!F4,'05_Расчёт'!G4,'05_Расчёт'!H4)) | C61: =IF(shooting_time=0,0,(CHOOSE(regime_no,'05_Расчёт'!B4,'05_Расчёт'!C4,'05_Расчёт'!D4,'05_Расчёт'!E4,'05_Расчёт'!F4,'05_Расчёт'!G4,'05_Расчёт'!H4))/shooting_time) | D61: =1 | F61: ИТОГО берёте с клиента | G61: =(current_rate*shooting_time) | H61: =IF(shooting_time=0,0,(current_rate*shooting_time)/shooting_time) | I61: =1 | K61: ИТОГО берёте с клиента | L61: =(CHOOSE(regime_no,'05_Расчёт'!B22,'05_Расчёт'!C22,'05_Расчёт'!D22,'05_Расчёт'!E22,'05_Расчёт'!F22,'05_Расчёт'!G22,'05_Расчёт'!H22)) | M61: =IF(shooting_time=0,0,(CHOOSE(regime_no,'05_Расчёт'!B22,'05_Расчёт'!C22,'05_Расчёт'!D22,'05_Расчёт'!E22,'05_Расчёт'!F22,'05_Расчёт'!G22,'05_Расчёт'!H22))/shooting_time) | N61: =1
A84: 8 · ЧТО ЭТО ЗНАЧИТ — расшифровка простыми словами
A85: ЗА ОДИН ЧАС СЪЁМКИ ВАМ ЗАПЛАТЯТ — И ВОТ КУДА УЙДУТ ЭТИ ДЕНЬГИ:
A87: Вам заплатят за час съёмки: | B87: =IF(shooting_time=0,0,(CHOOSE(regime_no,'05_Расчёт'!B4,'05_Расчёт'!C4,'05_Расчёт'!D4,'05_Расчёт'!E4,'05_Расчёт'!F4,'05_Расчёт'!G4,'05_Расчёт'!H4))/shooting_time)
A89: Из них вы заработаете (за все свои роли) | B89: =IF(shooting_time=0,0,target_income/shooting_time)
A90: Это оплата не одного часа, а ВСЕЙ работы вокруг него. Разбивка по ролям — в таблице ниже.
A91: Откладываете на оборудование и обучение | B91: =IF(shooting_time=0,0,investment/shooting_time)
A92: Камера, компьютер, объективы и курсы изнашиваются. Если не откладывать — через 3 года купить новое будет не на что.
A93: Платите за рекламу, аренду и подписки | B93: =IF(shooting_time=0,0,variable_costs/shooting_time)
A94: Директ, хостинг, Adobe, доля квартиры под кабинет. Это уходит каждый месяц, даже когда съёмок нет.
A95: Отдаёте государству | B95: =IF(shooting_time=0,0,(CHOOSE(regime_no,'05_Расчёт'!B4,'05_Расчёт'!C4,'05_Расчёт'!D4,'05_Расчёт'!E4,'05_Расчёт'!F4,'05_Расчёт'!G4,'05_Расчёт'!H4))*rate_current/shooting_time)
A96: Налог по вашему режиму и страховые взносы. Считается с оборота, а не с того, что осталось.
A97: Отдаёте банку | B97: =IF(shooting_time=0,0,(CHOOSE(regime_no,'05_Расчёт'!B4,'05_Расчёт'!C4,'05_Расчёт'!D4,'05_Расчёт'!E4,'05_Расчёт'!F4,'05_Расчёт'!G4,'05_Расчёт'!H4))*acquiring/shooting_time)
A98: Комиссия за приём оплаты картой. Берётся с каждого поступления.
A100: ЗА КАКИЕ РОЛИ ВЫ ЭТО ЗАРАБОТАЛИ
A101: Роль | B101: Часов в год | C101: Часов на 1 проект | D101: Заработок ₽/год | E101: ₽ с часа съёмки
A102: ФОТОГРАФ — работа на съёмочной площадке | B102: =shooting_time | C102: =shoot_duration | D102: =(target_income/net_time)*shooting_time | E102: =IF(shooting_time=0,0,(target_income/net_time)*shooting_time/shooting_time)
A103: РЕТУШЁР — обработка отснятого материала | B103: =post_time | C103: =shoot_duration*post_ratio | D103: =(target_income/net_time)*post_time | E103: =IF(shooting_time=0,0,(target_income/net_time)*post_time/shooting_time)
A104: МЕНЕДЖЕР ПО ПРОДАЖАМ — переговоры, согласования | B104: =client_total | C104: =client_time | D104: =(target_income/net_time)*client_total | E104: =IF(shooting_time=0,0,(target_income/net_time)*client_total/shooting_time)
A105: МАРКЕТОЛОГ и SMM — продвижение, соцсети, отклики | B105: =promo_time | C105: =IF(projects_year=0,0,promo_time/projects_year) | D105: =(target_income/net_time)*promo_time | E105: =IF(shooting_time=0,0,(target_income/net_time)*promo_time/shooting_time)
A106: БУХГАЛТЕР — учёт, отчётность, налоги | B106: =accounting_time | C106: =IF(projects_year=0,0,accounting_time/projects_year) | D106: =(target_income/net_time)*accounting_time | E106: =IF(shooting_time=0,0,(target_income/net_time)*accounting_time/shooting_time)
A107: Компенсация сорванных съёмок | B107: =fm_time | C107: =IF(projects_year=0,0,fm_time/projects_year) | D107: =(target_income/net_time)*fm_time | E107: =IF(shooting_time=0,0,(target_income/net_time)*fm_time/shooting_time)
A108: ИТОГО за все роли | B108: =net_time | C108: =IF(projects_year=0,0,net_time/projects_year) | D108: =target_income | E108: =IF(shooting_time=0,0,target_income/shooting_time)
A110: Обратите внимание: собственно ФОТОГРАФОМ вы работаете меньше всего часов. Основное время уходит
A111: на обработку и продвижение — и всё это оплачивается из той же суммы за час съёмки.
A113: ЕСЛИ ВЫ БЕРЁТЕ МЕНЬШЕ, ЧЕМ НУЖНО
A114: Ваша текущая ставка | B114: =current_rate
A115: Остаётся вам на руки за год | B115: =MAX(0,((current_rate*shooting_time)*(1-rate_current-acquiring)-total_costs))
A116: Недополучено за год | B116: =MAX(0,target_income-((current_rate*shooting_time)*(1-rate_current-acquiring)-total_costs))
A117: Недополучено с каждого часа съёмки | B117: =IF(shooting_time=0,0,MAX(0,target_income-((current_rate*shooting_time)*(1-rate_current-acquiring)-total_costs))/shooting_time)
A119: Расходы бизнеса не уменьшаются от того, что вы взяли меньше. Аренда, реклама и амортизация
A120: останутся прежними — сократится только ваш собственный доход. Разницу вы фактически дарите клиенту.
A122: МИНИМУМ, НИЖЕ КОТОРОГО РАБОТАТЬ НЕЛЬЗЯ
A123: Ставка при работе в ноль | B123: =IF(shooting_time=0,0,(CHOOSE(regime_no,'05_Расчёт'!B22,'05_Расчёт'!C22,'05_Расчёт'!D22,'05_Расчёт'!E22,'05_Расчёт'!F22,'05_Расчёт'!G22,'05_Расчёт'!H22))/shooting_time)
A124: Цена проекта при работе в ноль | B124: =IF(projects_year=0,0,(CHOOSE(regime_no,'05_Расчёт'!B22,'05_Расчёт'!C22,'05_Расчёт'!D22,'05_Расчёт'!E22,'05_Расчёт'!F22,'05_Расчёт'!G22,'05_Расчёт'!H22))/projects_year)
A126: При этой ставке вы покрываете расходы, налоги и откладываете на технику — но не получаете НИЧЕГО.
A127: Всё, что ниже, означает, что вы доплачиваете за право работать.
A129: 6 · ВАША НЕДЕЛЯ — 7 дней по 24 часа. Серое: сон и отдых. Цветное: работа
A130: Каждый квадрат = 1 час. Часы работы распределены пропорционально годовым затратам времени.
A131: час | B131: ПН | C131: ВТ | D131: СР | E131: ЧТ | F131: ПТ | G131: СБ | H131: ВС
A132: 00:00
A133: 01:00
A134: 02:00
A135: 03:00
A136: 04:00
A137: 05:00
A138: 06:00
A139: 07:00
A140: 08:00
A141: 09:00
A142: 10:00
...

Sheet 07_Интерфейс
A1: 07 · ИНТЕРФЕЙС — блоки и формы калькулятора
A3: Блок | B3: Раздел | C3: Заголовок | D3: Тип поля | E3: Формы | F3: Что задаёт | G3: Параметры в 02_Параметры
A4: Block1 | B4: Section1 | C4: Ваш желаемый доход | D4: input_number | E4: — | F4: Сумма на руки в месяц | G4: income_month
A5: Block2 | B5: Section1 | C5: Текущая стоимость часа | D5: input_number | E5: — | F5: Для сравнения | G5: current_rate
A6: Block3 | B6: Section1 | C6: Минимальный выезд (часов) | D6: input_number | E6: — | F6: Базовый заказ: ниже не выезжаете | G6: shoot_duration
A7: Block3a | B7: Section1 | C7: Коэффициент обработки | D7: input_number | E7: — | F7: Часов обработки на 1 час съёмки | G7: post_ratio
A8: Block4 | B8: Section1 | C8: Режим налогообложения | D8: dropdown | E8: Form015, Form016 | F8: ПЕРЕКЛЮЧАТЕЛЬ, 7 вариантов | G8: regime
A9: Block5 | B9: Section1 | C9: Как мы считаем | D9: info_block | E9: — | F9: Пояснение | G9: —
A10: Block6 | B10: Section2 | C10: Съёмочное оборудование | D10: dynamic_table | E10: Form001 | F10: Список позиций | G10: dep_shoot
A11: Block7 | B11: Section2 | C11: Офисное оборудование | D11: dynamic_table | E11: Form002 | F11: Список позиций | G11: dep_office
A12: Block8 | B12: Section2 | C12: Программное обеспечение | D12: dynamic_tables | E12: Form003, Form004 | F12: Подписки и разовые | G12: var_software, dep_software
A13: Block9 | B13: Section2 | C13: Рабочее место | D13: dropdown + table | E13: Form005, Form013 | F13: ПЕРЕКЛЮЧАТЕЛЬ дом/аренда | G13: ws_mode, var_workspace, dep_workspace
A14: Block10 | B14: Section2 | C14: Проф. обучение | D14: input_extended | E14: Form006 | F14: Стоимость, месяцы обучения и срок окупаемости | G14: edu_opportunity, dep_education
... A23: Block18 | B23: Section5 | C23: Сравнение режимов | D23: report | E23: — | F23: Вывод | G23: 04_Расчёт

Sheet 08_UI
A1: 08 · UI-МАТРИЦА — точная карта интерфейса. Каждая строка = один элемент на экране
A2: Переносится в HTML построчно. Колонки: где стоит, что за поле, какая ширина, чем управляется, куда пишет значение.
A4: № | B4: Блок | C4: Раздел | D4: Заголовок / подпись | E4: Элемент | F4: Тип поля | G4: Ширина | H4: Значение по умолч. | I4: Ед. | J4: Форма | K4: Параметр (ID) | L4: Условие показа / блокировки
A5: 01 | B5: Block1 | C5: 1 · О вас | D5: Ваш желаемый доход | E5: самый важный параметр — на всю ширину
D6: Хочу получать на руки | E6: поле ввода | F6: input_number | G6: 52% + кнопка сброса | H6: 110 216 | I6: ₽/мес | J6: — | K6: income_month
A7: 02 | B7: Block4 + Block2 | C7: 1 · О вас | D7: Режим налогообложения и текущая ставка | E7: две колонки в одну строку
D8: Ваш режим налогообложения | E8: выпадающий список | F8: select | G8: 50% | H8: Самозанятый (НПД), средняя 5% | J8: Form015 | K8: regime | L8: 7 вариантов: НПД средняя/физ/юр, УСН 6, УСН 15, АУСН 8, АУСН 20
D9: Моя ставка сейчас | E9: поле ввода | F9: input_number | G9: 52% + кнопка сброса | H9: 6 000 | I9: ₽/час | J9: — | K9: current_rate | L9: необязательное; если 0 — блок «сколько теряете» скрыт
A10: 03 | B10: Block5 | C10: 1 · О вас | D10: Как мы считаем: | E10: информационный блок, полей нет
D11: Пояснительный текст | E11: текстовый блок | F11: info_block | G11: 100% | H11: Работа на себя должна делать вашу жизнь лучше, а не превращать её в бесконечную работу. Поэтому в расчётах Счётикс мы ориентируемся на нормы трудового законодательства РФ и производственный календарь — чтобы у вас оставались силы на творчество, развитие и жизнь вне работы. | J11: — | K11: — | L11: про отпуск, больничный, эффективные часы, почему час съёмки дороже часа работы
A12: 04 | B12: Block3 + Block3a | C12: 2 · Работа | D12: Как устроена ваша работа | E12: две колонки | H12: Время — ваш главный рабочий ресурс. Три плашки: «Всё рабочее время», «Невидимая нагрузка», «Честная стоимость часа». Каждая содержит крупную иконку и короткий тезис. Под заголовком: «Посчитаем время, которое обычно остаётся невидимым».
D13: Время на постпродакшн | E13: поле ввода | F13: input_number | G13: 52% + кнопка сброса | H13: 3 | I13: × | J13: — | K13: post_ratio
D14: Работа с клиентом (на один проект) | E14: поле ввода · блок можно исключить | F14: input_number | G14: 52% + кнопка сброса | H14: 1 | I14: ч | J14: Form012 | K14: client_time
D15: Поиск заказов | E15: поле ввода · блок можно исключить | F15: input_number | G15: 52% + кнопка сброса | H15: 2 | I15: ч/день | J15: Form009 | K15: promo_per_day
D16: Минимальный выезд (часов) | E16: поле ввода | F16: input_number | G16: 52% + кнопка сброса | H16: 2 | I16: ч | J16: — | K16: shoot_duration | L16: Активно всегда. По умолчанию 2 ч — типовой заказ
D17: Готовых кадров за 1 час | E17: поле ввода | F17: input_number | G17: 52% + кнопка сброса | H17: 2 | I17: ч | J17: — | K17: shoot_manual | L17: Дублирует shoot_duration в форме. Пользователь меняет свободно
D18: Шаг изменения | E18: поле ввода | F18: input_number | G18: 50% | H18: 0,5 | I18: ч | J18: — | K18: shoot_step | L18: Шаг стрелок в поле: 0,5 ч. Минимум 0,5 ч
A19: 05 | B19: Block14a | C19: 2 · Работа | D19: Резерв на форс-мажоры | E19: галочка активирует поле
D20: Заложить время на форс-мажоры | E20: галочка | F20: checkbox | G20: 100% | H20: включена | J20: — | K20: fm_on
D21: Размер резерва | E21: поле ввода | F21: input_number | G21: 50% | H21: 5 | I21: % | J21: — | K21: fm_pct | L21: БЛОКИРУЕТСЯ, если галочка снята
A22: 06 | B22: Block6 | C22: 3 · Инвестиции | D22: Съёмочная техника | E22: динамическая таблица, 10 строк по умолчанию
D23: Не учитывать этот блок | E23: галочка | F23: checkbox | G23: авто | H23: снята | J23: Form001 | K23: use_Form001 | L23: при включении вся амортизация блока = 0
D24: Заголовки таблицы | E24: шапка | F24: table_head | G24: 100% | H24: Позиция · Стоимость ₽ · Срок лет · ₽/год | J24: Form001 | K24: —
D25: Canon EOS R6 Mark II Body | E25: строка таблицы | F25: table_row | G25: — | H25: 166 999 ₽ / 3 лет | L25: удаляется крестиком
D26: Canon RF 24–105mm f/4.0 L IS USM | E26: строка таблицы | F26: table_row | G26: — | H26: 130 999 ₽ / 5 лет | L26: удаляется крестиком
D27: Godox V1Pro C | E27: строка таблицы | F27: table_row | G27: — | H27: 36 990 ₽ / 5 лет | L27: удаляется крестиком
D28: Godox XPro II C | E28: строка таблицы | F28: table_row | G28: — | H28: 9 355 ₽ / 5 лет | L28: удаляется крестиком
D29: Аккумулятор LP-E6NH | E29: строка таблицы | F29: table_row | G29: — | H29: 12 978 ₽ / 3 лет | L29: удаляется крестиком
D30: SanDisk Extreme PRO 256 ГБ #1 | E30: строка таблицы | F30: table_row | G30: — | H30: 6 990 ₽ / 2 лет | L30: удаляется крестиком
D31: SanDisk Extreme PRO 256 ГБ #2 | E31: строка таблицы | F31: table_row | G31: — | H31: 6 990 ₽ / 2 лет | L31: удаляется крестиком
D32: Рюкзак Lowepro ProTactic | E32: строка таблицы | F32: table_row | G32: — | H32: 27 962 ₽ / 7 лет | L32: удаляется крестиком
D33: Godox RFT-05 отражатель | E33: строка таблицы | F33: table_row | G33: — | H33: 3 000 ₽ / 5 лет | L33: удаляется крестиком
D34: X-Rite ColorChecker | E34: строка таблицы | F34: table_row | G34: — | H34: 5 000 ₽ / 7 лет | L34: удаляется крестиком
D35: + Добавить позицию | E35: кнопка | F35: button_add | G35: авто | H35: — | J35: Form001 | K35: — | L35: добавляет пустую строку
D36: Итого амортизация | E36: строка итога | F36: calc_row | G36: 100% | H36: 137 893,32 | I36: ₽/год | J36: Form001 | K36: dep_shoot
A37: 07 | B37: Block7 | C37: 3 · Инвестиции | D37: Офисная техника | E37: динамическая таблица, 9 строк
D38: Не учитывать этот блок | E38: галочка | F38: checkbox | G38: авто | H38: снята | J38: Form002 | K38: use_Form002
D39: Заголовки таблицы | E39: шапка | F39: table_head | G39: 100% | H39: Позиция · Стоимость ₽ · Срок лет · ₽/год | J39: Form002 | K39: —
D40: Системный блок | E40: строка таблицы | F40: table_row | G40: — | H40: 180 000 ₽ / 5 лет | L40: удаляется крестиком
D41: Монитор ASUS ProArt | E41: строка таблицы | F41: table_row | G41: — | H41: 55 000 ₽ / 5 лет | L41: удаляется крестиком
D42: Calibrite ColorChecker | E42: строка таблицы | F42: table_row | G42: — | H42: 30 000 ₽ / 5 лет | L42: удаляется крестиком
D43: Колонки Logitech Z207 | E43: строка таблицы | F43: table_row | G43: — | H43: 5 000 ₽ / 5 лет | L43: удаляется крестиком
D44: Клавиатура Logitech K380 | E44: строка таблицы | F44: table_row | G44: — | H44: 3 500 ₽ / 7 лет | L44: удаляется крестиком
D45: Мышь Logitech M650 | E45: строка таблицы | F45: table_row | G45: — | H45: 4 000 ₽ / 3 лет | L45: удаляется крестиком
D46: Веб-камера Logitech Brio | E46: строка таблицы | F46: table_row | G46: — | H46: 15 999 ₽ / 5 лет | L46: удаляется крестиком
D47: Микрофон FIFINE K669B | E47: строка таблицы | F47: table_row | G47: — | H47: 3 500 ₽ / 5 лет | L47: удаляется крестиком
D48: Принтер Canon PIXMA G640 | E48: строка таблицы | F48: table_row | G48: — | H48: 29 999 ₽ / 5 лет | L48: удаляется крестиком
D49: + Добавить позицию | E49: кнопка | F49: button_add | G49: авто | H49: — | J49: Form002 | K49: —
D50: Итого амортизация | E50: строка итога | F50: calc_row | G50: 100% | H50: 65 732,93 | I50: ₽/год | J50: Form002 | K50: dep_office
A51: 08 | B51: Block8 | C51: 3 · Инвестиции | D51: Программное обеспечение | E51: ДВЕ таблицы в одном блоке | H51: Укажите программы и сервисы, которые нужны вам для профессиональной деятельности и работы вокруг неё.
D52: Не учитывать этот блок | E52: галочка | F52: checkbox | G52: авто | H52: снята | J52: Form003, Form004 | K52: use_Form008
D53: — Подписки (платятся регулярно) | E53: подзаголовок | F53: subhead | G53: 100% | H53: Лицензии и сервисы, за которые вы регулярно платите. | J53: Form003 | K53: —
D54: Заголовки | E54: шапка | F54: table_head | G54: 100% | H54: Позиция · Стоимость ₽ · Период · ₽/год | J54: Form003 | K54: —
D55: Adobe CC Photography | E55: строка таблицы | F55: table_row | G55: — | H55: 2 000 ₽ / Месяц | L55: удаляется крестиком
D56: Яндекс Диск 1 ТБ | E56: строка таблицы | F56: table_row | G56: — | H56: 250 ₽ / Месяц | L56: удаляется крестиком
D57: + Добавить подписку | E57: кнопка | F57: button_add | G57: авто | H57: — | J57: Form003 | K57: —
D58: Итого подписки | E58: строка итога | F58: calc_row | G58: 100% | H58: 27 000 | I58: ₽/год | J58: Form003 | K58: var_software
D59: — Разовые покупки (амортизируются) | E59: подзаголовок | F59: subhead | G59: 100% | H59: Программы и лицензии, которые вы оплачивали один раз и используете длительное время. | J59: Form004 | K59: —
D60: Заголовки | E60: шапка | F60: table_head | G60: 100% | H60: Позиция · Стоимость ₽ · Срок лет · ₽/год | J60: Form004 | K60: —
D61: Retouch4me Heal | E61: строка таблицы | F61: table_row | G61: — | H61: 6 900 ₽ / 3 лет | L61: удаляется крестиком
D62: Retouch4me Dodge & Burn | E62: строка таблицы | F62: table_row | G62: — | H62: 6 900 ₽ / 3 лет | L62: удаляется крестиком
D63: Retouch4me Fabric | E63: строка таблицы | F63: table_row | G63: — | H63: 6 900 ₽ / 3 лет | L63: удаляется крестиком
D64: Retouch4me Clean Backdrop | E64: строка таблицы | F64: table_row | G64: — | H64: 6 900 ₽ / 3 лет | L64: удаляется крестиком
D65: Retouch4me Dust | E65: строка таблицы | F65: table_row | G65: — | H65: 6 900 ₽ / 3 лет | L65: удаляется крестиком
D66: + Добавить программу | E66: кнопка | F66: button_add | G66: авто | H66: — | J66: Form004 | K66: —
D67: Итого разовые | E67: строка итога | F67: calc_row | G67: 100% | H67: 11 500 | I67: ₽/год | J67: Form004 | K67: dep_software
A68: 09 | B68: Block9 | C68: 3 · Инвестиции | D68: Рабочее место | E68: переключатель; дома аренда и коммунальные считаются по доле площади, офис — полностью
D69: Не учитывать этот блок | E69: галочка | F69: checkbox | G69: авто | H69: снята | J69: Form005, Form013 | K69: use_Form009
D70: Где вы работаете | E70: переключатель | F70: radio | G70: 100% | H70: Работаю из дома | J70: Form005 | K70: ws_mode | L70: 2 варианта: Работаю из дома / Арендую помещение
D71: Аренда или ипотека | E71: поле ввода | F71: input_number | G71: 50% | H71: 40 000; строка обязательная, без удаления | I71: ₽/мес | J71: Form005 | K71: home_rent | L71: видно только при «Работаю из дома». Берётся ПО ДОЛЕ метров
D72: Коммунальные и связь | E72: поле ввода | F72: input_number | G72: 50% | H72: 7 000; строку можно удалить | I72: ₽/мес | J72: Form005 | K72: home_util | L72: видно при «дома». Берётся ЦЕЛИКОМ
D73: Общая площадь жилья | E73: поле ввода | F73: input_number | G73: 50% | H73: 50; строку можно удалить | I73: м² | J73: Form005 | K73: home_area | L73: видно при «дома»
D74: Площадь под кабинет | E74: поле ввода | F74: input_number | G74: 50% | H74: 6; строку можно удалить | I74: м² | J74: Form005 | K74: cab_area | L74: видно при «дома»
D75: Доля кабинета | E75: расчётное поле | F75: calc_field | G75: 50% | H75: 12,00 | I75: % | J75: Form005 | K75: cab_share | L75: только чтение
D76: Стоимость помещения | E76: поле ввода | F76: input_number | G76: 50% | H76: 15 000 | I76: ₽/мес | J76: Form005 | K76: office_rent | L76: видно только при «Арендую помещение». ЦЕЛИКОМ
D77: Коммунальные и связь | E77: поле ввода | F77: input_number | G77: 50% | H77: 7 000 | I77: ₽/мес | J77: Form005 | K77: office_util | L77: видно при «аренда». ЦЕЛИКОМ
D78: — Обустройство места (мебель, ремонт) | E78: подзаголовок | F78: subhead | G78: 100% | J78: Form013 | K78: —
D79: Заголовки | E79: шапка | F79: table_head | G79: 100% | H79: Позиция · Стоимость ₽ · Срок лет · ₽/год | J79: Form013 | K79: —
D80: Мебель | E80: строка таблицы | F80: table_row | G80: — | H80: 35 000 ₽ / 7 лет | L80: удаляется крестиком
D81: Косметический ремонт | E81: строка таблицы | F81: table_row | G81: — | H81: 30 000 ₽ / 7 лет | L81: удаляется крестиком
D82: + Добавить позицию | E82: кнопка | F82: button_add | G82: авто | H82: — | J82: Form013 | K82: —
D83: Итого содержание | E83: строка итога | F83: calc_row | G83: 100% | H83: 141 600 | I83: ₽/год | J83: Form005 | K83: var_workspace
D84: Итого обустройство | E84: строка итога | F84: calc_row | G84: 100% | H84: 9 285,71 | I84: ₽/год | J84: Form013 | K84: dep_workspace
A85: 10 | B85: Block10 | C85: 3 · Инвестиции | D85: Профессиональное обучение
D86: Не учитывать этот блок | E86: галочка | F86: checkbox | G86: авто | H86: снята | J86: Form006 | K86: use_Form006
D87: Заголовки | E87: шапка | F87: table_head | G87: 100% | H87: Курс · Стоимость ₽ · Месяцев учёбы · Срок лет | J87: Form006 | K87: —
D88: Курс по фотографии | E88: строка таблицы | F88: table_row | G88: — | H88: 80 000 ₽ / 7 лет | L88: удаляется крестиком
D89: Месяцев учёбы без дохода | E89: поле ввода | F89: input_number | G89: 50% | H89: 4 | I89: мес | J89: Form006 | K89: edu_months
L90: если включена: + месяцев × желаемый доход
D91: + Добавить курс | E91: кнопка | F91: button_add | G91: авто | H91: — | J91: Form006 | K91: —
D92: Итого амортизация | E92: строка итога | F92: calc_row | G92: 100% | H92: 73 713,71 | I92: ₽/год | J92: Form006 | K92: dep_education
A93: 11 | B93: Block12 | C93: 3 · Инвестиции | D93: Создание сайта | E93: переключатель; поля зафиксированы в двухколоночной сетке
D94: Не учитывать этот блок | E94: галочка | F94: checkbox | G94: авто | H94: снята | J94: Form014 | K94: use_Form014
D95: Как появился сайт | E95: переключатель | F95: radio | G95: 100% | H95: Нанимал (а) специалиста | J95: Form014 | K95: site_mode | L95: 2 варианта: Нанимал специалиста / Делал самостоятельно
D96: Стоимость подрядчика | E96: поле ввода | F96: input_number | G96: 50% | H96: 70 000 | I96: ₽ | J96: Form014 | K96: site_cost | L96: видно при «Нанимал»
D97: Часов своими руками | E97: поле ввода | F97: input_number | G97: 50% | H97: 0 | I97: ч | J97: Form014 | K97: site_hours | L97: видно при «Делал сам». Оценивается по ПОЛНОЙ ставке рабочего часа
D98: Срок амортизации | E98: поле ввода | F98: input_number | G98: 50% | H98: 7 | I98: лет | J98: Form014 | K98: site_life
D99: Итого амортизация | E99: строка итога | F99: calc_row | G99: 100% | H99: 10 000 | I99: ₽/год | J99: Form014 | K99: dep_website
A100: 12 | B100: Block11 | C100: 4 · Расходы | D100: Реклама и продвижение | E100: динамическая таблица
D101: Не учитывать этот блок | E101: галочка | F101: checkbox | G101: авто | H101: снята | J101: Form010 | K101: use_Form010
...

Sheet 08b_UI_Отчёт
A1: 08b · UI-МАТРИЦА ОТЧЁТА — что видно бесплатно, что после оплаты
A2: Зелёный — открыто всем. Жёлтый — под размытием до оплаты.
A4: № | B4: Доступ | C4: Заголовок / элемент | D4: Тип | E4: Ширина | F4: Что показывает | G4: Параметры
A5: ПРЕДВАРИТЕЛЬНЫЙ ОТЧЁТ — видят все
A6: П1 | B6: открыто | C6: Ваша расчётная ставка | D6: report_hero | E6: 100% | F6: Крупная цифра ₽/час на зелёном градиенте | G6: real_rate
A7: П2 | B7: открыто | C7: За одну съёмку · выручка в месяц · съёмок в месяц | D7: report_row | E7: 3 колонки | F7: Три показателя в строку под главной цифрой | G7: R/projects_year, R/12, projects_year/12
A8: П3 | B8: открыто | C8: Куда уходит каждый час съёмки | D8: chart_donut | E8: 100% | F8: Одна кольцевая диаграмма, 11 сегментов, легенда справа двумя группами | G8: parts(d)
A9: П4 | B9: открыто | C9: А теперь сравните со своей зарплатой | D9: compare_box | E9: 2 колонки | F9: Хотите получать / Получаете сейчас, полоса-индикатор, разница в месяц и за год | G9: target_income/12, leftC/12
A10: П5 | B10: открыто | C10: Блок оплаты | D10: paywall | E10: 100% | F10: Иконка, заголовок, цена, две кнопки, способы оплаты, список содержимого | G10: PRICE_REF, PRICE_FULL
A12: ПОЛНЫЙ ОТЧЁТ — после оплаты
A13: О1 | B13: закрыто | C13: Три кольцевые диаграммы | D13: chart_donut × 3 | E13: 3 колонки | F13: Расчётная · Текущая · Работа в ноль. Одинаковые сегменты и цвета | G13: parts, Pc, Pb
A14: О2 | B14: закрыто | C14: За какие роли вы это заработали | D14: report_table | E14: 100% | F14: 6 строк: фотограф, ретушёр, менеджер, маркетолог, бухгалтер, компенсация. Колонки: часов в год, часов на проект, ₽ в год, ₽ с часа съёмки | G14: hr × время роли
A15: О3 | B15: закрыто | C15: Чипы над таблицей | D15: chips | E15: авто | F15: Съёмка · Проект · Съёмочных часов в год · Занято в неделю | G15: S, project_time, shooting_time
A16: О4 | B16: закрыто | C16: Что это значит | D16: expl_list | E16: 100% | F16: 6 плашек с цветным маркером слева: вам заплатят, вы заработаете, отложите, заплатите, отдадите государству, отдадите банку | G16: CO[0,6,8,9,10]
A17: О5 | B17: закрыто | C17: Сколько вы теряете | D17: warn_box | E17: 100% | F17: Красный блок: текущая ставка, остаётся на руки, крупная цифра недобора, недобор с часа, минимум без убытка | G17: miss, Rb
A18: О6 | B18: закрыто | C18: Ваша неделя | D18: chart_week | E18: 100% | F18: Сетка 5 дней × 9 часов с 10:00 до 19:00. Обед серым. Легенда цветами диаграммы | G18: perDay, CO[0..5]
A20: ПОСЛЕ ОПЛАТЫ
A21: Б1 | B21: открыто | C21: Спасибо за поддержку | D21: thanks_box | E21: 100% | F21: Зелёный блок с галочкой, текст благодарности, кнопка «Скачать PDF» | G21: появляется при ?paid=1
A22: Б2 | B22: открыто | C22: Скачать PDF | D22: button_print | E22: 420px | F22: Вызывает печать браузера. @media print скрывает форму и оставляет только отчёт | G22: window.print()

Sheet 08c_Структура_отчёта
A1: 08c · СТРУКТУРА ОТЧЁТА — что и где показывается
A2: Порядок блоков сверху вниз, как в report.html. Колонка «Показатели» — какие цифры выводятся и по какой формуле. Колонка id — техническое имя контейнера в вёрстке, по нему цифра ищется в коде.
A4: ШАПКА И ГЛАВНЫЙ ЭКРАН
A5: № | B5: Блок | C5: Тип | D5: Показатели и формулы | E5: id в вёрстке
A6: — | B6: Шапка | C6: header | D6: Заголовок, подзаголовок, дата расчёта. Логотип справа | E6: rMeta
A7: — | B7: Зелёная плашка · ставка | C7: hero | D7: Крупно: ставка часа = revenue_full / shooting_time, округлена вверх до 500. В скобках точное значение. Под ней строка: фактическая стоимость часа = target_income / (net_time + idle_time) = 747 ₽. Три показателя в строку: · Ваш доход на руки = target_income / 12 · Всего расходов = (investment + variable_costs + налоги + эквайринг) / 12 · Общая выручка = revenue_full / 12 ПРОВЕРКА: доход + расходы = выручка | E7: hRate, hRateEx, hInc, hExp, hMon
A8: — | B8: Кнопка PDF | C8: button | D8: Печать. Имя файла: ГГГГ-ММ-ДД Счётикс для фотографа | E8: dlpdf
A9: — | B9: Условия труда по ТК | C9: cond | D9: 5/2 · 28 дней отпуска · 8 часов — константы календаря | E9: condGrid
A10: — | B10: Почему этому расчёту можно верить | C10: trust | D10: 4 аргумента доверия: считали от вашего дохода · учли всё время · нормы ТК РФ · 7 налоговых режимов | E10: —
A11: БЛОКИ ПОЛНОГО ОТЧЁТА
A12: № | B12: Блок | C12: Тип | D12: Показатели и формулы | E12: id в вёрстке
A13: 01 | B13: Как распределяется бюджет | C13: donut + легенда | D13: Кольцо: 15 сегментов, в центре ставка часа. Под кольцом текст: остаётся вам / идёт на расходы. ЛЕГЕНДА, три группы: 1. Ваш доход — 5 строк ролей: съёмка, обработка, клиент, продвижение, учёт 2. Не оплачивается — простой и форс-мажоры 3. Расходы и налоги — 9 строк: техника и ПО, обучение и сайт, рабочее место, реклама, подписки, аренда, банк, налоги, эквайринг Каждая строка: ₽ с часа · % · ₽/мес. Нулевые строки скрываются. ПРОВЕРКА: сумма всех строк = ставка часа | E13: dn1, dnSum, lg1
A14: 02 | B14: Как распределяется ваше время | C14: сетка 5×8 | D14: Рабочая неделя по слотам. Расшифровка по трём группам: фотограф / владелец бизнеса / не оплачивается | E14: wk, wknote, drows
A15: 03 | B15: Как считают обычно | C15: compare | D15: Формула: текущая ставка × часы съёмки в неделю × 4. Кажется / останется на самом деле + разница | E15: calcLine, inNaive, inReal, inNaiveTx | G15: УДАЛЁН из HTML 06.08.2026: не даёт пользователю полезной информации
A16: 04 | B16: Три сценария вашей работы | C16: 3 кольца | D16: ИДЕАЛЬНЫЙ (расчётная ставка) · РЕАЛЬНЫЙ (текущая) · В НОЛЬ (безубыточность). Для каждого: доход на руки, ставка часа, выручка в месяц. Ниже блок «При съёмке в ноль» + примечание о логистике | E16: dns, bRate, bProj
A17: 05 | B17: А если брать больше заказов | C17: scenario | D17: Съёмок в месяц, часов в день, рабочих дней, выходных при текущей ставке. Жёлтая плашка-предупреждение | E17: scn
A18: 06 | B18: Как формировать скидку | C18: 4 карточки | D18: Базовая цена часа + скидки от 3, 4, 5 часов. Скидка = снижение доли накладных | E18: dmap
A19: — | B19: Два запаса (рекомендация) | C19: 2 ползунка | D19: Фонд развития (% выручки) и запас на скидку. Живой пересчёт, проверка лимита НПД. В основной расчёт НЕ входит | E19: fundPct, discPct, recTot, recWarn | G19: ПЕРЕНЕСЁН в анкету, блок 15 «Запас прочности». Ползунки + галочки
A20: 07 | B20: Ваш идеальный налоговый режим | C20: таблица | D20: 7 режимов на ОДНОЙ реальной выручке. Колонки: налоги, нагрузка, на руки, в месяц. Потолок НПД. Правило выбора Доходы vs Д−Р | E20: bestBox, npdBox, txrows, txrule
A21: 08 | B21: Сколько людей делают это в компании | C21: donut + список | D21: 5 ролей: фотограф, маркетолог, продажи, бухгалтер, администратор. Часы в неделю и % от загрузки | E21: nmDonut, nmList | G21: УДАЛЁН из HTML 06.08.2026: не нужен
A22: 09 | B22: Четыре цифры, которые стоит запомнить | C22: 4 карточки | D22: · Час вашего времени = target_income / (net_time + idle_time) · Оборудование и ПО = equip_only / цена съёмки, в съёмках · Времени на одну съёмку = project_time · Цена одного кадра = цена съёмки / (frames_out × shoot_duration) Методика — лист 09b | E22: factGrid
A23: — | B23: Заключение | C23: хук | D23: «Фотографы, вы офигели?» — подставляется расчётная ставка. Цифр в тексте больше нет | E23: finRate
A24: 10 | B24: Объясняйте клиенту, из чего складывается цена | C24: текст + 4 карточки | D24: Цитата про «потому что» (эксперимент Лангер), текст про селлеров. 4 карточки «что клиент не видит» | E24: cstA, cstB, cstC, cstD
A25: CTA | B25: 30 готовых постов | C25: плашка | D25: Контент-план. Ссылка-заглушка #plan | E25: ctaLink
A26: PMK | B26: Что входит в каждую строку | C26: памятка | D26: Расшифровка по 6 видам работ, мелким текстом | E26: pmkText
A27: — | B27: Подвал | C27: footer | D27: Знак сверху, «счётикс» под ним | E27: —
A29: ЧТО ГДЕ ПРАВИТЬ
A30: № | B30: Блок | C30: Тип | D30: Показатели и формулы | E30: id в вёрстке
B31: Текст надписи | C31: 09_Тексты | D31: Найти по ключу data-t из вёрстки, править колонку «Текст» | E31: —
B32: Цифра или формула | C32: 02_Параметры | D32: Колонка «Значение» | E32: —
B33: Методика блока 09 | C33: 09b_Методика | D33: Как посчитана каждая цифра | E33: —
B34: Цвет | C34: 09c_Палитра | D34: 68 токенов, единых для формы и отчёта | E34: —
B35: Логотип | C35: 09d_Логотип | D35: Эталон знака, менять только там | E35: —
A37: НОВЫЙ ПОРЯДОК БЛОКОВ — 06.08.2026, 17 блоков
A38: — | B38: Шапка
A39: — | B39: Плашка со ставкой
A40: — | B40: Кнопка PDF
A41: — | B41: Ваши условия труда по ТК РФ
A42: — | B42: Из чего складывается ваша цена
A43: 01 | B43: Как распределяется бюджет
A44: 02 | B44: Как распределяется ваше время
A45: 03 | B45: Ваш идеальный налоговый режим ← было 07
A46: 04 | B46: Как формировать скидку ← было 06
A47: 05 | B47: Три сценария вашей работы ← было 04
A48: 06 | B48: А если просто брать больше заказов ← было 05
A49: 07 | B49: Четыре цифры, которые стоит запомнить ← было 09
... A54: — | B54: Подвал
A56: ПОРЯДОК НА 06.08.2026 — 18 блоков
A57: — | B57: Шапка
A58: — | B58: Плашка со ставкой
A59: — | B59: Кнопка PDF
A60: — | B60: Ваши условия труда по ТК РФ
A61: — | B61: Логистика: дорога в расчёт не входит ← НОВЫЙ
A62: — | B62: Из чего складывается ваша цена
A63: 01 | B63: Как распределяется бюджет
A64: 02 | B64: Как распределяется ваше время
A65: 03 | B65: Как формировать скидку ← поднят
A66: 04 | B66: Ваш идеальный налоговый режим
A67: 05 | B67: Три сценария вашей работы
A68: 06 | B68: А если просто брать больше заказов
... A74: — | B74: Подвал
A76: ДОБАВЛЕНО 06.08.2026 — два блока в конец, перед подвалом
A77: — | B77: Справочник: что означает каждое понятие | C77: 4 раздела, 17 определений. Источник — лист 01_Глоссарий, выжимка только по тому, что есть в отчёте
A78: — | B78: Все цифры расчёта в одной таблице | C78: 6 разделов, 39 строк: время, проект, доход, расходы, налоги, ставки. Три колонки: название, значение, пояснение
A80: ПРАВКА 06.08.2026: справочник понятий занял место памятки «Что входит в каждую строку расчёта» и её оформление (.pmknote — серая подложка, строки .pi2, без колонок). Итого 19 блоков: … 30 постов · справочник · таблица цифр · подвал

Sheet 09_Тексты
A1: 09 · ТЕКСТЫ — все надписи формы и отчёта
A2: Правьте только колонку «Текст». Колонка «Где находится» показывает поверхность: Форма (шапка / вопросы / подсказки / краткий результат / оплата / опрос / подписка / превью) или Полный отчёт. Красным помечено то, что в вёрстке больше не используется — это архив, не удаляем. После правок: python3 sync_texts.py apply-all
A4: Ключ | B4: Где находится | C4: Текст
A5: Заголовок страницы
A6: h1_01 | B6: Форма · шапка | C6: Сколько на самом деле стоит ваш час | H6: УДАЛЕНО из HTML: шапка анкеты приведена к отчёту, ключ заменён на rh_01 / rh_02 / rh_03 10.08.2026
A7: Подзаголовок
A8: sub_01 | B8: Форма · шапка | C8: Калькулятор для фотографов и видеографов. Считает ставку, которая покроет не только съёмку, но и обработку, продвижение, технику и налоги. | H8: УДАЛЕНО из HTML: шапка анкеты приведена к отчёту, ключ заменён на rh_01 / rh_02 / rh_03 10.08.2026
A9: Заголовок блока
A10: h2_01 | B10: Форма · вопросы анкеты | C10: Ваш желаемый доход
A11: Вопрос
A12: q_01 | B12: Форма · вопросы анкеты | C12: Сколько вы хотите получать на руки каждый месяц?
A13: Пояснение к вопросу
A14: qd_01 | B14: Форма · вопросы анкеты | C14: Это сумма, которая остаётся вам после всех расходов и налогов. От неё считается всё остальное.
A15: Единица измерения
A16: un_01 | B16: Форма · вопросы анкеты | C16: ₽/мес
A17: Заголовок блока
A18: h2_02 | B18: Форма · вопросы анкеты | C18: Ваш налоговый режим
A19: Вопрос
A20: q_02 | B20: Форма · вопросы анкеты | C20: На каком режиме налогообложения вы работаете?
A21: Пояснение к вопросу
A22: qd_02 | B22: Форма · вопросы анкеты | C22: Выберите свой режим налогообложения или воспользуйтесь автоматическим подбором.
A23: q_02b | B23: Форма · вопросы | C23: С кем вы чаще работаете?
A24: qd_02b | B24: Форма · вопросы | C24: Если работаете и с частными лицами, и с компаниями — НПД посчитаем по усреднённой ставке 5%.
A25: Вопрос
A26: q_03 | B26: Форма · вопросы анкеты | C26: Сколько вы берёте за час съёмки сейчас? | H26: УДАЛЕНО из HTML: вопрос убран, остались заголовок и подзаголовок блока 03 — 10.08.2026
A27: Пояснение к вопросу
A28: qd_03 | B28: Форма · вопросы анкеты | C28: Нужно, чтобы показать разницу между вашей текущей и расчётной ставкой. Можно оставить пустым. | H28: УДАЛЕНО из HTML: вопрос убран, остались заголовок и подзаголовок блока 03 — 10.08.2026
A29: Единица измерения
A30: un_02 | B30: Форма · вопросы анкеты | C30: ₽/час
A31: Заголовок блока
A32: h2_03 | B32: Форма · вопросы анкеты | C32: Как мы считаем:
A33: Надпись карточки
A34: tp_01 | B34: Форма · вопросы анкеты | C34: Человеческие условия
A35: Мелкий текст карточки
A36: sm_01 | B36: Форма · вопросы анкеты | C36: Официальные нормы труда и отдыха, установленные государством.
A37: Надпись карточки
A38: tp_02 | B38: Форма · вопросы анкеты | C38: Право на отдых
A39: Мелкий текст карточки
A40: sm_02 | B40: Форма · вопросы анкеты | C40: И один больничный — чтобы спокойно восстановиться без страха потерять доход.
A41: Надпись карточки
A42: tp_03 | B42: Форма · вопросы анкеты | C42: Комфортный распорядок
A43: Мелкий текст карточки
A44: sm_03 | B44: Форма · вопросы анкеты | C44: И 8-часовой рабочий день — норма труда, установленная законом.
A45: Заголовок блока
A46: h2_04 | B46: Форма · вопросы анкеты | C46: Посчитаем ваше время | H46: УДАЛЕНО из HTML: блок 04 разбит на пять карточек, вопросы стали заголовками — 10.08.2026
A47: Пояснение под заголовком
A48: hint_01 | B48: Форма · вопросы анкеты | C48: Ваш минимальный выезд. От него считается базовая ставка часа, а всё, что длиннее, — скидка за объём | H48: УДАЛЕНО из HTML: блок 04 разбит на пять карточек, вопросы стали заголовками — 10.08.2026
A49: Вопрос
A50: q_04 | B50: Форма · вопросы анкеты | C50: Какая у вас минимальная продолжительность съёмки? | H50: УДАЛЕНО из HTML: блок 04 разбит на пять карточек, вопросы стали заголовками — 10.08.2026
A51: Пояснение к вопросу
A52: qd_04 | B52: Форма · вопросы анкеты | C52: Укажите минимальное количество съёмочных часов, ради которых вы готовы выезжать на заказ.
A53: Единица измерения
A54: un_03 | B54: Форма · вопросы анкеты | C54: часов
A55: Пояснение к вопросу
A56: qd_05 | B56: Форма · вопросы анкеты | C56: Часть времени всегда уходит впустую: клиент перенёс, погода подвела, пришлось ехать повторно.
A57: Заголовок блока
A58: h2_05 | B58: Форма · вопросы анкеты | C58: Как устроена ваша работа | H58: ОБЪЕДИНЕНО: блок 05 слит с блоком 04, заголовок взят у него 10.08.2026
A59: Вопрос
A60: q_05 | B60: Форма · вопросы анкеты | C60: Сколько часов вы тратите на обработку одного часа отснятого материала? | H60: УДАЛЕНО из HTML: блок 04 разбит на пять карточек, вопросы стали заголовками — 10.08.2026
A61: Пояснение к вопросу
A62: qd_06 | B62: Форма · вопросы анкеты | C62: Укажите, сколько времени в среднем вы тратите на подготовку материала за 1 час съёмки. Учитывайте всё время — от начала выгрузки материала на компьютер до передачи готового результата клиенту.
A63: Единица измерения
A64: un_04 | B64: Форма · вопросы анкеты | C64: часа
A65: Вопрос
A66: q_06 | B66: Форма · вопросы анкеты | C66: Сколько времени уходит на общение с клиентом по одному заказу? | H66: УДАЛЕНО из HTML: блок 04 разбит на пять карточек, вопросы стали заголовками — 10.08.2026
A67: Пояснение к вопросу
A68: qd_07 | B68: Форма · вопросы анкеты | C68: Укажите, сколько времени в среднем вы тратите на общение с клиентом и организацию одного уже подтверждённого проекта.
A69: Единица измерения
A70: un_05 | B70: Форма · вопросы анкеты | C70: часа
A71: Вопрос
A72: q_07 | B72: Форма · вопросы анкеты | C72: Сколько часов в день вы тратите на продвижение? | H72: УДАЛЕНО из HTML: блок 04 разбит на пять карточек, вопросы стали заголовками — 10.08.2026
A73: Пояснение к вопросу
A74: qd_08 | B74: Форма · вопросы анкеты | C74: Укажите, сколько времени в среднем вы тратите на поиск новых клиентов и продвижение своих услуг.
A75: Единица измерения
A76: un_06 | B76: Форма · вопросы анкеты | C76: ч/день
A77: Заголовок блока
A78: h2_06 | B78: Форма · вопросы анкеты | C78: Съёмочная техника
A79: Пояснение под заголовком
A80: hint_02 | B80: Форма · вопросы анкеты | C80: Это набор вашего базового оборудования, без которого вы просто не сможете провести съёмку. Укажите текущую рыночную стоимость и срок, за который позицию придётся заменить. Не включайте сюда специфическое оборудование, которое требуется под задачи конкретного заказчика. Его стоимость лучше сразу закладывать в смету как дополнительную аренду.
A81: Заголовок колонки
A82: th_01 | B82: Форма · вопросы анкеты | C82: Позиция
A83: th_02 | B83: Форма · вопросы | C83: Стоимость
A84: th_03 | B84: Форма · вопросы | C84: Срок службы
A85: Кнопка добавления
A86: add_01 | B86: Форма · вопросы анкеты | C86: + Добавить позицию
A87: Заголовок блока
A88: h2_07 | B88: Форма · вопросы анкеты | C88: Офисная техника
A89: Пояснение под заголовком
A90: hint_03 | B90: Форма · вопросы анкеты | C90: Это оборудование, которое помогает вам выполнять заказы и решать рабочие задачи за компьютером. Укажите его текущую рыночную стоимость и срок, через который планируете заменить.
A91: Заголовок колонки
A92: th_04 | B92: Форма · вопросы анкеты | C92: Позиция
A93: th_05 | B93: Форма · вопросы | C93: Стоимость
A94: th_06 | B94: Форма · вопросы анкеты | C94: Срок службы
A95: Кнопка добавления
A96: add_02 | B96: Форма · вопросы анкеты | C96: + Добавить позицию
A97: Заголовок блока
A98: h2_08 | B98: Форма · вопросы анкеты | C98: Программное обеспечение
A99: Подзаголовок секции
A100: sh_01 | B100: Форма · вопросы анкеты | C100: Подписки
A101: Пояснение к секции
...

Sheet 09b_Методика_цифр
A1: 09b · МЕТОДИКА — как посчитана каждая цифра отчёта
A2: Столбец «Формула» записан через ID из 02_Параметры. Правите параметр — меняется цифра в отчёте.
A4: БЛОК 09 · ЧЕТЫРЕ ЦИФРЫ, КОТОРЫЕ СТОИТ ЗАПОМНИТЬ
A5: № | B5: Показатель | C5: Значение | D5: Формула (через ID) | E5: Что означает и почему так
A6: 9.1 | B6: Час вашего времени | C6: 747 ₽/ч | D6: '=target_income/(net_time+idle_time) | E6: Желаемый доход за год делится на ВСЁ рабочее время, включая рабочие паузы: 1 307 988 / (1533+219) = 747 ₽. Не путать со ставкой часа съёмки — это то, сколько стоит любой ваш час: и с камерой, и за компьютером.
A7: 9.2 | B7: Оборудование и ПО | C7: 11,4 съёмок | D7: '=(dep_shoot+dep_office+dep_software)/(revenue_full/projects_year) | E7: Амортизация техники и ПО за год (215 126 ₽) делится на цену одной съёмки (18 934 ₽). Показывает, сколько съёмок уходит ТОЛЬКО на окупаемость техники — без налогов, рекламы и вашего дохода. Обучение и сайт сюда НЕ входят, только железо и ПО.
A8: 9.3 | B8: Времени на одну съёмку | C8: 9,0 ч | D8: '=project_time = shoot_duration*(1+post_ratio)+client_time | E8: 2 ч съёмки × (1+3 обработка) + 1 ч на клиента = 9 ч. Это полный цикл одного заказа: переписка и согласование, съёмка, отбор, цветокоррекция, ретушь, экспорт и передача.
A9: 9.4 | B9: Цена одного кадра | C9: 118 ₽ | D9: '=(revenue_full/projects_year)/(frames_out*shoot_duration) | E9: Цена съёмки (18 934 ₽) делится на количество отданных кадров (80 кадров/час × 2 ч = 160). frames_out задаёт пользователь в форме.
A11: БЛОК 04 · КУДА УХОДИТ ВАШЕ ВРЕМЯ — откуда берутся рабочие паузы
A12: № | B12: Показатель | C12: Значение | D12: Формула (через ID) | E12: Что означает и почему так
A13: 4.1 | B13: Рабочее время по календарю | C13: 1 976 ч/год | D13: '=work_days*nominal_hours = 247*8 | E13: Производственный календарь: 247 рабочих дней по 8 часов.
A14: 4.2 | B14: Чистое время | C14: 1 533 ч/год | D14: '=net_days*eff_hours = (247-20-8)*7 | E14: Минус отпуск 20 раб. дней и больничный 8 раб. дней = 219 дней. По 7 продуктивных часов.
A15: 4.3 | B15: РАБОЧИЕ ПАУЗЫ (idle) | C15: 219 ч/год = 5,0 ч/нед | D15: '=net_days*(nominal_hours-eff_hours) = 219*(8-7) | E15: РОВНО 1 ЧАС В ДЕНЬ. Это НЕ дорога и НЕ простой. Это подготовка и уборка рабочего места, зарядка и проверка техники, размяться, отойти — разбросано по всему рабочему дню. Нормальная часть рабочего процесса, поэтому включена в базу распределения дохода.
A16: 4.4 | B16: База распределения дохода | C16: 1 752 ч/год | D16: '=net_time+idle_time = 1533+219 | E16: Доход раскладывается на чистое время ПЛЮС рабочие паузы — потому что паузы оплачиваются так же, как в найме: работодатель платит за 8 часов, а не за 7.
A18: ПРОВЕРКА · сходимость
A19: № | B19: Показатель | C19: Значение | D19: Формула (через ID) | E19: Что означает и почему так
A20: П1 | B20: Сумма недели | C20: 40,00 ч | D20: '=(shooting_time+post_time+promo_time+client_total+accounting_time+fm_time+idle_time)/net_weeks | E20: Съёмка 5,2 + обработка 15,7 + продвижение 10,0 + клиент 2,6 + учёт 0,3 + форс-мажор 1,2 + паузы 5,0 = 40,00 ч. Совпадает с 5-дневной 40-часовой неделей по ТК РФ.
A22: БЛОК «ДВА ЗАПАСА» · РЕКОМЕНДАЦИИ (в основной расчёт НЕ входят)
A23: № | B23: Показатель | C23: Значение | D23: Формула (через ID) | E23: Что означает и почему так
A24: Р.1 | B24: Фонд развития, % выручки | C24: 5% (ползунок 0–15) | D24: 'задаёт пользователь в отчёте | E24: Считается от ВЫРУЧКИ, а не от прибыли. Норма реинвестирования 20–30% прибыли для соло-специалиста неприменима: прибыль здесь и есть зарплата.
A25: Р.2 | B25: Выручка с фондом | C25: 2 290 039 ₽ | D25: '=(target_income+total_costs)/(1-налог-эквайринг-g) | E25: g — доля фонда. При 5%: ставка 10 016 ₽ вместо 9 467 ₽, рост 5,8%.
A26: Р.3 | B26: Сумма фонда за год | C26: 114 502 ₽ | D26: '=выручка_с_фондом*g | E26: 9 542 ₽/мес. Это 53% годовой амортизации техники — за два года накапливается стоимость всего парка оборудования.
A27: Р.4 | B27: Запас на скидку, % | C27: 10% (ползунок 0–25) | D27: 'задаёт пользователь в отчёте | E27: Максимальная скидка, которую хочется давать «просто так», вне объёмной сетки блока 06.
A28: Р.5 | B28: Наценка под скидку | C28: +11,1% при скидке 10% | D28: '=1/(1-D)-1 | E28: ДЕЛИТЬ, а не умножать. Чтобы после скидки 10% остаться при своих, поднять надо на 11,1%. При 15% → +17,6%, при 20% → +25%.
A29: Р.6 | B29: Итоговая ставка | C29: 11 129 ₽ | D29: '=выручка_с_фондом/(1-D)/shooting_time | E29: Фонд 5% + скидка 10% дают рост цены на 17,6% относительно базовой 9 467 ₽.
A30: Р.7 | B30: Проверка лимита НПД | C30: 2 544 488 ₽ > 2 400 000 ₽ | D30: '=итоговая_выручка>limit_npd | E30: ВАЖНО: с обоими запасами выручка вылетает за лимит самозанятости. Блок показывает предупреждение, что режим из блока 07 перестаёт подходить.
A32: ОКРУГЛЕНИЕ · только крупная цифра в шапке
A33: № | B33: Показатель | C33: Значение | D33: Формула (через ID) | E33: Что означает и почему так
A34: О.1 | B34: Ставка в шапке (hero) | C34: 9 500 ₽ | D34: '=ОКРВВЕРХ(ставка;500) | E34: ЕДИНСТВЕННОЕ округление во всём отчёте. Нужно, чтобы человек воспринимал свой час цельной величиной и мог её запомнить. Только вверх — вниз округлять нельзя, доход просядет.
A35: О.2 | B35: Точное значение рядом | C35: · точно 9 467 ₽ | D35: '=revenue_full/shooting_time | E35: Выводится в подписи под крупной цифрой, серым. Показывается только если округлённое и точное различаются.
A36: О.3 | B36: Все остальные цифры | C36: без округления | D36: '— | E36: Отчёт считает юнит-экономику специалиста, а не формирует прайс для клиента. Точные значения: кольцо блока 01, три сценария, «в ноль», сетка скидок, блок «Два запаса», хук, цена съёмки, выручка, налоги, четыре цифры блока 09.
A37: О.4 | B37: Подпись под кнопкой PDF | C37: rsv_02 | D37: '— | E37: Объясняет читателю разницу: «В шапке ставка округлена до 500 ₽ — так её проще держать в голове и называть. Все расчёты в отчёте идут по точному значению, без округлений».
A44: ТОЧКА БЕЗУБЫТОЧНОСТИ — исправлено 07.08.2026
A45: Было (неверно) | B45: Vb = costY + taxAll + aq. Налог и эквайринг брались из ЦЕЛЕВОГО сценария, хотя обе величины зависят от самой выручки. Ставка завышалась: 3 835 ₽/ч.
A46: Стало | B46: Решается уравнение V − costY − V×0,028 − налог(V) = 0 для режима из анкеты. Метод — деление пополам, 90 итераций: у налога изломы (взносы, минимальный налог), аналитической формулы нет.
A47: Проверка (демо, НПД 5%) | B47: V = 722 371 ₽ = расходы 666 026 + эквайринг 20 226 + налог 36 119. Невязка нетто 1e-10 ₽. Ставка 3 335 ₽/ч.
A48: По режимам | B48: НПД 4% — 3 299 ₽/ч · НПД 5% — 3 335 · НПД 6% — 3 372 · УСН 6% — 3 457 · УСН 15% — 3 484 · АУСН 8% — 3 447 · АУСН 20% — 3 264
A49: Текущий сценарий | B49: Налог и эквайринг тоже пересчитаны по своей выручке и своему режиму. Раньше налог был жёстко зашит под УСН 6%, даже если человек на НПД.
A51: БЛОК 03 — ДВЕ ПРИРОДЫ СКИДКИ, 07.08.2026
A52: Скидка за объём | B52: Источник — накладные: длинная съёмка размазывает подготовку и переписку на большее число часов. Доход не меняется. Считается: (S×(1+K)+cl)×hp/S, ступени S+2, S+4, S+6.
A53: Скидка из запаса | B53: Источник — наценка discP, заложенная в цену в анкете. Даётся по решению фотографа, доход не меняется, пока скидка ≤ запаса. Предел: базовая цена × (1 − discP).
A54: Складываются | B54: Обе скидки независимы. Клиент на 5 ч при запасе 10%: −16,2% за объём и ещё до −10% из запаса.
A55: Если запас не заложен | B55: Показывается .note.warn: любая уступка сверх объёмной идёт из дохода. Раньше блок 03 discP не использовал вообще, хотя из анкеты он приходил.
A56: Проверка (демо, запас 10%) | B56: база 9 900 ₽/ч → предел 9 000 ₽/ч, резерв 900 ₽/ч
A58: БЛОК 03 — СЦЕНАРИЙ «КАЖДЫЙ ТРЕТИЙ ЗАКАЗ ОТ ПОСТОЯННОГО», 09.08.2026
A59: Доля 30% | B59: Отраслевая норма Repeat Purchase Rate: хорошим считается 20–40% (mindbox.ru/journal/education/retention-rate, ads.vk.ru/insights/retention-rate-chto-eto-i-kak-ego-uvelichit, rush-agency.ru). Медиана по рынку 27% (retentionlab.ai), средний 25–30%, Shopify ~27% (mobiloud.com). Unisender разбирает ровно 30% как «почти каждый третий клиент возвращается». Взята середина коридора.
A60: Почему это выгодно | B60: Привлечь нового в 5–7 раз дороже удержания (prooflytics.io). Вероятность продажи существующему 60–70%, новому 5–20% (penguin-team.ua). Около 65% выручки дают действующие клиенты (mobiloud.com, finance.mail.ru).
A61: Разбивка 40/40/20 | B61: НЕ отраслевая статистика — таких данных по частоте визитов в услугах в открытых источниках нет. Взята от собственных ступеней скидки постоянному клиенту: 2, 4 и 12 съёмок в год. В отчёте прямо названа примером распределения.
A62: Расчёт | B62: Считаем от людей и от фонда, а не от заказов. Экономия на привлечении в покрытие скидок НЕ засчитывается — она остаётся выгодой фотографа. Фонд на постоянных 169 200 ₽ распределяется полностью: 10 чел × 2 съёмки = 20 заказов (5%, 47 000 ₽) · 5 чел × 4 = 20 (7%, 65 800 ₽) · 1 чел × 12 = 12 (10%, 56 400 ₽). Итого 16 клиентов, 52 заказа, скидок ровно 169 200 ₽. Средний чек 47 000 ₽.
A63: Итог | B63: 52 из 217 заказов = 24,0% — «каждый четвёртый». Сверх скидок фотограф получает 137 540 ₽/год экономии на привлечении и 121 ч (15 рабочих дней) — в отчёте показано отдельно как чистая выгода, в бюджет скидок не входит. Прежний вариант (64 заказа, 201 160 ₽ скидок, из фонда 31 880 ₽) отменён: фонд расходовался на 19% и выглядел нерациональным.
A64: Где зафиксировано | B64: Вся структура — лист 13b_Программа_лояльности. Там же формулы сходимости: сумма трёх направлений = бюджет фонда, скидки постоянным = бюджет направления. Здесь остаются только пояснения к решениям.
A65: Доли направлений уточнены | B65: Было 25 / 45 / 30 «ровными» процентами, суммы не сходились с фондом. Стало: постоянным = сумма ступеней (169 200 ₽), спецпредложения = номинал комплекта (114 000 ₽), объём = остаток (94 626 ₽). Доли получаются 25,0 / 44,8 / 30,2%. Кольцо и полосы в блоке 03 пересчитаны.
A67: Блок 03 переведён в живой код, 09.08.2026
A68: Как считается | B68: Все цифры выводятся из анкеты. Средний чек = базовая цена съёмки (ставка часа × минимальная длительность), НЕ фиксированные 47 000 ₽. Фонд = discY из calc.html. Резерв не заложен → показывается только скидка за объём, подблоки 2 и 3 и фонд скрыты.
A69: Два ограничителя постоянных | B69: Число клиентов = min(бюджет направления 45% фонда ÷ скидка на клиента; 30% потока заказов ÷ съёмок на клиента). Без второго ограничителя при большом фонде получалось 224 постоянных заказа из 217 — больше, чем всего заказов.
A70: Сходимость | B70: Скидка за объём = фонд − постоянным − сертификаты. Остаток всегда уходит в объём, поэтому сумма трёх направлений равна фонду при любых входных данных. Проверено на резерве 5% и 15%.
A71: Заголовок сценария | B71: «Каждый второй / третий / четвёртый / пятый» выбирается по факту: делим общее число заказов на заказы постоянных. Раньше стояло жёстко «каждый третий».
A72: Полная таблица: два новых раздела, 09.08.2026
A73: Привлечение клиента | B73: Показывается всегда. Поиск, переписка, реклама с сайтом — на один заказ. Стоимость нового клиента = (поиск + переписка) × ставка часа + реклама/сайт на заказ. Постоянный = переписка × 0,70 × ставка (на 30% короче, рекламы нет).
A74: Программа лояльности | B74: Показывается только при заложенном резерве. Резерв, фонд за год / месяц / съёмку, три направления с долями, средний чек, ступени постоянного клиента, итог по клиентам и заказам, комплект сертификатов, экономия на привлечении. Все величины берутся из тех же переменных, что и блок 03, — второго расчёта нет, расхождение невозможно.
A76: Блок 07 «Сколько стоит привести одного клиента», 09.08.2026
A77: Где стоит | B77: Перед блоком «Четыре цифры». Нумерация сдвинулась: новый блок 07, «Четыре цифры» стали 08, «Объясняйте клиенту» — 09. В собрать.py ожидаемое число блоков 18 → 19.
A78: Расчёт вынесен наверх | B78: Стоимость привлечения считается ОДИН раз до всех блоков и используется в блоке 03, блоке 07 и полной таблице. Раньше формула дублировалась в двух местах — риск расхождения при правке.
A79: Состав заявки | B79: Поиск и продвижение = promo/py × ставка часа. Переговоры = clT/py × ставка. Реклама и сайт = (varAds + depSite)/py. Ставка часа = Ny/(NT+idle).
A80: Постоянный клиент | B80: Поиск и реклама не тратятся, переписка короче на 30%: постЧ = перепЧ × 0,70. На демо-наборе новый 3 168 ₽ против 523 ₽ — дешевле в 6,1 раза.
A81: Ромб врезки | B81: Подсказка .exm при незаложенном резерве остаётся пустой, но ромб-маркер продолжал рисоваться и уезжал под текст. Добавлено .ex .exm:empty{display:none}.
A82: Блок 07 переделан по эталону блока 01, 09.08.2026
A83: Диаграмма | B83: Строится теми же классами, что легенда блока 01: .lgd → .lggrp → .lgi с заливкой .fill по доле от наибольшей величины. Геометрия сверена вычисленными стилями: сетка, отступы, радиус, маркеры, кегль групп совпадают с блоком 01 полностью.
A84: Две природы затрат | B84: Как «время / деньги» в блоке 01. Группа «Ваше время»: продвижение и реклама (promo/py) + переговоры (clT/py), обе оценены по стоимости часа. Группа «Прямые расходы»: реклама (varAds/py) и сайт (depSite/py) — раздельными строками.
A85: Итог | B85: Отдельной строкой .lgi.tot в конце диаграммы, а не плашкой: плашка дублировала бы сумму, которая уже видна в сравнении.
A86: Сравнение | B86: Таблица .cmp в три столбца: показатель · новый · постоянный. Прежние плашки .cacc/.cacw убраны — они повторяли те же суммы дважды. Строки таблицы повторяют состав диаграммы один в один.
A87: Стоимость привлечения и точка безубыточности — разная природа, 09.08.2026
A88: Вопрос | B88: Стоимость привлечения 3 168 ₽ выглядела больше безубыточной цены заказа 3 335 ₽ — казалось, что вся цена уходит на рекламу.
A89: Проверка | B89: Несостыковки нет. 3 335 ₽ — цена, при которой доход НУЛЕВОЙ: время специалиста там стоит 0 ₽, покрываются только живые деньги. 3 168 ₽ — из них 912 ₽ живых денег (реклама + сайт), остальные 2 256 ₽ — время, пересчитанное по ставке 747 ₽/ч из ДОХОДА на руки. Складывать нельзя — двойной счёт.
A90: Корректное сравнение | B90: 912 ₽ живых денег на привлечение из 3 335 ₽ безубыточной цены заказа = 27%. Формулы блока 05 верны, правок не требуют.
A91: Что исправлено | B91: Подпись «и 3,0 часа вашего времени» рядом с суммой в рублях создавала путаницу: часы уже переведены в деньги. Теперь плашка показывает сумму, подзаголовок объясняет перевод, ниже разбивка «время в деньгах 2 256 ₽ / прямые расходы 912 ₽». В таблице строка «Всего вашего времени» в часах заменена на «Эквивалент вашего времени в рублях».
A92: Блок 07 — косметика сравнения, 09.08.2026
A93: Заголовок | B93: У таблицы не было названия — непонятно, что сравнивается. Добавлен заголовок «Новый клиент против постоянного» стилем .lggrp, под ним пояснение без цифр.
A94: Плашки вынесены наверх | B94: Крупные суммы (3 168 ₽ и 523 ₽) стояли в шапке таблицы, из-за чего строка заголовков была высотой с плашку. Теперь итог — две цветные плашки НАД таблицей, а таблица только обосновывает состав. Шапка стала тонкой: 11 px, отступы 10 px.
A95: Порядок | B95: Диаграмма состава → плашка итога → заголовок сравнения → две плашки → таблица обоснования. Последняя строка таблицы — эквивалент времени в рублях, суммы заявки в ней больше нет: она уже названа в плашках.
A96: Блок 07 — сравнение перестроено, 09.08.2026
A97: Порядок | B97: Плашки итога → заголовок «Новый клиент vs Постоянный» → пояснение → таблица состава. Раньше заголовок стоял над плашками.
A98: Пояснение | B98: Говорит, ЗАЧЕМ смотреть блок («сравните, во что обходится каждая заявка, чтобы решать, сколько вкладывать в привлечение, а сколько в удержание»), а не пересказывает преимущества — выводы человек видит в цифрах.
A99: Шапка таблицы | B99: Серая заливка во всю ширину убрана: плашка выглядела тяжелее самой таблицы. Остались подписи столбцов 11 px с разделительной чертой, отступы 12/8, столбцы 118 px.
A100: БАГ: высокая шапка таблицы блока 07 — найдено 09.08.2026
A101: Симптом | B101: Строка заголовков таблицы была высотой 210 px при обычной строке 43 px. Правил четыре раза, уменьшая отступы и кегль, — не помогало, потому что причина была не в них.
A102: Причина | B102: Совпадение имён классов. Я назвала ячейки шапки .cn и .cp, а .cn уже занят информационными плашками отчёта: у него min-height:210px и декоративный круг ::before 130×130. Ячейка наследовала чужую геометрию.
A103: Решение | B103: Переименованы в .cmpn1 / .cmpp1. Шапка стала 37,5 px. Проверено измерением в настоящем браузере (puppeteer): jsdom высоту не вычисляет и этот баг увидеть не мог.
A104: Урок | B104: Перед добавлением класса проверять, не занято ли имя: grep по каркасу. Короткие имена (.cn, .cp, .ch) особенно опасны.
A105: Ссылки на справочник и второй экран шапки, 09.08.2026
A106: Ссылки вместо пересказа | B106: В диаграмме блока 07 под названием статьи стоял пересказ состава («контент, рилсы, тексты»). Заменён на ссылку «что входит в статью» на соответствующий термин справочника. Определение живёт в одном месте и не расходится по блокам.
A107: Как устроено | B107: Каждому термину справочника присвоен якорь ref0..ref25 по порядку. Функция window.PHR_REF(имя) возвращает id по названию. Справочник строится раньше блока 07, поэтому ссылки резолвятся.
A108: Экран 2 — время | B108: Продолжение шапки: первый экран про деньги, второй про загрузку. Гамма голубой плашки «Условий труда» (.cn.b). Показывает число съёмок за год, общее рабочее время и разбивку: съёмка / обработка / продвижение с работой с клиентом / учёт, паузы и форс-мажоры. Каждая колонка дублируется в часах в неделю.
A109: Проверка | B109: Сумма четырёх колонок = 1752 ч = NT + idle, то есть всё рабочее время года. Часы берутся из тех же полей, что блок 02, второго расчёта нет.
A110: Блок «Стоимость привлечения» вынесен из отчёта, 09.08.2026 | B110: Ожидаемое число блоков 19 → 20.
A111: Решение | B111: Убран полностью: это маркетинг, а не юнит-экономика, и требует отдельной проработки. Код сохранён в части/07_привлечение_клиента.html — 8 частей: разметка, стили, расчёты, раздел таблицы.
A112: Что убрано из отчёта | B112: Блок 07 целиком, раздел «Привлечение клиента» из полной таблицы, строка «Сэкономлено на привлечении» из раздела программы лояльности. Нумерация вернулась: «Четыре цифры» — 07, «Объясняйте клиенту» — 08. В собрать.py 20 → 19 блоков.
A113: Что осталось | B113: Экран 2 шапки (время) и ссылки на справочник — они не про привлечение. Переменные расчёта (ставкаЧ, поискЧ, перепЧ, новР, постР) оставлены: их использует блок 03 для экономии на привлечении.
A114: Нерешённые вопросы, зафиксированы в файле | B114: 1) Часть продвижения работает на удержание, а не только на привлечение — доля не определена. 2) Переговоры считаются только по состоявшимся заказам, время на несостоявшиеся не учтено нигде. 3) Коэффициент 0,7 для постоянного клиента взят БЕЗ ИСТОЧНИКА, обсуждалась цифра 50%. Для 2 и 3 нужен вопрос в анкете: из скольких обращений выходит заказ.
A115: Отраслевые данные | B115: Конверсия заявки в сделку по рынку 5–20% (brutalmarketing.me), для услуг 5–15% (vc.ru). Данных именно по фотоуслугам не найдено.

Sheet 09c_Палитра
A1: 09c · ПАЛИТРА — единая для формы, отчёта и всех подсказок
A2: Один и тот же набор из 68 токенов объявлен в :root обоих файлов — calc.html (#phc-root) и report.html (#phr-root). Собственных hex в вёрстке нет. Исключение: фирменные цвета Visa / Mastercard / МИР в иконках оплаты — их менять нельзя.
A4: Нейтральные · текст и линии
A5: Токен CSS | B5: HEX | C5: Образец | D5: Где применяется
A6: --c-ink | B6: #1A1A1A | D6: основной текст
A7: Прочее
A8: Токен CSS | B8: HEX | C8: Образец | D8: Где применяется
A9: --c-ink2 | B9: #374151 | D9: заголовки таблиц
A10: --c-ink3 | B10: #4B5563 | D10: вторичный текст
A11: Нейтральные · текст и линии
A12: Токен CSS | B12: HEX | C12: Образец | D12: Где применяется
A13: --c-gr | B13: #6B7280 | D13: подписи
A14: Прочее
A15: Токен CSS | B15: HEX | C15: Образец | D15: Где применяется
A16: --c-gr2 | B16: #9CA3AF | D16: мелкие подписи, капс
A17: --c-gr3 | B17: #B6BCC4 | D17: самый светлый текст
A18: Нейтральные · текст и линии
A19: Токен CSS | B19: HEX | C19: Образец | D19: Где применяется
A20: --c-ln | B20: #E5E7EB | D20: линии и границы
A21: Прочее
A22: Токен CSS | B22: HEX | C22: Образец | D22: Где применяется
A23: --c-ln2 | B23: #F0F2F5 | D23: светлые разделители
A24: Нейтральные · фоны
A25: Токен CSS | B25: HEX | C25: Образец | D25: Где применяется
A26: --c-bg | B26: #F5F6F8 | D26: фон страницы
A27: --c-surf | B27: #FAFBFC | D27: фон карточек-подложек
A28: --c-white | B28: #FFFFFF | D28: фон карточек
A29: Зелёный · доход, успех, база
A30: Токен CSS | B30: HEX | C30: Образец | D30: Где применяется
A31: --c-g-50 | B31: #F5FBF7 | D31: самый светлый зелёный фон
A32: --c-g-100 | B32: #EAF6EE | D32: фон зелёных плашек
A33: --c-g-200 | B33: #D8EEDF | D33: кольца, заливки
A34: --c-g-300 | B34: #A9DDB8 | D34: сегменты диаграмм
A35: --c-g-350 | B35: #6FD183 | D35: сегменты диаграмм
A36: --c-g-400 | B36: #4FC26A | D36: градиенты
A37: --c-g-500 | B37: #21A038 | D37: основной зелёный бренда
A38: --c-g-600 | B38: #1B9331 | D38: бейдж ИДЕАЛЬНЫЙ, кнопки
A39: --c-g-700 | B39: #158026 | D39: акцентные цифры
A40: --c-g-800 | B40: #0B6B22 | D40: тёмный градиент
A41: --c-g-900 | B41: #14532D | D41: текст на зелёном фоне
A42: --c-g-mut | B42: #5C9C6C | D42: приглушённый зелёный
A43: Красный · убыток, предупреждение, скидка
A44: Токен CSS | B44: HEX | C44: Образец | D44: Где применяется
A45: --c-r-50 | B45: #FFF6F6 | D45: фон красных плашек
A46: --c-r-100 | B46: #FDE8E8 | D46: светлая заливка
A47: --c-r-200 | B47: #F7D3D3 | D47: границы
A48: --c-r-300 | B48: #E4A9A9 | D48: сегменты
A49: --c-r-400 | B49: #E8828E | D49: бейдж, акценты
A50: --c-r-500 | B50: #EF4444 | D50: сердечки, ошибки
A51: --c-r-550 | B51: #D6566A | D51: бейдж В НОЛЬ
A52: --c-r-600 | B52: #C43D51 | D52: цифры в красном
A53: --c-r-650 | B53: #D0342F | D53: плашка «Скидка»
A54: --c-r-700 | B54: #B91C1C | D54: текст предупреждений
A55: --c-r-800 | B55: #991B1B | D55: заголовки в красном
A56: --c-r-900 | B56: #7F1D1D | D56: самый тёмный красный
A57: Янтарный · внимание, знак ⚠
A58: Токен CSS | B58: HEX | C58: Образец | D58: Где применяется
A59: --c-a-50 | B59: #FFFBEF | D59: фон жёлтых плашек
A60: --c-a-100 | B60: #FEF3D6 | D60: светлая заливка
A61: --c-a-200 | B61: #FBE3AE | D61: границы
A62: --c-a-300 | B62: #F2C48A | D62: сегменты
A63: --c-a-350 | B63: #E8A05C | D63: акценты
A64: --c-a-400 | B64: #F5B301 | D64: ЗНАК ВОСКЛИЦАНИЯ (треугольник)
A65: --c-a-500 | B65: #D9762E | D65: скидка средняя
A66: --c-a-600 | B66: #C4551F | D66: скидка крупная
A67: --c-a-700 | B67: #B45309 | D67: текст
A68: --c-a-800 | B68: #92400E | D68: тёмный текст
A69: --c-a-900 | B69: #7A5309 | D69: текст на жёлтом
A70: --c-a-br | B70: #8A5C4A | D70: коричневый текст
A71: --c-a-br2 | B71: #5F3B2E | D71: тёмно-коричневый
A72: Синий · нейтральные акценты, реальный сценарий
A73: Токен CSS | B73: HEX | C73: Образец | D73: Где применяется
A74: --c-b-50 | B74: #F6FAFE | D74: фон синих плашек
A75: --c-b-100 | B75: #E7F0FA | D75: светлая заливка
A76: --c-b-200 | B76: #CFE0F3 | D76: границы
A77: --c-b-250 | B77: #B7C9E8 | D77: сегменты
A78: --c-b-300 | B78: #8FC7E8 | D78: роль маркетолога
A79: --c-b-400 | B79: #5CA8E0 | D79: градиент
A80: --c-b-500 | B80: #3B82F6 | D80: акцент
A81: --c-b-600 | B81: #2F80C4 | D81: бейдж РЕАЛЬНЫЙ
A82: --c-b-700 | B82: #2A6FAB | D82: цифры
A83: --c-b-800 | B83: #1D4ED8 | D83: иконка роста
A84: --c-b-900 | B84: #3B6398 | D84: тёмный текст
A85: --c-b-mut | B85: #7189AE | D85: приглушённый
A86: Фиолетовый · цитата, математика
A87: Токен CSS | B87: HEX | C87: Образец | D87: Где применяется
A88: --c-v-50 | B88: #F8F5FE | D88: фон блока цитаты
A89: --c-v-300 | B89: #C7B9EC | D89: сегмент
A90: --c-v-500 | B90: #8B5CF6 | D90: акцент
A91: --c-v-700 | B91: #6D3FD4 | D91: «потому что»
A92: Розовый · обработка, SMM
A93: Токен CSS | B93: HEX | C93: Образец | D93: Где применяется
A94: --c-p-50 | B94: #FFF7FB | D94: фон розовых плашек
A95: --c-p-100 | B95: #FCE7F3 | D95: иконка обработки
A96: --c-p-500 | B96: #EC4899 | D96: SMM
A97: --c-p-700 | B97: #9D174D | D97: текст обработки
A99: ПРАВИЛА
A100: • Новый цвет в вёрстку не добавляем — берём ближайший токен из этого списка.
A101: • Знак восклицания везде один: равносторонний треугольник со скруглёнными углами, заливка --c-a-400, знак белый.
A102: • Размеры знака только два: 17×16 px в тексте (класс .iwt) и 42×39 px в плашке (класс .iwt.lg).
...

Sheet 09d_Логотип
A1: 09d · ЛОГОТИП — эталон, менять только здесь
A2: Знак зафиксирован. Любая правка вёрстки должна сверяться с этим листом. Если логотип в файле отличается от кода ниже — это ошибка, привести к эталону.
A4: ПРАВИЛА — нарушать нельзя
A5: Параметр | B5: Значение | C5: Пояснение
A6: Порядок в замке | B6: надпись СЛЕВА, знак СПРАВА | C6: Во всех местах обоих файлов: шапка отчёта, шапка формы, подвалы.
A7: Зелёный элемент | B7: ПРАВЫЙ ромб | C7: Крайний правый. Не нижний, не верхний. Фиксировано, не меняется при прокрутке.
A8: Цвет зелёного | B8: var(--c-g-500) = #21A038 | C8: Основной зелёный бренда из листа 09c. Другие оттенки не использовать.
A9: Цвет серых | B9: var(--c-ln) = #E5E7EB | C9: Три остальных ромба. В подвале те же цвета, гасится прозрачностью .55.
A10: Анимация | B10: ЗАПРЕЩЕНА | C10: Знак статичен. Подсветка «активного юнита» по прокрутке была удалена — из-за неё логотип менялся на каждом экране.
A12: ГЕОМЕТРИЯ · viewBox 32 × 32
A13: Параметр | B13: Значение | C13: Пояснение
A14: Сторона квадрата | B14: 10,10 | C14: Замерено по макету заказчика попиксельно.
A15: Смещение от центра | B15: 8,86 | C15: Отношение к габариту ромба 0,62 — даёт воздушный зазор.
A16: Скругление rx | B16: 1,90 | C16: 19% стороны.
A17: Поворот | B17: rotate(45) | C17: Вокруг центра каждого квадрата.
A18: Размеры вывода | B18: 46 px шапка · 20 px подвал | C18: Меняется только атрибут width/height, геометрия не трогается.
A20: ТИПОГРАФИКА
A21: Элемент | B21: Значение | C21: Пояснение
A22: Название | B22: счётикс | C22: Строчными. 19 px, вес 700, разрядка .11em, цвет --c-ink.
A23: Подпись | B23: твоя юнит-экономика | C23: 9 px, --c-gr2, растянута по ширине названия через space-between (каждая буква в теге i).
A24: Подвал | B24: счётикс | C24: 12 px, вес 700, --c-gr, прозрачность блока .55.
A25: Зазор знак↔текст | B25: 12 px шапка · 7 px подвал
A27: ИСХОДНЫЙ КОД — копировать отсюда
A28: Что | B28: Где применяется | C28: Код
A29: Знак | B29: шапка (class=bx) | C29: <svg class="bx" viewBox="0 0 32 32" fill="none" aria-hidden="true"><rect x="10.95" y="2.09" width="10.10" height="10.10" rx="1.90" transform="rotate(45 16 7.14)" fill="var(--c-ln)"/><rect x="19.81" y="10.95" width="10.10" height="10.10" rx="1.90" transform="rotate(45 24.86 16)" fill="var(--c-g-500)"/><rect x="10.95" y="19.81" width="10.10" height="10.10" rx="1.90" transform="rotate(45 16 24.86)" fill="var(--c-ln)"/><rect x="2.09" y="10.95" width="10.10" height="10.10" rx="1.90" transform="rotate(45 7.14 16)" fill="var(--c-ln)"/></svg>
A30: Замок целиком | B30: шапка отчёта и формы | C30: <div class="brand" title="Счётикс — твоя юнит-экономика"><span class="btx"><span class="bt">счётикс</span><span class="bd" data-t="bt_02"><i>т</i><i>в</i><i>о</i><i>я</i><i>&nbsp;</i><i>ю</i><i>н</i><i>и</i><i>т</i><i>-</i><i>э</i><i>к</i><i>о</i><i>н</i><i>о</i><i>м</i><i>и</i><i>к</i><i>а</i></span></span><svg class="bx" viewBox="0 0 32 32" fill="none" aria-hidden="true"><rect x="10.95" y="2.09" width="10.10" height="10.10" rx="1.90" transform="rotate(45 16 7.14)" fill="var(--c-ln)"/><rect x="19.81" y="10.95" width="10.10" height="10.10" rx="1.90" transform="rotate(45 24.86 16)" fill="var(--c-g-500)"/><rect x="10.95" y="19.81" width="10.10" height="10.10" rx="1.90" transform="rotate(45 16 24.86)" fill="var(--c-ln)"/><rect x="2.09" y="10.95" width="10.10" height="10.10" rx="1.90" transform="rotate(45 7.14 16)" fill="var(--c-ln)"/></svg></div>
A31: Подвал | B31: низ обоих файлов | C31: <span class="lgs" title="Счётикс — твоя юнит-экономика"><span class="lt">счётикс</span><svg class="lx" viewBox="0 0 32 32" fill="none" aria-hidden="true"><rect x="10.95" y="2.09" width="10.10" height="10.10" rx="1.90" transform="rotate(45 16 7.14)" fill="var(--c-ln)"/><rect x="19.81" y="10.95" width="10.10" height="10.10" rx="1.90" transform="rotate(45 24.86 16)" fill="var(--c-g-500)"/><rect x="10.95" y="19.81" width="10.10" height="10.10" rx="1.90" transform="rotate(45 16 24.86)" fill="var(--c-ln)"/><rect x="2.09" y="10.95" width="10.10" height="10.10" rx="1.90" transform="rotate(45 7.14 16)" fill="var(--c-ln)"/></svg></span></span>
A33: ПРОВЕРКА ПОСЛЕ ЛЮБОЙ ПРАВКИ
A34: • В обоих файлах ровно один зелёный ромб на знак, атрибут x="19.81".
A35: • Порядок дочерних элементов: сначала span с текстом, потом svg.
A36: • В коде нет классов u-inc / u-exp / u-res / u-prof — это следы удалённой анимации.
A37: • В CSS нет правил .bx .u и .lx .u — цвет задаётся прямо в атрибутах fill.
A38: • Фоновые знаки в блоке 01 тоже с зелёным справа.
A40: ВЕРТИКАЛЬНЫЙ ВАРИАНТ · подвал
A41: • В подвале обоих файлов знак стоит СВЕРХУ, надпись «счётикс» — под ним.
A42: • Знак 26 px, надпись 11 px с разрядкой .17em, цвет --c-gr2, прозрачность блока .6.
A43: • Горизонтальный вариант (надпись слева, знак справа) — только в шапке.
A44: • Причина: в подвале мало места по ширине, горизонтальный замок расползался.
A46: ФОНОВАЯ ГРАФИКА
... A51: ФИРМЕННАЯ ГРАФИКА — три элемента, других не добавляем
A52: Элемент | B52: Где применяется | C52: Как задан
A53: 1. Знак — четыре ромба | B53: Шапка и подвал обоих файлов. Фон блока 01 (три размера). Фон зелёной плашки, белым 7%. Фон блока «Почему можно верить», зелёным 5%. | C53: <svg viewBox='0 0 32 32'> + 4 rect, геометрия из раздела выше
A54: 2. Камера — контур | B54: Фон блока 01 (справа сверху, 92px). Фон зелёной плашки (справа сверху, белым 9%). Обозначает нишу: для другой профессии меняется на свою иконку. | C54: <rect> корпус + <path> выступ + 2 <circle> объектив, stroke-width 1–1.1
A55: 3. Круг — мягкое пятно | B55: Плашки условий труда: right:-30px, top:-30px, 130×130, белый 10%. Фон блока 01: два больших круга 320 и 340px, заливка --c-g-50 и --c-b-50. | C55: border-radius:50% + background:rgba(255,255,255,.10) или <circle> с заливкой из палитры
A57: • Прозрачность фоновой графики: 5–13%. Она должна читаться только если присматриваться.
A58: • Цвета — строго из палитры 09c. На цветных подложках белый с прозрачностью.
A59: • Абстрактных иконок (часы, стрелки, звёзды, диафрагма) больше не используем — только эти три элемента.
A60: • Диафрагма объектива была удалена с зелёной плашки: читалась как посторонний символ.
A62: ЦВЕТ ЗНАКА ЗАВИСИТ ОТ ФОНА
A63: • На белом фоне серые ромбы — var(--c-ln) #E5E7EB.
A64: • На сером фоне страницы (--c-bg #F5F6F8) — var(--c-gr3) #B6BCC4, иначе знак сливается: контраст 1,14 против 1,77.
A65: • Зелёный ромб всегда var(--c-g-500), контраст к обоим фонам достаточный.
A67: ЗНАЧКИ В ТЕКСТЕ
A68: • В текстовых блоках используем системные эмодзи: ⚠️ «важно», ☝️ «внимание».
A69: • Векторный треугольник остаётся только в плашках-предупреждениях (классы .iwt, .scwarn).
A70: • Эмодзи ставим в <span class="wic">, размер 17px, ширина колонки 22px.
A72: ПОДВАЛ — обновлено 06.08.2026
A73: Конструкция | C73: Та же, что в шапке: надпись СЛЕВА, знак СПРАВА
A74: Знак | C74: 46 px (в шапке 62 px)
A75: «счётикс» | C75: 14 px, --c-ink, letter-spacing .11em (в шапке 19 px)
A76: «твоя юнит-экономика» | C76: 6,6 px, растянута через space-between (в шапке 9 px)
A77: Серые ромбы | C77: --c-gr3, не --c-ln: на сером фоне контраст 1,77 против 1,14
A78: Зелёный ромб | C78: правый, x=19.81 — как везде

Sheet 09e_Как_считается
A1: 09e · КАК СЧИТАЕТСЯ СТОИМОСТЬ ЧАСА СЪЁМКИ
A2: Полная цепочка расчёта по шагам — ровно так, как считает калькулятор. Все ID в колонке «Формула» ссылаются на лист 02_Параметры. Цифры в колонке «Результат» — для демо-набора (доход 108 999 ₽/мес, съёмка 2 ч, обработка ×3).
A4: № | B4: Что считаем | C4: Как считаем — словами | D4: Формула (ID) | E4: Результат
A5: 1 | B5: Рабочие дни за вычетом отпуска и больничного | C5: Берём производственный календарь — 247 рабочих дней. Вычитаем отпуск 20 рабочих дней (28 календарных по ТК РФ) и больничный 8 рабочих дней (10 календарных). Столько дней вы действительно на работе. | D5: net_days = work_days − vacation_work − sick_work | E5: 247 − 20 − 8 = 219 дней
A6: 2 | B6: Чистое рабочее время в часах | C6: Номинальный день 8 часов, но продуктивных из них 7. Восьмой час уходит на подготовку и уборку рабочего места, зарядку и проверку техники, разминку и паузы — он размазан по всему дню и в проектное время не попадает. | D6: net_time = net_days × eff_hours | E6: 219 × 7 = 1 533 часа
A7: 3 | B7: Вычитаем операционное время | C7: Продвижение — 2 часа в день: съёмка контента, монтаж рилсов, тексты постов, ответы в директ, настройка рекламы. Учёт и отчётность — 3 часа в квартал. Это работа, но она не привязана к конкретному заказу. | D7: side_time = promo_time + accounting_time pool_gross = net_time − side_time | E7: продвижение 438 ч учёт 12 ч 1533 − 450 = 1 083 часа
A8: 4 | B8: Откладываем резерв на форс-мажоры | C8: 5% времени уходит на переносы, отмены, повторные выезды по вине клиента. Это время вы тратите, но денег за него не получаете, поэтому убираем его из фонда, доступного под заказы. | D8: fm_time = pool_gross × fm_pct project_pool = pool_gross − fm_time | E8: 1083 × 5% = 54,15 ч 1083 − 54,15 = 1 028,85 часа
A9: 5 | B9: Считаем, сколько часов съедает один заказ | C9: Пользователь задаёт три величины: типовая длительность съёмки (2 ч), сколько часов обработки приходится на час съёмки (3), сколько времени уходит на переписку и согласование одного заказа (1 ч). Полный цикл заказа складывается из них. | D9: project_time = shoot_duration × (1 + post_ratio) + client_time | E9: 2 × (1+3) + 1 = 9 часов
A10: 6 | B10: Сколько заказов помещается в год | C10: Делим доступное проектное время на длительность одного заказа. Дробное число — это нормально: часть заказа переходит на следующий период. | D10: projects_year = project_pool / project_time | E10: 1028,85 / 9 = 114,32 заказа
A11: 7 | B11: Сколько из них — ОПЛАЧИВАЕМЫЕ часы съёмки | C11: КЛЮЧЕВОЙ ШАГ. Клиент покупает только часы на площадке. Обработка, переписка, продвижение и паузы в его счёт не попадают. Из 1 752 часов вашей работы в году продаётся только 229 — это 13%. | D11: shooting_time = projects_year × shoot_duration | E11: 114,32 × 2 = 228,63 часа
A12: 8 | B12: Сколько денег нужно собрать за год | C12: Складываем желаемый доход на руки и все расходы бизнеса: амортизацию техники, офиса, ПО, обучения и сайта плюс переменные — рекламу, подписки, аренду, банк. | D12: target_income = income_month × 12 total_costs = investment + variable_costs | E12: 1 307 988 ₽ доход 666 026 ₽ расходы
A13: 9 | B13: Раскручиваем выручку назад через налоги | C13: Здесь нельзя просто сложить доход и расходы. С выручки ещё уйдёт налог по вашему режиму и комиссия банка за приём платежей. Поэтому мы ДЕЛИМ нужную сумму на оставшуюся долю — так получается выручка, из которой после всех вычетов останется ровно желаемый доход. | D13: R = (target_income + total_costs) / (1 − acquiring − rate_current) | E13: (1 307 988 + 666 026) / (1 − 0,028 − 0,06) = 2 164 489 ₽
A14: 10 | B14: Делим выручку на оплачиваемые часы | C14: Вся годовая выручка должна собраться с тех самых 229 съёмочных часов, потому что больше клиент ничего не покупает. Это и есть ставка часа. | D14: СТАВКА = R / shooting_time | E14: 2 164 489 / 228,63 = 9 467 ₽/час
A16: ПРОВЕРКА — сходится ли
B17: Выручка минус всё | C17: 2 164 489 − 666 026 расходов − 60 606 эквайринга − 129 869 налога | D17: '= 1 307 988 ₽ | E17: совпало с желаемым доходом
B18: Легенда блока 01 | C18: сумма всех 15 строк | D18: '= 9 467 ₽ | E18: совпало со ставкой часа
B19: Шапка отчёта | C19: 108 999 доход + 71 375 расходы | D19: '= 180 374 ₽ | E19: совпало с выручкой в месяц
A21: ДВЕ РАЗНЫЕ СТАВКИ — не путать
B22: Ставка за час съёмки | C22: Цена в прайсе. Её платит клиент за час вашего присутствия на площадке. | D22: R / shooting_time | E22: 9 467 ₽
B23: Фактическая стоимость часа | C23: Сколько вы реально зарабатываете за час ЛЮБОЙ работы — с камерой или за компьютером. | D23: target_income / (net_time + idle_time) | E23: 747 ₽
B24: Разница в 12,7 раза возникает по двум причинам сразу: оплачивается только 13% рабочего времени (229 часов съёмки из 1 752), и ещё 40% выручки уходит на расходы и налоги.

Sheet 09f_Группы_затрат
A1: 09f · ГРУППЫ ЗАТРАТ — основа для всех диаграмм
A2: Единая группировка. Все графики отчёта строятся на этих группах. Добавляете новый расход — определяете, в какую группу он идёт.
A4: ВРЕМЯ · 6 групп
A5: Всего 1 752 ч/год = 40 ч/нед. Проверка: сумма групп = норма рабочей недели
A6: № | B6: Группа | C6: Что входит | D6: Параметры (ID) | E6: Значение
A7: 1 | B7: Съёмка на площадке | C7: Часы с камерой. ЕДИНСТВЕННОЕ, что оплачивает клиент | D7: shooting_time | E7: 228,6 ч/год · 5,2 ч/нед
A8: 2 | B8: Обработка материала | C8: Отбор, кадрирование, цвет, ретушь, экспорт, заливка в облако, правки | D8: post_time | E8: 685,9 ч/год · 15,7 ч/нед
A9: 3 | B9: Продвижение и поиск заказов | C9: Контент, рилсы, тексты, реклама, директ, портфолио, отзывы | D9: promo_time | E9: 438 ч/год · 10,0 ч/нед
A10: 4 | B10: Работа с клиентом | C10: Переписка, согласование даты и референсов, договор, предоплата | D10: client_total | E10: 114,3 ч/год · 2,6 ч/нед
A11: 5 | B11: Учёт и отчётность | C11: Чеки, декларации, взносы по срокам, книга учёта | D11: accounting_time | E11: 12 ч/год · 0,3 ч/нед
A12: 6 | B12: Рабочие паузы и форс-мажоры | C12: Подготовка места, зарядка техники, разминка, переносы, отмены | D12: idle_time + fm_time | E12: 273,2 ч/год · 6,2 ч/нед
A14: ДЕНЬГИ · 8 групп
A15: Всего 856 500 ₽/год = 71 375 ₽/мес. Проверка: сумма групп = строка «Всего расходов» в шапке
A16: № | B16: Группа | C16: Что входит | D16: Параметры (ID) | E16: Значение
A17: 1 | B17: Съёмочная техника | C17: Камера, оптика, свет, синхронизаторы, карты, сумки, аккумуляторы | D17: dep_shoot (Form001) | E17: 137 893 ₽/год · 11 491 ₽/мес
A18: 2 | B18: Компьютер и рабочее место | C18: Системный блок, монитор, периферия, мебель, ремонт | D18: dep_office + dep_workspace | E18: 75 019 ₽/год · 6 252 ₽/мес
A19: 3 | B19: Программное обеспечение | C19: Плагины разово (Form004) плюс подписки помесячно (Form003) | D19: dep_software + var_software | E19: 45 100 ₽/год · 3 758 ₽/мес
A20: 4 | B20: Обучение и сайт | C20: Курсы и сайт, разложенные по сроку амортизации | D20: dep_education + dep_website | E20: 83 714 ₽/год · 6 976 ₽/мес
A21: 5 | B21: Реклама и продвижение | C21: Директ, таргет, размещения у блогеров, домен и хостинг | D21: var_ads (Form010) | E21: 295 000 ₽/год · 24 583 ₽/мес
A22: 6 | B22: Аренда и связь | C22: Помещение или доля квартиры, коммунальные, РКО, СМС | D22: var_workspace + var_bank | E22: 29 300 ₽/год · 2 442 ₽/мес
A23: 7 | B23: Налоги и взносы | C23: По выбранному режиму, вместе со страховыми взносами ИП | D23: taxAll (05_Расчёт) | E23: 129 869 ₽/год · 10 822 ₽/мес
A24: 8 | B24: Банковский эквайринг | C24: Комиссия 2,8% с каждого поступления | D24: acquiring | E24: 60 606 ₽/год · 5 050 ₽/мес
A26: ПРАВИЛА
A27: • Новый расход — сначала определяем группу, потом добавляем в 03_Каталоги с нужным кодом формы.
A28: • Группы не пересекаются: каждый рубль и каждый час попадает ровно в одну.
A29: • Диаграммы блока 01 и блока 05 строятся на этих же группах — при изменении списка правим и там.
A30: • Строки с нулевым значением в отчёте скрываются автоматически.

Sheet 09g_Сокращения
A1: 09g · СОКРАЩЕНИЯ — единый стандарт для книги, calc.html и report.html
A2: Правило: составные единицы пишем через слэш, без пробелов вокруг. Между числом и единицей — неразрывный пробел. Знак ₽ после числа.
A4: ЕДИНИЦЫ ИЗМЕРЕНИЯ
A5: Смысл | B5: ПИШЕМ ТАК | C5: НЕ пишем | D5: Пример | E5: Где применяется
A6: Деньги за час | B6: ₽/ч | C6: ₽ в час · ₽/час · руб/ч | D6: 747 ₽/ч | E6: ставка, легенда, итог
A7: Деньги в месяц | B7: ₽/мес | C7: ₽ в месяц · ₽ в мес | D7: 71 375 ₽/мес | E7: расходы, формы
A8: Деньги в год | B8: ₽/год | C8: ₽ в год | D8: 856 500 ₽/год | E8: расходы, группы затрат
A9: Деньги за проект | B9: ₽/проект | C9: ₽ за проект | D9: 18 934 ₽/проект | E9: сценарии
A10: Часы в год | B10: ч/год | C10: часов в год · ч в год | D10: 228,6 ч/год | E10: легенда, время
A11: Часы в неделю | B11: ч/нед | C11: часов в неделю | D11: 5,2 ч/нед | E11: неделя, группы
A12: Часы в день | B12: ч/день | C12: часов в день | D12: 8 ч/день | E12: условия труда
A13: Часы (просто) | B13: ч | C13: часа · часов | D13: 7,7 ч | E13: итог под кольцом
A14: Дни в году | B14: дн/год | C14: дней в году | D14: 219 дн/год | E14: условия труда
A15: Проценты | B15: % | C15: процентов | D15: 2,8 % | E15: налоги, эквайринг
A16: Штуки | B16: шт | C16: штук | D16: 80 шт | E16: кадры
A18: ЧИСЛА И ЗНАКИ
A19: Что | B19: ПИШЕМ ТАК | C19: НЕ пишем | D19: Пример | E19: Примечание
A20: Разряды | B20: пробел | C20: запятая · точка | D20: 2 164 489 | E20: неразрывный пробел
A21: Дробная часть | B21: запятая | C21: точка | D21: 7,7 · 228,6 | E21: одна цифра после запятой
A22: Рубли в тексте | B22: ₽ | C22: руб. · р. · rub | D22: 9 467 ₽ | E22: знак после числа
A23: Тире между словами | B23: — | C23: - · – | D23: Как фотограф — съёмка | E23: длинное тире с пробелами
A24: Диапазон | B24: – | C24: - · — | D24: 5–7 ч | E24: короткое тире без пробелов
A25: Округление | B25: до рубля | C25: до сотен | D25: 9 467 ₽ | E25: кроме крупной цифры в шапке
A26: ПОДПИСИ МЕТРИК
A27: Что
A28: Сумма за период | B28: Налоги и взносы / год | C28: Налоги и взносы за год
A29: Сумма в месяц | B29: Налоги и взносы / мес | C29: В месяц государству
A30: Количество за период | B30: Проектов / год · Съёмок / мес | C30: Проектов в год · Съёмок в месяц
A31: Выручка | B31: Расчётная выручка / год | C31: Ваша расчётная выручка
A32: Где НЕ применяем | B32: в связном тексте: «платятся даже в месяцы без заказов»
A34: Правило одно на все три файла. Появилась новая единица — сначала строка здесь, потом в вёрстку.

Sheet 09h_Элементы
A1: 09h · ПОВТОРЯЮЩИЕСЯ ЭЛЕМЕНТЫ — единый стиль для всех документов
A2: Одна сущность — один класс. Появился похожий элемент — сначала строка здесь, потом вёрстка. Свои hex запрещены, только токены палитры 09c.
A4: ЗНАЧОК В КРУЖКЕ — общая геометрия
A5: Параметр | B5: Значение | C5: Примечание
A6: диаметр | B6: 18 px | C6: одинаков во всех документах
A7: скругление | B7: 50% | C7: идеальный круг
A8: размер знака | B8: 11 px | C8: font-weight 700
A9: выравнивание | B9: flex, по центру | C9: align-items и justify-content center
A10: отступ до текста | B10: 10 px | C10: padding-left у блока текста
A11: положение | B11: absolute, left 0 | C11: верх выровнен по первой строке
A13: ВИДЫ ЗНАЧКА
A14: Класс | B14: Знак | C14: Кружок | D14: Знак — цвет | E14: Когда применяем
A15: .ic.warn | B15: ! | C15: --c-a-400 | D15: --c-white | E15: предупреждение: что будет, если не сделать
A16: .ic.info | B16: i | C16: --c-b-400 | D16: --c-white | E16: важное пояснение, без тревоги
A17: .ic.ok | B17: ✓ | C17: --c-g-500 | D17: --c-white | E17: подтверждение, лучший вариант
A18: .ic.tip | B18: ? | C18: --c-ln | D18: --c-gr | E18: подсказка при наведении, у поля ввода
A20: БЛОКИ-ПРИМЕЧАНИЯ
A21: Класс | B21: Размер | C21: Цвет текста | D21: Фон и рамка | E21: Когда применяем
A22: .note | B22: 13 px | C22: --c-gr | D22: нет | E22: нейтральное пояснение под блоком
A23: .note.sm | B23: 12 px | C23: --c-gr2 | D23: нет | E23: мелкая сноска под строкой
A24: .note.warn | B24: 13 px | C24: --c-a-800 | D24: фон --c-a-50, рамка 1px dashed --c-a-300 | E24: предупреждение о последствиях
A25: .note.info | B25: 13 px | C25: --c-b-800 | D25: фон --c-b-50, рамка 1px solid --c-b-200 | E25: важное пояснение
A26: .note.ok | B26: 13 px | C26: --c-g-800 | D26: фон --c-g-50, рамка 1px solid --c-g-200 | E26: подтверждение, всё верно
A27: .note.plain | B27: 13 px | C27: --c-gr | D27: фон --c-surf, без рамки | E27: длинная методическая сноска
A29: ЧТО ЗАМЕНЯЕТ — старые классы, переводим постепенно
A30: Старый класс | B30: Было | C30: Станет | D30: Блок | E30: Статус
A31: .lgwarn | B31: 13 px, кружок 14 px --c-a-400 | C31: .note.warn | D31: 01 | E31: переведён
A32: .lognote | B32: 13 px, кружок 20 px --c-a-200 | C32: .note.warn | D32: 09 | E32: ждёт
A33: .lgnote | B33: 12,5 px --c-gr2 | C33: .note | D33: 01 | E33: переведён
A34: .lgsub | B34: 12,5 px --c-gr2 | C34: .note.sm | D34: 01 | E34: переведён
A35: .recbm | B35: 12,5 px --c-gr | C35: .note | D35: cardRec | E35: ждёт
A36: .dnote2 | B36: 12,5 px --c-gr2 | C36: .note.sm | D36: — | E36: ждёт
A37: .dnote3 | B37: 13 px --c-gr, фон --c-surf | C37: .note.plain | D37: — | E37: ждёт
A38: .wknote | B38: 14,5 px --c-ink2, фон #fff | C38: рамка 1.5px, радиус --r, градиент, левое поле 65px | D38: 02 | E38: Блок 02. Текст начинается там же, где плашки дней: 58px (колонка часов) + 7px (зазор сетки) = 65px. Отступ карточки прибавлять НЕ нужно — плашка уже внутри неё. Знак «Счётикс»: 150px, left −58px, top −58px, прозрачность 6%, уходит в левый верхний угол под градиент, текст не перекрывает. Знак рисуется в JS вместе с текстом — innerHTML затирает разметку
A39: .tip (calc) | B39: кружок 17 px | C39: .ic.tip | D39: анкета | E39: ждёт
A41: ПРАВИЛО ПЕРЕВОДА: старые классы не трогаем скопом. Блок переводится на новую систему тогда, когда мы этот блок и так правим. Когда все переведены — старые правила удаляются одной операцией со сверкой «пропавшие селекторы = только удаляемые».
A43: .saletag | B43: Стикер «Скидка» | C43: абсолют, по центру над блоком | D43: --c-r-500, белый текст | E43: Блок 03. Отступ карточки сверху 48 px — втрое больше обычного. Плашка: left 50%, top −28 px, translateX(−50%), без наклона. Выходит за верхнюю границу, до предыдущего блока остаётся 20 px. Карточке нужен overflow:visible. Заголовок и описание по центру
A45: .cn.s1/.s2/.s3 | B45: Плашка со статистикой | C45: форма из .cn | D45: лайм · мандарин · малина | E45: Блок 08. Та же геометрия, что «Условия труда»: радиус --r, padding 28/26, min-height 210, круг-блик в углу. Отличаются только градиентом
A47: ПОВЕДЕНИЕ КНОПОК — единое во всех документах
A48: Состояние | B48: Что происходит | C48: Как задано | E48: Правило
A49: обычное | B49: — | C49: — | E49: базовый вид кнопки
A50: :hover | B50: фон темнеет на ступень | C50: background --c-g-50 / --gd, либо filter brightness(.94) | E50: только цвет, размер и положение не меняются
A51: :active | B51: слегка утапливается | C51: translateY(1px) + фон ещё темнее | E51: ощущение нажатия, сдвиг ровно 1 px
A52: запрещено | B52: подпрыгивание, разлетающаяся тень, вращение | C52: translateY(-2px), scale, rotate | E52: никаких сложных анимаций на кнопках
A54: Исключение: сердечко в опросе анкеты — не кнопка действия, а реакция. Допустимо scale(1.06), не больше.
A56: КОММЕНТАРИЙ-ФЛАЖОК — вместо полоски слева
A57: .ex | B57: комментарий в карточке | C57: рамка 1.5px, радиус --r, радиальный градиент сверху | E57: то же устройство, что у плашки дохода .dnsum. Цвета: --exb рамка, --exg подложка
A58: .wknote | B58: комментарий под календарём | C58: рамка 1.5px, радиус --r, градиент, левое поле 65px | E58: Блок 02. Текст начинается там же, где плашки дней: 58px (колонка часов) + 7px (зазор сетки) = 65px. Отступ карточки прибавлять НЕ нужно — плашка уже внутри неё. Знак «Счётикс»: 150px, left −58px, top −58px, прозрачность 6%, уходит в левый верхний угол под градиент, текст не перекрывает. Знак рисуется в JS вместе с текстом — innerHTML затирает разметку
A59: --exb / --exg | B59: цвет рамки и подложки | C59: инлайн: style="--exb:var(--c-v-300);--exg:var(--c-v-50)" | E59: по умолчанию --c-g-200 и --c-g-50
A61: Пояснительные плашки в блоках 02 и 03 оформлены так же, как «Ваш доход на руки»: лёгкая рамка 1,5 px, радиус --r и мягкий радиальный градиент от верхнего края. Полосок-флажков и явных границ слева больше нет.
A63: БЛОК 07 «ЧЕТЫРЕ ЦИФРЫ» — сетка изменена 07.08.2026
A64: Было | B64: Крест 3×3: плашка сверху, справа, снизу, слева, знак «Счётикс» в середине. На широком экране по бокам оставалось много пустого поля.
A65: Стало | B65: Сетка 2×2 на всех ширинах — та же раскладка, что раньше была только на узком экране. Знак из середины убран (.fgmk и FGMK удалены).
A67: БЛОК 05 — ДОРАБОТКА 07.08.2026
A68: .scn3 тени | B68: box-shadow 0 10px 26px rgba(16,24,40,.09) + 0 2px 6px; на наведении глубже и подъём на 2px
A69: .scdeco | B69: Фоновый круг в правом верхнем углу — тот же приём, что .cn:before и .npd .g div:before: сплошной круг 130px, right/top -30px. Отдельный слой с overflow:hidden внутри .scn3, сам .scn3 обрезать нельзя (метка .nm3 выше края).
A70: .mbsc | B70: Схема безубыточности: две чаши весов «Пришло от клиентов» = «Ушло на работу», между ними знак =. Зелёная и янтарная подложки. | H70: ОТКАЧЕНО 07.08.2026: плашка возвращена к прежнему виду
A71: .mbres | B71: Итог схемы — янтарная плашка с кругом «0»: себе ничего не осталось. | H71: ОТКАЧЕНО 07.08.2026: плашка возвращена к прежнему виду
A72: .minb .t | B72: Заголовок врезки поднят до 21px со знаком равенства в квадрате слева — это ключевая мысль, а не строка текста. | H72: ОТКАЧЕНО 07.08.2026: заголовок вернулся к 16px без знака
A74: УВЕДОМЛЕНИЯ — ЕДИНЫЙ ВИД, 07.08.2026
A75: Эталон | B75: .note.warn — жёлтая подложка --c-a-50, пунктирная рамка --c-a-300, круг --c-a-400 со знаком «!», текст --c-a-800. Так оформлены уведомления блока 01.
A76: Блок 05 «Логистика» | B76: был .lognote — серая подложка --c-surf со сплошным кругом. Переведён на .note.warn, класс .lognote удалён из CSS.
A77: Блок 06 «Выгорание» | B77: был .note.warn.lg — та же гамма, но шрифт 17px и padding 24/28/56. Переведён на обычный .note.warn.
A78: Многоабзацные | B78: .note.warn p{margin:0} + p+p{margin-top:10px} — раньше отступы давал только .lg
A80: УВЕДОМЛЕНИЯ — ЕДИНАЯ ТИПОГРАФИКА, 07.08.2026
A81: Причина разнобоя | B81: Правило #phr-root .note{font-size:12.5px;text-align:center;line-height:1.5} стояло ниже по файлу и перебивало базовое .note{13px;1.6}. Уведомления .warn/.info/.ok получали чужой кегль, центровку и межстрочный — отсюда разные отступы и интерлиньяж между блоками.
A82: Решение | B82: Позднее правило сужено до :not(.warn):not(.info):not(.ok):not(.plain) — оно нужно только мелким сноскам (источники, подписи). Уведомлениям задана своя типографика: 13px / 1.6 / по левому краю.
A83: Абзацы внутри | B83: p{margin:0;font-size:inherit;line-height:inherit}, между абзацами 8px. Раньше абзацы наследовали разные размеры.
A84: Вывод последней строкой | B84: p:last-child:not(:only-child){text-align:right;font-weight:600} — только если абзацев больше одного.
A85: Блок 06 — тип уведомления | B85: Жёлтое .note.warn заменено на синее .note.info — точная копия уведомления из блока 08. Оформление, цвета и знак «i» не менялись, только текст.
A87: ПРОВЕРКА ВЁРСТКИ — новый скрипт, 08.08.2026
A88: Где | B88: _архив/скрипты/проверка_вёрстки.py · встроен в собрать.py, запускается после сборки
A89: Запуск отдельно | B89: python3 проверка_вёрстки.py файл.html [--было прежний.html] — работает на любом HTML, включая макеты в «части»
A90: 1. Скобки | B90: баланс {} в CSS и открытых/закрытых тегов, с номером строки
A91: 2. Переменные | B91: используются, но не объявлены. Не считает ошибкой var(--x,запасное), инлайн в style="" и setProperty из JS
A92: 3. Медиазапросы | B92: незакрытый @media проглатывает весь CSS ниже — правила есть, но не работают. Плюс сигнал, если @media охватывает больше 40 правил
A93: 4. Дубли селекторов | B93: два правила с одним селектором и общим свойством: нижнее молча перебивает верхнее. Так .note{text-align:center} перебивал .note.warn
A94: 5. Сверка с прежней | B94: что пропало, что добавилось и у каких свойств изменились значения. Показывает, что правка задела соседние элементы
A95: Зачем | B95: Ловит класс ошибок «поехала разметка после правки»: потерянные отступы, сбитое оформление, случайно задетые блоки
A97: НУМЕРАЦИЯ СПРАВОЧНИКА И ССЫЛКИ, 10.08.2026
A98: Справочник | B98: Каждый термин пронумерован: кружок 26 px слева, номер 01–26 по порядку. Якорь ref0..ref25 — по индексу, не по названию (имена кириллические).
A99: Ссылка из блока | B99: .refl — ОБЫЧНАЯ ТЕКСТОВАЯ ссылка «Подробнее в п. 7 Справочника»: синий цвет, тонкое подчёркивание. Никаких плашек, рамок и фона — внутри текста они не нужны. Номер без ведущего нуля. Один вид на весь отчёт.
A100: Подсветка перехода | B100: Через :target. У целевого пункта голубой фон, номер заливается синим градиентом, термин синеет. Работает без скрипта, ничего не сбрасывает.
A101: Блок 01 | B101: 13 строк легенды связаны с терминами массивом REFLB. Съёмка → 22, Обработка → 07, Работа с клиентом → 15, Продвижение → 13, Учёт → 24, Форс-мажоры → 25, Оборудование → 23, Реклама → 13, Текущие счета → 18, Налоги → 06, Эквайринг → 26, Фонд и Запас → 05. Битых ссылок нет.
A102: Порядок объявления | B102: REFD и PHR_REF вынесены выше отрисовки блоков: легенда блока 01 строится раньше справочника и без этого ссылок не получала.
A104: ВТОРОЙ ЭКРАН И КНОПКИ БЛАГОДАРНОСТИ, 10.08.2026
A105: Экран 2 — рабочий месяц | B105: Всё переведено в месяц: год человек не чувствует, месяц планирует. Один заголовок «Ваш рабочий месяц» и три рамки: съёмок в месяц, часов на работу с заказом (обработка + клиент), продвижение и прочее. Рамки прозрачные, только контур. Проверка: 18+72+56=146 ч = всё рабочее время за месяц.
A106: Гамма и фон | B106: Морская волна #176B77 → #58B1B9 — взята из карточки «Ставка в ноль» блока «Четыре цифры» (.fct.b). Ближе к зелёному, чем прежний синий. Фоновый рисунок — часы вместо фотоаппарата, прозрачность 13%.
A107: Кнопка благодарности | B107: .thxb — форма от .savebtn (ширина 100%, высота 72px, кегль 17px, радиус, отступы 0/30, зазор 11px), оформление от плашек блока 08 (.cn.s1..s3): инста-градиент заливкой --c-ig-1 → --c-ig-2 → --c-ig-4, белый текст и сердце, круг-блик :before в углу, тень. Рамки нет. При наведении яркость +6%. Мест три: под кнопкой PDF, между блоками 04 и 05, баннер перед справочником. Из шапки убрана 10.08.2026.
A108: Баннер | B108: .cta.thx — тот же приём, что «30 сценариев», гамма тёплая (--c-a-700 → --c-a-500), декор-сердце вместо стопки карточек.
A109: THANKS_URL | B109: Адрес задаётся одной переменной в скрипте отчёта, подставляется во все кнопки разом. Сейчас заглушка #thanks. Если адрес внешний — ссылки автоматически открываются в новой вкладке.
A110: собрать.py | B110: Ожидаемое число прямых детей .wp: 19 → 22 (добавились две плашки с кнопками и баннер).
A112: ССЫЛКИ И КНОПКИ — единый вид, 10.08.2026
A113: Ссылка на справочник | B113: .refl — цветом НЕ выделяется: color:inherit, font:inherit. Наследует кегль, начертание и цвет того описания, вместо которого стоит. Обозначена только подчёркиванием currentColor. Текст короткий: «п. 22 Справочника», без «Подробнее в».
A114: Ссылки в памятке | B114: Блок 04 и другие .pmknote: было своё оформление (цвет --c-fns-2, полужирный) — приведено к тому же правилу, что .refl.
A115: Кнопки и баннер | B115: Единая гамма: инста-градиент --c-ig-1 → --c-ig-2 → --c-ig-4. Баннер был тёплый (--c-a-700), переведён в ту же гамму. Декор везде одинаковый: круг-блик плюс сердечки. На кнопках два сердца (.thxd справа 56px, .thxd2 слева 34px), на баннере два круга и два сердца.
A117: БАННЕР «30 СЦЕНАРИЕВ» ВЫНЕСЕН, 10.08.2026
A118: Куда | B118: части/09_баннер_сценарии.html — полноценная страница, дизайн сохранён без изменений. В собрать.py 22 → 21 блока.
A119: Важно | B119: Стили .cta ОСТАЛИСЬ в каркасе: их наследует баннер благодарности .cta.thx. Вынесена только разметка. При первой попытке я скопировала правила в каркас поверх существующих — получились дубли, убраны.
A120: Пояснение под кнопкой | B120: .thxn — абзац под кнопкой «Поблагодарить проект» (той, что под сохранением в PDF). Лежит ВНУТРИ .thxbar, иначе становится прямым ребёнком .wp и ломает проверку структуры. Ширина 720px, кегль 13, по центру, цвет --c-gr.
...

Sheet 09i_Справочник
A1: 09i · СПРАВОЧНИК: ТЕРМИНЫ И ОПРЕДЕЛЕНИЯ
A2: Плоский список по алфавиту, без разделов. Только те термины, которые человек встречает в анкете и в отчёте. Внутренние термины методики сюда не входят.
A4: Термин | B4: Определение
A5: Амортизация | B5: способ распределения стоимости разовой покупки на весь её срок службы — ежегодные или ежемесячные расходы на износ оборудования.
A6: Выручка | B6: общий объём денежных средств, которые необходимо получить от клиентов за год, чтобы после всех обязательных вычетов у вас остался желаемый чистый доход.
A7: Готовые кадры | B7: среднее количество готовых снимков, получаемых клиентом с часа съёмки. Из этого рассчитывается цена одного кадра.
A8: Доход на руки | B8: чистая сумма, которая остаётся у вас после вычета всех расходов и налогов. Это ключевая точка отсчёта для всех дальнейших расчётов.
A9: Запас прочности | B9: финансовый резерв, формирующий фонд развития и запас на предоставление скидок. Не входит в обязательный базовый расчёт и может включаться по вашему усмотрению.
A10: Налоги и взносы | B10: платежи в соответствии с вашим налоговым режимом. Для индивидуальных предпринимателей включают фиксированные страховые взносы, подлежащие уплате независимо от наличия дохода.
A11: Обработка | B11: время, необходимое для обработки полученного контента за один час съёмки: скачивание и бэкап, отбор и отбраковка кадров, выгрузка и загрузка в ПО, кадрирование, устранение значимых артефактов, цветовая и тоновая коррекция, сведение к единому стилю, настройка чёткости кадра, сохранение в нужном формате, экспорт, загрузка в облако, правки при необходимости, а также формирование и хранение архива.
A12: Обустройство места | B12: закупка необходимой для работы мебели, косметический ремонт помещения, предусмотренного под рабочую зону и хранение оборудования.
A13: Обучение | B13: прохождение профессиональных курсов и работа с наставниками. Помимо прямой финансовой стоимости, учитывает периоды временного снижения или полного отсутствия дохода во время учёбы.
A14: Офисное оборудование | B14: оборудование, необходимое для профессиональной деятельности фотографа и выполнения всего комплекса работ: от обработки заказов и решения текущих задач до поиска новых клиентов, ведения учёта и сопутствующей административной деятельности.
A15: Подписки | B15: регулярные платежи за цифровые сервисы и инструменты, без которых невозможна ежедневная работа: Adobe Creative Cloud, облачные хранилища, хостинг, доменное имя и подобное.
... A30: Эквайринг | B30: банковская комиссия за приём платежей по картам или через QR-код. Рассчитывается со всей суммы поступлений, а не с чистой прибыли.
A32: Нормативная основа «Рабочих пауз»: Межотраслевые методические рекомендации «Определение нормативов времени на отдых и личные надобности» (Госкомтруд СССР) — 10–15 минут в смену на личные надобности всем работающим; 3–5% оперативного времени на отдых при монотонной работе. Санитарные рекомендации для работы за монитором: 10–15 минут каждые 45–60 минут (СанПиН 2.2.2/2.4.1340-03 и ТОИ Р-45-084-01 утратили силу с 01.01.2021, цифры используются как ориентир). Обеденный перерыв не входит.
A34: ЕДИНЫЕ НАЗВАНИЯ В ТАБЛИЦЕ ПОЛНОЙ ВЫГРУЗКИ — 06.08.2026
A35: Было | B35: Стало
A36: Съёмочная техника | B36: Съёмочное оборудование
A37: Компьютер и периферия | B37: Офисное оборудование
A38: Программы разово + Подписки и сервисы | B38: Программное обеспечение — одной строкой
A39: Обустройство места | B39: Обустройство рабочего места
A40: Реклама и продвижение | B40: Продвижение и реклама
A41: Аренда и коммунальные | B41: Содержание рабочего места
A42: Банк и РКО + Эквайринг | B42: Банк и РКО — эквайринг входит сюда, в налогах не дублируется
A43: Съёмка на площадке | B43: Съёмочных часов
A44: Обработка материала | B44: Часов на обработку
A45: Продвижение | B45: Часов на продвижение и рекламу
A46: Работа с клиентом | B46: Часов на работу с клиентом
... A54: Ваша текущая ставка | B54: УДАЛЕНА — заменена на «Стоимость одного готового кадра»

Sheet 10_Монетизация
A1: 10 · МОНЕТИЗАЦИЯ — цены, комиссии, партнёрская программа
A2: Тестовый этап: задача не заработать, а проверить готовность платить. Жёлтое — редактируется.
A4: ЦЕНЫ
A5: Параметр | B5: Значение | C5: Ед. | F5: Комментарий
A6: Базовая цена скачивания | B6: 490 | C6: ₽ | F6: Без реферальной ссылки. Ориентир по рынку микропродуктов
A7: Цена по реферальной ссылке | B7: 169 | C7: ₽ | F7: Тестовая. Целевая аудитория — самозанятые с низким доходом
A8: Зачёркнутая цена в блоке | B8: 560 | C8: ₽ | F8: Якорь. Показывается рядом с реферальной
A9: Модель | B9: за скачивание | F9: Не подписка и не доступ. Каждый отчёт оплачивается отдельно
A10: Цель по скачиваниям | B10: 10000 | C10: шт | F10: Порог, после которого продукт считается подтверждённым
A12: ПРОГНОЗ ОБОРОТА
A13: Сценарий | B13: Скачиваний | C13: Цена | D13: Оборот | E13: Доля | F13: Комментарий
A14: По реферальной ссылке | B14: 8500 | C14: 169 | D14: =B14*C14 | E14: 85% | F14: Основной канал: партнёры, соцсети
A15: Прямые заходы | B15: 1500 | C15: 490 | D15: =B15*C15 | E15: 15% | F15: Поиск, прямые ссылки
A16: ИТОГО | B16: =B14+B15 | D16: =D14+D15 | E16: 100%
A18: КОМИССИИ ПЛАТЁЖНЫХ СИСТЕМ 2026
A19: Способ оплаты | B19: Ставка | C19: НДС 22% | D19: Итого с оборота | E19: Остаётся | F19: Комментарий
A20: СБП, льготный тариф | B20: 0.004 | C20: нет | D20: =$D$16*B20 | E20: =$D$16-D20 | F20: 0,4% — для отдельных категорий, не более 1 500 ₽ за операцию
A21: СБП, обычный тариф | B21: 0.007 | C21: нет | D21: =$D$16*B21 | E21: =$D$16-D21 | F21: 0,7% — большинство отраслей. НДС не начисляется
A22: Карты, интернет-эквайринг | B22: 0.028 | C22: да | D22: =$D$16*B22*1.22 | E22: =$D$16-D22 | F22: С 2026 к комиссии добавляется НДС 22%
A23: Смешанный: 70% СБП + 30% карты | D23: =$D$16*0.7*B21+$D$16*0.3*B22*1.22 | E23: =$D$16-D23 | F23: Реалистичный сценарий. Ставьте СБП первым способом
A24: Экономия СБП против карт | D24: =D22-D21 | F24: Разница только на комиссиях
A26: ПЛАТЁЖНЫЕ СИСТЕМЫ — ЧТО ВЫБРАТЬ ДЛЯ ООО
A27: Сервис | B27: Карты | C27: СБП | D27: Онлайн-касса | E27: Tilda | F27: Комментарий
A28: ЮKassa | B28: от 2,8% | C28: 0,4–0,7% | D28: отдельно | E28: готовый модуль | F28: Уже подключена. Касса нужна отдельно или через партнёра
A29: Т-Банк | B29: от 2,46% | C29: 0,4–0,7% | D29: встроенная | E29: через универсальный | F29: Ниже ставка, быстрое подключение. РКО только для СБП
A30: Продамус | B30: до 3,5% | C30: есть | D30: встроенная | E30: готовый модуль | F30: Проще всего, но дороже по картам
A31: Робокасса | B31: от 2,7% | C31: есть | D31: встроенная | E31: готовый модуль | F31: 40+ способов оплаты
A32: РЕКОМЕНДАЦИЯ | F32: Оставить ЮKassa, включить СБП основным способом. При росте оборота сравнить с Т-Банком
A34: ОКВЭД И НАЗНАЧЕНИЕ ПЛАТЕЖА
A35: Код | B35: Название | C35: Подходит | F35: Комментарий
A36: 62.01 | B36: Разработка компьютерного программного обеспечения | C36: ДА | F36: Основной. Именно его добавить, чтобы платежи шли как IT
A37: 62.02 | B37: Консультативная деятельность в области ИТ | C37: да | F37: Дополнительный, если будут консультации
A38: 63.11 | B38: Деятельность по обработке данных | C38: да | F38: Дополнительный, для облачных сервисов
A39: Назначение платежа | B39: Предоставление права использования ПО (расчётный сервис) | F39: Формулировка для чека и договора-оферты
A40: Предмет продажи | B40: Электронный отчёт, формируемый программой | F40: Не «услуга» и не «консультация» — именно результат работы ПО
A42: ПАРТНЁРСКАЯ ПРОГРАММА
A43: Параметр | B43: Значение | C43: Ед. | F43: Комментарий
A44: Вознаграждение партнёру | B44: 0.3 | C44: % | F44: От суммы каждой оплаты по его ссылке
A45: Выплата с одной продажи | B45: =B44*B7 | C45: ₽ | F45: При реферальной цене
A46: Остаётся проекту | B46: =B7-B45 | C46: ₽ | F46: До вычета комиссии эквайринга
A47: Минимальная сумма выплаты | B47: 3000 | C47: ₽ | F47: Накопительно, чтобы не гонять мелкие переводы
A48: Период выплат | B48: раз в месяц | F48: До 10 числа за предыдущий месяц
A49: Срок жизни метки | B49: 30 | C49: дней | F49: Сколько помнить источник перехода в браузере

Sheet 11_Ссылки
A1: 11 · ССЫЛКИ И МЕТКИ — реферальные адреса и учёт переходов
A2: Домен подставьте в ячейку B4 — все ссылки соберутся автоматически.
A4: Домен сайта | B4: vashsite.ru | C4: без https:// и без слэша в конце
A5: Страница калькулятора | B5: /photo-unit | C5: юнит-экономика фотографа. Варианты: /hour, /chas, /calc
A7: РЕФЕРАЛЬНЫЕ ССЫЛКИ
A8: Партнёр / канал | B8: Метка ref | C8: Готовая ссылка | D8: Цена | E8: Что отслеживаем
A9: Telegram-канал | B9: tg | C9: ="https://"&$B$4&$B$5&"?ref="&B9&"&utm_source=telegram&utm_medium=referral&utm_campaign=calc" | D9: 169 ₽ | E9: переходы, время, клик по кнопке
A10: ВКонтакте | B10: vk | C10: ="https://"&$B$4&$B$5&"?ref="&B10&"&utm_source=vk&utm_medium=referral&utm_campaign=calc" | D10: 169 ₽ | E10: переходы, время, клик по кнопке
A11: Instagram / блог | B11: ig | C11: ="https://"&$B$4&$B$5&"?ref="&B11&"&utm_source=instagram&utm_medium=referral&utm_campaign=calc" | D11: 169 ₽ | E11: переходы, время, клик по кнопке
A12: Партнёр №1 | B12: p1 | C12: ="https://"&$B$4&$B$5&"?ref="&B12&"&utm_source=partner&utm_medium=referral&utm_campaign=calc" | D12: 169 ₽ | E12: переходы, время, клик по кнопке
A13: Партнёр №2 | B13: p2 | C13: ="https://"&$B$4&$B$5&"?ref="&B13&"&utm_source=partner&utm_medium=referral&utm_campaign=calc" | D13: 169 ₽ | E13: переходы, время, клик по кнопке
A14: Рассылка | B14: mail | C14: ="https://"&$B$4&$B$5&"?ref="&B14&"&utm_source=email&utm_medium=referral&utm_campaign=calc" | D14: 169 ₽ | E14: переходы, время, клик по кнопке
A15: Прямой заход | B15: — | C15: ="https://"&$B$4&$B$5 | D15: 490 ₽ | E15: переходы, время, клик по кнопке
A17: КАК ЭТО РАБОТАЕТ
A18: Калькулятор проверяет параметры ref, utm_source или from в адресе страницы.
A19: Если хоть один есть — показывает цену 169 ₽ и зачёркнутые 560 ₽. Если нет — 490 ₽.
A21: УЧЁТ ПЕРЕХОДОВ. Отдельный сервис сокращения не нужен: Яндекс.Метрика считает UTM сама.
A22: Отчёт «Источники → Метки UTM» покажет переходы, время на странице и достижение целей.
A24: КОРОТКАЯ ССЫЛКА для соцсетей: сделайте в Tilda страницу-редирект /tg,
A25: которая перенаправляет на полный адрес с метками. Так и учёт сохранится, и ссылка читаемая.
A27: ЦЕЛИ В МЕТРИКЕ (обязательно настроить):
A28: calc_done — нажал «Рассчитать стоимость часа»
A29: buy_click — нажал «Поблагодарить и скачать отчёт»
A30: paid — вернулся на страницу с параметром ?paid=1
A32: Номер счётчика пропишите в HTML: var YM_ID=0; → var YM_ID=ваш_номер;

Sheet 11b_Связка
A1: 11b · СВЯЗКА ФОРМЫ И ОТЧЁТА
A2: calc.html считает → кладёт в localStorage[«phc_report»] → report.html читает. Если ключа нет, отчёт показывает демо-набор.
A4: ПОЛЯ, КОТОРЫЕ ПЕРЕДАЁТ ФОРМА
A5: Поле | B5: Что это | C5: Откуда в форме | D5: Где в отчёте
A6: sh | B6: часы съёмки в год | C6: py × S | D6: знаменатель всех сумм
A7: post | B7: часы обработки | C7: sh × K | D7: легенда, блок 01
A8: clT | B8: часы на клиента | C8: py × cl | D8: легенда
A9: promo | B9: часы продвижения | C9: promo_per_day × ND | D9: легенда
A10: accT | B10: часы учёта | C10: acc_per_quarter × 4 | D10: легенда
A11: fmT, idle | B11: форс-мажор и паузы | C11: gross × fm_pct, ND×(8−EFF) | D11: легенда
A12: Ny | B12: целевой доход в год | C12: income_month × 12 | D12: база распределения
A13: R | B13: требуемая выручка | C13: (Ny+C)/(1−a−sdiv−fund−disc−ставка) | D13: ставка часа
A14: depShoot | B14: съёмочная техника | C14: Form001 | D14: строка «оборудование и ПО»
A15: depOffice | B15: компьютер | C15: Form002 | D15: строка «оборудование и ПО»
A16: depSoft | B16: плагины разово | C16: Form004 | D16: строка «оборудование и ПО»
... A33: npd_who | B33: заказчики на НПД (mix/phys/jur) | C33: select #npd_who, виден только при НПД | D33: раскрывает НПД в npd4/npd5/npd6 → ставка 4/5/6%
A34: profession
A36: ПРОВЕРКА: сумма всех сегментов диаграммы = R. Расхождение должно быть 0 ₽. Сумма доходных сегментов = Ny.
A37: Запасной путь, если localStorage недоступен: reportLink(d) отдаёт ссылку report.html?data=<base64>. Отчёт читает параметр data первым делом.

Sheet 12_Диаграммы
A1: 12 · ДИАГРАММЫ — состав, группы и подписи
A2: Одна строка = один сегмент диаграммы. Порядок строк = порядок сегментов по кругу. Жёлтое — редактируется, серое — служебное.
A4: Д1 · ОСНОВНАЯ КОЛЬЦЕВАЯ — предварительный отчёт, видна всем
A5: Тип диаграммы | C5: Кольцевая (donut), 11–13 секторов | F5: 260 px, кольцо 58 px, отверстие 47%. Центр — белый диск и внутренняя шайба с мягкой тенью: цифра лежит на подложке, а не висит в пустоте
A6: Где размещена | C6: Блок «Куда уходит каждый час съёмки» | F6: Открыта без оплаты
A7: Что показывает | C7: Разбор одного оплаченного часа съёмки | F7: Все суммы делятся на shooting_time
A8: В центре кольца | C8: Ставка часа + подпись «за час съёмки» | F8: real_rate = R / shooting_time
A9: Строка легенды | C9: Название · сумма · «за N ч» | F9: Отдельного столбца времени нет. Часы — подписью под суммой: «747 ₽ / за 1,0 ч». Часы на ОДИН оплаченный час съёмки, сумма по всем строкам = 7,7 ч
A10: Две плашки | C10: Одинаковые по форме | F10: «Ваш доход на руки» и «Ваши расходы» — одинаковые по вёрстке: обе прямые дети карточки, один набор элементов (знак, заголовок, подводка, сумма, строка снизу). Отличаются только цветом рамки и текстом
A11: Заголовки плашек | C11: 21 px, --c-ink, без заливки | F11: Выделяются размером шрифта, не цветом. Капсул и цветных подложек нет
A12: № | B12: Группа | C12: Код сегмента | D12: Подпись в легенде | E12: Параметр расчёта | F12: Формула / что берём | G12: Цвет | H12: Условие | I12: Комментарий | J12: Предупреждение
A13: 1 | B13: ПО СПЕЦИАЛЬНОСТИ | C13: earn_shoot | D13: Как фотограф — съёмка | E13: shooting_time | F13: hr × shooting_time | G13: #0B6B22 | H13: всегда | I13: Работа по специальности — холодный зелёный, градация от тёмного к светлому
A14: 2 | B14: ПО СПЕЦИАЛЬНОСТИ | C14: earn_post | D14: Как фотограф — обработка | E14: post_time | F14: hr × post_time | G14: #2FA84A | H14: всегда
A15: 3 | B15: ОСТАЛЬНАЯ КОМАНДА | C15: earn_sales | D15: Как отдел продаж — работа с клиентом | E15: client_total | F15: hr × client_total | G15: #5F8A1B | H15: всегда | I15: Работа за остальную команду — тёплый зелёный (салатовый), та же градация
A16: 4 | B16: ОСТАЛЬНАЯ КОМАНДА | C16: earn_promo | D16: Как маркетолог и SMM — продвижение | E16: promo_time | F16: hr × promo_time | G16: #8CB82F | H16: всегда
A17: 5 | B17: ОСТАЛЬНАЯ КОМАНДА | C17: earn_acc | D17: Как бухгалтер — учёт и отчётность | E17: accounting_time | F17: hr × accounting_time | G17: #B9D96F | H17: только если acc_mode = «Веду самостоятельно» | I17: Скрыт, если нанят бухгалтер
A18: 6 | B18: НЕ ОПЛАЧИВАЕТСЯ | C18: earn_idle | D18: Форс-мажоры и простой | E18: fm_time + idle | F18: hr × (fm_time + idle) | G18: #B6BCC4 | H18: всегда | I18: Не оплачивается — серый. idle = 219 ч, час в день на паузы
A19: 7 | B19: ВАШИ РАСХОДЫ | C19: cost_equip | D19: Отложите на оборудование и ПО | E19: equip | F19: dep_shoot + dep_office + dep_software | G19: #EF4444 | H19: всегда | I19: Чтобы обновить технику, когда придёт в негодность
A20: 8 | B20: ВАШИ РАСХОДЫ | C20: cost_promo | D20: Потратите на рекламу и продвижение | E20: promoM | F20: var_ads + dep_website | G20: #F59E0B | H20: всегда | I20: Сайт отнесён сюда, а не в оборудование
A21: 9 | B21: ВАШИ РАСХОДЫ | C21: cost_current | D21: Заплатите по текущим счетам | E21: current | F21: var_workspace + var_bank + var_accounting + var_software + dep_workspace + dep_education | G21: #FB923C | H21: всегда | I21: Аренда, подписки, бухгалтер, обустройство, обучение
A22: 10 | B22: ВАШИ РАСХОДЫ | C22: cost_tax | D22: Заплатите налогов и взносов | E22: taxAll | F22: налог + страховые взносы по выбранному режиму | G22: #8B5CF6 | H22: всегда
A23: 11 | B23: ВАШИ РАСХОДЫ | C23: cost_bank | D23: Отдадите банку за эквайринг | E23: aq | F23: R × acquiring | G23: #3B82F6 | H23: всегда
A24: 12 | B24: ВАШИ РАСХОДЫ | C24: cost_fund | D24: Отложите в фонд развития | E24: fundY | F24: R × fund_pct | G24: #7189AE | H24: всегда, даже при нуле | I24: Галочка «Закладывать фонд развития» в анкете СНЯТА по умолчанию, поле % неактивно. При нуле — предупреждение: «Технику придётся менять из своего кармана или в кредит». Анкета, блок 15 | J24: да
A25: 13 | B25: ВАШИ РАСХОДЫ | C25: cost_disc | D25: Заложите запас на скидку | E25: discY | F25: R × disc_pct | G25: #B7C9E8 | H25: всегда, даже при нуле | I25: Галочка «Закладывать запас на скидку» СНЯТА по умолчанию, поле % неактивно. При нуле — предупреждение: «Любая скидка просто так будет вычтена из вашего дохода». Анкета, блок 15 | J25: да
A27: Д2 · ТРИ КОЛЬЦА СРАВНЕНИЯ — полный отчёт, после оплаты
A28: Тип диаграммы | C28: Три кольцевые рядом (donut × 3) | F28: 190 px каждая, в ряд на десктопе, столбцом на мобильном
A29: Где размещена | C29: Блок «Куда уходит каждый час» | F29: Под размытием до оплаты
A30: Что показывает | C30: Одни и те же сегменты при трёх ставках | F30: Сегменты и цвета совпадают с Д1
A31: Кольцо 1 | C31: Ваша расчётная ставка | F31: Выручка R, доход = target_income
A32: Кольцо 2 | C32: Ваша текущая ставка | F32: Выручка current_rate × shooting_time, доход = leftC
A33: Кольцо 3 | C33: Работа в ноль | F33: Выручка Rb (безубыточность), доход = 0
A34: Единица легенды | C34: Рубли и проценты
A36: № | B36: Группа | C36: Код сегмента | D36: Подпись в легенде | E36: Параметр расчёта | F36: Формула / что берём | G36: Цвет | H36: Условие | I36: Комментарий
A37: 1–11 | B37: те же | C37: см. Д1 | D37: Состав полностью совпадает с Д1 | E37: parts(d) | F37: Для кольца 2 доходные сегменты × коэффициент leftC / target_income | G37: — | H37: всегда | I37: Для кольца 3 все доходные сегменты = 0
A39: Д3 · СЕТКА НЕДЕЛИ — блок 02. Обновлено 06.08.2026: расшифровка убрана, добавлена легенда цветов под сеткой
A40: Тип диаграммы | C40: Тепловая сетка (heatmap) 5 × 9 | F40: 5 рабочих дней, часы с 10:00 до 19:00
A41: Где размещена | C41: Блок «Ваша неделя» | F41: Под размытием до оплаты
A42: Что показывает | C42: Как распределяется рабочий день по видам работ | F42: Часы в неделю ÷ 5 дней
A43: Обед | C43: Один час в 14:00, серый | F43: Не входит в рабочее время
A44: Легенда цветов | C44: Под сеткой, класс .slg | F44: Съёмка · Обработка · Продвижение · Работа с клиентом · Учёт · Рабочие паузы · Форс-мажоры (штриховка, только если > 0)
A45: Комментарий | C45: Один, крупным шрифтом | F45: «За неделю у вас одна съёмка на N ч… Получается всего N часа с камерой в руках, а остальное время — это та самая невидимая, но огромная работа за кадром, без которой ни одна съёмка просто не состоится»
A46: № | B46: Группа | C46: Код сегмента | D46: Подпись в легенде | E46: Параметр расчёта | F46: Формула / что берём | G46: Цвет | H46: Условие | I46: Комментарий
A47: 1 | B47: ВРЕМЯ | C47: wk_shoot | D47: Съёмка | E47: shooting_time | F47: shooting_time / net_weeks / 5 | G47: #0B6B22 | H47: всегда | I47: Цвет совпадает с Д1
A48: 2 | B48: ВРЕМЯ | C48: wk_post | D48: Обработка | E48: post_time | F48: post_time / net_weeks / 5 | G48: #1B9331 | H48: всегда
A49: 3 | B49: ВРЕМЯ | C49: wk_client | D49: Работа с клиентом | E49: client_total | F49: client_total / net_weeks / 5 | G49: #35B94C | H49: всегда
A50: 4 | B50: ВРЕМЯ | C50: wk_promo | D50: Продвижение | E50: promo_time | F50: promo_time / net_weeks / 5 | G50: #6FD183 | H50: всегда
A51: 5 | B51: ВРЕМЯ | C51: wk_acc | D51: Учёт | E51: accounting_time | F51: accounting_time / net_weeks / 5 | G51: #A6E5B2 | H51: только при acc_mode = сам
A52: 6 | B52: ВРЕМЯ | C52: wk_fm | D52: Резерв на срывы | E52: fm_time | F52: fm_time / net_weeks / 5 | G52: #CDF2D5 | H52: только при fm_on
A53: 7 | B53: СЛУЖЕБНОЕ | C53: wk_lunch | D53: Обед | E53: — | F53: фиксированно 1 час в 14:00 | G53: #E5E7EB | H53: всегда | I53: Нейтральный серый
A55: Д4 · РЕЗЕРВ — заготовка под будущую диаграмму
A56: Тип диаграммы | C56: (заполнить) | F56: Варианты: столбчатая, линейная, воронка
A57: Где размещена | C57: (заполнить)
A58: Что показывает | C58: (заполнить)
A59: Идея 1 | C59: Динамика ставки при разной длительности съёмки | F59: Как S влияет на цену часа
A60: Идея 2 | C60: Структура года: оплачиваемые и неоплачиваемые часы | F60: Наглядное соотношение
A61: Идея 3 | C61: Сравнение с наймом | F61: Ставка фрилансера против зарплаты в штате
A63: № | B63: Группа | C63: Код сегмента | D63: Подпись в легенде | E63: Параметр расчёта | F63: Формула / что берём | G63: Цвет | H63: Условие | I63: Комментарий
A64: 1
A65: 2
A66: 3
A67: 4
A68: 5
A69: 6
A71: ОБЩИЕ ПРАВИЛА
A72: Порядок сегментов в таблице = порядок отрисовки по часовой стрелке от 12 часов.
A73: Цвета едины для всех диаграмм: зелёная гамма — заработок, тёплая и холодная — расходы.
A74: Проценты подписываются прямо на сегменте, если доля не меньше 3,2%. Мельче — не читается.
A75: Сегмент с нулевым значением не отрисовывается и не попадает в легенду.
A76: Условные сегменты (бухгалтер, резерв) исчезают, когда соответствующая опция выключена.
A77: Сумма всех сегментов всегда равна выручке — это проверяется формулой в листе 05_Расчёт.
A79: ЧТО ПРАВИТЬ В ЭТОМ ЛИСТЕ: подписи в легенде (жёлтая колонка) и состав групп.
A80: Формулы и коды сегментов менять только вместе с кодом HTML.

Sheet 13_Сетка_скидок
A1: 13 · СЕТКА ЦЕН ПО ОБЪЁМУ
A2: Постоянная величина — час ПРОЕКТНОГО времени. Цена съёмочного часа падает за счёт накладных, а не дохода.
A4: ПРИНЦИП
A5: Час проектного времени = выручка / проектное время за год. Величина ПОСТОЯННАЯ.
A6: Проект = S × (1 + коэффициент обработки) + 1 час на клиента.
A7: Час на клиента одинаков и для съёмки на 2 часа, и для съёмки на 6 часов.
A8: Чем длиннее съёмка, тем меньше накладных приходится на каждый съёмочный час.
A10: ВАЖНО: доход специалиста НЕ уменьшается. Годовая выручка одинакова при любой длительности.
A12: ПРИМЕР: минимальная съёмка 2 ч, коэффициент обработки 3
A13: Длительность | B13: Проектное время | C13: Цена заказа | D13: Цена часа | E13: Скидка | F13: Комментарий
A14: 2 ч — базовая | B14: 9 ч | C14: 18708 | D14: 9354 | E14: — | F14: Максимальная ставка
A15: 3 ч | B15: 13 ч | C15: 27023 | D15: 9008 | E15: −3.7% | F15: Клиент экономит 346 ₽ с часа
A16: 4 ч | B16: 17 ч | C16: 35338 | D16: 8835 | E16: −5.6% | F16: Клиент экономит 520 ₽ с часа
A17: 5 ч | B17: 21 ч | C17: 43653 | D17: 8731 | E17: −6.7% | F17: Клиент экономит 624 ₽ с часа
A18: 6 ч | B18: 25 ч | C18: 51968 | D18: 8661 | E18: −7.4% | F18: Клиент экономит 693 ₽ с часа
A19: 7 ч | B19: 29 ч | C19: 60283 | D19: 8612 | E19: −7.9% | F19: Клиент экономит 742 ₽ с часа
A21: ПРОВЕРКА | B21: Выручка за год при любом S | C21: 2138693 | F21: Сумма всех заказов одинакова
A23: ПЕРЕСМОТР 06.08.2026 — база от 1 часа, ступени 2/4/6
A24: Было | B24: Ступени S, S+1, S+2, S+3 — зависели от введённой длительности. Первая карточка считалась «базой», хотя при S=2 это уже цена со скидкой 10%
A25: Стало | B25: База всегда 1 час — короче никто не работает. Ступени фиксированы: 2, 4, 6 часов
A26: Формула | B26: час(S) = (S × (1+K) + cl) × hp / S, где hp = R / project_pool
A27: Почему час дороже | B27: Час на работу с клиентом тратится на каждый заказ независимо от длины. При S=1 он занимает 20% проекта, при S=6 — только 4%
A28: На демо-наборе | B28: 1 ч → 9 874 ₽ · 2 ч → 8 887 ₽ (−10,0%) · 4 ч → 8 393 ₽ (−15,0%) · 6 ч → 8 228 ₽ (−16,7%)

Sheet 13b_Программа_лояльности
A1: 13b · ПРОГРАММА ЛОЯЛЬНОСТИ — ФОНД, СКИДКИ, СЕРТИФИКАТЫ
A2: Структура скидок блока 03 отчёта. Жёлтое — исходные данные, зелёное — итог. Всё остальное считается формулами.
A3: ПРАВИЛО: скидки покрываются ТОЛЬКО фондом. Экономия на привлечении и высвобожденное время в покрытие не идут — это выгода фотографа.
A5: ИСХОДНЫЕ ДАННЫЕ — из анкеты и расчёта
A6: Показатель | B6: Значение | C6: Ед. | G6: Откуда
A7: Резерв на скидку (discP) | B7: 0.15 | C7: доля | G7: Анкета, блок «резерв на скидку»: 5 / 10 / 15%
A8: Выручка целевая (R) | B8: 2138693 | C8: ₽/год | G8: 05_Расчёт
A9: Съёмок (заказов) в год | B9: 216.6 | C9: шт | G9: 06_Отчёт, py. Дробное — это среднее за год. В отчёте показывается округлённым
A10: Средний чек | B10: 47000 | C10: ₽ | G10: Прайс 11 700 ₽/ч × средняя съёмка 5 ч, округлено
A11: Стоимость привлечения нового клиента | B11: 2645 | C11: ₽ | G11: 09b, строки о стоимости клиента
A12: Время на привлечение нового клиента | B12: 2.32 | C12: ч | G12: 09b: поиск 2,02 ч + переписка сверх постоянного 0,30 ч
A13: Рабочих часов в дне | B13: 8 | C13: ч | G13: 02_Параметры
A15: ФОНД ПРОГРАММЫ ЛОЯЛЬНОСТИ — сколько денег и на что
A16: Направление | B16: Доля | C16: Сумма / год | G16: Комментарий
A17: Бюджет фонда, всего | C17: 377826 | G17: Резерв, заложенный в цену: цена = база / (1 − резерв). Считается в calc.html
A18: Скидка за объём | B18: =C18/$C$17 | C18: =C17-C19-C20 | G18: Остаток фонда: то, что не ушло на постоянных и спецпредложения
A19: Постоянным клиентам | B19: =C19/$C$17 | C19: =F30 | G19: Ровно сумма ступеней ниже — направление расходуется полностью
A20: Специальные предложения | B20: =C20/$C$17 | C20: =E46 | G20: Ровно номинал комплекта сертификатов
A21: ИТОГО | B21: =SUM(B18:B20) | C21: =SUM(C18:C20) | G21: Должно совпасть с бюджетом фонда
A22: В месяц | C22: =ROUND(C17/12,0)
A23: С каждой съёмки | C23: =ROUND(C17/B9,0)
A25: СКИДКА ПОСТОЯННОМУ КЛИЕНТУ — ступени и распределение бюджета
A26: Частота визитов | B26: Скидка | C26: Съёмок / год | D26: Клиентов | E26: Заказов | F26: Скидка / год | G26: Порог: принесёт вам от
A27: Раз в полгода | B27: 0.05 | C27: 2 | D27: 10 | E27: =C27*D27 | F27: =ROUND(E27*$B$10*B27,0) | G27: =ROUND(C27*$B$10*(1-B27),-2)
A28: Раз в квартал | B28: 0.07 | C28: 4 | D28: 5 | E28: =C28*D28 | F28: =ROUND(E28*$B$10*B28,0) | G28: =ROUND(C28*$B$10*(1-B28),-2)
A29: Раз в месяц | B29: 0.1 | C29: 12 | D29: 1 | E29: =C29*D29 | F29: =ROUND(E29*$B$10*B29,0) | G29: =ROUND(C29*$B$10*(1-B29),-2)
A30: ИТОГО | D30: =SUM(D27:D29) | E30: =SUM(E27:E29) | F30: =SUM(F27:F29)
A31: Сходимость фонда | F31: =C21-C17 | G31: Должно быть 0: сумма трёх направлений равна бюджету фонда
A32: Доля заказов от постоянных | F32: =E30/B9 | G32: Отраслевая норма Repeat Purchase Rate 20–40%, медиана 27% — см. 09b
A34: ВЫГОДА ФОТОГРАФА СВЕРХ СКИДОК — в покрытие НЕ идёт
A35: Показатель | C35: Значение | G35: Комментарий
A36: Сэкономлено на привлечении | C36: =ROUND(E30*B11,0) | G36: Повторный заказ не требует поиска и повторных согласований
A37: Высвобождено времени, ч | C37: =ROUND(E30*B12,0)
A38: То же в рабочих днях | C38: =ROUND(C37/B13,0)
A39: Решение 09.08.2026 | G39: Раньше экономия засчитывалась в покрытие скидок, из фонда уходило 19% — фонд выглядел нерасходуемым. Теперь скидки считаются от бюджета фонда, а экономия показана отдельной строкой.
A41: СПЕЦИАЛЬНЫЕ ПРЕДЛОЖЕНИЯ — комплект сертификатов на год
A42: Код | B42: Название | C42: Номинал | D42: Штук / год | E42: Сумма | G42: Как использовать
A43: SP-26001 | B43: День рождения | C43: 5000 | D43: 7 | E43: =C43*D43 | G43: Точечный прогрев в несезон
A44: SP-26002 | B44: На свадьбу | C44: 10000 | D44: 1 | E44: =C44*D44 | G44: Розыгрыш среди подписчиков, ажиотаж вокруг услуги
A45: SP-26003 | B45: Событие | C45: 3000 | D45: 23 | E45: =C45*D45 | G45: Бонус клиенту или под удобные праздники
A46: ИТОГО | D46: =SUM(D43:D45) | E46: =SUM(E43:E45)
A47: Остаток направления | E47: 0 | G47: Направление задано ровно по номиналу комплекта. Чтобы добавить сертификатов, увеличьте комплект — фонд перераспределится сам
A49: СКИДКА ЗА ОБЪЁМ — ступени прайса
A50: Длительность | B50: Цена часа | C50: Скидка | G50: Комментарий
A51: от 1 часа — базовая | B51: 11700 | C51: — | G51: Базовая ставка прайса, резерв уже включён
A52: от 3 часов | B52: 10500 | C52: =B52/$B$51-1 | G52: Проценты считаются от ОКРУГЛЁННЫХ цен — клиент проверит на калькуляторе
A53: от 5 часов | B53: 9400 | C53: =B53/$B$51-1
A54: от 7 часов | B54: 8300 | C54: =B54/$B$51-1
A55: Природа скидки | G55: Часть — накладные (подготовка размазывается на больше часов), часть — из фонда. Доход фотографа не меняется.

Sheet 14_Опрос
A1: 14 · ОПРОС — что доработать в первую очередь
A2: Показываются все 4 варианта пула, всегда в одном порядке. Метрика — лайки / показы. Жёлтое редактируется, иконка берётся по коду.
A4: ПУЛ ВАРИАНТОВ
A5: № | B5: price | C5: Прайс для клиентов | D5: готовый прайс-лист, который не стыдно отправить | E5: да
A6: 1 | B6: invoice | C6: Счета и акты | D6: выставить за минуту, без бухгалтера | E6: да
A7: 2 | B7: pocket | C7: Карманный помощник | D7: приложение, которое всегда с вами | E7: да
A8: 3 | B8: search | C8: Поиск клиентов | D8: где брать заказы, когда сарафанное радио молчит | E8: да
A9: 4 | B9: tax | C9: Налоговый помощник | D9: какой режим выгоднее именно вам | E9: да | F9: УДАЛЕНО из HTML: пул сокращён до 4 фиксированных вариантов
A10: 5 | B10: calendar | C10: Календарь съёмок | D10: планировать загрузку на месяц | E10: да | F10: УДАЛЕНО из HTML: пул сокращён до 4 фиксированных вариантов
A11: 6 | B11: clients | C11: База клиентов | D11: помнить, кто и сколько заказывал | E11: да | F11: УДАЛЕНО из HTML: пул сокращён до 4 фиксированных вариантов
A12: 7 | B12: contract | C12: Договоры | D12: шаблоны под съёмку и предоплату | E12: да | F12: УДАЛЕНО из HTML: пул сокращён до 4 фиксированных вариантов
A13: 8 | B13: analytics | C13: Аналитика года | D13: сравнить месяцы и увидеть рост | E13: да | F13: УДАЛЕНО из HTML: пул сокращён до 4 фиксированных вариантов
A14: 9 | B14: budget | C14: Сравнение с рынком | D14: какие цены у коллег в вашем городе | E14: да | F14: УДАЛЕНО из HTML: пул сокращён до 4 фиксированных вариантов
A15: 10 | B15: analytics | C15: Расчёт на команду | D15: если работаете не одни | E15: да | F15: иконка переиспользована
A17: КАК РАБОТАЕТ
A18: Показываются все 4 варианта пула — без случайной выборки, порядок фиксирован.
A19: Пользователь отмечает сердечком те, что ему нужны, и нажимает «Отправить».
A21: ВАЖНО ПРО СТАТИСТИКУ: считаем не только лайки, но и показы.
A22: Метрика = лайки / показы. Иначе сравнение нечестное: у вариантов разное число показов.
A23: Показы = число расчётов: каждый вариант видят все, кто дошёл до отчёта.
A25: Добавить вариант: впишите строку выше, продублируйте в POOL внутри HTML и добавьте иконку в ICONS.
A27: ЦЕЛИ В ЯНДЕКС.МЕТРИКЕ
A28: № | B28: Цель | C28: Когда срабатывает | D28: Параметры
A29: 1 | B29: poll_show | C29: при отрисовке блока опроса | D29: shown — какие 4 варианта показаны
A30: 2 | B30: poll_vote | C30: при нажатии «Отправить» | D30: liked — отмеченные, other — своя идея, shown
A31: 3 | B31: buy_click | C31: клик по ценнику или кнопке оплаты | D31: —
A32: 4 | B32: paid | C32: возврат на страницу с ?paid=1 | D32: —
A34: Номер счётчика пропишите в HTML: var YM_ID=0; → var YM_ID=ваш_номер;
A35: Отчёт в Метрике: «Отчёты → Конверсии → Цели», параметры видны в «Содержание → Параметры визитов».
A37: ЕСЛИ НУЖНО СОБИРАТЬ ОТВЕТЫ В TILDA
A38: Вариант 1. Метрика — уже настроено, ничего не нужно. Смотрите статистику в отчётах.
A39: Вариант 2. Форма Tilda — добавить скрытое поле и отправлять ответы в Заявки.
A40: В HTML заменить отправку в ym() на fetch к форме Tilda с полями liked и other.
A41: Вариант 3. Google-таблица через Tilda — заявки автоматически падают в таблицу.
A43: Для теста хватит Метрики: она уже стоит и не требует бэкенда.
