Workbook
Name days_year: 'calc'!$C$6
Name work_days: 'calc'!$C$7
Name days_week: 'calc'!$C$8
Name months: 'calc'!$C$9
Name quarters: 'calc'!$C$10
Name weeks_year: 'calc'!$C$11
Name nominal_hours: 'calc'!$C$12
Name work_months: 'calc'!$C$13
Name vacation_cal: 'calc'!$C$14
Name vacation_work: 'calc'!$C$15
Name sick_cal: 'calc'!$C$16
Name sick_work: 'calc'!$C$17
Name eff_hours: 'calc'!$C$18
Name work_time: 'calc'!$C$21
Name net_days: 'calc'!$C$22
Name net_time: 'calc'!$C$23
Name net_weeks: 'calc'!$C$24
Name promo_per_day: 'calc'!$C$25
Name promo_time: 'calc'!$C$26
Name acc_mode: 'calc'!$C$27
Name acc_per_quarter: 'calc'!$C$28
Name accounting_time: 'calc'!$C$29
Name side_time: 'calc'!$C$30
Name pool_gross: 'calc'!$C$31
Name fm_on: 'calc'!$C$32
Name fm_pct: 'calc'!$C$33
Name fm_time: 'calc'!$C$34
Name fm_week: 'calc'!$C$35
Name project_pool: 'calc'!$C$36
Name post_ratio: 'calc'!$C$39
Name profile_multiplier: 'calc'!$C$40
Name client_time: 'calc'!$C$41
Name shoot_duration: 'calc'!$C$42
Name week_target: 'calc'!$C$43
Name shoot_auto: 'calc'!$C$44
Name project_time: 'calc'!$C$45
Name projects_year: 'calc'!$C$46
Name projects_month: 'calc'!$C$47
Name projects_week: 'calc'!$C$48
Name shooting_time: 'calc'!$C$49
Name shooting_month: 'calc'!$C$50
Name shooting_week: 'calc'!$C$51
Name post_time: 'calc'!$C$52
Name core_time: 'calc'!$C$53
Name client_total: 'calc'!$C$54
Name ops_per_shoot: 'calc'!$C$55
Name income_month: 'calc'!$C$58
Name target_income: 'calc'!$C$59
Name current_rate: 'calc'!$C$60
Name ws_mode: 'calc'!$C$63
Name own_home: 'calc'!$C$64
Name home_rent: 'calc'!$C$65
Name home_util: 'calc'!$C$66
Name home_area: 'calc'!$C$67
Name cab_area: 'calc'!$C$68
Name cab_share: 'calc'!$C$69
Name office_rent: 'calc'!$C$70
Name office_util: 'calc'!$C$71
Name var_workspace: 'calc'!$C$72
Name edu_cost: 'calc'!$C$75

Sheet 00_Читать
A1: СЧЁТИКС · калькулятор стоимости часа
A2: Расчёт юнит-экономики для фотографов и видеографов. Обновлено 25 августа 2026.
A4: ИЗ ЧЕГО СОСТОИТ ПРОДУКТ — ЧЕТЫРЕ ФАЙЛА
A5: Файл | B5: Что это и где живёт
A6: Книга/Калькулятор_ставки_часа.xlsx | B6: ЭТА КНИГА, 30 листов: параметры, каталоги, расчёт, глоссарий, реестры. Источник понятий и сверка
A7: Веб/index.html | B7: СТРАНИЦА ВХОДА. Обложка; кто уже начинал — сразу в анкету
A8: Веб/calc.html | B8: АНКЕТА + ВЕСЬ РАСЧЁТ — функция calc(). Результат вынесен в отчёт
A9: Веб/report.html | B9: ПОЛНЫЙ ОТЧЁТ: 21 блок, справочник на 77 понятий, 8 таблиц детализации. Бесплатный; данные приходят из анкеты
A11: ОПОРНЫЕ ЛИСТЫ КНИГИ — 30 ЛИСТОВ
A12: Лист | B12: Назначение
A13: 00_Читать | B13: Этот лист — карта книги
A14: 01_Глоссарий | B14: Источник понятий: 125 строк
A15: calc | B15: 121 именованная величина. ГЛАВНЫЙ лист для правки цифр
A16: Состав | B16: Группировка параметров отчёта: ID из calc, наименование из глоссария, составные части по номерам. Заполняется по блокам
A17: 03_Каталоги | B17: Позиции форм: техника, ПО, реклама, банк
A18: 04_Итог / 05_Расчёт | B18: Свод по режиму и расчёт по семи налоговым режимам
A19: 06_Отчёт / 06b_Отчёт_полный | B19: Отчёт в книге; 06b — 46 показателей со сверкой с калькулятором
A20: 07_Интерфейс / 08_UI / 08c_Структура_отчёта | B20: Структура анкеты и отчёта
A21: 09_Тексты | B21: 514 надписей: ключ data-t → текст
A22: 09b_Методика_цифр / 09e_Как_считается | B22: Как посчитана каждая цифра отчёта
A23: 09c_Палитра / 09d_Логотип / 09g_Сокращения / 09h_Элементы | B23: Единый стиль записи и оформления
... A28: 28_Журнал_изменений | B28: Летопись модели
A30: ЧТО ГДЕ ПРАВИТЬ
A31: Задача | B31: Куда идти
A32: Поменять текст надписи | B32: 09_Тексты → найти по ключу data-t из HTML → колонка «Текст»
A33: Поменять цифру или формулу | B33: calc → колонка «Значение»
A34: Поменять цвет | B34: 09c_Палитра → HEX → тот же токен в :root обоих HTML
A35: Добавить оборудование | B35: 03_Каталоги → новая строка с кодом формы
A36: Изменить скидки, фонд, сертификаты | B36: 13b_Программа_лояльности → жёлтые ячейки
A38: ПЕРЕД ПУБЛИКАЦИЕЙ — ОБЯЗАТЕЛЬНО
A39: 1 | B39: YM_ID → номер счётчика Метрики (сейчас 0)
A40: 2 | B40: PAY_URL → ссылка оплаты (сейчас «#order»); возврат — report.html?paid=1
A41: 3 | B41: Выполнить З-039: публикационная копия без DEMO
A42: 4 | B42: Пройти путь целиком на телефоне и на компьютере
A44: Подробности — Документация/Подготовка к запуску/ и README.md в корне проекта.

Sheet 01_Глоссарий
A1: № | B1: Наименование | C1: ID | D1: Назначение | E1: Тип | F1: Определение
A1: 1 | B2: Маркер | C2: marker | D2: meta | E2: — | F2: Служебный параметр, который используется для обозначения принадлежности элемента или понятия к определённому типу, категории или назначению.
A2: 2 | B3: id в вёрстке | C3: id | D3: meta | E3: — | F3: Обозначение элемента на странице, по которому скрипт подставляет в него рассчитанное значение.
A3: 3 | B4: Служебное понятие | C4: meta | D4: meta | E4: marker | F4: Обозначение, описывающее устройство самого калькулятора, а не деятельность специалиста.
A4: 4 | B5: Пользовательское понятие | C5: user | D5: meta | E5: marker | F5: Понятие глоссария, предназначенное для публикации в пользовательском справочнике. Одновременно используется во внутренних расчётах, документации и связях проекта.
A5: 5 | B6: Параметр | C6: — | D6: meta | F6: Именованная величина, или характеристика со своим постоянным обозначением, которая используется в расчётах и на которую могут ссылаться формулы и другие параметры.
A6: 6 | B7: Назначение | C7: — | D7: meta | E7: marker | F7: Область использования элемента или понятия в структуре Счётикс и его проектной документации.
A7: 7 | B8: Тип | C8: — | D8: meta | E8: marker
A8: 8 | B9: Значение | D9: meta | F9: Конкретная величина или характеристика параметра, используемая калькулятором для отображения, расчёта или настройки результата.
A9: 9 | B10: Константа | C10: const | D10: meta | F10: Заранее установленное значение, которое используется в расчётах и не изменяется в зависимости от введённых пользователем данных.
A10: 10 | B11: Значение по умолчанию | C11: default | D11: meta | F11: Заранее установленное значение параметра, которое используется автоматически, если пользователь не указал другое значение.
A11: 11 | B12: Введённое значение | D12: meta | F12: Значение параметра, которое пользователь самостоятельно указал (выбрал из выпадающего списка, ввёл вручную или другим способом) или изменил вручную.
A12: 12 | B13: Тип значения | D13: meta | F13: Определяет, что означает значение параметра и как с ним работать в калькуляторе: процент, денежная сумма, время, количество, текст, выбор и т. д.
A13: 13 | B14: Расчётное значение (Формула) | D14: meta | F14: Значение, полученное в результате вычисления на основе других параметров.
A14: 14 | B15: Отображаемое значение | D15: meta | F15: Значение, которое выводится пользователю в интерфейсе и может отличаться от фактического значения параметра из-за форматирования, округления или способа представления.
A15: 15 | B16: Вводимые данные | C16: input_data | D16: meta | F16: Данные введенные пользователем вручную
A16: 16 | B17: Интерфейс | C17: ui | D17: meta | E17: marker | F17: Совокупность элементов, с которыми взаимодействует пользователь.
A17: 17 | B18: Страница | D18: meta | E18: ui | F18: Отдельный экран интерфейса, содержащий определённый набор элементов.
A18: 18 | B19: Анкета | D19: meta | E19: ui | F19: Часть интерфейса, предназначенная для последовательного ввода пользователем данных для расчета.
A19: 19 | B20: Отчёт | C20: report | D20: meta | E20: ui | F20: Часть интерфейса, предназначенная для представления результатов расчёта.
A20: 20 | B21: Главный экран | C21: hero | D21: meta | E21: ui | F21: Главный блок на странице
A21: 21 | B22: Раздел | C22: section | D22: meta | E22: ui | F22: Крупная часть анкеты, объединяющая несколько блоков.
A22: 22 | B23: Блок | C23: block | D23: meta | E23: ui | F23: Смысловая часть анкеты: один вопрос или группа связанных вопросов с общим заголовком.
A23: 23 | B24: Выпадающий список | C24: dropdown | D24: meta | E24: ui | F24: Выпадающий список с выбором одного варианта.
A24: 24 | B25: Поле с ручным вводом | D25: meta | E25: ui | F25: Элемент интерфейса, позволяющий пользователю самостоятельно ввести значение с клавиатуры в предусмотренное для этого поле.
A25: 25 | B26: Галочка | C26: checkbox | D26: meta | E26: ui | F26: Включает или выключает блок либо строку расчёта.
A26: 26 | B27: Обратная галочка | D27: meta | E27: ui | F27: Элемент интерфейса, позволяющий пользователю включить или отключить определённую опцию. Установка галочки активирует соответствующий блок или функцию, снятие галочки — отключает их.
A27: 27 | B28: Переключатель | C28: switch | D28: meta | E28: ui | F28: Параметр с выбором из нескольких вариантов, который меняет не только значение, но и сам ход расчёта.
A28: 28 | B29: Текстовый блок | C29: info_block | D29: meta | E29: ui | F29: Пояснительный текст без полей ввода.
A29: 29 | B30: Форма | C30: form | D30: meta | E30: ui | F30: Набор однотипных строк, которые пользователь заполняет списком.
A30: 30 | B31: Каталог | C31: cat_form, cat_year | D31: meta | E31: ui | F31: Список позиций формы вместе с ценой, сроком службы, периодом платежа и годовой суммой.
A31: 31 | B32: Таблица | D32: meta | E32: ui | F32: Элемент интерфейса, предназначенный для представления структурированной информации в виде строк и столбцов, где данные распределены по определённым категориям и показателям.
A32: 32 | B33: Шапка таблицы | C33: table_head | D33: meta | E33: ui | F33: Названия столбцов таблицы.
A33: 33 | B34: Строка таблицы | C34: table_row | D34: meta | E34: ui | F34: Одна строка, заполняемая пользователем.
A34: 34 | B35: Кнопка | C35: button | D35: meta | E35: ui | F35: Элемент интерфейса, предназначенный для выполнения определённого действия при нажатии.
A35: 35 | B36: Строка показателей | C36: report_row | D36: meta | E36: ui | F36: Три показателя в строку под главной плашкой.
A36: 36 | B37: Диаграмма | C37: chart_donut | D37: meta | E37: ui | F37: Кольцо с сегментами и легендой.
A37: 37 | B38: Книга | D38: meta | E38: ui | F38: Совокупность взаимосвязанных таблиц, объединённых в один файл или документ и предназначенных для совместного хранения, обработки и расчёта данных.
A38: 38 | B39: Лист книги | C39: list | D39: meta | E39: ui | F39: Отдельная страница книги с номером и назначением в названии.
A39: 39 | B40: Выручка | D40: user | F40: Общая сумма денежных средств, которую специалист получает от продажи своих услуг за определённый период, включая суммы, предназначенные для покрытия всех расходов и обязательных платежей, налогов, стоимости оборудования и его амортизации, банковских расходов, резервов на отпуск, развитие, обучение и другие предусмотренные расчётом затраты, а также доход специалиста.
A40: 40 | B41: Доход | D41: user | F41: Денежные средства, остающиеся у специалиста от профессиональной деятельности после покрытия связанных с этой деятельностью расходов, налогов и обязательных платежей.
A41: 41 | B42: Желаемый доход | D42: user | F42: Сумма денежных средств, которую специалист планирует получать на руки от своей профессиональной деятельности после покрытия всех расходов, налогов и обязательных платежей ежемесячно в течение года, включая периоды оплачиваемого отпуска.
A42: 42 | B43: Доход на руки | D43: user | F43: Сумма денежных средств, остающаяся у специалиста после вычета налогов, обязательных платежей и других предусмотренных расходов.
A43: 43 | B44: Ставка часа съёмки (стоимость часа съёмки) | D44: user | F44: Стоимость одного часа съёмочных работ, установленная специалистом для клиента.
A44: 44 | B45: Текущая ставка | C45: current_rate | D45: user | E45: default | F45: Стоимость одного часа работы фотографа на съёмочной площадке, по которой он в настоящее время оказывает услуги клиентам.
A46: 46 | B47: Ставка в ноль | D47: user | F47: Минимальная стоимость съёмочного часа, при которой специалист достигает точки безубыточности, то есть получает выручку, достаточную для покрытия предусмотренных расчётом расходов и обязательных платежей, но не получает дохода сверх них. | C47: rateZero | E47: calc
A47: 47 | B48: Точка безубыточности | D48: user | F48: Минимальный объём выручки или продаж за определённый период, необходимый для покрытия всех предусмотренных расчётом расходов, налогов и обязательных платежей без получения дополнительного дохода. Может выражаться в денежных единицах, количестве съёмок, съёмочных часах или других единицах объёма деятельности.
A48: 48 | B49: Минимальное количество съёмок для покрытия расходов | D49: user | F49: Точка безубыточности в натуральном выражении. Объём реализации в натуральных единицах, при котором выручка покрывает все предусмотренные расчётом затраты, а доход специалиста равен нулю. Для фотографа показатель может выражаться в количестве съёмочных проектов, необходимых для достижения точки безубыточности за выбранный период.
A49: 49 | B50: Доход в час на руки | D50: user | F50: Сумма, которую специалист получает на руки за один рабочий час при сравнении с наймом. Считается так: желаемый доход на руки за 11 месяцев делится на рабочее время — рабочие дни, умноженные на восемь часов.
A50: 50 | B51: Базовая ставка | C51: base_rate | D51: user | E51: calc | F51: Стоимость одного часа работы специалиста при оказании услуг клиенту вне съёмочной площадки, рассчитанная с учётом всех затрат, необходимых для профессиональной деятельности специалиста, включая расходы на оборудование, налоги, обязательные платежи, отпуск и другие предусмотренные расчётом затраты, без повышающего коэффициента, применяемого к съёмочному часу. Используется для формирования стоимости услуг, не связанных непосредственно со съёмкой, например ретуши, индивидуальных консультаций и выполнения индивидуальных задач для клиента.
A51: 51 | B52: Месяц | D52: user | F52: Календарный период продолжительностью от 28 до 31 календарного дня, имеющий наименование и порядковый номер в году.
A52: 52 | B53: Квартал | D53: user | F53: Календарный период продолжительностью три последовательных месяца. Календарный год состоит из четырёх кварталов.
A53: 53 | B54: Год | D54: user | F54: Календарный период продолжительностью 12 последовательных месяцев, включающий четыре квартала.
A54: 54 | B55: Рабочее время | D55: user | F55: Время, в течение которого специалист выполняет профессиональные обязанности, включая непосредственную работу, подготовку, организационные задачи и другие действия, связанные с выполнением работы. Нормальная продолжительность рабочего времени не может превышать 40 часов в неделю.
A55: 55 | B56: Эффективное рабочее время | D56: user | F56: Время рабочего дня, фактически доступное для выполнения профессиональных задач после учёта объективно необходимых перерывов на отдых, личные потребности, восстановление работоспособности, подготовку и обслуживание рабочего места. Такие затраты времени являются естественной частью организации труда и учитываются при нормировании рабочей нагрузки.
A56: 56 | B57: Неэффективное рабочее время | D57: user | F57: Часть рабочего времени, затрачиваемая на действия и перерывы, не связанные непосредственно с выполнением основной оплачиваемой работы, включая личные потребности, отдых, обслуживание рабочего места, внутренние коммуникации и другие отвлечения. Используется в Счётикс для учёта времени, которое фактически не может быть использовано для выполнения оплачиваемой работы.
A57: 57 | B58: Выходной | D58: user | F58: Дни недели, в которые работник освобождён от выполнения трудовых обязанностей в соответствии с установленным режимом рабочего времени. Предоставляются для еженедельного непрерывного отдыха. По общему правилу при пятидневной рабочей неделе предоставляются два выходных дня, при шестидневной — один.
A58: 58 | B59: Праздник | D59: user | F59: Дни, в которые в соответствии с Трудовым кодексом Российской Федерации работник освобождён от исполнения трудовых обязанностей; конкретные даты выходных и нерабочих праздничных дней и их переносы определяются с учётом производственного календаря.
A59: 59 | B60: Отпуск | D60: user | F60: Ежегодный период освобождения от работы для отдыха и восстановления, на время которого специалист предусматривает сохранение дохода. Основная продолжительность ежегодного оплачиваемого отпуска составляет 28 календарных дней.
A60: 60 | B61: Отпуск / рабочих дней | D61: meta | F61: Количество рабочих дней, приходящихся на период ежегодного оплачиваемого отпуска, используемое Счётикс для расчёта доступного рабочего времени. Показатель определяется на основании продолжительности отпуска и производственного календаря и используется только для внутренних расчётов.
A61: 61 | B62: Больничный | D62: user | F62: Период временной нетрудоспособности из-за болезни, травмы или иных обстоятельств, в течение которого человек не может выполнять работу.
A62: 62 | B63: Больничный / рабочих дней | D63: meta | F63: Рабочие дни временной нетрудоспособности — количество рабочих дней, приходящихся на период временной нетрудоспособности, используемое Счётикс исключительно для расчёта доступного рабочего времени.
... A138: 137 | B138: Всего расходов | D138: user | F138: Общая сумма денежных средств, которую специалист затрачивает на покрытие финансовых расходов, налогов и банковских комиссий, связанных с профессиональной деятельностью, за определённый период.
A139: 138 | B139: Желаемая ставка | C139: rateHour | D139: user | E139: calc | F139: Стоимость одного часа съёмки, которая позволяет специалисту получать желаемый доход.
A140: 139 | B140: Текущий доход | C140: currentResult | D140: user | E140: calc | F140: Сумма денежных средств, которую специалист может получать на руки при текущей ставке и условиях профессиональной деятельности, указанных в анкете, после покрытия всех расходов, налогов и обязательных платежей.

Sheet calc
A1: 02 · ПАРАМЕТРЫ — каждая величина объявлена один раз, формулы записаны через ID
A2: Жёлтое — ввод пользователя. Оранжевое — ПЕРЕКЛЮЧАТЕЛЬ (выпадающий список). Зелёное — вычисляется. Серое — константа.
A4: 1 · КАЛЕНДАРЬ
A5: ID | B5: Название | C5: Значение | D5: Ед. | E5: Формула / как получено | F5: Тип | G5: Зависит от | H5: Источник / форма
A6: days_year | B6: Всего дней в году | C6: 365 | D6: дн | F6: const
A7: work_days | B7: Рабочих дней в году | C7: 247 | D7: дн | F7: const | H7: Произв. календарь РФ 2026
A8: days_week | B8: Рабочих дней в неделю | C8: 5 | D8: дн | F8: const
A9: months | B9: Месяцев в году | C9: 12 | D9: мес | F9: const
A10: quarters | B10: Кварталов в году | C10: 4 | D10: кв | F10: const
A11: weeks_year | B11: Всего недель в году | C11: =days_year/7 -> 52.142857 | D11: нед | E11: days_year/7 | F11: calc | G11: days_year
A12: nominal_hours | B12: Номинальных часов в дне | C12: 8 | D12: ч | F12: const | H12: ст. 91 ТК РФ
A13: work_months | B13: Рабочих месяцев в году | C13: 11 | D13: мес | F13: const | H13: СПРАВОЧНО, в расчёте не участвует
A14: vacation_cal | B14: Отпуск, календарных дней | C14: 28 | D14: дн | F14: const | H14: ст. 115 ТК РФ
A15: vacation_work | B15: Отпуск, рабочих дней | C15: 20 | D15: дн | F15: const
A16: sick_cal | B16: Больничный, календарных дней | C16: 10 | D16: дн | F16: const | H16: среднее за год
A17: sick_work | B17: Больничный, рабочих дней | C17: 8 | D17: дн | F17: const
A18: eff_hours | B18: Чистых (эффективных) часов в дне | C18: 7 | D18: ч | F18: const | H18: 8 минус час на перерывы
A19: 2 · ВРЕМЯ — иерархия по вашему определению
A20: ID | B20: Название | C20: Значение | D20: Ед. | E20: Формула / как получено | F20: Тип | G20: Зависит от | H20: Источник / форма
A21: work_time | B21: Рабочее время по календарю | C21: =work_days*nominal_hours -> 1976 | D21: ч/год | E21: work_days*nominal_hours | F21: calc | G21: work_days, nominal_hours | H21: 247 × 8. Справочно
A22: net_days | B22: Чистое рабочее время, дней | C22: =work_days-vacation_work-sick_work -> 219 | D22: дн/год | E22: work_days-vacation_work-sick_work | F22: calc | G22: work_days, vacation_work, sick_work
A23: net_time | B23: ЧИСТОЕ время | C23: =net_days*eff_hours -> 1533 | D23: ч/год | E23: net_days*eff_hours | F23: calc | G23: net_days, eff_hours | H23: Верхний уровень: всё доступное время
A24: net_weeks | B24: Чистое время, недель | C24: =net_days/days_week -> 43.8 | D24: нед | E24: net_days/days_week | F24: calc | G24: net_days, days_week
A25: promo_per_day | B25: Продвижение, часов в день | C25: 2 | D25: ч/дн | F25: default | H25: Form009
A26: promo_time | B26: Продвижение за год | C26: =promo_per_day*net_days -> 438 | D26: ч/год | E26: promo_per_day*net_days | F26: calc | G26: promo_per_day, net_days | H26: Form009
A27: acc_mode | B27: ПЕРЕКЛЮЧАТЕЛЬ · учёт и планирование | C27: Веду самостоятельно | F27: default | H27: Form011 · Block14
A28: acc_per_quarter | B28: Учёт: часов в квартал, если веду сам | C28: 3 | D28: ч/кв | F28: default | H28: Form011
A29: accounting_time | B29: Учёт и планирование, время | C29: =IF(acc_mode="Веду самостоятельно",acc_per_quarter*quarters,0) -> 12 | D29: ч/год | E29: IF(acc_mode="Веду самостоятельно",acc_per_quarter*quarters,0) | F29: calc | G29: acc_mode, acc_per_quarter, quarters | H29: Если наняли — время = 0
A30: side_time | B30: ОПЕРАЦИОННОЕ время | C30: =promo_time+accounting_time -> 450 | D30: ч/год | E30: promo_time+accounting_time | F30: calc | G30: promo_time, accounting_time | H30: Второстепенные операции. Клиенту не продаётся
A31: pool_gross | B31: Время на заказы до резерва | C31: =net_time-side_time -> 1083 | D31: ч/год | E31: net_time-side_time | F31: calc | G31: net_time, side_time | H31: Чистое минус операционное
A32: fm_on | B32: ПЕРЕКЛЮЧАТЕЛЬ · резерв времени на простой и форс-мажоры | C32: Не закладывать | F32: default | H32: Block14a | I32: Галочка «Учитывать резерв времени на простой и форс-мажоры» СНЯТА по умолчанию (06.08.2026). Поле % неактивно, пока не включена
A33: fm_pct | B33: Резерв времени на простой и форс-мажоры, % | C33: 0.05 | D33: % | F33: default | H33: Периоды без заказов, перенос и отмена съёмок, срывы по вине клиента, повторные выезды. Редактируется | I33: Галочка «Учитывать резерв времени на простой и форс-мажоры» СНЯТА по умолчанию (06.08.2026). Поле % неактивно, пока не включена
A34: fm_time | B34: Резерв времени на простой и форс-мажоры, часов | C34: =IF(fm_on="Заложить резерв",pool_gross*fm_pct,0) -> 0 | D34: ч/год | E34: IF(fm_on="Заложить резерв",pool_gross*fm_pct,0) | F34: calc | G34: fm_on, fm_pct, pool_gross | H34: Вычитается из времени на заказы
A35: fm_week | B35: Резерв, часов в неделю | C35: =IF(net_weeks=0,0,fm_time/net_weeks) -> 0 | D35: ч/нед | E35: IF(net_weeks=0,0,fm_time/net_weeks) | F35: calc | G35: fm_time, net_weeks | H35: Для наглядности
A36: project_pool | B36: ПРОЕКТНОЕ время за год | C36: =pool_gross-fm_time -> 1083 | D36: ч/год | E36: pool_gross-fm_time | F36: calc | G36: pool_gross, fm_time | H36: Всё, что остаётся на выполнение проектов
A37: 3 · ПРОЕКТ — S × (1+K) + 1. Длительность съёмки задаёт пользователь
A38: ID | B38: Название | C38: Значение | D38: Ед. | E38: Формула / как получено | F38: Тип | G38: Зависит от | H38: Источник / форма
A39: post_ratio | B39: Коэффициент обработки | C39: 3 | D39: × | F39: default | H39: Часов обработки на 1 час съёмки. МЕНЯЕТСЯ пользователем: у свадебного ретушёра больше, у репортажника меньше
A40: profile_multiplier | B40: Множитель профильного времени | C40: =1+post_ratio -> 4 | D40: × | E40: 1+post_ratio | F40: calc | G40: post_ratio | H40: ПРОФИЛЬНОЕ на проект = S × (1 + коэффициент): съёмка плюс обработка
A41: client_time | B41: Работа с клиентом на проект | C41: 1 | D41: ч/проект | F41: default | H41: Form012 · Block13 · продажа, согласования, организация
A42: shoot_duration | B42: ТИПОВАЯ продолжительность съёмки (S) | C42: 1 | D42: ч | F42: default | H42: Block3 · самый частый формат заказа. ЗАДАЁТ ПОЛЬЗОВАТЕЛЬ, по умолчанию 2 ч
A43: week_target | B43: Целевых проектов в неделю | C43: 1 | D43: шт/нед | F43: default | H43: СПРАВОЧНАЯ. В расчёте ставки не участвует
A44: shoot_auto | B44: Максимальная съёмка при целевом темпе | C44: =IF(profile_multiplier*week_target=0,0,(project_pool/net_weeks/week_target-client_time)/profile_multiplier) -> 5.9315068 | D44: ч | E44: IF(profile_multiplier*week_target=0,0,(project_pool/net_weeks/week_target-client_time)/profile_multiplier) | F44: calc | G44: project_pool, net_weeks, week_target, client_time, profile_multiplier | H44: СПРАВОЧНАЯ: какая съёмка влезет при таком темпе. В расчёте НЕ участвует
A45: project_time | B45: ПРОЕКТНОЕ время на 1 проект | C45: =shoot_duration*profile_multiplier+client_time -> 5 | D45: ч/проект | E45: shoot_duration*profile_multiplier+client_time | F45: calc | G45: shoot_duration, profile_multiplier, client_time | H45: S × (1 + коэффициент) + час клиента — полная реализация заказа
A46: projects_year | B46: Проектов в год | C46: =IF(project_time=0,0,project_pool/project_time) -> 216.6 | D46: шт/год | E46: IF(project_time=0,0,project_pool/project_time) | F46: calc | G46: project_pool, project_time
A47: projects_month | B47: Проектов в месяц | C47: =projects_year/months -> 18.05 | D47: шт/мес | E47: projects_year/months | F47: calc | G47: projects_year, months
A48: projects_week | B48: Проектов в неделю | C48: =projects_year/net_weeks -> 4.9452055 | D48: шт/нед | E48: projects_year/net_weeks | F48: calc | G48: projects_year, net_weeks | H48: При авторежиме равно week_target
A49: shooting_time | B49: СЪЁМОЧНОЕ время | C49: =projects_year*shoot_duration -> 216.6 | D49: ч/год | E49: projects_year*shoot_duration | F49: calc | G49: projects_year, shoot_duration | H49: ЦЕЛЬ РАСЧЁТА — знаменатель ставки
A50: shooting_month | B50: Съёмочное время в месяц | C50: =shooting_time/months -> 18.05 | D50: ч/мес | E50: shooting_time/months | F50: calc | G50: shooting_time, months
A51: shooting_week | B51: Съёмочное время в неделю | C51: =shooting_time/net_weeks -> 4.9452055 | D51: ч/нед | E51: shooting_time/net_weeks | F51: calc | G51: shooting_time, net_weeks
A52: post_time | B52: Постпродакшн за год | C52: =shooting_time*post_ratio -> 649.8 | D52: ч/год | E52: shooting_time*post_ratio | F52: calc | G52: shooting_time, post_ratio | H52: S × коэффициент на каждый проект
A53: core_time | B53: ПРОФИЛЬНОЕ время | C53: =shooting_time*profile_multiplier -> 866.4 | D53: ч/год | E53: shooting_time*profile_multiplier | F53: calc | G53: shooting_time, profile_multiplier | H53: Съёмка + обработка = S × (1 + коэффициент). БЕЗ работы с клиентом
A54: client_total | B54: Работа с клиентом за год | C54: =projects_year*client_time -> 216.6 | D54: ч/год | E54: projects_year*client_time | F54: calc | G54: projects_year, client_time
A55: ops_per_shoot | B55: Операционных часов на час съёмки | C55: =IF(shooting_time=0,0,side_time/shooting_time) -> 2.0775623 | D55: ч | E55: IF(shooting_time=0,0,side_time/shooting_time) | F55: calc | G55: side_time, shooting_time
A56: 4 · ДОХОД
A57: ID | B57: Название | C57: Значение | D57: Ед. | E57: Формула / как получено | F57: Тип | G57: Зависит от | H57: Источник / форма
A58: income_month | B58: Желаемый доход на руки | C58: 110216 | D58: ₽/мес | F58: default | H58: Block1 · Росстат 2026
A59: target_income | B59: Желаемый доход за год | C59: =income_month*months -> 1322592 | D59: ₽/год | E59: income_month*months | F59: calc | G59: income_month, months | H59: N — на руки после всех платежей
A60: current_rate | B60: Текущая ставка часа | C60: 6000 | D60: ₽/ч | F60: default | H60: Block2 · для сравнения
A61: 5 · РАБОЧЕЕ МЕСТО · ПЕРЕКЛЮЧАТЕЛЬ (Form005/013 · Block9)
A62: ID | B62: Название | C62: Значение | D62: Ед. | E62: Формула / как получено | F62: Тип | G62: Зависит от | H62: Источник / форма
A63: ws_mode | B63: ПЕРЕКЛЮЧАТЕЛЬ · рабочее место | C63: Работаю из дома | F63: default | H63: Form005 · A111
A64: own_home | B64: ДОМА · живу в своём, ипотеки нет | C64: нет | F64: default | H64: Контекстная галочка: показывает рекомендацию, но не обнуляет стоимость жилья
A65: home_rent | B65: ДОМА · аренда или ипотека | C65: 40000 | D65: ₽/мес | F65: default | H65: По доле метров; поле остаётся активным при own_home = да
A66: home_util | B66: ДОМА · коммунальные и связь | C66: 7000 | D66: ₽/мес | F66: default | H66: По доле метров рабочего места
A67: home_area | B67: ДОМА · общая площадь жилья | C67: 50 | D67: м² | F67: default
A68: cab_area | B68: ДОМА · площадь под кабинет | C68: 6 | D68: м² | F68: default
A69: cab_share | B69: ДОМА · доля кабинета | C69: =IF(home_area=0,0,cab_area/home_area) -> 0.12 | D69: % | E69: IF(home_area=0,0,cab_area/home_area) | F69: calc | G69: cab_area, home_area
A70: office_rent | B70: АРЕНДА · стоимость помещения | C70: 15000 | D70: ₽/мес | F70: default | H70: ЦЕЛИКОМ
A71: office_util | B71: АРЕНДА · коммунальные и связь | C71: 7000 | D71: ₽/мес | F71: default | H71: ЦЕЛИКОМ
A72: var_workspace | B72: Содержание рабочего места | C72: =IF(ws_mode="Работаю из дома",(home_rent+home_util)*cab_share*months,(office_rent+office_util)*months) -> 67680 | D72: ₽/год | E72: IF(ws_mode="Работаю из дома",(home_rent+home_util)*cab_share*months,(office_rent+office_util)*months) | F72: calc | G72: ws_mode, home_rent, cab_share, home_util, office_rent, office_util
A73: 6 · ОБУЧЕНИЕ И САЙТ · ПЕРЕКЛЮЧАТЕЛИ
A74: ID | B74: Название | C74: Значение | D74: Ед. | E74: Формула / как получено | F74: Тип | G74: Зависит от | H74: Источник / форма
A75: edu_cost | B75: Обучение · стоимость курса | C75: 80000 | D75: ₽ | F75: default | H75: Form006 · Block10
A76: edu_months | B76: Обучение · месяцев без дохода | C76: 4 | D76: мес | F76: default
A77: edu_life | B77: Обучение · срок амортизации | C77: 7 | D77: лет | F77: default
A79: edu_opportunity | B79: Обучение · упущенная выгода | C79: =edu_months*income_month -> 440864 | D79: ₽ | E79: edu_months*income_month | F79: calc | G79: edu_months, income_month
A80: dep_education | B80: Амортизация · обучение | C80: =IF(edu_life=0,0,(edu_cost+edu_opportunity)/edu_life) -> 74409.143 | D80: ₽/год | E80: IF(edu_life=0,0,(edu_cost+edu_opportunity)/edu_life) | F80: calc | G80: edu_cost, edu_opportunity, edu_life
A81: site_mode | B81: ПЕРЕКЛЮЧАТЕЛЬ · создание сайта | C81: Нанимал (а) специалиста | F81: default | H81: Form014 · A123 · Block12
A82: site_cost | B82: Сайт · стоимость подрядчика | C82: 70000 | D82: ₽ | F82: default
A83: site_hours | B83: Сайт · часов своими руками | C83: 80 | D83: ч | F83: default | H83: при варианте «делал сам»
A84: site_life | B84: Сайт · срок амортизации | C84: 7 | D84: лет | F84: default
A85: dep_website | B85: Амортизация · сайт | C85: =IF(site_mode="Нанимал (а) специалиста",IF(site_life=0,0,site_cost/site_life),0) -> 10000 | D85: ₽/год | E85: IF(site_mode="Нанимал (а) специалиста",IF(site_life=0,0,site_cost/site_life),0) | F85: calc | G85: site_mode, site_cost, site_life | H85: при «делал сам» уходит в site_divisor
A86: site_divisor | B86: Сайт · поправка знаменателя | C86: =IF(site_mode="Нанимал (а) специалиста",0,IF(site_life*net_time=0,0,site_hours/(site_life*net_time))) -> 0 | E86: IF(site_mode="Нанимал (а) специалиста",0,IF(site_life*net_time=0,0,site_hours/(site_life*net_time))) | F86: calc | G86: site_mode, site_hours, site_life, net_time | H86: Свой труд по ПОЛНОЙ ставке рабочего часа (выручка / чистое время), а не по съёмочной
A87: 7 · РАСХОДЫ · итоги из 03_Каталоги по КОДУ ФОРМЫ
A88: ID | B88: Название | C88: Значение | D88: Ед. | E88: Формула / как получено | F88: Тип | G88: Зависит от | H88: Источник / форма
A89: dep_shoot | B89: Амортизация · съёмочное оборудование | C89: =SUMIF(cat_form,"Form001",cat_year) -> 107759.99 | D89: ₽/год | E89: SUMIF(cat_form,"Form001",cat_year) | F89: calc | G89: Form001 | H89: Block6
A90: dep_office | B90: Амортизация · офисное оборудование | C90: =SUMIF(cat_form,"Form002",cat_year) -> 65732.933 | D90: ₽/год | E90: SUMIF(cat_form,"Form002",cat_year) | F90: calc | G90: Form002 | H90: Block7
A91: dep_software | B91: Амортизация · ПО разовые покупки | C91: =SUMIF(cat_form,"Form004",cat_year) -> 11500 | D91: ₽/год | E91: SUMIF(cat_form,"Form004",cat_year) | F91: calc | G91: Form004 | H91: Block8
A92: dep_workspace | B92: Амортизация · обустройство места | C92: =SUMIF(cat_form,"Form013",cat_year) -> 9285.7143 | D92: ₽/год | E92: SUMIF(cat_form,"Form013",cat_year) | F92: calc | G92: Form013 | H92: Block9
A93: investment | B93: ИТОГО амортизация | C93: =dep_shoot+dep_office+dep_software+dep_workspace+dep_education+dep_website -> 278687.78 | D93: ₽/год | E93: dep_shoot+dep_office+dep_software+dep_workspace+dep_education+dep_website | F93: calc | G93: dep_*
A94: var_software | B94: Переменные · подписки ПО | C94: =SUMIF(cat_form,"Form003",cat_year) -> 27000 | D94: ₽/год | E94: SUMIF(cat_form,"Form003",cat_year) | F94: calc | G94: Form003 | H94: Block8
A95: var_ads | B95: Переменные · реклама и продвижение | C95: =SUMIF(cat_form,"Form010",cat_year) -> 187500 | D95: ₽/год | E95: SUMIF(cat_form,"Form010",cat_year) | F95: calc | G95: Form010 | H95: Block11
A96: var_bank | B96: Переменные · банк РКО и СМС | C96: =SUMIF(cat_form,"Form007",cat_year) -> 1800 | D96: ₽/год | E96: SUMIF(cat_form,"Form007",cat_year) | F96: calc | G96: Form007 | H96: Block15
A97: acc_cost_month | B97: Специалист по учёту · стоимость в месяц | C97: 10000 | D97: ₽/мес | F97: default | H97: Form011
A98: var_accounting | B98: Переменные · специалист по учёту | C98: =IF(acc_mode="Нанимаю специалиста",acc_cost_month*months,0) -> 0 | D98: ₽/год | E98: IF(acc_mode="Нанимаю специалиста",acc_cost_month*months,0) | F98: calc | G98: acc_mode, acc_cost_month, months | H98: Если веду сам — 0, но растёт время
A99: variable_costs | B99: ИТОГО переменные | C99: =var_software+var_ads+var_bank+var_accounting+var_workspace -> 283980 | D99: ₽/год | E99: var_software+var_ads+var_bank+var_accounting+var_workspace | F99: calc | G99: var_*
A100: total_costs | B100: ВСЕГО РАСХОДОВ (C) | C100: =investment+variable_costs -> 562667.78 | D100: ₽/год | E100: investment+variable_costs | F100: calc | G100: investment, variable_costs | H100: Без эквайринга
A101: revenue_base | B101: База для выручки | C101: =target_income+total_costs -> 1885259.8 | D101: ₽/год | E101: target_income+total_costs | F101: calc | G101: target_income, total_costs | H101: N + C
A102: 8 · НАЛОГИ И ВЗНОСЫ 2026
...

Sheet Состав
A1: СОСТАВ · ЧТО ИЗ ЧЕГО СКЛАДЫВАЕТСЯ
A2: Лист содержит только группирующие понятия и фиксирует, какие понятия и поля калькулятора входят в их состав. Формулы, алгоритмы вычисления, пользовательские вводы и отдельные расчётные показатели сюда не заносятся: формулы хранятся на листе calc, подробные алгоритмы — в паспортах расчётов. Наименования берутся только из листа 01_Глоссарий; ID — из calc.html.
C3: Составные части
A4: ID | B4: Наименование | C4: 1 | D4: 2 | E4: 3 | F4: 4 | G4: 5 | H4: 6 | I4: 7 | J4: 8 | K4: 9 | L4: 10
A5: R | B5: Выручка | C5: Желаемый доход | D5: Финансовые расходы | E5: Налоги | F5: Эквайринг | G5: Инвестиционное время | H5: Резерв на развитие | I5: Резерв на программу лояльности
A6: C | B6: Финансовые расходы | C6: Финансовые вложения (инвестиции) | D6: Регулярные расходы специалиста
A7: — | B7: Всего расходов | C7: Финансовые расходы | D7: Налоги | E7: Эквайринг
A8: — | B8: Резервный фонд | C8: Резерв на отпуск | D8: Резерв на развитие | E8: Резерв на программу лояльности
A9: vari | B9: Регулярные расходы специалиста | C9: Подписки | D9: Реклама | E9: Банковское обслуживание | F9: Бухгалтерия | G9: Содержание рабочего места
A10: amort | B10: Финансовые вложения (инвестиции) | C10: Съёмочное оборудование | D10: Офисное оборудование | E10: ПО | F10: Обустройство рабочего места | G10: Обучение | H10: Сайт
A11: workHours | B11: Временные расходы | C11: Съёмочное время | D11: Время на постпродакшн | E11: Проектное клиентское время | F11: Поиск заказов | G11: Учёт | H11: Резерв времени на простой и форс-мажоры | I11: Неэффективное рабочее время
A12: — | B12: Инвестиционное время | C12: Обучение | D12: Сайт

Sheet 03_Каталоги
A1: 03 · КАТАЛОГИ — списки значений по умолчанию для форм калькулятора
A2: Только данные, никаких строк «ИТОГО». Итог берётся формулой SUMIF по коду формы. Период: Год=1, Месяц=12, Квартал=4 — как в ваших выпадающих списках.
A4: Форма | B4: Позиция | C4: Стоимость, ₽ | D4: Срок, лет | E4: Период | F4: Платежей/год | G4: ₽/год | H4: Тип расхода
A5: Form001 | B5: Canon EOS R6 Mark II Body | C5: 166999 | D5: 3 | F5: =IF(E5="Год",1,IF(E5="Квартал",4,IF(E5="Месяц",12,0))) -> 0 | G5: =IF(N(D5)>0,C5/D5,C5*F5) -> 55666.333 | H5: амортизация
A6: Form001 | B6: Canon RF 24–105mm f/4.0 L IS USM | C6: 130999 | D6: 5 | F6: =IF(E6="Год",1,IF(E6="Квартал",4,IF(E6="Месяц",12,0))) -> 0 | G6: =IF(N(D6)>0,C6/D6,C6*F6) -> 26199.8 | H6: амортизация
A7: Form001 | B7: Godox V1Pro C | C7: 36990 | D7: 5 | F7: =IF(E7="Год",1,IF(E7="Квартал",4,IF(E7="Месяц",12,0))) -> 0 | G7: =IF(N(D7)>0,C7/D7,C7*F7) -> 7398 | H7: амортизация
A8: Form001 | B8: Godox XPro II C | C8: 9355 | D8: 5 | F8: =IF(E8="Год",1,IF(E8="Квартал",4,IF(E8="Месяц",12,0))) -> 0 | G8: =IF(N(D8)>0,C8/D8,C8*F8) -> 1871 | H8: амортизация
A9: Form001 | B9: Аккумулятор LP-E6NH | C9: 12978 | D9: 3 | F9: =IF(E9="Год",1,IF(E9="Квартал",4,IF(E9="Месяц",12,0))) -> 0 | G9: =IF(N(D9)>0,C9/D9,C9*F9) -> 4326 | H9: амортизация
A10: Form001 | B10: SanDisk Extreme PRO 256 ГБ #1 | C10: 6990 | D10: 2 | F10: =IF(E10="Год",1,IF(E10="Квартал",4,IF(E10="Месяц",12,0))) -> 0 | G10: =IF(N(D10)>0,C10/D10,C10*F10) -> 3495 | H10: амортизация
A11: Form001 | B11: SanDisk Extreme PRO 256 ГБ #2 | C11: 6990 | D11: 2 | F11: =IF(E11="Год",1,IF(E11="Квартал",4,IF(E11="Месяц",12,0))) -> 0 | G11: =IF(N(D11)>0,C11/D11,C11*F11) -> 3495 | H11: амортизация
A12: Form001 | B12: Рюкзак Lowepro ProTactic | C12: 27962 | D12: 7 | F12: =IF(E12="Год",1,IF(E12="Квартал",4,IF(E12="Месяц",12,0))) -> 0 | G12: =IF(N(D12)>0,C12/D12,C12*F12) -> 3994.5714 | H12: амортизация
A13: Form001 | B13: Godox RFT-05 отражатель | C13: 3000 | D13: 5 | F13: =IF(E13="Год",1,IF(E13="Квартал",4,IF(E13="Месяц",12,0))) -> 0 | G13: =IF(N(D13)>0,C13/D13,C13*F13) -> 600 | H13: амортизация
A14: Form001 | B14: X-Rite ColorChecker | C14: 5000 | D14: 7 | F14: =IF(E14="Год",1,IF(E14="Квартал",4,IF(E14="Месяц",12,0))) -> 0 | G14: =IF(N(D14)>0,C14/D14,C14*F14) -> 714.28571 | H14: амортизация
A15: Form002 | B15: Системный блок | C15: 180000 | D15: 5 | F15: =IF(E15="Год",1,IF(E15="Квартал",4,IF(E15="Месяц",12,0))) -> 0 | G15: =IF(N(D15)>0,C15/D15,C15*F15) -> 36000 | H15: амортизация
A16: Form002 | B16: Монитор ASUS ProArt | C16: 55000 | D16: 5 | F16: =IF(E16="Год",1,IF(E16="Квартал",4,IF(E16="Месяц",12,0))) -> 0 | G16: =IF(N(D16)>0,C16/D16,C16*F16) -> 11000 | H16: амортизация
... A30: Form013 | B30: Косметический ремонт | C30: 30000 | D30: 7 | F30: =IF(E30="Год",1,IF(E30="Квартал",4,IF(E30="Месяц",12,0))) -> 0 | G30: =IF(N(D30)>0,C30/D30,C30*F30) -> 4285.7143 | H30: амортизация
A31: Form003 | B31: Adobe CC Photography | C31: 2000 | E31: Месяц | F31: =IF(E31="Год",1,IF(E31="Квартал",4,IF(E31="Месяц",12,0))) -> 12 | G31: =IF(N(D31)>0,C31/D31,C31*F31) -> 24000 | H31: регулярный платёж
A32: Form003 | B32: Яндекс Диск 1 ТБ | C32: 250 | E32: Месяц | F32: =IF(E32="Год",1,IF(E32="Квартал",4,IF(E32="Месяц",12,0))) -> 12 | G32: =IF(N(D32)>0,C32/D32,C32*F32) -> 3000 | H32: регулярный платёж
A33: Form007 | B33: Обслуживание счёта (РКО) | C33: 0 | E33: Месяц | F33: =IF(E33="Год",1,IF(E33="Квартал",4,IF(E33="Месяц",12,0))) -> 12 | G33: =IF(N(D33)>0,C33/D33,C33*F33) -> 0 | H33: регулярный платёж
A34: Form007 | B34: СМС-уведомления | C34: 150 | E34: Месяц | F34: =IF(E34="Год",1,IF(E34="Квартал",4,IF(E34="Месяц",12,0))) -> 12 | G34: =IF(N(D34)>0,C34/D34,C34*F34) -> 1800 | H34: регулярный платёж
A35: Form010 | B35: Домен сайта | C35: 1500 | E35: Год | F35: =IF(E35="Год",1,IF(E35="Квартал",4,IF(E35="Месяц",12,0))) -> 1 | G35: =IF(N(D35)>0,C35/D35,C35*F35) -> 1500 | H35: регулярный платёж
A36: Form010 | B36: Хостинг сайта | C36: 6000 | E36: Год | F36: =IF(E36="Год",1,IF(E36="Квартал",4,IF(E36="Месяц",12,0))) -> 1 | G36: =IF(N(D36)>0,C36/D36,C36*F36) -> 6000 | H36: регулярный платёж
A37: Form010 | B37: Яндекс Директ | C37: 15000 | E37: Месяц | F37: =IF(E37="Год",1,IF(E37="Квартал",4,IF(E37="Месяц",12,0))) -> 12 | G37: =IF(N(D37)>0,C37/D37,C37*F37) -> 180000 | H37: регулярный платёж
A38: Form010 | B38: Авито | C38: 0 | E38: Месяц | F38: =IF(E38="Год",1,IF(E38="Квартал",4,IF(E38="Месяц",12,0))) -> 12 | G38: =IF(N(D38)>0,C38/D38,C38*F38) -> 0 | H38: регулярный платёж
A39: Form010 | B39: Таргетированная реклама | C39: 0 | E39: Месяц | F39: =IF(E39="Год",1,IF(E39="Квартал",4,IF(E39="Месяц",12,0))) -> 12 | G39: =IF(N(D39)>0,C39/D39,C39*F39) -> 0 | H39: регулярный платёж
A40: Form010 | B40: Платные размещения у блогеров | C40: 0 | E40: Месяц | F40: =IF(E40="Год",1,IF(E40="Квартал",4,IF(E40="Месяц",12,0))) -> 12 | G40: =IF(N(D40)>0,C40/D40,C40*F40) -> 0 | H40: регулярный платёж
A41: Form010 | B41: Отклики на Profi.ru | C41: 0 | E41: Месяц | F41: =IF(E41="Год",1,IF(E41="Квартал",4,IF(E41="Месяц",12,0))) -> 12 | G41: =IF(N(D41)>0,C41/D41,C41*F41) -> 0 | H41: регулярный платёж

Sheet 04_Итог
A1: 04 · ИТОГ по выбранному режиму
A3: ГЛАВНЫЙ РЕЗУЛЬТАТ
A4: Выбранный режим | B4: =regime -> Самозанятый (НПД), средняя ставка | C4: меняется в calc → regime
A5: Ставка часа съёмки, ₽/час | B5: =CHOOSE(regime_no,'05_Расчёт'!B19,'05_Расчёт'!C19,'05_Расчёт'!D19,'05_Расчёт'!E19,'05_Расчёт'!F19,'05_Расчёт'!G19,'05_Расчёт'!H19) -> 9429.986 | C5: цена съёмочного часа для клиента
A6: Стоимость проекта, ₽ | B6: =CHOOSE(regime_no,'05_Расчёт'!B20,'05_Расчёт'!C20,'05_Расчёт'!D20,'05_Расчёт'!E20,'05_Расчёт'!F20,'05_Расчёт'!G20,'05_Расчёт'!H20) -> 9429.986
A7: Базовая ставка, ₽/час | B7: =base_rate -> 1332.3777 | C7: цена любого часа: съёмка, обработка, продвижение
A8: Выручка, ₽/год | B8: =CHOOSE(regime_no,'05_Расчёт'!B4,'05_Расчёт'!C4,'05_Расчёт'!D4,'05_Расчёт'!E4,'05_Расчёт'!F4,'05_Расчёт'!G4,'05_Расчёт'!H4) -> 2042535
A9: Выручка, ₽/месяц | B9: =CHOOSE(regime_no,'05_Расчёт'!B5,'05_Расчёт'!C5,'05_Расчёт'!D5,'05_Расчёт'!E5,'05_Расчёт'!F5,'05_Расчёт'!G5,'05_Расчёт'!H5) -> 170211.25
A10: Всего налогов и взносов, ₽/год | B10: =CHOOSE(regime_no,'05_Расчёт'!B15,'05_Расчёт'!C15,'05_Расчёт'!D15,'05_Расчёт'!E15,'05_Расчёт'!F15,'05_Расчёт'!G15,'05_Расчёт'!H15) -> 102126.75
A11: Эффективная нагрузка | B11: =CHOOSE(regime_no,'05_Расчёт'!B17,'05_Расчёт'!C17,'05_Расчёт'!D17,'05_Расчёт'!E17,'05_Расчёт'!F17,'05_Расчёт'!G17,'05_Расчёт'!H17) -> 0.05
A12: Точка безубыточности, ₽/год | B12: =CHOOSE(regime_no,'05_Расчёт'!B22,'05_Расчёт'!C22,'05_Расчёт'!D22,'05_Расчёт'!E22,'05_Расчёт'!F22,'05_Расчёт'!G22,'05_Расчёт'!H22) -> 609607.56
A13: ВРЕМЯ — иерархия
A14: ЧИСТОЕ время (всё доступное) | B14: =net_time -> 1533 | C14: производств. календарь − отпуск − больничный − час/день
A15: ├ ОПЕРАЦИОННОЕ (второстепенное) | B15: =side_time -> 450 | C15: продвижение + учёт
A16: ├ РЕЗЕРВ ВРЕМЕНИ на простой и форс-мажоры | B16: =fm_time -> 0 | C16: периоды без заказов, переносы, отмены, срывы
A17: └ ПРОЕКТНОЕ за год | B17: =project_pool -> 1083 | C17: на выполнение всех проектов
A18: ├ ПРОФИЛЬНОЕ (по профилю) | B18: =core_time -> 866.4 | C18: S × (1+коэф.): площадка + обработка
A19: │ ├ СЪЁМОЧНОЕ ← ЦЕЛЬ | B19: =shooting_time -> 216.6 | C19: S — работа на площадке
A20: │ └ постпродакшн | B20: =post_time -> 649.8 | C20: S × коэффициент — обработка
A21: └ работа с клиентом | B21: =client_total -> 216.6 | C21: 1 ч на проект: продажа, согласования
A22: Продолжительность съёмки (S) | B22: =shoot_duration -> 1 | C22: типовой заказ, задаёт пользователь
A23: Коэффициент обработки | B23: =post_ratio -> 3 | C23: часов обработки на 1 час съёмки
A24: Проектное время на 1 проект | B24: =project_time -> 5 | C24: S × (1+коэф.) + 1
A25: Проектов в год | B25: =projects_year -> 216.6
A26: Проектов в неделю | B26: =projects_week -> 4.9452055 | C26: при авторежиме = 1
A28: ПРОВЕРКА ИЕРАРХИИ ВРЕМЕНИ
A29: Операционное + резерв + проектное = чистое | B29: =IF(ABS(side_time+fm_time+project_pool-net_time)<0.01,"OK","ОШИБКА") -> OK
A30: Профильное + клиентское = проектное | B30: =IF(ABS(core_time+client_total-project_pool)<0.01,"OK","ОШИБКА") -> OK
A31: Съёмочное + постпродакшн = профильное | B31: =IF(ABS(shooting_time+post_time-core_time)<0.01,"OK","ОШИБКА") -> OK
A33: РАСХОДЫ
A34: Амортизация | B34: =investment -> 278687.78
A35: Переменные расходы | B35: =variable_costs -> 283980
A36: ВСЕГО расходов (C) | B36: =total_costs -> 562667.78
A37: Эквайринг (% от выручки) | B37: =acquiring -> 0.027
A38: Ваша текущая ставка, ₽/час | B38: =current_rate -> 6000
A39: СКОЛЬКО ВЫ ТЕРЯЕТЕ
A41: Остаётся на руки за год при текущей ставке, ₽ | B41: =(current_rate*shooting_time)*(1-rate_current-acquiring)-total_costs -> 636863.02
A42: Ваша расчётная ставка, ₽/час | B42: =B5 -> 9429.986
A43: Разница с текущей, ₽/час | B43: =B5-current_rate -> 3429.986
A44: Недополучено за год, ₽ | B44: =target_income-B41 -> 685728.98
A46: САМОПРОВЕРКИ
A47: Все режимы дают желаемый доход | B47: =IF(SUMPRODUCT(--(ABS('05_Расчёт'!B24:H24-target_income)>1))=0,"OK","ОШИБКА") -> OK
A48: Точки безубыточности сходятся в ноль | B48: =IF(SUMPRODUCT(--(ABS('05_Расчёт'!B23:H23)>1))=0,"OK","ОШИБКА") -> OK
A49: Амортизация + переменные = всего расходов | B49: =IF(ABS(investment+variable_costs-total_costs)<0.01,"OK","ОШИБКА") -> OK
A50: Проектное время положительно | B50: =IF(project_pool>0,"OK","ОШИБКА: операционное больше чистого") -> OK
A51: Съёмочных часов больше нуля | B51: =IF(shooting_time>0,"OK","ЗАПОЛНИТЕ продолжительность съёмки") -> OK
A52: Лимиты режимов не превышены | B52: =IF(COUNTIF('05_Расчёт'!B25:H25,"ок")=7,"OK","ПРОВЕРЬТЕ") -> OK
A53: Бухгалтер: либо деньги, либо время | B53: =IF(OR(AND(var_accounting>0,accounting_time=0),AND(var_accounting=0,accounting_time>0)),"OK","ПРОВЕРЬТЕ") -> OK
A54: Длительность съёмки задана | B54: =IF(shoot_duration>0,"OK","ЗАПОЛНИТЕ") -> OK
A55: Резерв времени на простой и форс-мажоры не больше 30% | B55: =IF(fm_pct<=0.3,"OK","СЛИШКОМ БОЛЬШОЙ") -> OK
A56: Сайт: либо сумма, либо часы | B56: =IF(OR(AND(dep_website>0,site_divisor=0),AND(dep_website=0,site_divisor>=0)),"OK","ПРОВЕРЬТЕ") -> OK

Sheet 05_Расчёт
A1: 05 · РАСЧЁТ — семь режимов, как в вашем выпадающем списке
A3: Показатель | B3: НПД средняя 5% | C3: НПД физлица 4% | D3: НПД юрлица 6% | E3: УСН Доходы 6% | F3: УСН Д−Р 15% | G3: АУСН Доходы 8% | H3: АУСН Д−Р 20%
A4: ВЫРУЧКА, ₽/год | B4: =(target_income+total_costs)/((1-acquiring-site_divisor)-rate_npd_avg) -> 2042535 | C4: =(target_income+total_costs)/((1-acquiring-site_divisor)-rate_npd_fiz) -> 2020642.9 | D4: =(target_income+total_costs)/((1-acquiring-site_divisor)-rate_npd_ur) -> 2064906.7 | E4: =MAX(((target_income+total_costs)+fixed_contrib-threshold_credit)/((1-acquiring-site_divisor)-extra_contrib),(target_income+total_costs)/((1-acquiring-site_divisor)-rate_usn_inc)) -> 2064906.7 | F4: =((target_income/(1-rate_usn_prof))+(fixed_contrib-threshold_credit+extra_contrib*(target_income/(1-rate_usn_prof)))+total_costs)/(1-acquiring-site_divisor) -> 2249340.5 | G4: =((target_income+total_costs)+injury_contrib)/((1-acquiring-site_divisor)-rate_ausn_inc) -> 2111153.2 | H4: =((target_income/(1-rate_ausn_prof))+total_costs+injury_contrib)/(1-acquiring-site_divisor) -> 2277397.5
A5: Выручка, ₽/месяц | B5: =B4/months -> 170211.25 | C5: =C4/months -> 168386.9 | D5: =D4/months -> 172075.56 | E5: =E4/months -> 172075.56 | F5: =F4/months -> 187445.04 | G5: =G4/months -> 175929.43 | H5: =H4/months -> 189783.13
A7: Эквайринг, ₽/год | B7: =B4*acquiring -> 55148.444 | C7: =C4*acquiring -> 54557.357 | D7: =D4*acquiring -> 55752.48 | E7: =E4*acquiring -> 55752.48 | F7: =F4*acquiring -> 60732.193 | G7: =G4*acquiring -> 57001.136 | H7: =H4*acquiring -> 61489.733
A8: Страховые взносы (фикс.) | B8: =0 -> 0 | C8: =0 -> 0 | D8: =0 -> 0 | E8: =fixed_contrib -> 57390 | F8: =fixed_contrib -> 57390 | G8: =0 -> 0 | H8: =0 -> 0
A9: База для доначисления 1% | B9: =0 -> 0 | C9: =0 -> 0 | D9: =0 -> 0 | E9: =MAX(0,E4-contrib_threshold) -> 1764906.7 | F9: =MAX(0,(target_income/(1-rate_usn_prof))-contrib_threshold) -> 1255990.6 | G9: =0 -> 0 | H9: =0 -> 0
A10: Доначисление 1% | B10: =0 -> 0 | C10: =0 -> 0 | D10: =0 -> 0 | E10: =MIN(E9*extra_contrib,contrib_cap) -> 17649.067 | F10: =MIN(F9*extra_contrib,contrib_cap) -> 12559.906 | G10: =0 -> 0 | H10: =0 -> 0
A11: Налог | B11: =B4*rate_npd_avg -> 102126.75 | C11: =C4*rate_npd_fiz -> 80825.714 | D11: =D4*rate_npd_ur -> 123894.4 | E11: =MAX(0,E4*rate_usn_inc-(E8+E10)) -> 48855.333 | F11: =MAX((target_income/(1-rate_usn_prof))*rate_usn_prof,F4*min_tax_usn) -> 233398.59 | G11: =G4*rate_ausn_inc -> 168892.25 | H11: =MAX((target_income/(1-rate_ausn_prof))*rate_ausn_prof,H4*min_tax_ausn) -> 330648
A12: Взнос на травматизм | B12: =0 -> 0 | C12: =0 -> 0 | D12: =0 -> 0 | E12: =0 -> 0 | F12: =0 -> 0 | G12: =injury_contrib -> 0 | H12: =injury_contrib -> 0
A13: Применён минимальный налог? | B13: ="—" -> — | C13: ="—" -> — | D13: ="—" -> — | E13: ="—" -> — | F13: =IF((target_income/(1-rate_usn_prof))*rate_usn_prof<F4*min_tax_usn,"ДА","нет") -> нет | G13: ="—" -> — | H13: =IF((target_income/(1-rate_ausn_prof))*rate_ausn_prof<H4*min_tax_ausn,"ДА","нет") -> нет
A15: ВСЕГО налогов и взносов | B15: =B8+B10+B11+B12 -> 102126.75 | C15: =C8+C10+C11+C12 -> 80825.714 | D15: =D8+D10+D11+D12 -> 123894.4 | E15: =E8+E10+E11+E12 -> 123894.4 | F15: =F8+F10+F11+F12 -> 303348.49 | G15: =G8+G10+G11+G12 -> 168892.25 | H15: =H8+H10+H11+H12 -> 330648
A16: Всего налогов и взносов, ₽/мес | B16: =B15/months -> 8510.5624 | C16: =C15/months -> 6735.4762 | D16: =D15/months -> 10324.533 | E16: =E15/months -> 10324.533 | F16: =F15/months -> 25279.041 | G16: =G15/months -> 14074.354 | H16: =H15/months -> 27554
A17: Эффективная нагрузка | B17: =IF(B4=0,0,B15/B4) -> 0.05 | C17: =IF(C4=0,0,C15/C4) -> 0.04 | D17: =IF(D4=0,0,D15/D4) -> 0.06 | E17: =IF(E4=0,0,E15/E4) -> 0.06 | F17: =IF(F4=0,0,F15/F4) -> 0.13486108 | G17: =IF(G4=0,0,G15/G4) -> 0.08 | H17: =IF(H4=0,0,H15/H4) -> 0.14518677
A19: ПОЛНАЯ СТАВКА ЧАСА, ₽/час | B19: =IF(shooting_time=0,0,B4/shooting_time) -> 9429.986 | C19: =IF(shooting_time=0,0,C4/shooting_time) -> 9328.9144 | D19: =IF(shooting_time=0,0,D4/shooting_time) -> 9533.2717 | E19: =IF(shooting_time=0,0,E4/shooting_time) -> 9533.2717 | F19: =IF(shooting_time=0,0,F4/shooting_time) -> 10384.767 | G19: =IF(shooting_time=0,0,G4/shooting_time) -> 9746.7829 | H19: =IF(shooting_time=0,0,H4/shooting_time) -> 10514.301
A20: Стоимость проекта, ₽ | B20: =IF(projects_year=0,0,B4/projects_year) -> 9429.986 | C20: =IF(projects_year=0,0,C4/projects_year) -> 9328.9144 | D20: =IF(projects_year=0,0,D4/projects_year) -> 9533.2717 | E20: =IF(projects_year=0,0,E4/projects_year) -> 9533.2717 | F20: =IF(projects_year=0,0,F4/projects_year) -> 10384.767 | G20: =IF(projects_year=0,0,G4/projects_year) -> 9746.7829 | H20: =IF(projects_year=0,0,H4/projects_year) -> 10514.301
A22: Точка безубыточности, ₽/год | B22: =total_costs/((1-acquiring-site_divisor)-rate_npd_avg) -> 609607.56 | C22: =total_costs/((1-acquiring-site_divisor)-rate_npd_fiz) -> 603073.72 | D22: =total_costs/((1-acquiring-site_divisor)-rate_npd_ur) -> 616284.54 | E22: =MAX((total_costs+fixed_contrib-threshold_credit)/((1-acquiring-site_divisor)-extra_contrib),total_costs/((1-acquiring-site_divisor)-rate_usn_inc)) -> 640766.13 | F22: =(total_costs+fixed_contrib)/((1-acquiring-site_divisor)-min_tax_usn) -> 643881.39 | G22: =(total_costs+injury_contrib)/((1-acquiring-site_divisor)-rate_ausn_inc) -> 630087.1 | H22: =(total_costs+injury_contrib)/((1-acquiring-site_divisor)-min_tax_ausn) -> 596678.45
A23: ПРОВЕРКА безубыточности (=0) | B23: =B22-total_costs-B22*acquiring-B22*rate_npd_avg -> 1.8189894e-11 | C23: =C22-total_costs-C22*acquiring-C22*rate_npd_fiz -> 7.2759576e-11 | D23: =D22-total_costs-D22*acquiring-D22*rate_npd_ur -> -5.0931703e-11 | E23: =E22-total_costs-E22*acquiring-MAX(fixed_contrib+MIN(MAX(0,E22-contrib_threshold)*extra_contrib,contrib_cap),E22*rate_usn_inc) -> -3.6379788e-11 | F23: =F22-total_costs-F22*acquiring-fixed_contrib-F22*min_tax_usn -> -3.5470293e-11 | G23: =G22-total_costs-G22*acquiring-G22*rate_ausn_inc -> -2.1827873e-11 | H23: =H22-total_costs-H22*acquiring-H22*min_tax_ausn -> 7.2759576e-12
A24: ПРОВЕРКА: остаётся на руки | B24: =B4-total_costs-B7-B15 -> 1322592 | C24: =C4-total_costs-C7-C15 -> 1322592 | D24: =D4-total_costs-D7-D15 -> 1322592 | E24: =E4-total_costs-E7-E15 -> 1322592 | F24: =F4-total_costs-F7-F15 -> 1322592 | G24: =G4-total_costs-G7-G15 -> 1322592 | H24: =H4-total_costs-H7-H15 -> 1322592
A25: Контроль лимитов | B25: =IF(B4>limit_npd,"! лимит НПД","ок") -> ок | C25: =IF(C4>limit_npd,"! лимит НПД","ок") -> ок | D25: =IF(D4>limit_npd,"! лимит НПД","ок") -> ок | E25: =IF(E4>vat_threshold,"! НДС","ок") -> ок | F25: =IF(F4>vat_threshold,"! НДС","ок") -> ок | G25: =IF(G4>limit_ausn,"! лимит АУСН","ок") -> ок | H25: =IF(H4>limit_ausn,"! лимит АУСН","ок") -> ок

Sheet 06_Отчёт
A1: 06 · ОТЧЁТ — куда уходит каждый рубль с часа съёмки
A2: Личный доход разложен по ролям: фотограф, ретушёр, менеджер, маркетолог, бухгалтер. Расходы — по назначению.
A4: 1 · ВАШ ЛИЧНЫЙ ДОХОД ПО РОЛЯМ (ставка любого рабочего часа = доход / чистое время)
A5: Статья | B5: ₽/год | C5: ₽/месяц | D5: ₽/съём. час | E5: ₽/проект | F5: доля | G5: часов/год
A6: Как ФОТОГРАФ — работа на площадке | B6: =(target_income/net_time)*shooting_time -> 186871.12 | C6: =IF(months=0,0,B6/months) -> 15572.593 | D6: =IF(shooting_time=0,0,B6/shooting_time) -> 862.74755 | E6: =IF(projects_year=0,0,B6/projects_year) -> 862.74755 | F6: =IF((CHOOSE(regime_no,'05_Расчёт'!B4,'05_Расчёт'!C4,'05_Расчёт'!D4,'05_Расчёт'!E4,'05_Расчёт'!F4,'05_Расчёт'!G4,'05_Расчёт'!H4))=0,0,B6/(CHOOSE(regime_no,'05_Расчёт'!B4,'05_Расчёт'!C4,'05_Расчёт'!D4,'05_Расчёт'!E4,'05_Расчёт'!F4,'05_Расчёт'!G4,'05_Расчёт'!H4))) -> 0.091489802 | G6: =shooting_time -> 216.6
A7: Как РЕТУШЁР — обработка материала | B7: =(target_income/net_time)*post_time -> 560613.36 | C7: =IF(months=0,0,B7/months) -> 46717.78 | D7: =IF(shooting_time=0,0,B7/shooting_time) -> 2588.2427 | E7: =IF(projects_year=0,0,B7/projects_year) -> 2588.2427 | F7: =IF((CHOOSE(regime_no,'05_Расчёт'!B4,'05_Расчёт'!C4,'05_Расчёт'!D4,'05_Расчёт'!E4,'05_Расчёт'!F4,'05_Расчёт'!G4,'05_Расчёт'!H4))=0,0,B7/(CHOOSE(regime_no,'05_Расчёт'!B4,'05_Расчёт'!C4,'05_Расчёт'!D4,'05_Расчёт'!E4,'05_Расчёт'!F4,'05_Расчёт'!G4,'05_Расчёт'!H4))) -> 0.27446941 | G7: =post_time -> 649.8
A8: Как МЕНЕДЖЕР — работа с клиентом | B8: =(target_income/net_time)*client_total -> 186871.12 | C8: =IF(months=0,0,B8/months) -> 15572.593 | D8: =IF(shooting_time=0,0,B8/shooting_time) -> 862.74755 | E8: =IF(projects_year=0,0,B8/projects_year) -> 862.74755 | F8: =IF((CHOOSE(regime_no,'05_Расчёт'!B4,'05_Расчёт'!C4,'05_Расчёт'!D4,'05_Расчёт'!E4,'05_Расчёт'!F4,'05_Расчёт'!G4,'05_Расчёт'!H4))=0,0,B8/(CHOOSE(regime_no,'05_Расчёт'!B4,'05_Расчёт'!C4,'05_Расчёт'!D4,'05_Расчёт'!E4,'05_Расчёт'!F4,'05_Расчёт'!G4,'05_Расчёт'!H4))) -> 0.091489802 | G8: =client_total -> 216.6
A9: Как МАРКЕТОЛОГ — продвижение | B9: =(target_income/net_time)*promo_time -> 377883.43 | C9: =IF(months=0,0,B9/months) -> 31490.286 | D9: =IF(shooting_time=0,0,B9/shooting_time) -> 1744.6142 | E9: =IF(projects_year=0,0,B9/projects_year) -> 1744.6142 | F9: =IF((CHOOSE(regime_no,'05_Расчёт'!B4,'05_Расчёт'!C4,'05_Расчёт'!D4,'05_Расчёт'!E4,'05_Расчёт'!F4,'05_Расчёт'!G4,'05_Расчёт'!H4))=0,0,B9/(CHOOSE(regime_no,'05_Расчёт'!B4,'05_Расчёт'!C4,'05_Расчёт'!D4,'05_Расчёт'!E4,'05_Расчёт'!F4,'05_Расчёт'!G4,'05_Расчёт'!H4))) -> 0.18500708 | G9: =promo_time -> 438
A10: Как БУХГАЛТЕР — учёт и отчётность | B10: =(target_income/net_time)*accounting_time -> 10352.971 | C10: =IF(months=0,0,B10/months) -> 862.74755 | D10: =IF(shooting_time=0,0,B10/shooting_time) -> 47.797648 | E10: =IF(projects_year=0,0,B10/projects_year) -> 47.797648 | F10: =IF((CHOOSE(regime_no,'05_Расчёт'!B4,'05_Расчёт'!C4,'05_Расчёт'!D4,'05_Расчёт'!E4,'05_Расчёт'!F4,'05_Расчёт'!G4,'05_Расчёт'!H4))=0,0,B10/(CHOOSE(regime_no,'05_Расчёт'!B4,'05_Расчёт'!C4,'05_Расчёт'!D4,'05_Расчёт'!E4,'05_Расчёт'!F4,'05_Расчёт'!G4,'05_Расчёт'!H4))) -> 0.0050686871 | G10: =accounting_time -> 12
A11: Компенсация простоя и форс-мажоров | B11: =(target_income/net_time)*fm_time -> 0 | C11: =IF(months=0,0,B11/months) -> 0 | D11: =IF(shooting_time=0,0,B11/shooting_time) -> 0 | E11: =IF(projects_year=0,0,B11/projects_year) -> 0 | F11: =IF((CHOOSE(regime_no,'05_Расчёт'!B4,'05_Расчёт'!C4,'05_Расчёт'!D4,'05_Расчёт'!E4,'05_Расчёт'!F4,'05_Расчёт'!G4,'05_Расчёт'!H4))=0,0,B11/(CHOOSE(regime_no,'05_Расчёт'!B4,'05_Расчёт'!C4,'05_Расчёт'!D4,'05_Расчёт'!E4,'05_Расчёт'!F4,'05_Расчёт'!G4,'05_Расчёт'!H4))) -> 0 | G11: =fm_time -> 0
A12: ИТОГО НА РУКИ | B12: =target_income -> 1322592 | C12: =IF(months=0,0,B12/months) -> 110216 | D12: =IF(shooting_time=0,0,B12/shooting_time) -> 6106.1496 | E12: =IF(projects_year=0,0,B12/projects_year) -> 6106.1496 | F12: =IF((CHOOSE(regime_no,'05_Расчёт'!B4,'05_Расчёт'!C4,'05_Расчёт'!D4,'05_Расчёт'!E4,'05_Расчёт'!F4,'05_Расчёт'!G4,'05_Расчёт'!H4))=0,0,B12/(CHOOSE(regime_no,'05_Расчёт'!B4,'05_Расчёт'!C4,'05_Расчёт'!D4,'05_Расчёт'!E4,'05_Расчёт'!F4,'05_Расчёт'!G4,'05_Расчёт'!H4))) -> 0.64752478 | G12: =net_time -> 1533
A14: 2 · ОТЛОЖИТЬ НА ВОССТАНОВЛЕНИЕ ВЛОЖЕНИЙ (амортизация)
A15: Статья | B15: ₽/год | C15: ₽/месяц | D15: ₽/съём. час | E15: ₽/проект | F15: доля | G15: часов/год
A16: На съёмочное оборудование | B16: =dep_shoot -> 107759.99 | C16: =IF(months=0,0,B16/months) -> 8979.9992 | D16: =IF(shooting_time=0,0,B16/shooting_time) -> 497.50688 | E16: =IF(projects_year=0,0,B16/projects_year) -> 497.50688 | F16: =IF((CHOOSE(regime_no,'05_Расчёт'!B4,'05_Расчёт'!C4,'05_Расчёт'!D4,'05_Расчёт'!E4,'05_Расчёт'!F4,'05_Расчёт'!G4,'05_Расчёт'!H4))=0,0,B16/(CHOOSE(regime_no,'05_Расчёт'!B4,'05_Расчёт'!C4,'05_Расчёт'!D4,'05_Расчёт'!E4,'05_Расчёт'!F4,'05_Расчёт'!G4,'05_Расчёт'!H4))) -> 0.052757966
A17: На офисное оборудование | B17: =dep_office -> 65732.933 | C17: =IF(months=0,0,B17/months) -> 5477.7444 | D17: =IF(shooting_time=0,0,B17/shooting_time) -> 303.47615 | E17: =IF(projects_year=0,0,B17/projects_year) -> 303.47615 | F17: =IF((CHOOSE(regime_no,'05_Расчёт'!B4,'05_Расчёт'!C4,'05_Расчёт'!D4,'05_Расчёт'!E4,'05_Расчёт'!F4,'05_Расчёт'!G4,'05_Расчёт'!H4))=0,0,B17/(CHOOSE(regime_no,'05_Расчёт'!B4,'05_Расчёт'!C4,'05_Расчёт'!D4,'05_Расчёт'!E4,'05_Расчёт'!F4,'05_Расчёт'!G4,'05_Расчёт'!H4))) -> 0.032182036
A18: На ПО (разовые покупки) | B18: =dep_software -> 11500 | C18: =IF(months=0,0,B18/months) -> 958.33333 | D18: =IF(shooting_time=0,0,B18/shooting_time) -> 53.093259 | E18: =IF(projects_year=0,0,B18/projects_year) -> 53.093259 | F18: =IF((CHOOSE(regime_no,'05_Расчёт'!B4,'05_Расчёт'!C4,'05_Расчёт'!D4,'05_Расчёт'!E4,'05_Расчёт'!F4,'05_Расчёт'!G4,'05_Расчёт'!H4))=0,0,B18/(CHOOSE(regime_no,'05_Расчёт'!B4,'05_Расчёт'!C4,'05_Расчёт'!D4,'05_Расчёт'!E4,'05_Расчёт'!F4,'05_Расчёт'!G4,'05_Расчёт'!H4))) -> 0.0056302585
A19: На обустройство рабочего места | B19: =dep_workspace -> 9285.7143 | C19: =IF(months=0,0,B19/months) -> 773.80952 | D19: =IF(shooting_time=0,0,B19/shooting_time) -> 42.870334 | E19: =IF(projects_year=0,0,B19/projects_year) -> 42.870334 | F19: =IF((CHOOSE(regime_no,'05_Расчёт'!B4,'05_Расчёт'!C4,'05_Расчёт'!D4,'05_Расчёт'!E4,'05_Расчёт'!F4,'05_Расчёт'!G4,'05_Расчёт'!H4))=0,0,B19/(CHOOSE(regime_no,'05_Расчёт'!B4,'05_Расчёт'!C4,'05_Расчёт'!D4,'05_Расчёт'!E4,'05_Расчёт'!F4,'05_Расчёт'!G4,'05_Расчёт'!H4))) -> 0.0045461715
A20: На обучение | B20: =dep_education -> 74409.143 | C20: =IF(months=0,0,B20/months) -> 6200.7619 | D20: =IF(shooting_time=0,0,B20/shooting_time) -> 343.53252 | E20: =IF(projects_year=0,0,B20/projects_year) -> 343.53252 | F20: =IF((CHOOSE(regime_no,'05_Расчёт'!B4,'05_Расчёт'!C4,'05_Расчёт'!D4,'05_Расчёт'!E4,'05_Расчёт'!F4,'05_Расчёт'!G4,'05_Расчёт'!H4))=0,0,B20/(CHOOSE(regime_no,'05_Расчёт'!B4,'05_Расчёт'!C4,'05_Расчёт'!D4,'05_Расчёт'!E4,'05_Расчёт'!F4,'05_Расчёт'!G4,'05_Расчёт'!H4))) -> 0.036429801
A21: На сайт | B21: =dep_website -> 10000 | C21: =IF(months=0,0,B21/months) -> 833.33333 | D21: =IF(shooting_time=0,0,B21/shooting_time) -> 46.168052 | E21: =IF(projects_year=0,0,B21/projects_year) -> 46.168052 | F21: =IF((CHOOSE(regime_no,'05_Расчёт'!B4,'05_Расчёт'!C4,'05_Расчёт'!D4,'05_Расчёт'!E4,'05_Расчёт'!F4,'05_Расчёт'!G4,'05_Расчёт'!H4))=0,0,B21/(CHOOSE(regime_no,'05_Расчёт'!B4,'05_Расчёт'!C4,'05_Расчёт'!D4,'05_Расчёт'!E4,'05_Расчёт'!F4,'05_Расчёт'!G4,'05_Расчёт'!H4))) -> 0.004895877
A22: ИТОГО амортизация | B22: =investment -> 278687.78 | C22: =IF(months=0,0,B22/months) -> 23223.982 | D22: =IF(shooting_time=0,0,B22/shooting_time) -> 1286.6472 | E22: =IF(projects_year=0,0,B22/projects_year) -> 1286.6472 | F22: =IF((CHOOSE(regime_no,'05_Расчёт'!B4,'05_Расчёт'!C4,'05_Расчёт'!D4,'05_Расчёт'!E4,'05_Расчёт'!F4,'05_Расчёт'!G4,'05_Расчёт'!H4))=0,0,B22/(CHOOSE(regime_no,'05_Расчёт'!B4,'05_Расчёт'!C4,'05_Расчёт'!D4,'05_Расчёт'!E4,'05_Расчёт'!F4,'05_Расчёт'!G4,'05_Расчёт'!H4))) -> 0.13644211
A24: 3 · РЕГУЛЯРНЫЕ РАСХОДЫ
A25: Статья | B25: ₽/год | C25: ₽/месяц | D25: ₽/съём. час | E25: ₽/проект | F25: доля | G25: часов/год
A26: Подписки на ПО | B26: =var_software -> 27000 | C26: =IF(months=0,0,B26/months) -> 2250 | D26: =IF(shooting_time=0,0,B26/shooting_time) -> 124.65374 | E26: =IF(projects_year=0,0,B26/projects_year) -> 124.65374 | F26: =IF((CHOOSE(regime_no,'05_Расчёт'!B4,'05_Расчёт'!C4,'05_Расчёт'!D4,'05_Расчёт'!E4,'05_Расчёт'!F4,'05_Расчёт'!G4,'05_Расчёт'!H4))=0,0,B26/(CHOOSE(regime_no,'05_Расчёт'!B4,'05_Расчёт'!C4,'05_Расчёт'!D4,'05_Расчёт'!E4,'05_Расчёт'!F4,'05_Расчёт'!G4,'05_Расчёт'!H4))) -> 0.013218868
A27: Реклама и продвижение | B27: =var_ads -> 187500 | C27: =IF(months=0,0,B27/months) -> 15625 | D27: =IF(shooting_time=0,0,B27/shooting_time) -> 865.65097 | E27: =IF(projects_year=0,0,B27/projects_year) -> 865.65097 | F27: =IF((CHOOSE(regime_no,'05_Расчёт'!B4,'05_Расчёт'!C4,'05_Расчёт'!D4,'05_Расчёт'!E4,'05_Расчёт'!F4,'05_Расчёт'!G4,'05_Расчёт'!H4))=0,0,B27/(CHOOSE(regime_no,'05_Расчёт'!B4,'05_Расчёт'!C4,'05_Расчёт'!D4,'05_Расчёт'!E4,'05_Расчёт'!F4,'05_Расчёт'!G4,'05_Расчёт'!H4))) -> 0.091797694
A28: Банк: РКО и СМС | B28: =var_bank -> 1800 | C28: =IF(months=0,0,B28/months) -> 150 | D28: =IF(shooting_time=0,0,B28/shooting_time) -> 8.3102493 | E28: =IF(projects_year=0,0,B28/projects_year) -> 8.3102493 | F28: =IF((CHOOSE(regime_no,'05_Расчёт'!B4,'05_Расчёт'!C4,'05_Расчёт'!D4,'05_Расчёт'!E4,'05_Расчёт'!F4,'05_Расчёт'!G4,'05_Расчёт'!H4))=0,0,B28/(CHOOSE(regime_no,'05_Расчёт'!B4,'05_Расчёт'!C4,'05_Расчёт'!D4,'05_Расчёт'!E4,'05_Расчёт'!F4,'05_Расчёт'!G4,'05_Расчёт'!H4))) -> 0.00088125786
A29: Бухгалтер (0 = веду самостоятельно) | B29: =var_accounting -> 0 | C29: =IF(months=0,0,B29/months) -> 0 | D29: =IF(shooting_time=0,0,B29/shooting_time) -> 0 | E29: =IF(projects_year=0,0,B29/projects_year) -> 0 | F29: =IF((CHOOSE(regime_no,'05_Расчёт'!B4,'05_Расчёт'!C4,'05_Расчёт'!D4,'05_Расчёт'!E4,'05_Расчёт'!F4,'05_Расчёт'!G4,'05_Расчёт'!H4))=0,0,B29/(CHOOSE(regime_no,'05_Расчёт'!B4,'05_Расчёт'!C4,'05_Расчёт'!D4,'05_Расчёт'!E4,'05_Расчёт'!F4,'05_Расчёт'!G4,'05_Расчёт'!H4))) -> 0
A30: Аренда и коммунальные | B30: =var_workspace -> 67680 | C30: =IF(months=0,0,B30/months) -> 5640 | D30: =IF(shooting_time=0,0,B30/shooting_time) -> 312.46537 | E30: =IF(projects_year=0,0,B30/projects_year) -> 312.46537 | F30: =IF((CHOOSE(regime_no,'05_Расчёт'!B4,'05_Расчёт'!C4,'05_Расчёт'!D4,'05_Расчёт'!E4,'05_Расчёт'!F4,'05_Расчёт'!G4,'05_Расчёт'!H4))=0,0,B30/(CHOOSE(regime_no,'05_Расчёт'!B4,'05_Расчёт'!C4,'05_Расчёт'!D4,'05_Расчёт'!E4,'05_Расчёт'!F4,'05_Расчёт'!G4,'05_Расчёт'!H4))) -> 0.033135296
A31: ИТОГО переменные | B31: =variable_costs -> 283980 | C31: =IF(months=0,0,B31/months) -> 23665 | D31: =IF(shooting_time=0,0,B31/shooting_time) -> 1311.0803 | E31: =IF(projects_year=0,0,B31/projects_year) -> 1311.0803 | F31: =IF((CHOOSE(regime_no,'05_Расчёт'!B4,'05_Расчёт'!C4,'05_Расчёт'!D4,'05_Расчёт'!E4,'05_Расчёт'!F4,'05_Расчёт'!G4,'05_Расчёт'!H4))=0,0,B31/(CHOOSE(regime_no,'05_Расчёт'!B4,'05_Расчёт'!C4,'05_Расчёт'!D4,'05_Расчёт'!E4,'05_Расчёт'!F4,'05_Расчёт'!G4,'05_Расчёт'!H4))) -> 0.13903312
A33: 4 · ГОСУДАРСТВУ И БАНКУ
A34: Статья | B34: ₽/год | C34: ₽/месяц | D34: ₽/съём. час | E34: ₽/проект | F34: доля | G34: часов/год
A35: Налог и страховые взносы | B35: =CHOOSE(regime_no,'05_Расчёт'!B15,'05_Расчёт'!C15,'05_Расчёт'!D15,'05_Расчёт'!E15,'05_Расчёт'!F15,'05_Расчёт'!G15,'05_Расчёт'!H15) -> 102126.75 | C35: =IF(months=0,0,B35/months) -> 8510.5624 | D35: =IF(shooting_time=0,0,B35/shooting_time) -> 471.4993 | E35: =IF(projects_year=0,0,B35/projects_year) -> 471.4993 | F35: =IF((CHOOSE(regime_no,'05_Расчёт'!B4,'05_Расчёт'!C4,'05_Расчёт'!D4,'05_Расчёт'!E4,'05_Расчёт'!F4,'05_Расчёт'!G4,'05_Расчёт'!H4))=0,0,B35/(CHOOSE(regime_no,'05_Расчёт'!B4,'05_Расчёт'!C4,'05_Расчёт'!D4,'05_Расчёт'!E4,'05_Расчёт'!F4,'05_Расчёт'!G4,'05_Расчёт'!H4))) -> 0.05
A36: Эквайринг (комиссия банка) | B36: =(CHOOSE(regime_no,'05_Расчёт'!B4,'05_Расчёт'!C4,'05_Расчёт'!D4,'05_Расчёт'!E4,'05_Расчёт'!F4,'05_Расчёт'!G4,'05_Расчёт'!H4))*acquiring -> 55148.444 | C36: =IF(months=0,0,B36/months) -> 4595.7037 | D36: =IF(shooting_time=0,0,B36/shooting_time) -> 254.60962 | E36: =IF(projects_year=0,0,B36/projects_year) -> 254.60962 | F36: =IF((CHOOSE(regime_no,'05_Расчёт'!B4,'05_Расчёт'!C4,'05_Расчёт'!D4,'05_Расчёт'!E4,'05_Расчёт'!F4,'05_Расчёт'!G4,'05_Расчёт'!H4))=0,0,B36/(CHOOSE(regime_no,'05_Расчёт'!B4,'05_Расчёт'!C4,'05_Расчёт'!D4,'05_Расчёт'!E4,'05_Расчёт'!F4,'05_Расчёт'!G4,'05_Расчёт'!H4))) -> 0.027
A38: ВСЕГО = ВЫРУЧКА | B38: =CHOOSE(regime_no,'05_Расчёт'!B4,'05_Расчёт'!C4,'05_Расчёт'!D4,'05_Расчёт'!E4,'05_Расчёт'!F4,'05_Расчёт'!G4,'05_Расчёт'!H4) -> 2042535 | C38: =IF(months=0,0,B38/months) -> 170211.25 | D38: =IF(shooting_time=0,0,B38/shooting_time) -> 9429.986 | E38: =IF(projects_year=0,0,B38/projects_year) -> 9429.986 | F38: =1 -> 1
A39: Сверка: сумма всех статей | B39: =IF(ABS(B12+investment+variable_costs+B35+B36-B38)<1,"OK — сходится до рубля","РАСХОЖДЕНИЕ") -> OK — сходится до рубля
A41: 5 · ТРИ СЦЕНАРИЯ — сравните, где вы сейчас
A42: Сценарий | B42: Ставка часа | C42: Цена проекта | D42: Выручка/год | E42: На руки/год | F42: На руки/мес | G42: % от цели
A43: ВАША РАСЧЁТНАЯ — чтобы получать желаемое | B43: =(CHOOSE(regime_no,'05_Расчёт'!B4,'05_Расчёт'!C4,'05_Расчёт'!D4,'05_Расчёт'!E4,'05_Расчёт'!F4,'05_Расчёт'!G4,'05_Расчёт'!H4))/shooting_time -> 9429.986 | C43: =(CHOOSE(regime_no,'05_Расчёт'!B4,'05_Расчёт'!C4,'05_Расчёт'!D4,'05_Расчёт'!E4,'05_Расчёт'!F4,'05_Расчёт'!G4,'05_Расчёт'!H4))/projects_year -> 9429.986 | D43: =CHOOSE(regime_no,'05_Расчёт'!B4,'05_Расчёт'!C4,'05_Расчёт'!D4,'05_Расчёт'!E4,'05_Расчёт'!F4,'05_Расчёт'!G4,'05_Расчёт'!H4) -> 2042535 | E43: =target_income -> 1322592 | F43: =target_income/months -> 110216 | G43: =1 -> 1
A44: ВАША ТЕКУЩАЯ — по ней работаете сейчас | B44: =current_rate -> 6000 | C44: =current_rate*shooting_time/projects_year -> 6000 | D44: =current_rate*shooting_time -> 1299600 | E44: =(current_rate*shooting_time*(1-rate_current-acquiring)-total_costs) -> 636863.02 | F44: =(current_rate*shooting_time*(1-rate_current-acquiring)-total_costs)/months -> 53071.918 | G44: =(current_rate*shooting_time*(1-rate_current-acquiring)-total_costs)/target_income -> 0.48152644
A45: БЕЗУБЫТОЧНОСТЬ — работа в ноль | B45: =(CHOOSE(regime_no,'05_Расчёт'!B22,'05_Расчёт'!C22,'05_Расчёт'!D22,'05_Расчёт'!E22,'05_Расчёт'!F22,'05_Расчёт'!G22,'05_Расчёт'!H22))/shooting_time -> 2814.4394 | C45: =(CHOOSE(regime_no,'05_Расчёт'!B22,'05_Расчёт'!C22,'05_Расчёт'!D22,'05_Расчёт'!E22,'05_Расчёт'!F22,'05_Расчёт'!G22,'05_Расчёт'!H22))/projects_year -> 2814.4394 | D45: =CHOOSE(regime_no,'05_Расчёт'!B22,'05_Расчёт'!C22,'05_Расчёт'!D22,'05_Расчёт'!E22,'05_Расчёт'!F22,'05_Расчёт'!G22,'05_Расчёт'!H22) -> 609607.56 | E45: =0 -> 0 | F45: =0 -> 0 | G45: =0 -> 0
A47: Недополучено за год при текущей ставке | B47: =target_income-(current_rate*shooting_time*(1-rate_current-acquiring)-total_costs) -> 685728.98 | C47: это ваш вклад в чужой бизнес
A51: 7 · ТРИ КАРТИНЫ ОДНОГО ЧАСА — куда уходят деньги клиента
A52: Слева направо: сколько НУЖНО брать · сколько берёте СЕЙЧАС · минимум, чтобы не работать в убыток.
A54: ВАША РАСЧЁТНАЯ СТАВКА | F54: ВАША ТЕКУЩАЯ СТАВКА | K54: РАБОТА В НОЛЬ
A55: Статья | B55: ₽/год | C55: ₽/час | D55: доля | F55: Статья | G55: ₽/год | H55: ₽/час | I55: доля | K55: Статья | L55: ₽/год | M55: ₽/час | N55: доля
A56: Ваш доход на руки | B56: =MAX(0,target_income) -> 1322592 | C56: =IF(shooting_time=0,0,B56/shooting_time) -> 6106.1496 | D56: =IF((CHOOSE(regime_no,'05_Расчёт'!B4,'05_Расчёт'!C4,'05_Расчёт'!D4,'05_Расчёт'!E4,'05_Расчёт'!F4,'05_Расчёт'!G4,'05_Расчёт'!H4))=0,0,B56/(CHOOSE(regime_no,'05_Расчёт'!B4,'05_Расчёт'!C4,'05_Расчёт'!D4,'05_Расчёт'!E4,'05_Расчёт'!F4,'05_Расчёт'!G4,'05_Расчёт'!H4))) -> 0.64752478 | F56: Ваш доход на руки | G56: =MAX(0,((current_rate*shooting_time)*(1-rate_current-acquiring)-total_costs)) -> 636863.02 | H56: =IF(shooting_time=0,0,G56/shooting_time) -> 2940.2725 | I56: =IF((current_rate*shooting_time)=0,0,G56/(current_rate*shooting_time)) -> 0.49004541 | K56: Ваш доход на руки | L56: =MAX(0,0) -> 0 | M56: =IF(shooting_time=0,0,L56/shooting_time) -> 0 | N56: =IF((CHOOSE(regime_no,'05_Расчёт'!B22,'05_Расчёт'!C22,'05_Расчёт'!D22,'05_Расчёт'!E22,'05_Расчёт'!F22,'05_Расчёт'!G22,'05_Расчёт'!H22))=0,0,L56/(CHOOSE(regime_no,'05_Расчёт'!B22,'05_Расчёт'!C22,'05_Расчёт'!D22,'05_Расчёт'!E22,'05_Расчёт'!F22,'05_Расчёт'!G22,'05_Расчёт'!H22))) -> 0
A57: Отложить на оборудование и обучение | B57: =MAX(0,investment) -> 278687.78 | C57: =IF(shooting_time=0,0,B57/shooting_time) -> 1286.6472 | D57: =IF((CHOOSE(regime_no,'05_Расчёт'!B4,'05_Расчёт'!C4,'05_Расчёт'!D4,'05_Расчёт'!E4,'05_Расчёт'!F4,'05_Расчёт'!G4,'05_Расчёт'!H4))=0,0,B57/(CHOOSE(regime_no,'05_Расчёт'!B4,'05_Расчёт'!C4,'05_Расчёт'!D4,'05_Расчёт'!E4,'05_Расчёт'!F4,'05_Расчёт'!G4,'05_Расчёт'!H4))) -> 0.13644211 | F57: Отложить на оборудование и обучение | G57: =MAX(0,investment) -> 278687.78 | H57: =IF(shooting_time=0,0,G57/shooting_time) -> 1286.6472 | I57: =IF((current_rate*shooting_time)=0,0,G57/(current_rate*shooting_time)) -> 0.2144412 | K57: Отложить на оборудование и обучение | L57: =MAX(0,investment) -> 278687.78 | M57: =IF(shooting_time=0,0,L57/shooting_time) -> 1286.6472 | N57: =IF((CHOOSE(regime_no,'05_Расчёт'!B22,'05_Расчёт'!C22,'05_Расчёт'!D22,'05_Расчёт'!E22,'05_Расчёт'!F22,'05_Расчёт'!G22,'05_Расчёт'!H22))=0,0,L57/(CHOOSE(regime_no,'05_Расчёт'!B22,'05_Расчёт'!C22,'05_Расчёт'!D22,'05_Расчёт'!E22,'05_Расчёт'!F22,'05_Расчёт'!G22,'05_Расчёт'!H22))) -> 0.45715932
A58: Регулярные расходы (реклама, аренда, ПО) | B58: =MAX(0,variable_costs) -> 283980 | C58: =IF(shooting_time=0,0,B58/shooting_time) -> 1311.0803 | D58: =IF((CHOOSE(regime_no,'05_Расчёт'!B4,'05_Расчёт'!C4,'05_Расчёт'!D4,'05_Расчёт'!E4,'05_Расчёт'!F4,'05_Расчёт'!G4,'05_Расчёт'!H4))=0,0,B58/(CHOOSE(regime_no,'05_Расчёт'!B4,'05_Расчёт'!C4,'05_Расчёт'!D4,'05_Расчёт'!E4,'05_Расчёт'!F4,'05_Расчёт'!G4,'05_Расчёт'!H4))) -> 0.13903312 | F58: Регулярные расходы (реклама, аренда, ПО) | G58: =MAX(0,variable_costs) -> 283980 | H58: =IF(shooting_time=0,0,G58/shooting_time) -> 1311.0803 | I58: =IF((current_rate*shooting_time)=0,0,G58/(current_rate*shooting_time)) -> 0.21851339 | K58: Регулярные расходы (реклама, аренда, ПО) | L58: =MAX(0,variable_costs) -> 283980 | M58: =IF(shooting_time=0,0,L58/shooting_time) -> 1311.0803 | N58: =IF((CHOOSE(regime_no,'05_Расчёт'!B22,'05_Расчёт'!C22,'05_Расчёт'!D22,'05_Расчёт'!E22,'05_Расчёт'!F22,'05_Расчёт'!G22,'05_Расчёт'!H22))=0,0,L58/(CHOOSE(regime_no,'05_Расчёт'!B22,'05_Расчёт'!C22,'05_Расчёт'!D22,'05_Расчёт'!E22,'05_Расчёт'!F22,'05_Расчёт'!G22,'05_Расчёт'!H22))) -> 0.46584068
A59: Налог и страховые взносы | B59: =MAX(0,(CHOOSE(regime_no,'05_Расчёт'!B4,'05_Расчёт'!C4,'05_Расчёт'!D4,'05_Расчёт'!E4,'05_Расчёт'!F4,'05_Расчёт'!G4,'05_Расчёт'!H4))*rate_current) -> 102126.75 | C59: =IF(shooting_time=0,0,B59/shooting_time) -> 471.4993 | D59: =IF((CHOOSE(regime_no,'05_Расчёт'!B4,'05_Расчёт'!C4,'05_Расчёт'!D4,'05_Расчёт'!E4,'05_Расчёт'!F4,'05_Расчёт'!G4,'05_Расчёт'!H4))=0,0,B59/(CHOOSE(regime_no,'05_Расчёт'!B4,'05_Расчёт'!C4,'05_Расчёт'!D4,'05_Расчёт'!E4,'05_Расчёт'!F4,'05_Расчёт'!G4,'05_Расчёт'!H4))) -> 0.05 | F59: Налог и страховые взносы | G59: =MAX(0,(current_rate*shooting_time)*rate_current) -> 64980 | H59: =IF(shooting_time=0,0,G59/shooting_time) -> 300 | I59: =IF((current_rate*shooting_time)=0,0,G59/(current_rate*shooting_time)) -> 0.05 | K59: Налог и страховые взносы | L59: =MAX(0,(CHOOSE(regime_no,'05_Расчёт'!B22,'05_Расчёт'!C22,'05_Расчёт'!D22,'05_Расчёт'!E22,'05_Расчёт'!F22,'05_Расчёт'!G22,'05_Расчёт'!H22))*rate_current) -> 30480.378 | M59: =IF(shooting_time=0,0,L59/shooting_time) -> 140.72197 | N59: =IF((CHOOSE(regime_no,'05_Расчёт'!B22,'05_Расчёт'!C22,'05_Расчёт'!D22,'05_Расчёт'!E22,'05_Расчёт'!F22,'05_Расчёт'!G22,'05_Расчёт'!H22))=0,0,L59/(CHOOSE(regime_no,'05_Расчёт'!B22,'05_Расчёт'!C22,'05_Расчёт'!D22,'05_Расчёт'!E22,'05_Расчёт'!F22,'05_Расчёт'!G22,'05_Расчёт'!H22))) -> 0.05
A60: Банку за эквайринг | B60: =MAX(0,(CHOOSE(regime_no,'05_Расчёт'!B4,'05_Расчёт'!C4,'05_Расчёт'!D4,'05_Расчёт'!E4,'05_Расчёт'!F4,'05_Расчёт'!G4,'05_Расчёт'!H4))*acquiring) -> 55148.444 | C60: =IF(shooting_time=0,0,B60/shooting_time) -> 254.60962 | D60: =IF((CHOOSE(regime_no,'05_Расчёт'!B4,'05_Расчёт'!C4,'05_Расчёт'!D4,'05_Расчёт'!E4,'05_Расчёт'!F4,'05_Расчёт'!G4,'05_Расчёт'!H4))=0,0,B60/(CHOOSE(regime_no,'05_Расчёт'!B4,'05_Расчёт'!C4,'05_Расчёт'!D4,'05_Расчёт'!E4,'05_Расчёт'!F4,'05_Расчёт'!G4,'05_Расчёт'!H4))) -> 0.027 | F60: Банку за эквайринг | G60: =MAX(0,(current_rate*shooting_time)*acquiring) -> 35089.2 | H60: =IF(shooting_time=0,0,G60/shooting_time) -> 162 | I60: =IF((current_rate*shooting_time)=0,0,G60/(current_rate*shooting_time)) -> 0.027 | K60: Банку за эквайринг | L60: =MAX(0,(CHOOSE(regime_no,'05_Расчёт'!B22,'05_Расчёт'!C22,'05_Расчёт'!D22,'05_Расчёт'!E22,'05_Расчёт'!F22,'05_Расчёт'!G22,'05_Расчёт'!H22))*acquiring) -> 16459.404 | M60: =IF(shooting_time=0,0,L60/shooting_time) -> 75.989862 | N60: =IF((CHOOSE(regime_no,'05_Расчёт'!B22,'05_Расчёт'!C22,'05_Расчёт'!D22,'05_Расчёт'!E22,'05_Расчёт'!F22,'05_Расчёт'!G22,'05_Расчёт'!H22))=0,0,L60/(CHOOSE(regime_no,'05_Расчёт'!B22,'05_Расчёт'!C22,'05_Расчёт'!D22,'05_Расчёт'!E22,'05_Расчёт'!F22,'05_Расчёт'!G22,'05_Расчёт'!H22))) -> 0.027
A61: ИТОГО берёте с клиента | B61: =(CHOOSE(regime_no,'05_Расчёт'!B4,'05_Расчёт'!C4,'05_Расчёт'!D4,'05_Расчёт'!E4,'05_Расчёт'!F4,'05_Расчёт'!G4,'05_Расчёт'!H4)) -> 2042535 | C61: =IF(shooting_time=0,0,(CHOOSE(regime_no,'05_Расчёт'!B4,'05_Расчёт'!C4,'05_Расчёт'!D4,'05_Расчёт'!E4,'05_Расчёт'!F4,'05_Расчёт'!G4,'05_Расчёт'!H4))/shooting_time) -> 9429.986 | D61: =1 -> 1 | F61: ИТОГО берёте с клиента | G61: =(current_rate*shooting_time) -> 1299600 | H61: =IF(shooting_time=0,0,(current_rate*shooting_time)/shooting_time) -> 6000 | I61: =1 -> 1 | K61: ИТОГО берёте с клиента | L61: =(CHOOSE(regime_no,'05_Расчёт'!B22,'05_Расчёт'!C22,'05_Расчёт'!D22,'05_Расчёт'!E22,'05_Расчёт'!F22,'05_Расчёт'!G22,'05_Расчёт'!H22)) -> 609607.56 | M61: =IF(shooting_time=0,0,(CHOOSE(regime_no,'05_Расчёт'!B22,'05_Расчёт'!C22,'05_Расчёт'!D22,'05_Расчёт'!E22,'05_Расчёт'!F22,'05_Расчёт'!G22,'05_Расчёт'!H22))/shooting_time) -> 2814.4394 | N61: =1 -> 1
A84: 8 · ЧТО ЭТО ЗНАЧИТ — расшифровка простыми словами
A85: ЗА ОДИН ЧАС СЪЁМКИ ВАМ ЗАПЛАТЯТ — И ВОТ КУДА УЙДУТ ЭТИ ДЕНЬГИ:
A87: Вам заплатят за час съёмки: | B87: =IF(shooting_time=0,0,(CHOOSE(regime_no,'05_Расчёт'!B4,'05_Расчёт'!C4,'05_Расчёт'!D4,'05_Расчёт'!E4,'05_Расчёт'!F4,'05_Расчёт'!G4,'05_Расчёт'!H4))/shooting_time) -> 9429.986
A89: Из них вы заработаете (за все свои роли) | B89: =IF(shooting_time=0,0,target_income/shooting_time) -> 6106.1496
A90: Это оплата не одного часа, а ВСЕЙ работы вокруг него. Разбивка по ролям — в таблице ниже.
A91: Откладываете на оборудование и обучение | B91: =IF(shooting_time=0,0,investment/shooting_time) -> 1286.6472
A92: Камера, компьютер, объективы и курсы изнашиваются. Если не откладывать — через 3 года купить новое будет не на что.
A93: Платите за рекламу, аренду и подписки | B93: =IF(shooting_time=0,0,variable_costs/shooting_time) -> 1311.0803
A94: Директ, хостинг, Adobe, доля квартиры под кабинет. Это уходит каждый месяц, даже когда съёмок нет.
A95: Отдаёте государству | B95: =IF(shooting_time=0,0,(CHOOSE(regime_no,'05_Расчёт'!B4,'05_Расчёт'!C4,'05_Расчёт'!D4,'05_Расчёт'!E4,'05_Расчёт'!F4,'05_Расчёт'!G4,'05_Расчёт'!H4))*rate_current/shooting_time) -> 471.4993
A96: Налог по вашему режиму и страховые взносы. Считается с оборота, а не с того, что осталось.
A97: Отдаёте банку | B97: =IF(shooting_time=0,0,(CHOOSE(regime_no,'05_Расчёт'!B4,'05_Расчёт'!C4,'05_Расчёт'!D4,'05_Расчёт'!E4,'05_Расчёт'!F4,'05_Расчёт'!G4,'05_Расчёт'!H4))*acquiring/shooting_time) -> 254.60962
A98: Комиссия за приём оплаты картой. Берётся с каждого поступления.
A100: ЗА КАКИЕ РОЛИ ВЫ ЭТО ЗАРАБОТАЛИ
A101: Роль | B101: Часов в год | C101: Часов на 1 проект | D101: Заработок ₽/год | E101: ₽ с часа съёмки
A102: ФОТОГРАФ — работа на съёмочной площадке | B102: =shooting_time -> 216.6 | C102: =shoot_duration -> 1 | D102: =(target_income/net_time)*shooting_time -> 186871.12 | E102: =IF(shooting_time=0,0,(target_income/net_time)*shooting_time/shooting_time) -> 862.74755
A103: РЕТУШЁР — обработка отснятого материала | B103: =post_time -> 649.8 | C103: =shoot_duration*post_ratio -> 3 | D103: =(target_income/net_time)*post_time -> 560613.36 | E103: =IF(shooting_time=0,0,(target_income/net_time)*post_time/shooting_time) -> 2588.2427
A104: МЕНЕДЖЕР ПО ПРОДАЖАМ — переговоры, согласования | B104: =client_total -> 216.6 | C104: =client_time -> 1 | D104: =(target_income/net_time)*client_total -> 186871.12 | E104: =IF(shooting_time=0,0,(target_income/net_time)*client_total/shooting_time) -> 862.74755
A105: МАРКЕТОЛОГ и SMM — продвижение, соцсети, отклики | B105: =promo_time -> 438 | C105: =IF(projects_year=0,0,promo_time/projects_year) -> 2.0221607 | D105: =(target_income/net_time)*promo_time -> 377883.43 | E105: =IF(shooting_time=0,0,(target_income/net_time)*promo_time/shooting_time) -> 1744.6142
A106: БУХГАЛТЕР — учёт, отчётность, налоги | B106: =accounting_time -> 12 | C106: =IF(projects_year=0,0,accounting_time/projects_year) -> 0.055401662 | D106: =(target_income/net_time)*accounting_time -> 10352.971 | E106: =IF(shooting_time=0,0,(target_income/net_time)*accounting_time/shooting_time) -> 47.797648
A107: Компенсация сорванных съёмок | B107: =fm_time -> 0 | C107: =IF(projects_year=0,0,fm_time/projects_year) -> 0 | D107: =(target_income/net_time)*fm_time -> 0 | E107: =IF(shooting_time=0,0,(target_income/net_time)*fm_time/shooting_time) -> 0
A108: ИТОГО за все роли | B108: =net_time -> 1533 | C108: =IF(projects_year=0,0,net_time/projects_year) -> 7.0775623 | D108: =target_income -> 1322592 | E108: =IF(shooting_time=0,0,target_income/shooting_time) -> 6106.1496
A110: Обратите внимание: собственно ФОТОГРАФОМ вы работаете меньше всего часов. Основное время уходит
A111: на обработку и продвижение — и всё это оплачивается из той же суммы за час съёмки.
A113: ЕСЛИ ВЫ БЕРЁТЕ МЕНЬШЕ, ЧЕМ НУЖНО
A114: Ваша текущая ставка | B114: =current_rate -> 6000
A115: Остаётся вам на руки за год | B115: =MAX(0,((current_rate*shooting_time)*(1-rate_current-acquiring)-total_costs)) -> 636863.02
A116: Недополучено за год | B116: =MAX(0,target_income-((current_rate*shooting_time)*(1-rate_current-acquiring)-total_costs)) -> 685728.98
A117: Недополучено с каждого часа съёмки | B117: =IF(shooting_time=0,0,MAX(0,target_income-((current_rate*shooting_time)*(1-rate_current-acquiring)-total_costs))/shooting_time) -> 3165.8771
A119: Расходы бизнеса не уменьшаются от того, что вы взяли меньше. Аренда, реклама и амортизация
A120: останутся прежними — сократится только ваш собственный доход. Разницу вы фактически дарите клиенту.
A122: МИНИМУМ, НИЖЕ КОТОРОГО РАБОТАТЬ НЕЛЬЗЯ
A123: Ставка при работе в ноль | B123: =IF(shooting_time=0,0,(CHOOSE(regime_no,'05_Расчёт'!B22,'05_Расчёт'!C22,'05_Расчёт'!D22,'05_Расчёт'!E22,'05_Расчёт'!F22,'05_Расчёт'!G22,'05_Расчёт'!H22))/shooting_time) -> 2814.4394
A124: Цена проекта при работе в ноль | B124: =IF(projects_year=0,0,(CHOOSE(regime_no,'05_Расчёт'!B22,'05_Расчёт'!C22,'05_Расчёт'!D22,'05_Расчёт'!E22,'05_Расчёт'!F22,'05_Расчёт'!G22,'05_Расчёт'!H22))/projects_year) -> 2814.4394
A126: При этой ставке вы покрываете расходы, налоги и откладываете на технику — но не получаете НИЧЕГО.
A127: Всё, что ниже, означает, что вы доплачиваете за право работать.
A129: 6 · ВАША НЕДЕЛЯ — 7 дней по 24 часа. Серое: сон и отдых. Цветное: работа
A130: Каждый квадрат = 1 час. Часы работы распределены пропорционально годовым затратам времени.
A131: час | B131: ПН | C131: ВТ | D131: СР | E131: ЧТ | F131: ПТ | G131: СБ | H131: ВС
A132: 00:00
A133: 01:00
A134: 02:00
A135: 03:00
A136: 04:00
A137: 05:00
A138: 06:00
A139: 07:00
A140: 08:00
A141: 09:00
A142: 10:00
...

Sheet 07_Интерфейс
A1: 07 · ИНТЕРФЕЙС — блоки и формы калькулятора
A3: Блок | B3: Раздел | C3: Заголовок | D3: Тип поля | E3: Формы | F3: Что задаёт | G3: Параметры в calc
A4: Block1 | B4: Section1 | C4: Ваш желаемый доход | D4: input_number | E4: — | F4: Сумма на руки в месяц | G4: income_month
A5: Block2 | B5: Section1 | C5: Текущая стоимость часа | D5: input_number | E5: — | F5: Для сравнения | G5: current_rate
A6: Block3 | B6: Section1 | C6: Минимальный заказ (часов) | D6: input_number | E6: — | F6: Базовый заказ: ниже не выезжаете | G6: shoot_duration
A7: Block3a | B7: Section1 | C7: Коэффициент обработки | D7: input_number | E7: — | F7: Часов обработки на 1 час съёмки | G7: post_ratio
A8: Block4 | B8: Section1 | C8: Режим налогообложения | D8: dropdown | E8: Form015, Form016 | F8: ПЕРЕКЛЮЧАТЕЛЬ, 7 вариантов | G8: regime
A9: Block5 | B9: Section1 | C9: Как мы считаем | D9: info_block | E9: — | F9: Пояснение | G9: —
A10: Block6 | B10: Section2 | C10: Съёмочное оборудование | D10: dynamic_table | E10: Form001 | F10: Список позиций | G10: dep_shoot
A11: Block7 | B11: Section2 | C11: Офисное оборудование | D11: dynamic_table | E11: Form002 | F11: Список позиций | G11: dep_office
A12: Block8 | B12: Section2 | C12: Программное обеспечение | D12: dynamic_tables | E12: Form003, Form004 | F12: Подписки и разовые | G12: var_software, dep_software
A13: Block9 | B13: Section2 | C13: Рабочее место | D13: dropdown + table | E13: Form005, Form013 | F13: ПЕРЕКЛЮЧАТЕЛЬ дом/аренда | G13: ws_mode, var_workspace, dep_workspace
A14: Block10 | B14: Section2 | C14: Проф. обучение | D14: input_extended | E14: Form006 | F14: Стоимость, месяцы обучения и срок окупаемости | G14: edu_opportunity, dep_education
... A23: Block18 | B23: Section5 | C23: Сравнение режимов | D23: report | E23: — | F23: Вывод | G23: 04_Расчёт

Sheet 08_UI
A1: 08 · UI-МАТРИЦА — точная карта интерфейса. Каждая строка = один элемент на экране
A2: Переносится в HTML построчно. Колонки: где стоит, что за поле, какая ширина, чем управляется, куда пишет значение.
A4: № | B4: Блок | C4: Раздел | D4: Заголовок / подпись | E4: Элемент | F4: Тип поля | G4: Ширина | H4: Значение по умолч. | I4: Ед. | J4: Форма | K4: Параметр (ID) | L4: Условие показа / блокировки
A5: 01 | B5: Block1 | C5: 1 · О вас | D5: Ваш желаемый доход | E5: самый важный параметр — на всю ширину
D6: Хочу получать на руки | E6: поле ввода | F6: input_number | G6: 52% + кнопка сброса | H6: 110 216 | I6: ₽/мес | J6: — | K6: income_month
A7: 02 | B7: Block4 + Block2 | C7: 1 · О вас | D7: Режим налогообложения и текущая ставка | E7: две колонки в одну строку
D8: Ваш режим налогообложения | E8: выпадающий список | F8: select | G8: 50% | H8: Самозанятый (НПД), средняя 5% | J8: Form015 | K8: regime | L8: 7 вариантов: НПД средняя/физ/юр, УСН 6, УСН 15, АУСН 8, АУСН 20
D9: Моя ставка сейчас | E9: поле ввода | F9: input_number | G9: 52% + кнопка сброса | H9: 6 000 | I9: ₽/час | J9: — | K9: current_rate | L9: необязательное; если 0 — блок «сколько теряете» скрыт
A10: 03 | B10: Block5 | C10: 1 · О вас | D10: Как мы считаем: | E10: информационный блок, полей нет
D11: Пояснительный текст | E11: текстовый блок | F11: info_block | G11: 100% | H11: Работа на себя должна делать вашу жизнь лучше, а не превращать её в бесконечную работу. Поэтому в расчётах Счётикс мы ориентируемся на нормы трудового законодательства РФ и производственный календарь — чтобы у вас оставались силы на творчество, развитие и жизнь вне работы. | J11: — | K11: — | L11: про отпуск, больничный, эффективные часы, почему час съёмки дороже часа работы
A12: 04 | B12: Block3 + Block3a | C12: 2 · Работа | D12: Как устроена ваша работа | E12: две колонки | H12: Время — ваш главный рабочий ресурс. Три плашки: «Всё рабочее время», «Невидимая нагрузка», «Честная стоимость часа». Каждая содержит крупную иконку и короткий тезис. Под заголовком: «Посчитаем время, которое обычно остаётся невидимым».
D13: Время на постпродакшн | E13: поле ввода | F13: input_number | G13: 52% + кнопка сброса | H13: 3 | I13: × | J13: — | K13: post_ratio
D14: Работа с клиентом (на один проект) | E14: поле ввода · блок можно исключить | F14: input_number | G14: 52% + кнопка сброса | H14: 1 | I14: ч | J14: Form012 | K14: client_time
D15: Поиск заказов | E15: поле ввода · блок можно исключить | F15: input_number | G15: 52% + кнопка сброса | H15: 2 | I15: ч/день | J15: Form009 | K15: promo_per_day
D16: Минимальный заказ (часов) | E16: поле ввода | F16: input_number | G16: 52% + кнопка сброса | H16: 2 | I16: ч | J16: — | K16: shoot_duration | L16: Активно всегда. По умолчанию 2 ч — типовой заказ
D17: Готовых кадров за 1 час | E17: поле ввода | F17: input_number | G17: 52% + кнопка сброса | H17: 2 | I17: ч | J17: — | K17: shoot_manual | L17: Дублирует shoot_duration в форме. Пользователь меняет свободно
D18: Шаг изменения | E18: поле ввода | F18: input_number | G18: 50% | H18: 0,5 | I18: ч | J18: — | K18: shoot_step | L18: Шаг стрелок в поле: 0,5 ч. Минимум 0,5 ч
A19: 05 | B19: Block14a | C19: 2 · Работа | D19: Резерв времени на простой и форс-мажоры | E19: галочка активирует поле
D20: Учитывать резерв времени на простой и форс-мажоры | E20: галочка | F20: checkbox | G20: 100% | H20: включена | J20: — | K20: fm_on
D21: Размер резерва | E21: поле ввода | F21: input_number | G21: 50% | H21: 5 | I21: % | J21: — | K21: fm_pct | L21: БЛОКИРУЕТСЯ, если галочка снята
A22: 06 | B22: Block6 | C22: 3 · Инвестиции | D22: Съёмочная техника | E22: динамическая таблица, 10 строк по умолчанию
D23: Не учитывать этот блок | E23: галочка | F23: checkbox | G23: авто | H23: снята | J23: Form001 | K23: use_Form001 | L23: при включении вся амортизация блока = 0
D24: Заголовки таблицы | E24: шапка | F24: table_head | G24: 100% | H24: Позиция · Стоимость ₽ · Срок лет · ₽/год | J24: Form001 | K24: —
D25: Canon EOS R6 Mark II Body | E25: строка таблицы | F25: table_row | G25: — | H25: 166 999 ₽ / 3 лет | L25: удаляется крестиком
D26: Canon RF 24–105mm f/4.0 L IS USM | E26: строка таблицы | F26: table_row | G26: — | H26: 130 999 ₽ / 5 лет | L26: удаляется крестиком
D27: Godox V1Pro C | E27: строка таблицы | F27: table_row | G27: — | H27: 36 990 ₽ / 5 лет | L27: удаляется крестиком
D28: Godox XPro II C | E28: строка таблицы | F28: table_row | G28: — | H28: 9 355 ₽ / 5 лет | L28: удаляется крестиком
D29: Аккумулятор LP-E6NH | E29: строка таблицы | F29: table_row | G29: — | H29: 12 978 ₽ / 3 лет | L29: удаляется крестиком
D30: SanDisk Extreme PRO 256 ГБ #1 | E30: строка таблицы | F30: table_row | G30: — | H30: 6 990 ₽ / 2 лет | L30: удаляется крестиком
D31: SanDisk Extreme PRO 256 ГБ #2 | E31: строка таблицы | F31: table_row | G31: — | H31: 6 990 ₽ / 2 лет | L31: удаляется крестиком
D32: Рюкзак Lowepro ProTactic | E32: строка таблицы | F32: table_row | G32: — | H32: 27 962 ₽ / 7 лет | L32: удаляется крестиком
D33: Godox RFT-05 отражатель | E33: строка таблицы | F33: table_row | G33: — | H33: 3 000 ₽ / 5 лет | L33: удаляется крестиком
D34: X-Rite ColorChecker | E34: строка таблицы | F34: table_row | G34: — | H34: 5 000 ₽ / 7 лет | L34: удаляется крестиком
D35: + Добавить позицию | E35: кнопка | F35: button_add | G35: авто | H35: — | J35: Form001 | K35: — | L35: добавляет пустую строку
D36: Итого амортизация | E36: строка итога | F36: calc_row | G36: 100% | H36: 137 893,32 | I36: ₽/год | J36: Form001 | K36: dep_shoot
A37: 07 | B37: Block7 | C37: 3 · Инвестиции | D37: Офисная техника | E37: динамическая таблица, 9 строк
D38: Не учитывать этот блок | E38: галочка | F38: checkbox | G38: авто | H38: снята | J38: Form002 | K38: use_Form002
D39: Заголовки таблицы | E39: шапка | F39: table_head | G39: 100% | H39: Позиция · Стоимость ₽ · Срок лет · ₽/год | J39: Form002 | K39: —
D40: Системный блок | E40: строка таблицы | F40: table_row | G40: — | H40: 180 000 ₽ / 5 лет | L40: удаляется крестиком
D41: Монитор ASUS ProArt | E41: строка таблицы | F41: table_row | G41: — | H41: 55 000 ₽ / 5 лет | L41: удаляется крестиком
D42: Calibrite ColorChecker | E42: строка таблицы | F42: table_row | G42: — | H42: 30 000 ₽ / 5 лет | L42: удаляется крестиком
D43: Колонки Logitech Z207 | E43: строка таблицы | F43: table_row | G43: — | H43: 5 000 ₽ / 5 лет | L43: удаляется крестиком
D44: Клавиатура Logitech K380 | E44: строка таблицы | F44: table_row | G44: — | H44: 3 500 ₽ / 7 лет | L44: удаляется крестиком
D45: Мышь Logitech M650 | E45: строка таблицы | F45: table_row | G45: — | H45: 4 000 ₽ / 3 лет | L45: удаляется крестиком
D46: Веб-камера Logitech Brio | E46: строка таблицы | F46: table_row | G46: — | H46: 15 999 ₽ / 5 лет | L46: удаляется крестиком
D47: Микрофон FIFINE K669B | E47: строка таблицы | F47: table_row | G47: — | H47: 3 500 ₽ / 5 лет | L47: удаляется крестиком
D48: Принтер Canon PIXMA G640 | E48: строка таблицы | F48: table_row | G48: — | H48: 29 999 ₽ / 5 лет | L48: удаляется крестиком
D49: + Добавить позицию | E49: кнопка | F49: button_add | G49: авто | H49: — | J49: Form002 | K49: —
D50: Итого амортизация | E50: строка итога | F50: calc_row | G50: 100% | H50: 65 732,93 | I50: ₽/год | J50: Form002 | K50: dep_office
A51: 08 | B51: Block8 | C51: 3 · Инвестиции | D51: Программное обеспечение | E51: ДВЕ таблицы в одном блоке | H51: Укажите программы и сервисы, которые нужны вам для профессиональной деятельности и работы вокруг неё.
D52: Не учитывать этот блок | E52: галочка | F52: checkbox | G52: авто | H52: снята | J52: Form003, Form004 | K52: use_Form008
D53: — Подписки (платятся регулярно) | E53: подзаголовок | F53: subhead | G53: 100% | H53: Лицензии и сервисы, за которые вы регулярно платите. | J53: Form003 | K53: —
D54: Заголовки | E54: шапка | F54: table_head | G54: 100% | H54: Позиция · Стоимость ₽ · Период · ₽/год | J54: Form003 | K54: —
D55: Adobe CC Photography | E55: строка таблицы | F55: table_row | G55: — | H55: 2 000 ₽ / Месяц | L55: удаляется крестиком
D56: Яндекс Диск 1 ТБ | E56: строка таблицы | F56: table_row | G56: — | H56: 250 ₽ / Месяц | L56: удаляется крестиком
D57: + Добавить подписку | E57: кнопка | F57: button_add | G57: авто | H57: — | J57: Form003 | K57: —
D58: Итого подписки | E58: строка итога | F58: calc_row | G58: 100% | H58: 27 000 | I58: ₽/год | J58: Form003 | K58: var_software
D59: — Разовые покупки (амортизируются) | E59: подзаголовок | F59: subhead | G59: 100% | H59: Программы и лицензии, которые вы оплачивали один раз и используете длительное время. | J59: Form004 | K59: —
D60: Заголовки | E60: шапка | F60: table_head | G60: 100% | H60: Позиция · Стоимость ₽ · Срок лет · ₽/год | J60: Form004 | K60: —
D61: Retouch4me Heal | E61: строка таблицы | F61: table_row | G61: — | H61: 6 900 ₽ / 3 лет | L61: удаляется крестиком
D62: Retouch4me Dodge & Burn | E62: строка таблицы | F62: table_row | G62: — | H62: 6 900 ₽ / 3 лет | L62: удаляется крестиком
D63: Retouch4me Fabric | E63: строка таблицы | F63: table_row | G63: — | H63: 6 900 ₽ / 3 лет | L63: удаляется крестиком
D64: Retouch4me Clean Backdrop | E64: строка таблицы | F64: table_row | G64: — | H64: 6 900 ₽ / 3 лет | L64: удаляется крестиком
D65: Retouch4me Dust | E65: строка таблицы | F65: table_row | G65: — | H65: 6 900 ₽ / 3 лет | L65: удаляется крестиком
D66: + Добавить программу | E66: кнопка | F66: button_add | G66: авто | H66: — | J66: Form004 | K66: —
D67: Итого разовые | E67: строка итога | F67: calc_row | G67: 100% | H67: 11 500 | I67: ₽/год | J67: Form004 | K67: dep_software
A68: 09 | B68: Block9 | C68: 3 · Инвестиции | D68: Рабочее место | E68: переключатель; дома аренда и коммунальные считаются по доле площади, офис — полностью
D69: Не учитывать этот блок | E69: галочка | F69: checkbox | G69: авто | H69: снята | J69: Form005, Form013 | K69: use_Form009
D70: Где вы работаете | E70: переключатель | F70: radio | G70: 100% | H70: Работаю из дома | J70: Form005 | K70: ws_mode | L70: 2 варианта: Работаю из дома / Арендую помещение
D71: Аренда или ипотека | E71: поле ввода | F71: input_number | G71: 50% | H71: 40 000; строка обязательная, без удаления | I71: ₽/мес | J71: Form005 | K71: home_rent | L71: видно только при «Работаю из дома». Берётся ПО ДОЛЕ метров
D72: Коммунальные и связь | E72: поле ввода | F72: input_number | G72: 50% | H72: 7 000; строку можно удалить | I72: ₽/мес | J72: Form005 | K72: home_util | L72: видно при «дома». Берётся ЦЕЛИКОМ
D73: Общая площадь жилья | E73: поле ввода | F73: input_number | G73: 50% | H73: 50; строку можно удалить | I73: м² | J73: Form005 | K73: home_area | L73: видно при «дома»
D74: Площадь под кабинет | E74: поле ввода | F74: input_number | G74: 50% | H74: 6; строку можно удалить | I74: м² | J74: Form005 | K74: cab_area | L74: видно при «дома»
D75: Доля кабинета | E75: расчётное поле | F75: calc_field | G75: 50% | H75: 12,00 | I75: % | J75: Form005 | K75: cab_share | L75: только чтение
D76: Стоимость помещения | E76: поле ввода | F76: input_number | G76: 50% | H76: 15 000 | I76: ₽/мес | J76: Form005 | K76: office_rent | L76: видно только при «Арендую помещение». ЦЕЛИКОМ
D77: Коммунальные и связь | E77: поле ввода | F77: input_number | G77: 50% | H77: 7 000 | I77: ₽/мес | J77: Form005 | K77: office_util | L77: видно при «аренда». ЦЕЛИКОМ
D78: — Обустройство места (мебель, ремонт) | E78: подзаголовок | F78: subhead | G78: 100% | J78: Form013 | K78: —
D79: Заголовки | E79: шапка | F79: table_head | G79: 100% | H79: Позиция · Стоимость ₽ · Срок лет · ₽/год | J79: Form013 | K79: —
D80: Мебель | E80: строка таблицы | F80: table_row | G80: — | H80: 35 000 ₽ / 7 лет | L80: удаляется крестиком
D81: Косметический ремонт | E81: строка таблицы | F81: table_row | G81: — | H81: 30 000 ₽ / 7 лет | L81: удаляется крестиком
D82: + Добавить позицию | E82: кнопка | F82: button_add | G82: авто | H82: — | J82: Form013 | K82: —
D83: Итого содержание | E83: строка итога | F83: calc_row | G83: 100% | H83: 141 600 | I83: ₽/год | J83: Form005 | K83: var_workspace
D84: Итого обустройство | E84: строка итога | F84: calc_row | G84: 100% | H84: 9 285,71 | I84: ₽/год | J84: Form013 | K84: dep_workspace
A85: 10 | B85: Block10 | C85: 3 · Инвестиции | D85: Профессиональное обучение
D86: Не учитывать этот блок | E86: галочка | F86: checkbox | G86: авто | H86: снята | J86: Form006 | K86: use_Form006
D87: Заголовки | E87: шапка | F87: table_head | G87: 100% | H87: Курс · Стоимость ₽ · Месяцев учёбы · Срок лет | J87: Form006 | K87: —
D88: Курс по фотографии | E88: строка таблицы | F88: table_row | G88: — | H88: 80 000 ₽ / 7 лет | L88: удаляется крестиком
D89: Месяцев учёбы без дохода | E89: поле ввода | F89: input_number | G89: 50% | H89: 4 | I89: мес | J89: Form006 | K89: edu_months
L90: если включена: + месяцев × желаемый доход
D91: + Добавить курс | E91: кнопка | F91: button_add | G91: авто | H91: — | J91: Form006 | K91: —
D92: Итого амортизация | E92: строка итога | F92: calc_row | G92: 100% | H92: 73 713,71 | I92: ₽/год | J92: Form006 | K92: dep_education
A93: 11 | B93: Block12 | C93: 3 · Инвестиции | D93: Создание сайта | E93: переключатель; поля зафиксированы в двухколоночной сетке
D94: Не учитывать этот блок | E94: галочка | F94: checkbox | G94: авто | H94: снята | J94: Form014 | K94: use_Form014
D95: Как появился сайт | E95: переключатель | F95: radio | G95: 100% | H95: Нанимал (а) специалиста | J95: Form014 | K95: site_mode | L95: 2 варианта: Нанимал специалиста / Делал самостоятельно
D96: Стоимость подрядчика | E96: поле ввода | F96: input_number | G96: 50% | H96: 70 000 | I96: ₽ | J96: Form014 | K96: site_cost | L96: видно при «Нанимал»
D97: Часов своими руками | E97: поле ввода | F97: input_number | G97: 50% | H97: 0 | I97: ч | J97: Form014 | K97: site_hours | L97: видно при «Делал сам». Оценивается по ПОЛНОЙ ставке рабочего часа
D98: Срок амортизации | E98: поле ввода | F98: input_number | G98: 50% | H98: 7 | I98: лет | J98: Form014 | K98: site_life
D99: Итого амортизация | E99: строка итога | F99: calc_row | G99: 100% | H99: 10 000 | I99: ₽/год | J99: Form014 | K99: dep_website
A100: 12 | B100: Block11 | C100: 4 · Расходы | D100: Реклама и продвижение | E100: динамическая таблица
D101: Не учитывать этот блок | E101: галочка | F101: checkbox | G101: авто | H101: снята | J101: Form010 | K101: use_Form010
...

Sheet 08c_Структура_отчёта
A1: 08c · СТРУКТУРА ОТЧЁТА — что и где показывается
A2: Порядок блоков сверху вниз, как в report.html. Колонка «Показатели» — какие цифры выводятся и по какой формуле. Колонка id — техническое имя контейнера в вёрстке, по нему цифра ищется в коде.
A4: ШАПКА И ГЛАВНЫЙ ЭКРАН
A5: № | B5: Блок | C5: Тип | D5: Показатели и формулы | E5: id в вёрстке
A6: — | B6: Шапка | C6: header | D6: Заголовок, подзаголовок, дата расчёта. Логотип справа | E6: rMeta
A7: — | B7: Зелёная плашка · ставка | C7: hero | D7: Крупно: ставка часа = revenue_full / shooting_time, округлена вверх до 500. В скобках точное значение. Под ней строка: фактическая стоимость часа = target_income / (net_time + idle_time) = 747 ₽. Три показателя в строку: · Ваш доход на руки = target_income / 12 · Всего расходов = (investment + variable_costs + налоги + эквайринг) / 12 · Общая выручка = revenue_full / 12 ПРОВЕРКА: доход + расходы = выручка | E7: hRate, hRateEx, hInc, hExp, hMon
A8: — | B8: Кнопка PDF | C8: button | D8: Печать. Имя файла: ГГГГ-ММ-ДД Счётикс для фотографа | E8: dlpdf
A9: — | B9: Условия труда по ТК | C9: cond | D9: 5/2 · 28 дней отпуска · 8 часов — константы календаря | E9: condGrid
A10: — | B10: Почему этому расчёту можно верить | C10: trust | D10: 4 аргумента доверия: считали от вашего дохода · учли всё время · нормы ТК РФ · 7 налоговых режимов | E10: —
A11: БЛОКИ ПОЛНОГО ОТЧЁТА
A12: № | B12: Блок | C12: Тип | D12: Показатели и формулы | E12: id в вёрстке
A13: 01 | B13: Как распределяется бюджет | C13: donut + легенда | D13: Кольцо: 15 сегментов, в центре ставка часа. Под кольцом текст: остаётся вам / идёт на расходы. ЛЕГЕНДА, три группы: 1. Ваш доход — 5 строк ролей: съёмка, обработка, клиент, продвижение, учёт 2. Не оплачивается — простой и форс-мажоры 3. Расходы и налоги — 9 строк: техника и ПО, обучение и сайт, рабочее место, реклама, подписки, аренда, банк, налоги, эквайринг Каждая строка: ₽ с часа · % · ₽/мес. Нулевые строки скрываются. ПРОВЕРКА: сумма всех строк = ставка часа | E13: dn1, dnSum, lg1
A14: 02 | B14: Как распределяется ваше время | C14: сетка 5×8 | D14: Рабочая неделя по слотам. Расшифровка по трём группам: фотограф / владелец бизнеса / не оплачивается | E14: wk, wknote, drows
A15: 03 | B15: Как считают обычно | C15: compare | D15: Формула: текущая ставка × часы съёмки в неделю × 4. Кажется / останется на самом деле + разница | E15: calcLine, inNaive, inReal, inNaiveTx | G15: УДАЛЁН из HTML 06.08.2026: не даёт пользователю полезной информации
A16: 04 | B16: Три сценария вашей работы | C16: 3 кольца | D16: ИДЕАЛЬНЫЙ (расчётная ставка) · РЕАЛЬНЫЙ (текущая) · В НОЛЬ (безубыточность). Для каждого: доход на руки, ставка часа, выручка в месяц. Ниже блок «При съёмке в ноль» + примечание о логистике | E16: dns, bRate, bProj
A17: 05 | B17: А если брать больше заказов | C17: scenario | D17: Съёмок в месяц, часов в день, рабочих дней, выходных при текущей ставке. Жёлтая плашка-предупреждение | E17: scn
A18: 06 | B18: Как формировать скидку | C18: 4 карточки | D18: Базовая цена часа + скидки от 3, 4, 5 часов. Скидка = снижение доли накладных | E18: dmap
A19: — | B19: Два запаса (рекомендация) | C19: 2 ползунка | D19: Фонд развития (% выручки) и запас на скидку. Живой пересчёт, проверка лимита НПД. В основной расчёт НЕ входит | E19: fundPct, discPct, recTot, recWarn | G19: ПЕРЕНЕСЁН в анкету, блок 15 «Запас прочности». Ползунки + галочки
A20: 07 | B20: Ваш идеальный налоговый режим | C20: таблица | D20: 7 режимов на ОДНОЙ реальной выручке. Колонки: налоги, нагрузка, на руки, в месяц. Потолок НПД. Правило выбора Доходы vs Д−Р | E20: bestBox, npdBox, txrows, txrule
A21: 08 | B21: Сколько людей делают это в компании | C21: donut + список | D21: 5 ролей: фотограф, маркетолог, продажи, бухгалтер, администратор. Часы в неделю и % от загрузки | E21: nmDonut, nmList | G21: УДАЛЁН из HTML 06.08.2026: не нужен
A22: 09 | B22: Четыре цифры, которые стоит запомнить | C22: 4 карточки | D22: · Час вашего времени = target_income / (net_time + idle_time) · Оборудование и ПО = equip_only / цена съёмки, в съёмках · Времени на одну съёмку = project_time · Цена одного кадра = цена съёмки / (frames_out × shoot_duration) Методика — лист 09b | E22: factGrid
A23: — | B23: Заключение | C23: хук | D23: «Фотографы, вы офигели?» — подставляется расчётная ставка. Цифр в тексте больше нет | E23: finRate
A24: 10 | B24: Объясняйте клиенту, из чего складывается цена | C24: текст + 4 карточки | D24: Цитата про «потому что» (эксперимент Лангер), текст про селлеров. 4 карточки «что клиент не видит» | E24: cstA, cstB, cstC, cstD
A25: CTA | B25: 30 готовых постов | C25: плашка | D25: Контент-план. Ссылка-заглушка #plan | E25: ctaLink
A26: PMK | B26: Что входит в каждую строку | C26: памятка | D26: Расшифровка по 6 видам работ, мелким текстом | E26: pmkText
A27: — | B27: Подвал | C27: footer | D27: Знак сверху, «счётикс» под ним | E27: —
A29: ЧТО ГДЕ ПРАВИТЬ
A30: № | B30: Блок | C30: Тип | D30: Показатели и формулы | E30: id в вёрстке
B31: Текст надписи | C31: 09_Тексты | D31: Найти по ключу data-t из вёрстки, править колонку «Текст» | E31: —
B32: Цифра или формула | C32: calc | D32: Колонка «Значение» | E32: —
B33: Методика блока 09 | C33: 09b_Методика | D33: Как посчитана каждая цифра | E33: —
B34: Цвет | C34: 09c_Палитра | D34: 68 токенов, единых для формы и отчёта | E34: —
B35: Логотип | C35: 09d_Логотип | D35: Эталон знака, менять только там | E35: —
A37: НОВЫЙ ПОРЯДОК БЛОКОВ — 06.08.2026, 17 блоков
A38: — | B38: Шапка
A39: — | B39: Плашка со ставкой
A40: — | B40: Кнопка PDF
A41: — | B41: Ваши условия труда по ТК РФ
A42: — | B42: Из чего складывается ваша цена
A43: 01 | B43: Как распределяется бюджет
A44: 02 | B44: Как распределяется ваше время
A45: 03 | B45: Ваш идеальный налоговый режим ← было 07
A46: 04 | B46: Как формировать скидку ← было 06
A47: 05 | B47: Три сценария вашей работы ← было 04
A48: 06 | B48: А если просто брать больше заказов ← было 05
A49: 07 | B49: Четыре цифры, которые стоит запомнить ← было 09
... A54: — | B54: Подвал
A56: ПОРЯДОК НА 06.08.2026 — 18 блоков
A57: — | B57: Шапка
A58: — | B58: Плашка со ставкой
A59: — | B59: Кнопка PDF
A60: — | B60: Ваши условия труда по ТК РФ
A61: — | B61: Логистика: дорога в расчёт не входит ← НОВЫЙ
A62: — | B62: Из чего складывается ваша цена
A63: 01 | B63: Как распределяется бюджет
A64: 02 | B64: Как распределяется ваше время
A65: 03 | B65: Как формировать скидку ← поднят
A66: 04 | B66: Ваш идеальный налоговый режим
A67: 05 | B67: Три сценария вашей работы
A68: 06 | B68: А если просто брать больше заказов
... A74: — | B74: Подвал
A76: ДОБАВЛЕНО 06.08.2026 — два блока в конец, перед подвалом
A77: — | B77: Справочник: что означает каждое понятие | C77: 4 раздела, 17 определений. Источник — лист 01_Глоссарий, выжимка только по тому, что есть в отчёте
A78: — | B78: Все цифры расчёта в одной таблице | C78: 6 разделов, 39 строк: время, проект, доход, расходы, налоги, ставки. Три колонки: название, значение, пояснение
A80: ПРАВКА 06.08.2026: справочник понятий занял место памятки «Что входит в каждую строку расчёта» и её оформление (.pmknote — серая подложка, строки .pi2, без колонок). Итого 19 блоков: … 30 постов · справочник · таблица цифр · подвал

Sheet 09_Тексты
A1: 09 · ТЕКСТЫ — все надписи формы и отчёта
A2: Правьте только колонку «Текст». Колонка «Где находится» показывает поверхность: Форма (шапка / вопросы / подсказки / краткий результат / оплата / опрос / подписка / превью) или Полный отчёт. Красным помечено то, что в вёрстке больше не используется — это архив, не удаляем. После правок: python3 sync_texts.py apply-all
A4: Ключ | B4: Где находится | C4: Текст
A5: Заголовок страницы
A6: h1_01 | B6: Форма · шапка | C6: Сколько на самом деле стоит ваш час | H6: УДАЛЕНО из HTML: шапка анкеты приведена к отчёту, ключ заменён на rh_01 / rh_02 / rh_03 10.08.2026
A7: Подзаголовок
A8: sub_01 | B8: Форма · шапка | C8: Калькулятор для фотографов и видеографов. Считает ставку, которая покроет не только съёмку, но и обработку, продвижение, технику и налоги. | H8: УДАЛЕНО из HTML: шапка анкеты приведена к отчёту, ключ заменён на rh_01 / rh_02 / rh_03 10.08.2026
A9: Заголовок блока
A10: h2_01 | B10: Форма · вопросы анкеты | C10: Ваш желаемый доход
A11: Вопрос
A12: q_01 | B12: Форма · вопросы анкеты | C12: Сколько вы хотите получать на руки каждый месяц?
A13: Пояснение к вопросу
A14: qd_01 | B14: Форма · вопросы анкеты | C14: Это сумма, которая остаётся вам после всех расходов и налогов. От неё считается всё остальное.
A15: Единица измерения
A16: un_01 | B16: Форма · вопросы анкеты | C16: ₽/мес
A17: Заголовок блока
A18: h2_02 | B18: Форма · вопросы анкеты | C18: Ваш налоговый режим
A19: Вопрос
A20: q_02 | B20: Форма · вопросы анкеты | C20: На каком режиме налогообложения вы работаете?
A21: Пояснение к вопросу
A22: qd_02 | B22: Форма · вопросы анкеты | C22: Выберите свой режим налогообложения или воспользуйтесь автоматическим подбором.
A23: q_02b | B23: Форма · вопросы | C23: С кем вы чаще работаете?
A24: qd_02b | B24: Форма · вопросы | C24: Если работаете и с частными лицами, и с компаниями — НПД посчитаем по усреднённой ставке 5%.
A25: Вопрос
A26: q_03 | B26: Форма · вопросы анкеты | C26: Сколько вы берёте за час съёмки сейчас? | H26: УДАЛЕНО из HTML: вопрос убран, остались заголовок и подзаголовок блока 03 — 10.08.2026
A27: Пояснение к вопросу
A28: qd_03 | B28: Форма · вопросы анкеты | C28: Нужно, чтобы показать разницу между вашей текущей и расчётной ставкой. Можно оставить пустым. | H28: УДАЛЕНО из HTML: вопрос убран, остались заголовок и подзаголовок блока 03 — 10.08.2026
A29: Единица измерения
A30: un_02 | B30: Форма · вопросы анкеты | C30: ₽/час
A31: Заголовок блока
A32: h2_03 | B32: Форма · вопросы анкеты | C32: Как мы считаем:
A33: Надпись карточки
A34: tp_01 | B34: Форма · вопросы анкеты | C34: Человеческие условия
A35: Мелкий текст карточки
A36: sm_01 | B36: Форма · вопросы анкеты | C36: Официальные нормы труда и отдыха, установленные государством.
A37: Надпись карточки
A38: tp_02 | B38: Форма · вопросы анкеты | C38: Право на отдых
A39: Мелкий текст карточки
A40: sm_02 | B40: Форма · вопросы анкеты | C40: И один больничный — чтобы спокойно восстановиться без страха потерять доход.
A41: Надпись карточки
A42: tp_03 | B42: Форма · вопросы анкеты | C42: Комфортный распорядок
A43: Мелкий текст карточки
A44: sm_03 | B44: Форма · вопросы анкеты | C44: И 8-часовой рабочий день — норма труда, установленная законом.
A45: Заголовок блока
A46: h2_04 | B46: Форма · вопросы анкеты | C46: Посчитаем ваше время | H46: УДАЛЕНО из HTML: блок 04 разбит на пять карточек, вопросы стали заголовками — 10.08.2026
A47: Пояснение под заголовком
A48: hint_01 | B48: Форма · вопросы анкеты | C48: Ваш минимальный выезд. От него считается базовая ставка часа, а всё, что длиннее, — скидка за объём | H48: УДАЛЕНО из HTML: блок 04 разбит на пять карточек, вопросы стали заголовками — 10.08.2026
A49: Вопрос
A50: q_04 | B50: Форма · вопросы анкеты | C50: Какая у вас минимальная продолжительность съёмки? | H50: УДАЛЕНО из HTML: блок 04 разбит на пять карточек, вопросы стали заголовками — 10.08.2026
A51: Пояснение к вопросу
A52: qd_04 | B52: Форма · вопросы анкеты | C52: Укажите минимальное количество съёмочных часов, ради которых вы готовы выезжать на заказ.
A53: Единица измерения
A54: un_03 | B54: Форма · вопросы анкеты | C54: часов
A55: Пояснение к вопросу
A56: qd_05 | B56: Форма · вопросы анкеты | C56: Часть времени всегда уходит впустую: клиент перенёс, погода подвела, пришлось ехать повторно.
A57: Заголовок блока
A58: h2_05 | B58: Форма · вопросы анкеты | C58: Как устроена ваша работа | H58: ОБЪЕДИНЕНО: блок 05 слит с блоком 04, заголовок взят у него 10.08.2026
A59: Вопрос
A60: q_05 | B60: Форма · вопросы анкеты | C60: Сколько часов вы тратите на обработку одного часа отснятого материала? | H60: УДАЛЕНО из HTML: блок 04 разбит на пять карточек, вопросы стали заголовками — 10.08.2026
A61: Пояснение к вопросу
A62: qd_06 | B62: Форма · вопросы анкеты | C62: Укажите, сколько времени в среднем вы тратите на подготовку материала за 1 час съёмки. Учитывайте всё время — от начала выгрузки материала на компьютер до передачи готового результата клиенту.
A63: Единица измерения
A64: un_04 | B64: Форма · вопросы анкеты | C64: часа
A65: Вопрос
A66: q_06 | B66: Форма · вопросы анкеты | C66: Сколько времени уходит на общение с клиентом по одному заказу? | H66: УДАЛЕНО из HTML: блок 04 разбит на пять карточек, вопросы стали заголовками — 10.08.2026
A67: Пояснение к вопросу
A68: qd_07 | B68: Форма · вопросы анкеты | C68: Укажите, сколько времени в среднем вы тратите на общение с клиентом и организацию одного уже подтверждённого проекта.
A69: Единица измерения
A70: un_05 | B70: Форма · вопросы анкеты | C70: часа
A71: Вопрос
A72: q_07 | B72: Форма · вопросы анкеты | C72: Сколько часов в день вы тратите на продвижение? | H72: УДАЛЕНО из HTML: блок 04 разбит на пять карточек, вопросы стали заголовками — 10.08.2026
A73: Пояснение к вопросу
A74: qd_08 | B74: Форма · вопросы анкеты | C74: Укажите, сколько времени в среднем вы тратите на поиск новых клиентов и продвижение своих услуг.
A75: Единица измерения
A76: un_06 | B76: Форма · вопросы анкеты | C76: ч/день
A77: Заголовок блока
A78: h2_06 | B78: Форма · вопросы анкеты | C78: Съёмочная техника
A79: Пояснение под заголовком
A80: hint_02 | B80: Форма · вопросы анкеты | C80: Это набор вашего базового оборудования, без которого вы просто не сможете провести съёмку. Укажите текущую рыночную стоимость и срок, за который позицию придётся заменить. Не включайте сюда специфическое оборудование, которое требуется под задачи конкретного заказчика. Его стоимость лучше сразу закладывать в смету как дополнительную аренду.
A81: Заголовок колонки
A82: th_01 | B82: Форма · вопросы анкеты | C82: Позиция
A83: th_02 | B83: Форма · вопросы | C83: Стоимость
A84: th_03 | B84: Форма · вопросы | C84: Срок службы
A85: Кнопка добавления
A86: add_01 | B86: Форма · вопросы анкеты | C86: + Добавить позицию
A87: Заголовок блока
A88: h2_07 | B88: Форма · вопросы анкеты | C88: Офисная техника
A89: Пояснение под заголовком
A90: hint_03 | B90: Форма · вопросы анкеты | C90: Это оборудование, которое помогает вам выполнять заказы и решать рабочие задачи за компьютером. Укажите его текущую рыночную стоимость и срок, через который планируете заменить.
A91: Заголовок колонки
A92: th_04 | B92: Форма · вопросы анкеты | C92: Позиция
A93: th_05 | B93: Форма · вопросы | C93: Стоимость
A94: th_06 | B94: Форма · вопросы анкеты | C94: Срок службы
A95: Кнопка добавления
A96: add_02 | B96: Форма · вопросы анкеты | C96: + Добавить позицию
A97: Заголовок блока
A98: h2_08 | B98: Форма · вопросы анкеты | C98: Программное обеспечение
A99: Подзаголовок секции
A100: sh_01 | B100: Форма · вопросы анкеты | C100: Подписки
A101: Пояснение к секции
...

Sheet 09b_Методика_цифр
A1: 09b · МЕТОДИКА — как посчитана каждая цифра отчёта
A2: Столбец «Формула» записан через ID из calc. Правите параметр — меняется цифра в отчёте.
A4: БЛОК 09 · ЧЕТЫРЕ ЦИФРЫ, КОТОРЫЕ СТОИТ ЗАПОМНИТЬ
A5: № | B5: Показатель | C5: Значение | D5: Формула (через ID) | E5: Что означает и почему так
A6: 9.1 | B6: Доход в час на руки | C6: 692 ₽/ч | D6: '=target_income*11/12/(net_days*8) | E6: Желаемый доход за 11 месяцев (отпускной уже внутри года как месяц без работы) делится на рабочее время 219 × 8 = 1 752 ч: 1 212 376 / 1 752 = 692 ₽/ч. Это сравнение с наймом: как зарплата за 11 месяцев при восьмичасовом дне.
A7: 9.2 | B7: Оборудование и ПО | C7: 11,4 съёмок | D7: '=(dep_shoot+dep_office+dep_software)/(revenue_full/projects_year) | E7: Амортизация техники и ПО за год (215 126 ₽) делится на цену одной съёмки (18 934 ₽). Показывает, сколько съёмок уходит ТОЛЬКО на окупаемость техники — без налогов, рекламы и вашего дохода. Обучение и сайт сюда НЕ входят, только железо и ПО.
A8: 9.3 | B8: Времени на одну съёмку | C8: 9,0 ч | D8: '=project_time = shoot_duration*(1+post_ratio)+client_time | E8: 2 ч съёмки × (1+3 обработка) + 1 ч на клиента = 9 ч. Это полный цикл одного заказа: переписка и согласование, съёмка, отбор, цветокоррекция, ретушь, экспорт и передача.
A9: 9.4 | B9: Цена одного кадра | C9: 118 ₽ | D9: '=(revenue_full/projects_year)/(frames_out*shoot_duration) | E9: Цена съёмки (18 934 ₽) делится на количество отданных кадров (80 кадров/час × 2 ч = 160). frames_out задаёт пользователь в форме.
A11: БЛОК 04 · КУДА УХОДИТ ВАШЕ ВРЕМЯ — откуда берётся неэффективное время
A12: № | B12: Показатель | C12: Значение | D12: Формула (через ID) | E12: Что означает и почему так
A13: 4.1 | B13: Рабочее время по календарю | C13: 1 976 ч/год | D13: '=work_days*nominal_hours = 247*8 | E13: Производственный календарь: 247 рабочих дней по 8 часов.
A14: 4.2 | B14: Чистое время | C14: 1 533 ч/год | D14: '=net_days*eff_hours = (247-20-8)*7 | E14: Минус отпуск 20 раб. дней и больничный 8 раб. дней = 219 дней. По 7 продуктивных часов.
A15: 4.3 | B15: РАБОЧИЕ ПАУЗЫ (idle) | C15: 219 ч/год = 5,0 ч/нед | D15: '=net_days*(nominal_hours-eff_hours) = 219*(8-7) | E15: РОВНО 1 ЧАС В ДЕНЬ. Это НЕ дорога и НЕ простой. Это подготовка и уборка рабочего места, зарядка и проверка техники, размяться, отойти — разбросано по всему рабочему дню. Нормальная часть рабочего процесса, поэтому включена в базу распределения дохода.
A16: 4.4 | B16: База распределения дохода | C16: 1 752 ч/год | D16: '=net_time+idle_time = 1533+219 | E16: Доход раскладывается на чистое время ПЛЮС неэффективное рабочее время — потому что оно оплачивается так же, как в найме: работодатель платит за 8 часов, а не за 7.
A18: ПРОВЕРКА · сходимость
A19: № | B19: Показатель | C19: Значение | D19: Формула (через ID) | E19: Что означает и почему так
A20: П1 | B20: Сумма недели | C20: 40,00 ч | D20: '=(shooting_time+post_time+promo_time+client_total+accounting_time+fm_time+idle_time)/net_weeks | E20: Съёмка 5,2 + обработка 15,7 + продвижение 10,0 + клиент 2,6 + учёт 0,3 + простой и форс-мажор 1,2 + неэффективное время 5,0 = 40,00 ч. Совпадает с 5-дневной 40-часовой неделей по ТК РФ.
A22: БЛОК «ДВА ЗАПАСА» · РЕКОМЕНДАЦИИ (в основной расчёт НЕ входят)
A23: № | B23: Показатель | C23: Значение | D23: Формула (через ID) | E23: Что означает и почему так
A24: Р.1 | B24: Фонд развития, % выручки | C24: 5% (ползунок 0–15) | D24: 'задаёт пользователь в отчёте | E24: Считается от ВЫРУЧКИ, а не от прибыли. Норма реинвестирования 20–30% прибыли для соло-специалиста неприменима: прибыль здесь и есть зарплата.
A25: Р.2 | B25: Выручка с фондом | C25: 2 290 039 ₽ | D25: '=(target_income+total_costs)/(1-налог-эквайринг-g) | E25: g — доля фонда. При 5%: ставка 10 016 ₽ вместо 9 467 ₽, рост 5,8%.
A26: Р.3 | B26: Сумма фонда за год | C26: 114 502 ₽ | D26: '=выручка_с_фондом*g | E26: 9 542 ₽/мес. Это 53% годовой амортизации техники — за два года накапливается стоимость всего парка оборудования.
A27: Р.4 | B27: Запас на скидку, % | C27: 10% (ползунок 0–25) | D27: 'задаёт пользователь в отчёте | E27: Максимальная скидка, которую хочется давать «просто так», вне объёмной сетки блока 06.
A28: Р.5 | B28: Наценка под скидку | C28: +11,1% при скидке 10% | D28: '=1/(1-D)-1 | E28: ДЕЛИТЬ, а не умножать. Чтобы после скидки 10% остаться при своих, поднять надо на 11,1%. При 15% → +17,6%, при 20% → +25%.
A29: Р.6 | B29: Итоговая ставка | C29: 11 129 ₽ | D29: '=выручка_с_фондом/(1-D)/shooting_time | E29: Фонд 5% + скидка 10% дают рост цены на 17,6% относительно базовой 9 467 ₽.
A30: Р.7 | B30: Проверка лимита НПД | C30: 2 544 488 ₽ > 2 400 000 ₽ | D30: '=итоговая_выручка>limit_npd | E30: ВАЖНО: с обоими запасами выручка вылетает за лимит самозанятости. Блок показывает предупреждение, что режим из блока 07 перестаёт подходить.
A32: ОКРУГЛЕНИЕ · только крупная цифра в шапке
A33: № | B33: Показатель | C33: Значение | D33: Формула (через ID) | E33: Что означает и почему так
A34: О.1 | B34: Ставка в шапке (hero) | C34: 9 500 ₽ | D34: '=ОКРВВЕРХ(ставка;500) | E34: ЕДИНСТВЕННОЕ округление во всём отчёте. Нужно, чтобы человек воспринимал свой час цельной величиной и мог её запомнить. Только вверх — вниз округлять нельзя, доход просядет.
A35: О.2 | B35: Точное значение рядом | C35: · точно 9 467 ₽ | D35: '=revenue_full/shooting_time | E35: Выводится в подписи под крупной цифрой, серым. Показывается только если округлённое и точное различаются.
A36: О.3 | B36: Все остальные цифры | C36: без округления | D36: '— | E36: Отчёт считает юнит-экономику специалиста, а не формирует прайс для клиента. Точные значения: кольцо блока 01, три сценария, «в ноль», сетка скидок, блок «Два запаса», хук, цена съёмки, выручка, налоги, четыре цифры блока 09.
A37: О.4 | B37: Подпись под кнопкой PDF | C37: rsv_02 | D37: '— | E37: Объясняет читателю разницу: «В шапке ставка округлена до 500 ₽ — так её проще держать в голове и называть. Все расчёты в отчёте идут по точному значению, без округлений».
A44: ТОЧКА БЕЗУБЫТОЧНОСТИ — исправлено 07.08.2026
A45: Было (неверно) | B45: Vb = costY + taxAll + aq. Налог и эквайринг брались из ЦЕЛЕВОГО сценария, хотя обе величины зависят от самой выручки. Ставка завышалась: 3 835 ₽/ч.
A46: Стало | B46: Решается уравнение V − costY − V×0,027 − налог(V) = 0 для режима из анкеты. Метод — деление пополам, 90 итераций: у налога изломы (взносы, минимальный налог), аналитической формулы нет.
A47: Проверка (демо, НПД 5%) | B47: V = 609 608 ₽ = расходы 562 668 + эквайринг 16 459 + налог 30 480. Невязка нетто 1e-10 ₽. Ставка 2 814 ₽/ч.
A48: По режимам | B48: НПД 4% — 3 299 ₽/ч · НПД 5% — 3 335 · НПД 6% — 3 372 · УСН 6% — 3 457 · УСН 15% — 3 484 · АУСН 8% — 3 447 · АУСН 20% — 3 264
A49: Текущий сценарий | B49: Налог и эквайринг тоже пересчитаны по своей выручке и своему режиму. Раньше налог был жёстко зашит под УСН 6%, даже если человек на НПД.
A51: БЛОК 03 — ДВЕ ПРИРОДЫ СКИДКИ, 07.08.2026
A52: Скидка за объём | B52: Источник — накладные: длинная съёмка размазывает подготовку и переписку на большее число часов. Доход не меняется. Считается: (S×(1+K)+cl)×hp/S, ступени S+2, S+4, S+6.
A53: Скидка из запаса | B53: Источник — наценка discP, заложенная в цену в анкете. Даётся по решению фотографа, доход не меняется, пока скидка ≤ запаса. Предел: базовая цена × (1 − discP).
A54: Складываются | B54: Обе скидки независимы. Клиент на 5 ч при запасе 10%: −16,2% за объём и ещё до −10% из запаса.
A55: Если запас не заложен | B55: Показывается .note.warn: любая уступка сверх объёмной идёт из дохода. Раньше блок 03 discP не использовал вообще, хотя из анкеты он приходил.
A56: Проверка (демо, запас 10%) | B56: база 9 900 ₽/ч → предел 9 000 ₽/ч, резерв 900 ₽/ч
A58: БЛОК 03 — СЦЕНАРИЙ «КАЖДЫЙ ТРЕТИЙ ЗАКАЗ ОТ ПОСТОЯННОГО», 09.08.2026
A59: Доля 30% | B59: Отраслевая норма Repeat Purchase Rate: хорошим считается 20–40% (mindbox.ru/journal/education/retention-rate, ads.vk.ru/insights/retention-rate-chto-eto-i-kak-ego-uvelichit, rush-agency.ru). Медиана по рынку 27% (retentionlab.ai), средний 25–30%, Shopify ~27% (mobiloud.com). Unisender разбирает ровно 30% как «почти каждый третий клиент возвращается». Взята середина коридора.
A60: Почему это выгодно | B60: Привлечь нового в 5–7 раз дороже удержания (prooflytics.io). Вероятность продажи существующему 60–70%, новому 5–20% (penguin-team.ua). Около 65% выручки дают действующие клиенты (mobiloud.com, finance.mail.ru).
A61: Разбивка 40/40/20 | B61: НЕ отраслевая статистика — таких данных по частоте визитов в услугах в открытых источниках нет. Взята от собственных ступеней скидки постоянному клиенту: 2, 4 и 12 съёмок в год. В отчёте прямо названа примером распределения.
A62: Расчёт | B62: Считаем от людей и от фонда, а не от заказов. Экономия на привлечении в покрытие скидок НЕ засчитывается — она остаётся выгодой фотографа. Фонд на постоянных 169 200 ₽ распределяется полностью: 10 чел × 2 съёмки = 20 заказов (5%, 47 000 ₽) · 5 чел × 4 = 20 (7%, 65 800 ₽) · 1 чел × 12 = 12 (10%, 56 400 ₽). Итого 16 клиентов, 52 заказа, скидок ровно 169 200 ₽. Средний чек 47 000 ₽.
A63: Итог | B63: 52 из 217 заказов = 24,0% — «каждый четвёртый». Сверх скидок фотограф получает 137 540 ₽/год экономии на привлечении и 121 ч (15 рабочих дней) — в отчёте показано отдельно как чистая выгода, в бюджет скидок не входит. Прежний вариант (64 заказа, 201 160 ₽ скидок, из фонда 31 880 ₽) отменён: фонд расходовался на 19% и выглядел нерациональным.
A64: Где зафиксировано | B64: Вся структура — лист 13b_Программа_лояльности. Там же формулы сходимости: сумма трёх направлений = бюджет фонда, скидки постоянным = бюджет направления. Здесь остаются только пояснения к решениям.
A65: Доли направлений уточнены | B65: Было 25 / 45 / 30 «ровными» процентами, суммы не сходились с фондом. Стало: постоянным = сумма ступеней (169 200 ₽), спецпредложения = номинал комплекта (114 000 ₽), объём = остаток (94 626 ₽). Доли получаются 25,0 / 44,8 / 30,2%. Кольцо и полосы в блоке 03 пересчитаны.
A67: Блок 03 переведён в живой код, 09.08.2026
A68: Как считается | B68: Все цифры выводятся из анкеты. Средний чек = базовая цена съёмки (ставка часа × минимальная длительность), НЕ фиксированные 47 000 ₽. Фонд = discY из calc.html. Резерв не заложен → показывается только скидка за объём, подблоки 2 и 3 и фонд скрыты.
A69: Два ограничителя постоянных | B69: Число клиентов = min(бюджет направления 45% фонда ÷ скидка на клиента; 30% потока заказов ÷ съёмок на клиента). Без второго ограничителя при большом фонде получалось 224 постоянных заказа из 217 — больше, чем всего заказов.
A70: Сходимость | B70: Скидка за объём = фонд − постоянным − сертификаты. Остаток всегда уходит в объём, поэтому сумма трёх направлений равна фонду при любых входных данных. Проверено на резерве 5% и 15%.
A71: Заголовок сценария | B71: «Каждый второй / третий / четвёртый / пятый» выбирается по факту: делим общее число заказов на заказы постоянных. Раньше стояло жёстко «каждый третий».
A72: Полная таблица: два новых раздела, 09.08.2026
A73: Привлечение клиента | B73: Показывается всегда. Поиск, переписка, реклама с сайтом — на один заказ. Стоимость нового клиента = (поиск + переписка) × ставка часа + реклама/сайт на заказ. Постоянный = переписка × 0,70 × ставка (на 30% короче, рекламы нет).
A74: Программа лояльности | B74: Показывается только при заложенном резерве. Резерв, фонд за год / месяц / съёмку, три направления с долями, средний чек, ступени постоянного клиента, итог по клиентам и заказам, комплект сертификатов, экономия на привлечении. Все величины берутся из тех же переменных, что и блок 03, — второго расчёта нет, расхождение невозможно.
A76: Блок 07 «Сколько стоит привести одного клиента», 09.08.2026
A77: Где стоит | B77: Перед блоком «Четыре цифры». Нумерация сдвинулась: новый блок 07, «Четыре цифры» стали 08, «Объясняйте клиенту» — 09. В собрать.py ожидаемое число блоков 18 → 19.
A78: Расчёт вынесен наверх | B78: Стоимость привлечения считается ОДИН раз до всех блоков и используется в блоке 03, блоке 07 и полной таблице. Раньше формула дублировалась в двух местах — риск расхождения при правке.
A79: Состав заявки | B79: Поиск и продвижение = promo/py × ставка часа. Переговоры = clT/py × ставка. Реклама и сайт = (varAds + depSite)/py. Ставка часа = Ny/(NT+idle).
A80: Постоянный клиент | B80: Поиск и реклама не тратятся, переписка короче на 30%: постЧ = перепЧ × 0,70. На демо-наборе новый 3 168 ₽ против 523 ₽ — дешевле в 6,1 раза.
A81: Ромб врезки | B81: Подсказка .exm при незаложенном резерве остаётся пустой, но ромб-маркер продолжал рисоваться и уезжал под текст. Добавлено .ex .exm:empty{display:none}.
A82: Блок 07 переделан по эталону блока 01, 09.08.2026
A83: Диаграмма | B83: Строится теми же классами, что легенда блока 01: .lgd → .lggrp → .lgi с заливкой .fill по доле от наибольшей величины. Геометрия сверена вычисленными стилями: сетка, отступы, радиус, маркеры, кегль групп совпадают с блоком 01 полностью.
A84: Две природы затрат | B84: Как «время / деньги» в блоке 01. Группа «Ваше время»: продвижение и реклама (promo/py) + переговоры (clT/py), обе оценены по стоимости часа. Группа «Прямые расходы»: реклама (varAds/py) и сайт (depSite/py) — раздельными строками.
A85: Итог | B85: Отдельной строкой .lgi.tot в конце диаграммы, а не плашкой: плашка дублировала бы сумму, которая уже видна в сравнении.
A86: Сравнение | B86: Таблица .cmp в три столбца: показатель · новый · постоянный. Прежние плашки .cacc/.cacw убраны — они повторяли те же суммы дважды. Строки таблицы повторяют состав диаграммы один в один.
A87: Стоимость привлечения и точка безубыточности — разная природа, 09.08.2026
A88: Вопрос | B88: Стоимость привлечения 3 168 ₽ выглядела больше безубыточной цены заказа 3 335 ₽ — казалось, что вся цена уходит на рекламу.
A89: Проверка | B89: Несостыковки нет. 3 335 ₽ — цена, при которой доход НУЛЕВОЙ: время специалиста там стоит 0 ₽, покрываются только живые деньги. 3 168 ₽ — из них 912 ₽ живых денег (реклама + сайт), остальные 2 256 ₽ — время, пересчитанное по ставке 747 ₽/ч из ДОХОДА на руки. Складывать нельзя — двойной счёт.
A90: Корректное сравнение | B90: 912 ₽ живых денег на привлечение из 3 335 ₽ безубыточной цены заказа = 27%. Формулы блока 05 верны, правок не требуют.
A91: Что исправлено | B91: Подпись «и 3,0 часа вашего времени» рядом с суммой в рублях создавала путаницу: часы уже переведены в деньги. Теперь плашка показывает сумму, подзаголовок объясняет перевод, ниже разбивка «время в деньгах 2 256 ₽ / прямые расходы 912 ₽». В таблице строка «Всего вашего времени» в часах заменена на «Эквивалент вашего времени в рублях».
A92: Блок 07 — косметика сравнения, 09.08.2026
A93: Заголовок | B93: У таблицы не было названия — непонятно, что сравнивается. Добавлен заголовок «Новый клиент против постоянного» стилем .lggrp, под ним пояснение без цифр.
A94: Плашки вынесены наверх | B94: Крупные суммы (3 168 ₽ и 523 ₽) стояли в шапке таблицы, из-за чего строка заголовков была высотой с плашку. Теперь итог — две цветные плашки НАД таблицей, а таблица только обосновывает состав. Шапка стала тонкой: 11 px, отступы 10 px.
A95: Порядок | B95: Диаграмма состава → плашка итога → заголовок сравнения → две плашки → таблица обоснования. Последняя строка таблицы — эквивалент времени в рублях, суммы заявки в ней больше нет: она уже названа в плашках.
A96: Блок 07 — сравнение перестроено, 09.08.2026
A97: Порядок | B97: Плашки итога → заголовок «Новый клиент vs Постоянный» → пояснение → таблица состава. Раньше заголовок стоял над плашками.
A98: Пояснение | B98: Говорит, ЗАЧЕМ смотреть блок («сравните, во что обходится каждая заявка, чтобы решать, сколько вкладывать в привлечение, а сколько в удержание»), а не пересказывает преимущества — выводы человек видит в цифрах.
A99: Шапка таблицы | B99: Серая заливка во всю ширину убрана: плашка выглядела тяжелее самой таблицы. Остались подписи столбцов 11 px с разделительной чертой, отступы 12/8, столбцы 118 px.
A100: БАГ: высокая шапка таблицы блока 07 — найдено 09.08.2026
A101: Симптом | B101: Строка заголовков таблицы была высотой 210 px при обычной строке 43 px. Правил четыре раза, уменьшая отступы и кегль, — не помогало, потому что причина была не в них.
A102: Причина | B102: Совпадение имён классов. Я назвала ячейки шапки .cn и .cp, а .cn уже занят информационными плашками отчёта: у него min-height:210px и декоративный круг ::before 130×130. Ячейка наследовала чужую геометрию.
A103: Решение | B103: Переименованы в .cmpn1 / .cmpp1. Шапка стала 37,5 px. Проверено измерением в настоящем браузере (puppeteer): jsdom высоту не вычисляет и этот баг увидеть не мог.
A104: Урок | B104: Перед добавлением класса проверять, не занято ли имя: grep по каркасу. Короткие имена (.cn, .cp, .ch) особенно опасны.
A105: Ссылки на справочник и второй экран шапки, 09.08.2026
A106: Ссылки вместо пересказа | B106: В диаграмме блока 07 под названием статьи стоял пересказ состава («контент, рилсы, тексты»). Заменён на ссылку «что входит в статью» на соответствующий термин справочника. Определение живёт в одном месте и не расходится по блокам.
A107: Как устроено | B107: Каждому термину справочника присвоен якорь ref0..ref25 по порядку. Функция window.PHR_REF(имя) возвращает id по названию. Справочник строится раньше блока 07, поэтому ссылки резолвятся.
A108: Экран 2 — время | B108: Продолжение шапки: первый экран про деньги, второй про загрузку. Гамма голубой плашки «Условий труда» (.cn.b). Показывает число съёмок за год, общее рабочее время и разбивку: съёмка / обработка / продвижение с работой с клиентом / учёт, неэффективное время, простой и форс-мажоры. Каждая колонка дублируется в часах в неделю.
A109: Проверка | B109: Сумма четырёх колонок = 1752 ч = NT + idle, то есть всё рабочее время года. Часы берутся из тех же полей, что блок 02, второго расчёта нет.
A110: Блок «Стоимость привлечения» вынесен из отчёта, 09.08.2026 | B110: Ожидаемое число блоков 19 → 20.
A111: Решение | B111: Убран полностью: это маркетинг, а не юнит-экономика, и требует отдельной проработки. Код сохранён в части/07_привлечение_клиента.html — 8 частей: разметка, стили, расчёты, раздел таблицы.
A112: Что убрано из отчёта | B112: Блок 07 целиком, раздел «Привлечение клиента» из полной таблицы, строка «Сэкономлено на привлечении» из раздела программы лояльности. Нумерация вернулась: «Четыре цифры» — 07, «Объясняйте клиенту» — 08. В собрать.py 20 → 19 блоков.
A113: Что осталось | B113: Экран 2 шапки (время) и ссылки на справочник — они не про привлечение. Переменные расчёта (ставкаЧ, поискЧ, перепЧ, новР, постР) оставлены: их использует блок 03 для экономии на привлечении.
A114: Нерешённые вопросы, зафиксированы в файле | B114: 1) Часть продвижения работает на удержание, а не только на привлечение — доля не определена. 2) Переговоры считаются только по состоявшимся заказам, время на несостоявшиеся не учтено нигде. 3) Коэффициент 0,7 для постоянного клиента взят БЕЗ ИСТОЧНИКА, обсуждалась цифра 50%. Для 2 и 3 нужен вопрос в анкете: из скольких обращений выходит заказ.
A115: Отраслевые данные | B115: Конверсия заявки в сделку по рынку 5–20% (brutalmarketing.me), для услуг 5–15% (vc.ru). Данных именно по фотоуслугам не найдено.

Sheet 09c_Палитра
A1: 09c · ПАЛИТРА — единая для формы, отчёта и всех подсказок
A2: Один и тот же набор из 68 токенов объявлен в :root обоих файлов — calc.html (#phc-root) и report.html (#phr-root). Собственных hex в вёрстке нет. Исключение: фирменные цвета Visa / Mastercard / МИР в иконках оплаты — их менять нельзя.
A4: Нейтральные · текст и линии
A5: Токен CSS | B5: HEX | C5: Образец | D5: Где применяется
A6: --c-ink | B6: #1A1A1A | D6: основной текст
A7: Прочее
A8: Токен CSS | B8: HEX | C8: Образец | D8: Где применяется
A9: --c-ink2 | B9: #374151 | D9: заголовки таблиц
A10: --c-ink3 | B10: #4B5563 | D10: вторичный текст
A11: Нейтральные · текст и линии
A12: Токен CSS | B12: HEX | C12: Образец | D12: Где применяется
A13: --c-gr | B13: #6B7280 | D13: подписи
A14: Прочее
A15: Токен CSS | B15: HEX | C15: Образец | D15: Где применяется
A16: --c-gr2 | B16: #9CA3AF | D16: мелкие подписи, капс
A17: --c-gr3 | B17: #B6BCC4 | D17: самый светлый текст
A18: Нейтральные · текст и линии
A19: Токен CSS | B19: HEX | C19: Образец | D19: Где применяется
A20: --c-ln | B20: #E5E7EB | D20: линии и границы
A21: Прочее
A22: Токен CSS | B22: HEX | C22: Образец | D22: Где применяется
A23: --c-ln2 | B23: #F0F2F5 | D23: светлые разделители
A24: Нейтральные · фоны
A25: Токен CSS | B25: HEX | C25: Образец | D25: Где применяется
A26: --c-bg | B26: #F5F6F8 | D26: фон страницы
A27: --c-surf | B27: #FAFBFC | D27: фон карточек-подложек
A28: --c-white | B28: #FFFFFF | D28: фон карточек
A29: Зелёный · доход, успех, база
A30: Токен CSS | B30: HEX | C30: Образец | D30: Где применяется
A31: --c-g-50 | B31: #F5FBF7 | D31: самый светлый зелёный фон
A32: --c-g-100 | B32: #EAF6EE | D32: фон зелёных плашек
A33: --c-g-200 | B33: #D8EEDF | D33: кольца, заливки
A34: --c-g-300 | B34: #A9DDB8 | D34: сегменты диаграмм
A35: --c-g-350 | B35: #6FD183 | D35: сегменты диаграмм
A36: --c-g-400 | B36: #4FC26A | D36: градиенты
A37: --c-g-500 | B37: #21A038 | D37: основной зелёный бренда
A38: --c-g-600 | B38: #1B9331 | D38: бейдж ИДЕАЛЬНЫЙ, кнопки
A39: --c-g-700 | B39: #158026 | D39: акцентные цифры
A40: --c-g-800 | B40: #0B6B22 | D40: тёмный градиент
A41: --c-g-900 | B41: #14532D | D41: текст на зелёном фоне
A42: --c-g-mut | B42: #5C9C6C | D42: приглушённый зелёный
A43: Красный · убыток, предупреждение, скидка
A44: Токен CSS | B44: HEX | C44: Образец | D44: Где применяется
A45: --c-r-50 | B45: #FFF6F6 | D45: фон красных плашек
A46: --c-r-100 | B46: #FDE8E8 | D46: светлая заливка
A47: --c-r-200 | B47: #F7D3D3 | D47: границы
A48: --c-r-300 | B48: #E4A9A9 | D48: сегменты
A49: --c-r-400 | B49: #E8828E | D49: бейдж, акценты
A50: --c-r-500 | B50: #EF4444 | D50: сердечки, ошибки
A51: --c-r-550 | B51: #D6566A | D51: бейдж В НОЛЬ
A52: --c-r-600 | B52: #C43D51 | D52: цифры в красном
A53: --c-r-650 | B53: #D0342F | D53: плашка «Скидка»
A54: --c-r-700 | B54: #B91C1C | D54: текст предупреждений
A55: --c-r-800 | B55: #991B1B | D55: заголовки в красном
A56: --c-r-900 | B56: #7F1D1D | D56: самый тёмный красный
A57: Янтарный · внимание, знак ⚠
A58: Токен CSS | B58: HEX | C58: Образец | D58: Где применяется
A59: --c-a-50 | B59: #FFFBEF | D59: фон жёлтых плашек
A60: --c-a-100 | B60: #FEF3D6 | D60: светлая заливка
A61: --c-a-200 | B61: #FBE3AE | D61: границы
A62: --c-a-300 | B62: #F2C48A | D62: сегменты
A63: --c-a-350 | B63: #E8A05C | D63: акценты
A64: --c-a-400 | B64: #F5B301 | D64: ЗНАК ВОСКЛИЦАНИЯ (треугольник)
A65: --c-a-500 | B65: #D9762E | D65: скидка средняя
A66: --c-a-600 | B66: #C4551F | D66: скидка крупная
A67: --c-a-700 | B67: #B45309 | D67: текст
A68: --c-a-800 | B68: #92400E | D68: тёмный текст
A69: --c-a-900 | B69: #7A5309 | D69: текст на жёлтом
A70: --c-a-br | B70: #8A5C4A | D70: коричневый текст
A71: --c-a-br2 | B71: #5F3B2E | D71: тёмно-коричневый
A72: Синий · нейтральные акценты, реальный сценарий
A73: Токен CSS | B73: HEX | C73: Образец | D73: Где применяется
A74: --c-b-50 | B74: #F6FAFE | D74: фон синих плашек
A75: --c-b-100 | B75: #E7F0FA | D75: светлая заливка
A76: --c-b-200 | B76: #CFE0F3 | D76: границы
A77: --c-b-250 | B77: #B7C9E8 | D77: сегменты
A78: --c-b-300 | B78: #8FC7E8 | D78: роль маркетолога
A79: --c-b-400 | B79: #5CA8E0 | D79: градиент
A80: --c-b-500 | B80: #3B82F6 | D80: акцент
A81: --c-b-600 | B81: #2F80C4 | D81: бейдж РЕАЛЬНЫЙ
A82: --c-b-700 | B82: #2A6FAB | D82: цифры
A83: --c-b-800 | B83: #1D4ED8 | D83: иконка роста
A84: --c-b-900 | B84: #3B6398 | D84: тёмный текст
A85: --c-b-mut | B85: #7189AE | D85: приглушённый
A86: Фиолетовый · цитата, математика
A87: Токен CSS | B87: HEX | C87: Образец | D87: Где применяется
A88: --c-v-50 | B88: #F8F5FE | D88: фон блока цитаты
A89: --c-v-300 | B89: #C7B9EC | D89: сегмент
A90: --c-v-500 | B90: #8B5CF6 | D90: акцент
A91: --c-v-700 | B91: #6D3FD4 | D91: «потому что»
A92: Розовый · обработка, SMM
A93: Токен CSS | B93: HEX | C93: Образец | D93: Где применяется
A94: --c-p-50 | B94: #FFF7FB | D94: фон розовых плашек
A95: --c-p-100 | B95: #FCE7F3 | D95: иконка обработки
A96: --c-p-500 | B96: #EC4899 | D96: SMM
A97: --c-p-700 | B97: #9D174D | D97: текст обработки
A99: ПРАВИЛА
A100: • Новый цвет в вёрстку не добавляем — берём ближайший токен из этого списка.
A101: • Знак восклицания везде один: равносторонний треугольник со скруглёнными углами, заливка --c-a-400, знак белый.
A102: • Размеры знака только два: 17×16 px в тексте (класс .iwt) и 42×39 px в плашке (класс .iwt.lg).
...

Sheet 09d_Логотип
A1: 09d · ЛОГОТИП — эталон, менять только здесь
A2: Знак зафиксирован. Любая правка вёрстки должна сверяться с этим листом. Если логотип в файле отличается от кода ниже — это ошибка, привести к эталону.
A4: ПРАВИЛА — нарушать нельзя
A5: Параметр | B5: Значение | C5: Пояснение
A6: Порядок в замке | B6: надпись СЛЕВА, знак СПРАВА | C6: Во всех местах обоих файлов: шапка отчёта, шапка формы, подвалы.
A7: Зелёный элемент | B7: ПРАВЫЙ ромб | C7: Крайний правый. Не нижний, не верхний. Фиксировано, не меняется при прокрутке.
A8: Цвет зелёного | B8: var(--c-g-500) = #21A038 | C8: Основной зелёный бренда из листа 09c. Другие оттенки не использовать.
A9: Цвет серых | B9: var(--c-ln) = #E5E7EB | C9: Три остальных ромба. В подвале те же цвета, гасится прозрачностью .55.
A10: Анимация | B10: ЗАПРЕЩЕНА | C10: Знак статичен. Подсветка «активного юнита» по прокрутке была удалена — из-за неё логотип менялся на каждом экране.
A12: ГЕОМЕТРИЯ · viewBox 32 × 32
A13: Параметр | B13: Значение | C13: Пояснение
A14: Сторона квадрата | B14: 10,10 | C14: Замерено по макету заказчика попиксельно.
A15: Смещение от центра | B15: 8,86 | C15: Отношение к габариту ромба 0,62 — даёт воздушный зазор.
A16: Скругление rx | B16: 1,90 | C16: 19% стороны.
A17: Поворот | B17: rotate(45) | C17: Вокруг центра каждого квадрата.
A18: Размеры вывода | B18: 46 px шапка · 20 px подвал | C18: Меняется только атрибут width/height, геометрия не трогается.
A20: ТИПОГРАФИКА
A21: Элемент | B21: Значение | C21: Пояснение
A22: Название | B22: счётикс | C22: Строчными. 19 px, вес 700, разрядка .11em, цвет --c-ink.
A23: Подпись | B23: твоя юнит-экономика | C23: 9 px, --c-gr2, растянута по ширине названия через space-between (каждая буква в теге i).
A24: Подвал | B24: счётикс | C24: 12 px, вес 700, --c-gr, прозрачность блока .55.
A25: Зазор знак↔текст | B25: 12 px шапка · 7 px подвал
A27: ИСХОДНЫЙ КОД — копировать отсюда
A28: Что | B28: Где применяется | C28: Код
A29: Знак | B29: шапка (class=bx) | C29: <svg class="bx" viewBox="0 0 32 32" fill="none" aria-hidden="true"><rect x="10.95" y="2.09" width="10.10" height="10.10" rx="1.90" transform="rotate(45 16 7.14)" fill="var(--c-ln)"/><rect x="19.81" y="10.95" width="10.10" height="10.10" rx="1.90" transform="rotate(45 24.86 16)" fill="var(--c-g-500)"/><rect x="10.95" y="19.81" width="10.10" height="10.10" rx="1.90" transform="rotate(45 16 24.86)" fill="var(--c-ln)"/><rect x="2.09" y="10.95" width="10.10" height="10.10" rx="1.90" transform="rotate(45 7.14 16)" fill="var(--c-ln)"/></svg>
A30: Замок целиком | B30: шапка отчёта и формы | C30: <div class="brand" title="Счётикс — твоя юнит-экономика"><span class="btx"><span class="bt">счётикс</span><span class="bd" data-t="bt_02"><i>т</i><i>в</i><i>о</i><i>я</i><i>&nbsp;</i><i>ю</i><i>н</i><i>и</i><i>т</i><i>-</i><i>э</i><i>к</i><i>о</i><i>н</i><i>о</i><i>м</i><i>и</i><i>к</i><i>а</i></span></span><svg class="bx" viewBox="0 0 32 32" fill="none" aria-hidden="true"><rect x="10.95" y="2.09" width="10.10" height="10.10" rx="1.90" transform="rotate(45 16 7.14)" fill="var(--c-ln)"/><rect x="19.81" y="10.95" width="10.10" height="10.10" rx="1.90" transform="rotate(45 24.86 16)" fill="var(--c-g-500)"/><rect x="10.95" y="19.81" width="10.10" height="10.10" rx="1.90" transform="rotate(45 16 24.86)" fill="var(--c-ln)"/><rect x="2.09" y="10.95" width="10.10" height="10.10" rx="1.90" transform="rotate(45 7.14 16)" fill="var(--c-ln)"/></svg></div>
A31: Подвал | B31: низ обоих файлов | C31: <span class="lgs" title="Счётикс — твоя юнит-экономика"><span class="lt">счётикс</span><svg class="lx" viewBox="0 0 32 32" fill="none" aria-hidden="true"><rect x="10.95" y="2.09" width="10.10" height="10.10" rx="1.90" transform="rotate(45 16 7.14)" fill="var(--c-ln)"/><rect x="19.81" y="10.95" width="10.10" height="10.10" rx="1.90" transform="rotate(45 24.86 16)" fill="var(--c-g-500)"/><rect x="10.95" y="19.81" width="10.10" height="10.10" rx="1.90" transform="rotate(45 16 24.86)" fill="var(--c-ln)"/><rect x="2.09" y="10.95" width="10.10" height="10.10" rx="1.90" transform="rotate(45 7.14 16)" fill="var(--c-ln)"/></svg></span></span>
A33: ПРОВЕРКА ПОСЛЕ ЛЮБОЙ ПРАВКИ
A34: • В обоих файлах ровно один зелёный ромб на знак, атрибут x="19.81".
A35: • Порядок дочерних элементов: сначала span с текстом, потом svg.
A36: • В коде нет классов u-inc / u-exp / u-res / u-prof — это следы удалённой анимации.
A37: • В CSS нет правил .bx .u и .lx .u — цвет задаётся прямо в атрибутах fill.
A38: • Фоновые знаки в блоке 01 тоже с зелёным справа.
A40: ВЕРТИКАЛЬНЫЙ ВАРИАНТ · подвал
A41: • В подвале обоих файлов знак стоит СВЕРХУ, надпись «счётикс» — под ним.
A42: • Знак 26 px, надпись 11 px с разрядкой .17em, цвет --c-gr2, прозрачность блока .6.
A43: • Горизонтальный вариант (надпись слева, знак справа) — только в шапке.
A44: • Причина: в подвале мало места по ширине, горизонтальный замок расползался.
A46: ФОНОВАЯ ГРАФИКА
... A51: ФИРМЕННАЯ ГРАФИКА — три элемента, других не добавляем
A52: Элемент | B52: Где применяется | C52: Как задан
A53: 1. Знак — четыре ромба | B53: Шапка и подвал обоих файлов. Фон блока 01 (три размера). Фон зелёной плашки, белым 7%. Фон блока «Почему можно верить», зелёным 5%. | C53: <svg viewBox='0 0 32 32'> + 4 rect, геометрия из раздела выше
A54: 2. Камера — контур | B54: Фон блока 01 (справа сверху, 92px). Фон зелёной плашки (справа сверху, белым 9%). Обозначает нишу: для другой профессии меняется на свою иконку. | C54: <rect> корпус + <path> выступ + 2 <circle> объектив, stroke-width 1–1.1
A55: 3. Круг — мягкое пятно | B55: Плашки условий труда: right:-30px, top:-30px, 130×130, белый 10%. Фон блока 01: два больших круга 320 и 340px, заливка --c-g-50 и --c-b-50. | C55: border-radius:50% + background:rgba(255,255,255,.10) или <circle> с заливкой из палитры
A57: • Прозрачность фоновой графики: 5–13%. Она должна читаться только если присматриваться.
A58: • Цвета — строго из палитры 09c. На цветных подложках белый с прозрачностью.
A59: • Абстрактных иконок (часы, стрелки, звёзды, диафрагма) больше не используем — только эти три элемента.
A60: • Диафрагма объектива была удалена с зелёной плашки: читалась как посторонний символ.
A62: ЦВЕТ ЗНАКА ЗАВИСИТ ОТ ФОНА
A63: • На белом фоне серые ромбы — var(--c-ln) #E5E7EB.
A64: • На сером фоне страницы (--c-bg #F5F6F8) — var(--c-gr3) #B6BCC4, иначе знак сливается: контраст 1,14 против 1,77.
A65: • Зелёный ромб всегда var(--c-g-500), контраст к обоим фонам достаточный.
A67: ЗНАЧКИ В ТЕКСТЕ
A68: • В текстовых блоках используем системные эмодзи: ⚠️ «важно», ☝️ «внимание».
A69: • Векторный треугольник остаётся только в плашках-предупреждениях (классы .iwt, .scwarn).
A70: • Эмодзи ставим в <span class="wic">, размер 17px, ширина колонки 22px.
A72: ПОДВАЛ — обновлено 06.08.2026
A73: Конструкция | C73: Та же, что в шапке: надпись СЛЕВА, знак СПРАВА
A74: Знак | C74: 46 px (в шапке 62 px)
A75: «счётикс» | C75: 14 px, --c-ink, letter-spacing .11em (в шапке 19 px)
A76: «твоя юнит-экономика» | C76: 6,6 px, растянута через space-between (в шапке 9 px)
A77: Серые ромбы | C77: --c-gr3, не --c-ln: на сером фоне контраст 1,77 против 1,14
A78: Зелёный ромб | C78: правый, x=19.81 — как везде

Sheet 09e_Как_считается
A1: 09e · КАК СЧИТАЕТСЯ СТОИМОСТЬ ЧАСА СЪЁМКИ
A2: Полная цепочка расчёта по шагам — ровно так, как считает калькулятор. Все ID в колонке «Формула» ссылаются на лист calc. Цифры в колонке «Результат» — для демо-набора (доход 110 216 ₽/мес, съёмка 1 ч, обработка ×3).
A4: № | B4: Что считаем | C4: Как считаем — словами | D4: Формула (ID) | E4: Результат
A5: 1 | B5: Рабочие дни за вычетом отпуска и больничного | C5: Берём производственный календарь — 247 рабочих дней. Вычитаем отпуск 20 рабочих дней (28 календарных по ТК РФ) и больничный 8 рабочих дней (10 календарных). Столько дней вы действительно на работе. | D5: net_days = work_days − vacation_work − sick_work | E5: 247 − 20 − 8 = 219 дней
A6: 2 | B6: Чистое рабочее время в часах | C6: Номинальный день 8 часов, но продуктивных из них 7. Восьмой час уходит на подготовку и уборку рабочего места, зарядку и проверку техники, разминку и паузы — он размазан по всему дню и в проектное время не попадает. | D6: net_time = net_days × eff_hours | E6: 219 × 7 = 1 533 часа
A7: 3 | B7: Вычитаем операционное время | C7: Продвижение — 2 часа в день: съёмка контента, монтаж рилсов, тексты постов, ответы в директ, настройка рекламы. Учёт и отчётность — 3 часа в квартал. Это работа, но она не привязана к конкретному заказу. | D7: side_time = promo_time + accounting_time pool_gross = net_time − side_time | E7: продвижение 438 ч учёт 12 ч 1533 − 450 = 1 083 часа
A8: 4 | B8: Откладываем резерв времени на простой и форс-мажоры | C8: 5% времени уходит на периоды без заказов, переносы, отмены, повторные выезды по вине клиента. Это время вы тратите, но денег за него не получаете, поэтому убираем его из фонда, доступного под заказы. | D8: fm_time = pool_gross × fm_pct project_pool = pool_gross − fm_time | E8: по умолчанию выключен 1083 − 0 = 1 083 часа
A9: 5 | B9: Считаем, сколько часов съедает один заказ | C9: Пользователь задаёт три величины: типовая длительность съёмки (1 ч), сколько часов обработки приходится на час съёмки (3), сколько времени уходит на переписку и согласование одного заказа (1 ч). Полный цикл заказа складывается из них. | D9: project_time = shoot_duration × (1 + post_ratio) + client_time | E9: 1 × (1+3) + 1 = 5 часов
A10: 6 | B10: Сколько заказов помещается в год | C10: Делим доступное проектное время на длительность одного заказа. Дробное число — это нормально: часть заказа переходит на следующий период. | D10: projects_year = project_pool / project_time | E10: 1083 / 5 = 216,6 заказа
A11: 7 | B11: Сколько из них — ОПЛАЧИВАЕМЫЕ часы съёмки | C11: КЛЮЧЕВОЙ ШАГ. Клиент покупает только часы на площадке. Обработка, переписка, продвижение и неэффективное время в его счёт не попадают. Из 1 752 часов вашей работы в году продаётся только 229 — это 13%. | D11: shooting_time = projects_year × shoot_duration | E11: 216,6 × 1 = 216,6 часа
A12: 8 | B12: Сколько денег нужно собрать за год | C12: Складываем желаемый доход на руки и все расходы бизнеса: амортизацию техники, офиса, ПО, обучения и сайта плюс переменные — рекламу, подписки, аренду, банк. | D12: target_income = income_month × 12 total_costs = investment + variable_costs | E12: 1 322 592 ₽ доход 562 668 ₽ расходы
A13: 9 | B13: Раскручиваем выручку назад через налоги | C13: Здесь нельзя просто сложить доход и расходы. С выручки ещё уйдёт налог по вашему режиму и комиссия банка за приём платежей. Поэтому мы ДЕЛИМ нужную сумму на оставшуюся долю — так получается выручка, из которой после всех вычетов останется ровно желаемый доход. | D13: R = (target_income + total_costs) / (1 − acquiring − rate_current) | E13: (1 322 592 + 562 668) / (1 − 0,027 − 0,05) = 2 042 535 ₽
A14: 10 | B14: Делим выручку на оплачиваемые часы | C14: Вся годовая выручка должна собраться с тех самых 216,6 съёмочных часов, потому что больше клиент ничего не покупает. Это и есть ставка часа. | D14: СТАВКА = R / shooting_time | E14: 2 042 535 / 216,6 = 9 430 ₽/час
A16: ПРОВЕРКА — сходится ли
B17: Выручка минус всё | C17: 2 042 535 − 562 668 расходов − 55 148 эквайринга − 102 127 налога | D17: '= 1 322 592 ₽ | E17: совпало с желаемым доходом
B18: Легенда блока 01 | C18: сумма всех 15 строк | D18: '= 9 430 ₽ | E18: совпало со ставкой часа
B19: Шапка отчёта | C19: 110 216 доход + 46 889 расходы | D19: '= 170 211 ₽ | E19: совпало с выручкой в месяц
A21: ДВЕ РАЗНЫЕ СТАВКИ — не путать
B22: Ставка за час съёмки | C22: Цена в прайсе. Её платит клиент за час вашего присутствия на площадке. | D22: R / shooting_time | E22: 9 430 ₽
B23: Доход в час на руки | C23: Сколько вы реально получаете за час ЛЮБОЙ работы — с камерой или за компьютером. Из годового дохода выключен отпускной месяц: отпускные — дополнительная оплата, не плата за рабочий месяц | D23: '=(target_income*11/12)/(net_days*8) | E23: 692 ₽
B24: Разница в 13,6 раза возникает по двум причинам сразу: оплачивается только 13% рабочего времени (229 часов съёмки из 1 752), и ещё 40% выручки уходит на расходы и налоги.

Sheet 09g_Сокращения
A1: 09g · СОКРАЩЕНИЯ — единый стандарт для книги, calc.html и report.html
A2: Правило: составные единицы пишем через слэш, без пробелов вокруг. Между числом и единицей — неразрывный пробел. Знак ₽ после числа.
A4: ЕДИНИЦЫ ИЗМЕРЕНИЯ
A5: Смысл | B5: ПИШЕМ ТАК | C5: НЕ пишем | D5: Пример | E5: Где применяется
A6: Деньги за час | B6: ₽/ч | C6: ₽ в час · ₽/час · руб/ч | D6: 747 ₽/ч | E6: ставка, легенда, итог
A7: Деньги в месяц | B7: ₽/мес | C7: ₽ в месяц · ₽ в мес | D7: 71 375 ₽/мес | E7: расходы, формы
A8: Деньги в год | B8: ₽/год | C8: ₽ в год | D8: 856 500 ₽/год | E8: расходы, группы затрат
A9: Деньги за проект | B9: ₽/проект | C9: ₽ за проект | D9: 18 934 ₽/проект | E9: сценарии
A10: Часы в год | B10: ч/год | C10: часов в год · ч в год | D10: 228,6 ч/год | E10: легенда, время
A11: Часы в неделю | B11: ч/нед | C11: часов в неделю | D11: 5,2 ч/нед | E11: неделя, группы
A12: Часы в день | B12: ч/день | C12: часов в день | D12: 8 ч/день | E12: условия труда
A13: Часы (просто) | B13: ч | C13: часа · часов | D13: 7,7 ч | E13: итог под кольцом
A14: Дни в году | B14: дн/год | C14: дней в году | D14: 219 дн/год | E14: условия труда
A15: Проценты | B15: % | C15: процентов | D15: 2,8 % | E15: налоги, эквайринг
A16: Штуки | B16: шт | C16: штук | D16: 80 шт | E16: кадры
A18: ЧИСЛА И ЗНАКИ
A19: Что | B19: ПИШЕМ ТАК | C19: НЕ пишем | D19: Пример | E19: Примечание
A20: Разряды | B20: пробел | C20: запятая · точка | D20: 2 042 535 | E20: неразрывный пробел
A21: Дробная часть | B21: запятая | C21: точка | D21: 7,7 · 228,6 | E21: одна цифра после запятой
A22: Рубли в тексте | B22: ₽ | C22: руб. · р. · rub | D22: 9 467 ₽ | E22: знак после числа
A23: Тире между словами | B23: — | C23: - · – | D23: Как фотограф — съёмка | E23: длинное тире с пробелами
A24: Диапазон | B24: – | C24: - · — | D24: 5–7 ч | E24: короткое тире без пробелов
A25: Округление | B25: до рубля | C25: до сотен | D25: 9 467 ₽ | E25: кроме крупной цифры в шапке
A26: ПОДПИСИ МЕТРИК
A27: Что
A28: Сумма за период | B28: Налоги и взносы / год | C28: Налоги и взносы за год
A29: Сумма в месяц | B29: Налоги и взносы / мес | C29: В месяц государству
A30: Количество за период | B30: Проектов / год · Съёмок / мес | C30: Проектов в год · Съёмок в месяц
A31: Выручка | B31: Расчётная выручка / год | C31: Ваша расчётная выручка
A32: Где НЕ применяем | B32: в связном тексте: «платятся даже в месяцы без заказов»
A34: Правило одно на все три файла. Появилась новая единица — сначала строка здесь, потом в вёрстку.

Sheet 09h_Элементы
A1: 09h · ПОВТОРЯЮЩИЕСЯ ЭЛЕМЕНТЫ — единый стиль для всех документов
A2: Одна сущность — один класс. Появился похожий элемент — сначала строка здесь, потом вёрстка. Свои hex запрещены, только токены палитры 09c.
A4: ЗНАЧОК В КРУЖКЕ — общая геометрия
A5: Параметр | B5: Значение | C5: Примечание
A6: диаметр | B6: 18 px | C6: одинаков во всех документах
A7: скругление | B7: 50% | C7: идеальный круг
A8: размер знака | B8: 11 px | C8: font-weight 700
A9: выравнивание | B9: flex, по центру | C9: align-items и justify-content center
A10: отступ до текста | B10: 10 px | C10: padding-left у блока текста
A11: положение | B11: absolute, left 0 | C11: верх выровнен по первой строке
A13: ВИДЫ ЗНАЧКА
A14: Класс | B14: Знак | C14: Кружок | D14: Знак — цвет | E14: Когда применяем
A15: .ic.warn | B15: ! | C15: --c-a-400 | D15: --c-white | E15: предупреждение: что будет, если не сделать
A16: .ic.info | B16: i | C16: --c-b-400 | D16: --c-white | E16: важное пояснение, без тревоги
A17: .ic.ok | B17: ✓ | C17: --c-g-500 | D17: --c-white | E17: подтверждение, лучший вариант
A18: .ic.tip | B18: ? | C18: --c-ln | D18: --c-gr | E18: подсказка при наведении, у поля ввода
A20: БЛОКИ-ПРИМЕЧАНИЯ
A21: Класс | B21: Размер | C21: Цвет текста | D21: Фон и рамка | E21: Когда применяем
A22: .note | B22: 13 px | C22: --c-gr | D22: нет | E22: нейтральное пояснение под блоком
A23: .note.sm | B23: 12 px | C23: --c-gr2 | D23: нет | E23: мелкая сноска под строкой
A24: .note.warn | B24: 13 px | C24: --c-a-800 | D24: фон --c-a-50, рамка 1px dashed --c-a-300 | E24: предупреждение о последствиях
A25: .note.info | B25: 13 px | C25: --c-b-800 | D25: фон --c-b-50, рамка 1px solid --c-b-200 | E25: важное пояснение
A26: .note.ok | B26: 13 px | C26: --c-g-800 | D26: фон --c-g-50, рамка 1px solid --c-g-200 | E26: подтверждение, всё верно
A27: .note.plain | B27: 13 px | C27: --c-gr | D27: фон --c-surf, без рамки | E27: длинная методическая сноска
A29: ЧТО ЗАМЕНЯЕТ — старые классы, переводим постепенно
A30: Старый класс | B30: Было | C30: Станет | D30: Блок | E30: Статус
A31: .lgwarn | B31: 13 px, кружок 14 px --c-a-400 | C31: .note.warn | D31: 01 | E31: переведён
A32: .lognote | B32: 13 px, кружок 20 px --c-a-200 | C32: .note.warn | D32: 09 | E32: ждёт
A33: .lgnote | B33: 12,5 px --c-gr2 | C33: .note | D33: 01 | E33: переведён
A34: .lgsub | B34: 12,5 px --c-gr2 | C34: .note.sm | D34: 01 | E34: переведён
A35: .recbm | B35: 12,5 px --c-gr | C35: .note | D35: cardRec | E35: ждёт
A36: .dnote2 | B36: 12,5 px --c-gr2 | C36: .note.sm | D36: — | E36: ждёт
A37: .dnote3 | B37: 13 px --c-gr, фон --c-surf | C37: .note.plain | D37: — | E37: ждёт
A38: .wknote | B38: 14,5 px --c-ink2, фон #fff | C38: рамка 1.5px, радиус --r, градиент, левое поле 65px | D38: 02 | E38: Блок 02. Текст начинается там же, где плашки дней: 58px (колонка часов) + 7px (зазор сетки) = 65px. Отступ карточки прибавлять НЕ нужно — плашка уже внутри неё. Знак «Счётикс»: 150px, left −58px, top −58px, прозрачность 6%, уходит в левый верхний угол под градиент, текст не перекрывает. Знак рисуется в JS вместе с текстом — innerHTML затирает разметку
A39: .tip (calc) | B39: кружок 17 px | C39: .ic.tip | D39: анкета | E39: ждёт
A41: ПРАВИЛО ПЕРЕВОДА: старые классы не трогаем скопом. Блок переводится на новую систему тогда, когда мы этот блок и так правим. Когда все переведены — старые правила удаляются одной операцией со сверкой «пропавшие селекторы = только удаляемые».
A43: .saletag | B43: Стикер «Скидка» | C43: абсолют, по центру над блоком | D43: --c-r-500, белый текст | E43: Блок 03. Отступ карточки сверху 48 px — втрое больше обычного. Плашка: left 50%, top −28 px, translateX(−50%), без наклона. Выходит за верхнюю границу, до предыдущего блока остаётся 20 px. Карточке нужен overflow:visible. Заголовок и описание по центру
A45: .cn.s1/.s2/.s3 | B45: Плашка со статистикой | C45: форма из .cn | D45: лайм · мандарин · малина | E45: Блок 08. Та же геометрия, что «Условия труда»: радиус --r, padding 28/26, min-height 210, круг-блик в углу. Отличаются только градиентом
A47: ПОВЕДЕНИЕ КНОПОК — единое во всех документах
A48: Состояние | B48: Что происходит | C48: Как задано | E48: Правило
A49: обычное | B49: — | C49: — | E49: базовый вид кнопки
A50: :hover | B50: фон темнеет на ступень | C50: background --c-g-50 / --gd, либо filter brightness(.94) | E50: только цвет, размер и положение не меняются
A51: :active | B51: слегка утапливается | C51: translateY(1px) + фон ещё темнее | E51: ощущение нажатия, сдвиг ровно 1 px
A52: запрещено | B52: подпрыгивание, разлетающаяся тень, вращение | C52: translateY(-2px), scale, rotate | E52: никаких сложных анимаций на кнопках
A54: Исключение: сердечко в опросе анкеты — не кнопка действия, а реакция. Допустимо scale(1.06), не больше.
A56: КОММЕНТАРИЙ-ФЛАЖОК — вместо полоски слева
A57: .ex | B57: комментарий в карточке | C57: рамка 1.5px, радиус --r, радиальный градиент сверху | E57: то же устройство, что у плашки дохода .dnsum. Цвета: --exb рамка, --exg подложка
A58: .wknote | B58: комментарий под календарём | C58: рамка 1.5px, радиус --r, градиент, левое поле 65px | E58: Блок 02. Текст начинается там же, где плашки дней: 58px (колонка часов) + 7px (зазор сетки) = 65px. Отступ карточки прибавлять НЕ нужно — плашка уже внутри неё. Знак «Счётикс»: 150px, left −58px, top −58px, прозрачность 6%, уходит в левый верхний угол под градиент, текст не перекрывает. Знак рисуется в JS вместе с текстом — innerHTML затирает разметку
A59: --exb / --exg | B59: цвет рамки и подложки | C59: инлайн: style="--exb:var(--c-v-300);--exg:var(--c-v-50)" | E59: по умолчанию --c-g-200 и --c-g-50
A61: Пояснительные плашки в блоках 02 и 03 оформлены так же, как «Ваш доход на руки»: лёгкая рамка 1,5 px, радиус --r и мягкий радиальный градиент от верхнего края. Полосок-флажков и явных границ слева больше нет.
A63: БЛОК 07 «ЧЕТЫРЕ ЦИФРЫ» — сетка изменена 07.08.2026
A64: Было | B64: Крест 3×3: плашка сверху, справа, снизу, слева, знак «Счётикс» в середине. На широком экране по бокам оставалось много пустого поля.
A65: Стало | B65: Сетка 2×2 на всех ширинах — та же раскладка, что раньше была только на узком экране. Знак из середины убран (.fgmk и FGMK удалены).
A67: БЛОК 05 — ДОРАБОТКА 07.08.2026
A68: .scn3 тени | B68: box-shadow 0 10px 26px rgba(16,24,40,.09) + 0 2px 6px; на наведении глубже и подъём на 2px
A69: .scdeco | B69: Фоновый круг в правом верхнем углу — тот же приём, что .cn:before и .npd .g div:before: сплошной круг 130px, right/top -30px. Отдельный слой с overflow:hidden внутри .scn3, сам .scn3 обрезать нельзя (метка .nm3 выше края).
A70: .mbsc | B70: Схема безубыточности: две чаши весов «Пришло от клиентов» = «Ушло на работу», между ними знак =. Зелёная и янтарная подложки. | H70: ОТКАЧЕНО 07.08.2026: плашка возвращена к прежнему виду
A71: .mbres | B71: Итог схемы — янтарная плашка с кругом «0»: себе ничего не осталось. | H71: ОТКАЧЕНО 07.08.2026: плашка возвращена к прежнему виду
A72: .minb .t | B72: Заголовок врезки поднят до 21px со знаком равенства в квадрате слева — это ключевая мысль, а не строка текста. | H72: ОТКАЧЕНО 07.08.2026: заголовок вернулся к 16px без знака
A74: УВЕДОМЛЕНИЯ — ЕДИНЫЙ ВИД, 07.08.2026
A75: Эталон | B75: .note.warn — жёлтая подложка --c-a-50, пунктирная рамка --c-a-300, круг --c-a-400 со знаком «!», текст --c-a-800. Так оформлены уведомления блока 01.
A76: Блок 05 «Логистика» | B76: был .lognote — серая подложка --c-surf со сплошным кругом. Переведён на .note.warn, класс .lognote удалён из CSS.
A77: Блок 06 «Выгорание» | B77: был .note.warn.lg — та же гамма, но шрифт 17px и padding 24/28/56. Переведён на обычный .note.warn.
A78: Многоабзацные | B78: .note.warn p{margin:0} + p+p{margin-top:10px} — раньше отступы давал только .lg
A80: УВЕДОМЛЕНИЯ — ЕДИНАЯ ТИПОГРАФИКА, 07.08.2026
A81: Причина разнобоя | B81: Правило #phr-root .note{font-size:12.5px;text-align:center;line-height:1.5} стояло ниже по файлу и перебивало базовое .note{13px;1.6}. Уведомления .warn/.info/.ok получали чужой кегль, центровку и межстрочный — отсюда разные отступы и интерлиньяж между блоками.
A82: Решение | B82: Позднее правило сужено до :not(.warn):not(.info):not(.ok):not(.plain) — оно нужно только мелким сноскам (источники, подписи). Уведомлениям задана своя типографика: 13px / 1.6 / по левому краю.
A83: Абзацы внутри | B83: p{margin:0;font-size:inherit;line-height:inherit}, между абзацами 8px. Раньше абзацы наследовали разные размеры.
A84: Вывод последней строкой | B84: p:last-child:not(:only-child){text-align:right;font-weight:600} — только если абзацев больше одного.
A85: Блок 06 — тип уведомления | B85: Жёлтое .note.warn заменено на синее .note.info — точная копия уведомления из блока 08. Оформление, цвета и знак «i» не менялись, только текст.
A87: ПРОВЕРКА ВЁРСТКИ — новый скрипт, 08.08.2026
A88: Где | B88: _архив/скрипты/проверка_вёрстки.py · встроен в собрать.py, запускается после сборки
A89: Запуск отдельно | B89: python3 проверка_вёрстки.py файл.html [--было прежний.html] — работает на любом HTML, включая макеты в «части»
A90: 1. Скобки | B90: баланс {} в CSS и открытых/закрытых тегов, с номером строки
A91: 2. Переменные | B91: используются, но не объявлены. Не считает ошибкой var(--x,запасное), инлайн в style="" и setProperty из JS
A92: 3. Медиазапросы | B92: незакрытый @media проглатывает весь CSS ниже — правила есть, но не работают. Плюс сигнал, если @media охватывает больше 40 правил
A93: 4. Дубли селекторов | B93: два правила с одним селектором и общим свойством: нижнее молча перебивает верхнее. Так .note{text-align:center} перебивал .note.warn
A94: 5. Сверка с прежней | B94: что пропало, что добавилось и у каких свойств изменились значения. Показывает, что правка задела соседние элементы
A95: Зачем | B95: Ловит класс ошибок «поехала разметка после правки»: потерянные отступы, сбитое оформление, случайно задетые блоки
A97: НУМЕРАЦИЯ СПРАВОЧНИКА И ССЫЛКИ, 10.08.2026
A98: Справочник | B98: Каждый термин пронумерован: кружок 26 px слева, номер 01–26 по порядку. Якорь ref0..ref25 — по индексу, не по названию (имена кириллические).
A99: Ссылка из блока | B99: .refl — ОБЫЧНАЯ ТЕКСТОВАЯ ссылка «Подробнее в п. 7 Справочника»: синий цвет, тонкое подчёркивание. Никаких плашек, рамок и фона — внутри текста они не нужны. Номер без ведущего нуля. Один вид на весь отчёт.
A100: Подсветка перехода | B100: Через :target. У целевого пункта голубой фон, номер заливается синим градиентом, термин синеет. Работает без скрипта, ничего не сбрасывает.
A101: Блок 01 | B101: 13 строк легенды связаны с терминами массивом REFLB. Съёмка → 22, Обработка → 07, Работа с клиентом → 15, Продвижение → 13, Учёт → 24, Форс-мажоры → 25, Оборудование → 23, Реклама → 13, Текущие счета → 18, Налоги → 06, Эквайринг → 26, Фонд и Запас → 05. Битых ссылок нет.
A102: Порядок объявления | B102: REFD и PHR_REF вынесены выше отрисовки блоков: легенда блока 01 строится раньше справочника и без этого ссылок не получала.
A104: ВТОРОЙ ЭКРАН И КНОПКИ БЛАГОДАРНОСТИ, 10.08.2026
A105: Экран 2 — рабочий месяц | B105: Всё переведено в месяц: год человек не чувствует, месяц планирует. Один заголовок «Ваш рабочий месяц» и три рамки: съёмок в месяц, часов на работу с заказом (обработка + клиент), продвижение и прочее. Рамки прозрачные, только контур. Проверка: 18+72+56=146 ч = всё рабочее время за месяц.
A106: Гамма и фон | B106: Морская волна #176B77 → #58B1B9 — взята из карточки «Ставка в ноль» блока «Четыре цифры» (.fct.b). Ближе к зелёному, чем прежний синий. Фоновый рисунок — часы вместо фотоаппарата, прозрачность 13%.
A107: Кнопка благодарности | B107: .thxb — форма от .savebtn (ширина 100%, высота 72px, кегль 17px, радиус, отступы 0/30, зазор 11px), оформление от плашек блока 08 (.cn.s1..s3): инста-градиент заливкой --c-ig-1 → --c-ig-2 → --c-ig-4, белый текст и сердце, круг-блик :before в углу, тень. Рамки нет. При наведении яркость +6%. Мест три: под кнопкой PDF, между блоками 04 и 05, баннер перед справочником. Из шапки убрана 10.08.2026.
A108: Баннер | B108: .cta.thx — тот же приём, что «30 сценариев», гамма тёплая (--c-a-700 → --c-a-500), декор-сердце вместо стопки карточек.
A109: THANKS_URL | B109: Адрес задаётся одной переменной в скрипте отчёта, подставляется во все кнопки разом. Сейчас заглушка #thanks. Если адрес внешний — ссылки автоматически открываются в новой вкладке.
A110: собрать.py | B110: Ожидаемое число прямых детей .wp: 19 → 22 (добавились две плашки с кнопками и баннер).
A112: ССЫЛКИ И КНОПКИ — единый вид, 10.08.2026
A113: Ссылка на справочник | B113: .refl — цветом НЕ выделяется: color:inherit, font:inherit. Наследует кегль, начертание и цвет того описания, вместо которого стоит. Обозначена только подчёркиванием currentColor. Текст короткий: «п. 22 Справочника», без «Подробнее в».
A114: Ссылки в памятке | B114: Блок 04 и другие .pmknote: было своё оформление (цвет --c-fns-2, полужирный) — приведено к тому же правилу, что .refl.
A115: Кнопки и баннер | B115: Единая гамма: инста-градиент --c-ig-1 → --c-ig-2 → --c-ig-4. Баннер был тёплый (--c-a-700), переведён в ту же гамму. Декор везде одинаковый: круг-блик плюс сердечки. На кнопках два сердца (.thxd справа 56px, .thxd2 слева 34px), на баннере два круга и два сердца.
A117: БАННЕР «30 СЦЕНАРИЕВ» ВЫНЕСЕН, 10.08.2026
A118: Куда | B118: части/09_баннер_сценарии.html — полноценная страница, дизайн сохранён без изменений. В собрать.py 22 → 21 блока.
A119: Важно | B119: Стили .cta ОСТАЛИСЬ в каркасе: их наследует баннер благодарности .cta.thx. Вынесена только разметка. При первой попытке я скопировала правила в каркас поверх существующих — получились дубли, убраны.
A120: Пояснение под кнопкой | B120: .thxn — абзац под кнопкой «Поблагодарить проект» (той, что под сохранением в PDF). Лежит ВНУТРИ .thxbar, иначе становится прямым ребёнком .wp и ломает проверку структуры. Ширина 720px, кегль 13, по центру, цвет --c-gr.
...

Sheet 10_Монетизация
A1: 10 · МОНЕТИЗАЦИЯ — цены, комиссии, партнёрская программа
A2: Тестовый этап: задача не заработать, а проверить готовность платить. Жёлтое — редактируется.
A4: ЦЕНЫ
A5: Параметр | B5: Значение | C5: Ед. | F5: Комментарий
A6: Базовая цена скачивания | B6: 490 | C6: ₽ | F6: Без реферальной ссылки. Ориентир по рынку микропродуктов
A7: Цена по реферальной ссылке | B7: 169 | C7: ₽ | F7: Тестовая. Целевая аудитория — самозанятые с низким доходом
A8: Зачёркнутая цена в блоке | B8: 560 | C8: ₽ | F8: Якорь. Показывается рядом с реферальной
A9: Модель | B9: за скачивание | F9: Не подписка и не доступ. Каждый отчёт оплачивается отдельно
A10: Цель по скачиваниям | B10: 10000 | C10: шт | F10: Порог, после которого продукт считается подтверждённым
A12: ПРОГНОЗ ОБОРОТА
A13: Сценарий | B13: Скачиваний | C13: Цена | D13: Оборот | E13: Доля | F13: Комментарий
A14: По реферальной ссылке | B14: 8500 | C14: 169 | D14: =B14*C14 -> 1436500 | E14: 85% | F14: Основной канал: партнёры, соцсети
A15: Прямые заходы | B15: 1500 | C15: 490 | D15: =B15*C15 -> 735000 | E15: 15% | F15: Поиск, прямые ссылки
A16: ИТОГО | B16: =B14+B15 -> 10000 | D16: =D14+D15 -> 2171500 | E16: 100%
A18: КОМИССИИ ПЛАТЁЖНЫХ СИСТЕМ 2026
A19: Способ оплаты | B19: Ставка | C19: НДС 22% | D19: Итого с оборота | E19: Остаётся | F19: Комментарий
A20: СБП, льготный тариф | B20: 0.004 | C20: нет | D20: =$D$16*B20 -> 8686 | E20: =$D$16-D20 -> 2162814 | F20: 0,4% — для отдельных категорий, не более 1 500 ₽ за операцию
A21: СБП, обычный тариф | B21: 0.007 | C21: нет | D21: =$D$16*B21 -> 15200.5 | E21: =$D$16-D21 -> 2156299.5 | F21: 0,7% — большинство отраслей. НДС не начисляется
A22: Карты, интернет-эквайринг | B22: 0.028 | C22: да | D22: =$D$16*B22*1.22 -> 74178.44 | E22: =$D$16-D22 -> 2097321.6 | F22: С 2026 к комиссии добавляется НДС 22%
A23: Смешанный: 70% СБП + 30% карты | D23: =$D$16*0.7*B21+$D$16*0.3*B22*1.22 -> 32893.882 | E23: =$D$16-D23 -> 2138606.1 | F23: Реалистичный сценарий. Ставьте СБП первым способом
A24: Экономия СБП против карт | D24: =D22-D21 -> 58977.94 | F24: Разница только на комиссиях
A26: ПЛАТЁЖНЫЕ СИСТЕМЫ — ЧТО ВЫБРАТЬ ДЛЯ ООО
A27: Сервис | B27: Карты | C27: СБП | D27: Онлайн-касса | E27: Tilda | F27: Комментарий
A28: ЮKassa | B28: от 2,8% | C28: 0,4–0,7% | D28: отдельно | E28: готовый модуль | F28: Уже подключена. Касса нужна отдельно или через партнёра
A29: Т-Банк | B29: от 2,46% | C29: 0,4–0,7% | D29: встроенная | E29: через универсальный | F29: Ниже ставка, быстрое подключение. РКО только для СБП
A30: Продамус | B30: до 3,5% | C30: есть | D30: встроенная | E30: готовый модуль | F30: Проще всего, но дороже по картам
A31: Робокасса | B31: от 2,7% | C31: есть | D31: встроенная | E31: готовый модуль | F31: 40+ способов оплаты
A32: РЕКОМЕНДАЦИЯ | F32: Оставить ЮKassa, включить СБП основным способом. При росте оборота сравнить с Т-Банком
A34: ОКВЭД И НАЗНАЧЕНИЕ ПЛАТЕЖА
A35: Код | B35: Название | C35: Подходит | F35: Комментарий
A36: 62.01 | B36: Разработка компьютерного программного обеспечения | C36: ДА | F36: Основной. Именно его добавить, чтобы платежи шли как IT
A37: 62.02 | B37: Консультативная деятельность в области ИТ | C37: да | F37: Дополнительный, если будут консультации
A38: 63.11 | B38: Деятельность по обработке данных | C38: да | F38: Дополнительный, для облачных сервисов
A39: Назначение платежа | B39: Предоставление права использования ПО (расчётный сервис) | F39: Формулировка для чека и договора-оферты
A40: Предмет продажи | B40: Электронный отчёт, формируемый программой | F40: Не «услуга» и не «консультация» — именно результат работы ПО
A42: ПАРТНЁРСКАЯ ПРОГРАММА
A43: Параметр | B43: Значение | C43: Ед. | F43: Комментарий
A44: Вознаграждение партнёру | B44: 0.3 | C44: % | F44: От суммы каждой оплаты по его ссылке
A45: Выплата с одной продажи | B45: =B44*B7 -> 50.7 | C45: ₽ | F45: При реферальной цене
A46: Остаётся проекту | B46: =B7-B45 -> 118.3 | C46: ₽ | F46: До вычета комиссии эквайринга
A47: Минимальная сумма выплаты | B47: 3000 | C47: ₽ | F47: Накопительно, чтобы не гонять мелкие переводы
A48: Период выплат | B48: раз в месяц | F48: До 10 числа за предыдущий месяц
A49: Срок жизни метки | B49: 30 | C49: дней | F49: Сколько помнить источник перехода в браузере

Sheet 11_Ссылки
A1: 11 · ССЫЛКИ И МЕТКИ — реферальные адреса и учёт переходов
A2: Домен подставьте в ячейку B4 — все ссылки соберутся автоматически.
A4: Домен сайта | B4: vashsite.ru | C4: без https:// и без слэша в конце
A5: Страница калькулятора | B5: /photo-unit | C5: юнит-экономика фотографа. Варианты: /hour, /chas, /calc
A7: РЕФЕРАЛЬНЫЕ ССЫЛКИ
A8: Партнёр / канал | B8: Метка ref | C8: Готовая ссылка | D8: Цена | E8: Что отслеживаем
A9: Telegram-канал | B9: tg | C9: ="https://"&$B$4&$B$5&"?ref="&B9&"&utm_source=telegram&utm_medium=referral&utm_campaign=calc" -> https://vashsite.ru/photo-unit?ref=tg&utm_source=telegram&utm_medium=referral&utm_campaign=calc | D9: 169 ₽ | E9: переходы, время, клик по кнопке
A10: ВКонтакте | B10: vk | C10: ="https://"&$B$4&$B$5&"?ref="&B10&"&utm_source=vk&utm_medium=referral&utm_campaign=calc" -> https://vashsite.ru/photo-unit?ref=vk&utm_source=vk&utm_medium=referral&utm_campaign=calc | D10: 169 ₽ | E10: переходы, время, клик по кнопке
A11: Instagram / блог | B11: ig | C11: ="https://"&$B$4&$B$5&"?ref="&B11&"&utm_source=instagram&utm_medium=referral&utm_campaign=calc" -> https://vashsite.ru/photo-unit?ref=ig&utm_source=instagram&utm_medium=referral&utm_campaign=calc | D11: 169 ₽ | E11: переходы, время, клик по кнопке
A12: Партнёр №1 | B12: p1 | C12: ="https://"&$B$4&$B$5&"?ref="&B12&"&utm_source=partner&utm_medium=referral&utm_campaign=calc" -> https://vashsite.ru/photo-unit?ref=p1&utm_source=partner&utm_medium=referral&utm_campaign=calc | D12: 169 ₽ | E12: переходы, время, клик по кнопке
A13: Партнёр №2 | B13: p2 | C13: ="https://"&$B$4&$B$5&"?ref="&B13&"&utm_source=partner&utm_medium=referral&utm_campaign=calc" -> https://vashsite.ru/photo-unit?ref=p2&utm_source=partner&utm_medium=referral&utm_campaign=calc | D13: 169 ₽ | E13: переходы, время, клик по кнопке
A14: Рассылка | B14: mail | C14: ="https://"&$B$4&$B$5&"?ref="&B14&"&utm_source=email&utm_medium=referral&utm_campaign=calc" -> https://vashsite.ru/photo-unit?ref=mail&utm_source=email&utm_medium=referral&utm_campaign=calc | D14: 169 ₽ | E14: переходы, время, клик по кнопке
A15: Прямой заход | B15: — | C15: ="https://"&$B$4&$B$5 -> https://vashsite.ru/photo-unit | D15: 490 ₽ | E15: переходы, время, клик по кнопке
A17: КАК ЭТО РАБОТАЕТ
A18: Калькулятор проверяет параметры ref, utm_source или from в адресе страницы.
A19: Если хоть один есть — показывает цену 169 ₽ и зачёркнутые 560 ₽. Если нет — 490 ₽.
A21: УЧЁТ ПЕРЕХОДОВ. Отдельный сервис сокращения не нужен: Яндекс.Метрика считает UTM сама.
A22: Отчёт «Источники → Метки UTM» покажет переходы, время на странице и достижение целей.
A24: КОРОТКАЯ ССЫЛКА для соцсетей: сделайте в Tilda страницу-редирект /tg,
A25: которая перенаправляет на полный адрес с метками. Так и учёт сохранится, и ссылка читаемая.
A27: ЦЕЛИ В МЕТРИКЕ (обязательно настроить):
A28: calc_done — нажал «Рассчитать стоимость часа»
A29: buy_click — нажал «Поблагодарить и скачать отчёт»
A30: paid — вернулся на страницу с параметром ?paid=1
A32: Номер счётчика пропишите в HTML: var YM_ID=0; → var YM_ID=ваш_номер;

Sheet 11b_Связка
A1: 11b · СВЯЗКА ФОРМЫ И ОТЧЁТА
A2: calc.html считает → кладёт в localStorage[«phc_report»] → report.html читает. Если ключа нет, отчёт показывает демо-набор.
A4: ПОЛЯ, КОТОРЫЕ ПЕРЕДАЁТ ФОРМА
A5: Поле | B5: Что это | C5: Откуда в форме | D5: Где в отчёте
A6: sh | B6: часы съёмки в год | C6: py × S | D6: знаменатель всех сумм
A7: post | B7: часы обработки | C7: sh × K | D7: легенда, блок 01
A8: clT | B8: часы на клиента | C8: py × cl | D8: легенда
A9: promo | B9: часы продвижения | C9: promo_per_day × ND | D9: легенда
A10: accT | B10: часы учёта | C10: acc_per_quarter × 4 | D10: легенда
A11: fmT, idle | B11: резервы времени | C11: gross × fm_pct, ND×(8−EFF) | D11: легенда
A12: Ny | B12: целевой доход в год | C12: income_month × 12 | D12: база распределения
A13: R | B13: требуемая выручка | C13: (Ny+C)/(1−a−sdiv−fund−disc−ставка) | D13: ставка часа
A14: depShoot | B14: съёмочная техника | C14: Form001 | D14: строка «оборудование и ПО»
A15: depOffice | B15: компьютер | C15: Form002 | D15: строка «оборудование и ПО»
A16: depSoft | B16: плагины разово | C16: Form004 | D16: строка «оборудование и ПО»
... A33: npd_who | B33: заказчики на НПД (mix/phys/jur) | C33: select #npd_who, виден только при НПД | D33: раскрывает НПД в npd4/npd5/npd6 → ставка 4/5/6%
A34: profession
A36: ПРОВЕРКА: сумма всех сегментов диаграммы = R. Расхождение должно быть 0 ₽. Сумма доходных сегментов = Ny.
A37: Запасной путь, если localStorage недоступен: reportLink(d) отдаёт ссылку report.html?data=<base64>. Отчёт читает параметр data первым делом.

Sheet 12_Диаграммы
A1: 12 · ДИАГРАММЫ — состав, группы и подписи
A2: Одна строка = один сегмент диаграммы. Порядок строк = порядок сегментов по кругу. Жёлтое — редактируется, серое — служебное.
A4: Д1 · ОСНОВНАЯ КОЛЬЦЕВАЯ — предварительный отчёт, видна всем
A5: Тип диаграммы | C5: Кольцевая (donut), 11–13 секторов | F5: 260 px, кольцо 58 px, отверстие 47%. Центр — белый диск и внутренняя шайба с мягкой тенью: цифра лежит на подложке, а не висит в пустоте
A6: Где размещена | C6: Блок «Куда уходит каждый час съёмки» | F6: Открыта без оплаты
A7: Что показывает | C7: Разбор одного оплаченного часа съёмки | F7: Все суммы делятся на shooting_time
A8: В центре кольца | C8: Ставка часа + подпись «за час съёмки» | F8: real_rate = R / shooting_time
A9: Строка легенды | C9: Название · сумма · «за N ч» | F9: Отдельного столбца времени нет. Часы — подписью под суммой: «747 ₽ / за 1,0 ч». Часы на ОДИН оплаченный час съёмки, сумма по всем строкам = 7,7 ч
A10: Две плашки | C10: Одинаковые по форме | F10: «Ваш доход на руки» и «Ваши расходы» — одинаковые по вёрстке: обе прямые дети карточки, один набор элементов (знак, заголовок, подводка, сумма, строка снизу). Отличаются только цветом рамки и текстом
A11: Заголовки плашек | C11: 21 px, --c-ink, без заливки | F11: Выделяются размером шрифта, не цветом. Капсул и цветных подложек нет
A12: № | B12: Группа | C12: Код сегмента | D12: Подпись в легенде | E12: Параметр расчёта | F12: Формула / что берём | G12: Цвет | H12: Условие | I12: Комментарий | J12: Предупреждение
A13: 1 | B13: ПО СПЕЦИАЛЬНОСТИ | C13: earn_shoot | D13: Как фотограф — съёмка | E13: shooting_time | F13: hr × shooting_time | G13: #0B6B22 | H13: всегда | I13: Работа по специальности — холодный зелёный, градация от тёмного к светлому
A14: 2 | B14: ПО СПЕЦИАЛЬНОСТИ | C14: earn_post | D14: Как фотограф — обработка | E14: post_time | F14: hr × post_time | G14: #2FA84A | H14: всегда
A15: 3 | B15: ОСТАЛЬНАЯ КОМАНДА | C15: earn_sales | D15: Как отдел продаж — работа с клиентом | E15: client_total | F15: hr × client_total | G15: #5F8A1B | H15: всегда | I15: Работа за остальную команду — тёплый зелёный (салатовый), та же градация
A16: 4 | B16: ОСТАЛЬНАЯ КОМАНДА | C16: earn_promo | D16: Как маркетолог и SMM — продвижение | E16: promo_time | F16: hr × promo_time | G16: #8CB82F | H16: всегда
A17: 5 | B17: ОСТАЛЬНАЯ КОМАНДА | C17: earn_acc | D17: Как бухгалтер — учёт и отчётность | E17: accounting_time | F17: hr × accounting_time | G17: #B9D96F | H17: только если acc_mode = «Веду самостоятельно» | I17: Скрыт, если нанят бухгалтер
A18: 6 | B18: НЕ ОПЛАЧИВАЕТСЯ | C18: earn_idle | D18: Форс-мажоры и простой | E18: fm_time + idle | F18: hr × (fm_time + idle) | G18: #B6BCC4 | H18: всегда | I18: Не оплачивается — серый. idle = 219 ч, час в день на неэффективное время
A19: 7 | B19: ВАШИ РАСХОДЫ | C19: cost_equip | D19: Отложите на оборудование и ПО | E19: equip | F19: dep_shoot + dep_office + dep_software | G19: #EF4444 | H19: всегда | I19: Чтобы обновить технику, когда придёт в негодность
A20: 8 | B20: ВАШИ РАСХОДЫ | C20: cost_promo | D20: Потратите на рекламу и продвижение | E20: promoM | F20: var_ads + dep_website | G20: #F59E0B | H20: всегда | I20: Сайт отнесён сюда, а не в оборудование
A21: 9 | B21: ВАШИ РАСХОДЫ | C21: cost_current | D21: Заплатите по текущим счетам | E21: current | F21: var_workspace + var_bank + var_accounting + var_software + dep_workspace + dep_education | G21: #FB923C | H21: всегда | I21: Аренда, подписки, бухгалтер, обустройство, обучение
A22: 10 | B22: ВАШИ РАСХОДЫ | C22: cost_tax | D22: Заплатите налогов и взносов | E22: taxAll | F22: налог + страховые взносы по выбранному режиму | G22: #8B5CF6 | H22: всегда
A23: 11 | B23: ВАШИ РАСХОДЫ | C23: cost_bank | D23: Отдадите банку за эквайринг | E23: aq | F23: R × acquiring | G23: #3B82F6 | H23: всегда
A24: 12 | B24: ВАШИ РАСХОДЫ | C24: cost_fund | D24: Отложите в фонд развития | E24: fundY | F24: R × fund_pct | G24: #7189AE | H24: всегда, даже при нуле | I24: Галочка «Закладывать фонд развития» в анкете СНЯТА по умолчанию, поле % неактивно. При нуле — предупреждение: «Технику придётся менять из своего кармана или в кредит». Анкета, блок 15 | J24: да
A25: 13 | B25: ВАШИ РАСХОДЫ | C25: cost_disc | D25: Заложите запас на скидку | E25: discY | F25: R × disc_pct | G25: #B7C9E8 | H25: всегда, даже при нуле | I25: Галочка «Закладывать запас на скидку» СНЯТА по умолчанию, поле % неактивно. При нуле — предупреждение: «Любая скидка просто так будет вычтена из вашего дохода». Анкета, блок 15 | J25: да
A27: Д2 · ТРИ КОЛЬЦА СРАВНЕНИЯ — полный отчёт, после оплаты
A28: Тип диаграммы | C28: Три кольцевые рядом (donut × 3) | F28: 190 px каждая, в ряд на десктопе, столбцом на мобильном
A29: Где размещена | C29: Блок «Куда уходит каждый час» | F29: Под размытием до оплаты
A30: Что показывает | C30: Одни и те же сегменты при трёх ставках | F30: Сегменты и цвета совпадают с Д1
A31: Кольцо 1 | C31: Ваша расчётная ставка | F31: Выручка R, доход = target_income
A32: Кольцо 2 | C32: Ваша текущая ставка | F32: Выручка current_rate × shooting_time, доход = leftC
A33: Кольцо 3 | C33: Работа в ноль | F33: Выручка Rb (безубыточность), доход = 0
A34: Единица легенды | C34: Рубли и проценты
A36: № | B36: Группа | C36: Код сегмента | D36: Подпись в легенде | E36: Параметр расчёта | F36: Формула / что берём | G36: Цвет | H36: Условие | I36: Комментарий
A37: 1–11 | B37: те же | C37: см. Д1 | D37: Состав полностью совпадает с Д1 | E37: parts(d) | F37: Для кольца 2 доходные сегменты × коэффициент leftC / target_income | G37: — | H37: всегда | I37: Для кольца 3 все доходные сегменты = 0
A39: Д3 · СЕТКА НЕДЕЛИ — блок 02. Обновлено 06.08.2026: расшифровка убрана, добавлена легенда цветов под сеткой
A40: Тип диаграммы | C40: Тепловая сетка (heatmap) 5 × 9 | F40: 5 рабочих дней, часы с 10:00 до 19:00
A41: Где размещена | C41: Блок «Ваша неделя» | F41: Под размытием до оплаты
A42: Что показывает | C42: Как распределяется рабочий день по видам работ | F42: Часы в неделю ÷ 5 дней
A43: Обед | C43: Один час в 14:00, серый | F43: Не входит в рабочее время
A44: Легенда цветов | C44: Под сеткой, класс .slg | F44: Съёмка · Обработка · Продвижение · Работа с клиентом · Учёт · Неэффективное рабочее время · Резерв времени (штриховка, только если > 0)
A45: Комментарий | C45: Один, крупным шрифтом | F45: «За неделю у вас одна съёмка на N ч… Получается всего N часа с камерой в руках, а остальное время — это та самая невидимая, но огромная работа за кадром, без которой ни одна съёмка просто не состоится»
A46: № | B46: Группа | C46: Код сегмента | D46: Подпись в легенде | E46: Параметр расчёта | F46: Формула / что берём | G46: Цвет | H46: Условие | I46: Комментарий
A47: 1 | B47: ВРЕМЯ | C47: wk_shoot | D47: Съёмка | E47: shooting_time | F47: shooting_time / net_weeks / 5 | G47: #0B6B22 | H47: всегда | I47: Цвет совпадает с Д1
A48: 2 | B48: ВРЕМЯ | C48: wk_post | D48: Обработка | E48: post_time | F48: post_time / net_weeks / 5 | G48: #1B9331 | H48: всегда
A49: 3 | B49: ВРЕМЯ | C49: wk_client | D49: Работа с клиентом | E49: client_total | F49: client_total / net_weeks / 5 | G49: #35B94C | H49: всегда
A50: 4 | B50: ВРЕМЯ | C50: wk_promo | D50: Продвижение | E50: promo_time | F50: promo_time / net_weeks / 5 | G50: #6FD183 | H50: всегда
A51: 5 | B51: ВРЕМЯ | C51: wk_acc | D51: Учёт | E51: accounting_time | F51: accounting_time / net_weeks / 5 | G51: #A6E5B2 | H51: только при acc_mode = сам
A52: 6 | B52: ВРЕМЯ | C52: wk_fm | D52: Резерв на срывы | E52: fm_time | F52: fm_time / net_weeks / 5 | G52: #CDF2D5 | H52: только при fm_on
A53: 7 | B53: СЛУЖЕБНОЕ | C53: wk_lunch | D53: Обед | E53: — | F53: фиксированно 1 час в 14:00 | G53: #E5E7EB | H53: всегда | I53: Нейтральный серый
A55: Д4 · РЕЗЕРВ — заготовка под будущую диаграмму
A56: Тип диаграммы | C56: (заполнить) | F56: Варианты: столбчатая, линейная, воронка
A57: Где размещена | C57: (заполнить)
A58: Что показывает | C58: (заполнить)
A59: Идея 1 | C59: Динамика ставки при разной длительности съёмки | F59: Как S влияет на цену часа
A60: Идея 2 | C60: Структура года: оплачиваемые и неоплачиваемые часы | F60: Наглядное соотношение
A61: Идея 3 | C61: Сравнение с наймом | F61: Ставка фрилансера против зарплаты в штате
A63: № | B63: Группа | C63: Код сегмента | D63: Подпись в легенде | E63: Параметр расчёта | F63: Формула / что берём | G63: Цвет | H63: Условие | I63: Комментарий
A64: 1
A65: 2
A66: 3
A67: 4
A68: 5
A69: 6
A71: ОБЩИЕ ПРАВИЛА
A72: Порядок сегментов в таблице = порядок отрисовки по часовой стрелке от 12 часов.
A73: Цвета едины для всех диаграмм: зелёная гамма — заработок, тёплая и холодная — расходы.
A74: Проценты подписываются прямо на сегменте, если доля не меньше 3,2%. Мельче — не читается.
A75: Сегмент с нулевым значением не отрисовывается и не попадает в легенду.
A76: Условные сегменты (бухгалтер, резерв) исчезают, когда соответствующая опция выключена.
A77: Сумма всех сегментов всегда равна выручке — это проверяется формулой в листе 05_Расчёт.
A79: ЧТО ПРАВИТЬ В ЭТОМ ЛИСТЕ: подписи в легенде (жёлтая колонка) и состав групп.
A80: Формулы и коды сегментов менять только вместе с кодом HTML.

Sheet 13_Сетка_скидок
A1: 13 · СЕТКА ЦЕН ПО ОБЪЁМУ
A2: Постоянная величина — час ПРОЕКТНОГО времени. Цена съёмочного часа падает за счёт накладных, а не дохода.
A4: ПРИНЦИП
A5: Час проектного времени = выручка / проектное время за год. Величина ПОСТОЯННАЯ.
A6: Проект = S × (1 + коэффициент обработки) + 1 час на клиента.
A7: Час на клиента одинаков и для съёмки на 2 часа, и для съёмки на 6 часов.
A8: Чем длиннее съёмка, тем меньше накладных приходится на каждый съёмочный час.
A10: ВАЖНО: доход специалиста НЕ уменьшается. Годовая выручка одинакова при любой длительности.
A12: ПРИМЕР: минимальная съёмка 2 ч, коэффициент обработки 3
A13: Длительность | B13: Проектное время | C13: Цена заказа | D13: Цена часа | E13: Скидка | F13: Комментарий
A14: 2 ч — базовая | B14: 9 ч | C14: 18708 | D14: 9354 | E14: — | F14: Максимальная ставка
A15: 3 ч | B15: 13 ч | C15: 27023 | D15: 9008 | E15: −3.7% | F15: Клиент экономит 346 ₽ с часа
A16: 4 ч | B16: 17 ч | C16: 35338 | D16: 8835 | E16: −5.6% | F16: Клиент экономит 520 ₽ с часа
A17: 5 ч | B17: 21 ч | C17: 43653 | D17: 8731 | E17: −6.7% | F17: Клиент экономит 624 ₽ с часа
A18: 6 ч | B18: 25 ч | C18: 51968 | D18: 8661 | E18: −7.4% | F18: Клиент экономит 693 ₽ с часа
A19: 7 ч | B19: 29 ч | C19: 60283 | D19: 8612 | E19: −7.9% | F19: Клиент экономит 742 ₽ с часа
A21: ПРОВЕРКА | B21: Выручка за год при любом S | C21: 2138693 | F21: Сумма всех заказов одинакова
A23: ПЕРЕСМОТР 06.08.2026 — база от 1 часа, ступени 2/4/6
A24: Было | B24: Ступени S, S+1, S+2, S+3 — зависели от введённой длительности. Первая карточка считалась «базой», хотя при S=2 это уже цена со скидкой 10%
A25: Стало | B25: База всегда 1 час — короче никто не работает. Ступени фиксированы: 2, 4, 6 часов
A26: Формула | B26: час(S) = (S × (1+K) + cl) × hp / S, где hp = R / project_pool
A27: Почему час дороже | B27: Час на работу с клиентом тратится на каждый заказ независимо от длины. При S=1 он занимает 20% проекта, при S=6 — только 4%
A28: На демо-наборе | B28: 1 ч → 9 874 ₽ · 2 ч → 8 887 ₽ (−10,0%) · 4 ч → 8 393 ₽ (−15,0%) · 6 ч → 8 228 ₽ (−16,7%)

Sheet 13b_Программа_лояльности
A1: 13b · ПРОГРАММА ЛОЯЛЬНОСТИ — ФОНД, СКИДКИ, СЕРТИФИКАТЫ
A2: Структура скидок блока 03 отчёта. Жёлтое — исходные данные, зелёное — итог. Всё остальное считается формулами.
A3: ПРАВИЛО: скидки покрываются ТОЛЬКО фондом. Экономия на привлечении и высвобожденное время в покрытие не идут — это выгода фотографа.
A5: ИСХОДНЫЕ ДАННЫЕ — из анкеты и расчёта
A6: Показатель | B6: Значение | C6: Ед. | G6: Откуда
A7: Резерв на скидку (discP) | B7: 0.15 | C7: доля | G7: Анкета, блок «резерв на скидку»: 5 / 10 / 15%
A8: Выручка целевая (R) | B8: 2138693 | C8: ₽/год | G8: 05_Расчёт
A9: Съёмок (заказов) в год | B9: 216.6 | C9: шт | G9: 06_Отчёт, py. Дробное — это среднее за год. В отчёте показывается округлённым
A10: Средний чек | B10: 47000 | C10: ₽ | G10: Прайс 11 700 ₽/ч × средняя съёмка 5 ч, округлено
A11: Стоимость привлечения нового клиента | B11: 2645 | C11: ₽ | G11: 09b, строки о стоимости клиента
A12: Время на привлечение нового клиента | B12: 2.32 | C12: ч | G12: 09b: поиск 2,02 ч + переписка сверх постоянного 0,30 ч
A13: Рабочих часов в дне | B13: 8 | C13: ч | G13: calc
A15: ФОНД ПРОГРАММЫ ЛОЯЛЬНОСТИ — сколько денег и на что
A16: Направление | B16: Доля | C16: Сумма / год | G16: Комментарий
A17: Бюджет фонда, всего | C17: 377826 | G17: Резерв, заложенный в цену: цена = база / (1 − резерв). Считается в calc.html
A18: Скидка за объём | B18: =C18/$C$17 -> 0.25044862 | C18: =C17-C19-C20 -> 94626 | G18: Остаток фонда: то, что не ушло на постоянных и спецпредложения
A19: Постоянным клиентам | B19: =C19/$C$17 -> 0.44782519 | C19: =F30 -> 169200 | G19: Ровно сумма ступеней ниже — направление расходуется полностью
A20: Специальные предложения | B20: =C20/$C$17 -> 0.30172619 | C20: =E46 -> 114000 | G20: Ровно номинал комплекта сертификатов
A21: ИТОГО | B21: =SUM(B18:B20) -> 1 | C21: =SUM(C18:C20) -> 377826 | G21: Должно совпасть с бюджетом фонда
A22: В месяц | C22: =ROUND(C17/12,0) -> 31486
A23: С каждой съёмки | C23: =ROUND(C17/B9,0) -> 1744
A25: СКИДКА ПОСТОЯННОМУ КЛИЕНТУ — ступени и распределение бюджета
A26: Частота визитов | B26: Скидка | C26: Съёмок / год | D26: Клиентов | E26: Заказов | F26: Скидка / год | G26: Порог: принесёт вам от
A27: Раз в полгода | B27: 0.05 | C27: 2 | D27: 10 | E27: =C27*D27 -> 20 | F27: =ROUND(E27*$B$10*B27,0) -> 47000 | G27: =ROUND(C27*$B$10*(1-B27),-2) -> 89300
A28: Раз в квартал | B28: 0.07 | C28: 4 | D28: 5 | E28: =C28*D28 -> 20 | F28: =ROUND(E28*$B$10*B28,0) -> 65800 | G28: =ROUND(C28*$B$10*(1-B28),-2) -> 174800
A29: Раз в месяц | B29: 0.1 | C29: 12 | D29: 1 | E29: =C29*D29 -> 12 | F29: =ROUND(E29*$B$10*B29,0) -> 56400 | G29: =ROUND(C29*$B$10*(1-B29),-2) -> 507600
A30: ИТОГО | D30: =SUM(D27:D29) -> 16 | E30: =SUM(E27:E29) -> 52 | F30: =SUM(F27:F29) -> 169200
A31: Сходимость фонда | F31: =C21-C17 -> 0 | G31: Должно быть 0: сумма трёх направлений равна бюджету фонда
A32: Доля заказов от постоянных | F32: =E30/B9 -> 0.24007387 | G32: Отраслевая норма Repeat Purchase Rate 20–40%, медиана 27% — см. 09b
A34: ВЫГОДА ФОТОГРАФА СВЕРХ СКИДОК — в покрытие НЕ идёт
A35: Показатель | C35: Значение | G35: Комментарий
A36: Сэкономлено на привлечении | C36: =ROUND(E30*B11,0) -> 137540 | G36: Повторный заказ не требует поиска и повторных согласований
A37: Высвобождено времени, ч | C37: =ROUND(E30*B12,0) -> 121
A38: То же в рабочих днях | C38: =ROUND(C37/B13,0) -> 15
A39: Решение 09.08.2026 | G39: Раньше экономия засчитывалась в покрытие скидок, из фонда уходило 19% — фонд выглядел нерасходуемым. Теперь скидки считаются от бюджета фонда, а экономия показана отдельной строкой.
A41: СПЕЦИАЛЬНЫЕ ПРЕДЛОЖЕНИЯ — комплект сертификатов на год
A42: Код | B42: Название | C42: Номинал | D42: Штук / год | E42: Сумма | G42: Как использовать
A43: SP-26001 | B43: День рождения | C43: 5000 | D43: 7 | E43: =C43*D43 -> 35000 | G43: Точечный прогрев в несезон
A44: SP-26002 | B44: На свадьбу | C44: 10000 | D44: 1 | E44: =C44*D44 -> 10000 | G44: Розыгрыш среди подписчиков, ажиотаж вокруг услуги
A45: SP-26003 | B45: Событие | C45: 3000 | D45: 23 | E45: =C45*D45 -> 69000 | G45: Бонус клиенту или под удобные праздники
A46: ИТОГО | D46: =SUM(D43:D45) -> 31 | E46: =SUM(E43:E45) -> 114000
A47: Остаток направления | E47: 0 | G47: Направление задано ровно по номиналу комплекта. Чтобы добавить сертификатов, увеличьте комплект — фонд перераспределится сам
A49: СКИДКА ЗА ОБЪЁМ — ступени прайса
A50: Длительность | B50: Цена часа | C50: Скидка | G50: Комментарий
A51: от 1 часа — базовая | B51: 11700 | C51: — | G51: Базовая ставка прайса, резерв уже включён
A52: от 3 часов | B52: 10500 | C52: =B52/$B$51-1 -> -0.1025641 | G52: Проценты считаются от ОКРУГЛЁННЫХ цен — клиент проверит на калькуляторе
A53: от 5 часов | B53: 9400 | C53: =B53/$B$51-1 -> -0.1965812
A54: от 7 часов | B54: 8300 | C54: =B54/$B$51-1 -> -0.29059829
A55: Природа скидки | G55: Часть — накладные (подготовка размазывается на больше часов), часть — из фонда. Доход фотографа не меняется.

Sheet 14_Опрос
A1: 14 · ОПРОС — что доработать в первую очередь
A2: Показываются все 4 варианта пула, всегда в одном порядке. Метрика — лайки / показы. Жёлтое редактируется, иконка берётся по коду.
A4: ПУЛ ВАРИАНТОВ
A5: № | B5: price | C5: Прайс для клиентов | D5: готовый прайс-лист, который не стыдно отправить | E5: да
A6: 1 | B6: invoice | C6: Счета и акты | D6: выставить за минуту, без бухгалтера | E6: да
A7: 2 | B7: pocket | C7: Карманный помощник | D7: приложение, которое всегда с вами | E7: да
A8: 3 | B8: search | C8: Поиск клиентов | D8: где брать заказы, когда сарафанное радио молчит | E8: да
A9: 4 | B9: tax | C9: Налоговый помощник | D9: какой режим выгоднее именно вам | E9: да | F9: УДАЛЕНО из HTML: пул сокращён до 4 фиксированных вариантов
A10: 5 | B10: calendar | C10: Календарь съёмок | D10: планировать загрузку на месяц | E10: да | F10: УДАЛЕНО из HTML: пул сокращён до 4 фиксированных вариантов
A11: 6 | B11: clients | C11: База клиентов | D11: помнить, кто и сколько заказывал | E11: да | F11: УДАЛЕНО из HTML: пул сокращён до 4 фиксированных вариантов
A12: 7 | B12: contract | C12: Договоры | D12: шаблоны под съёмку и предоплату | E12: да | F12: УДАЛЕНО из HTML: пул сокращён до 4 фиксированных вариантов
A13: 8 | B13: analytics | C13: Аналитика года | D13: сравнить месяцы и увидеть рост | E13: да | F13: УДАЛЕНО из HTML: пул сокращён до 4 фиксированных вариантов
A14: 9 | B14: budget | C14: Сравнение с рынком | D14: какие цены у коллег в вашем городе | E14: да | F14: УДАЛЕНО из HTML: пул сокращён до 4 фиксированных вариантов
A15: 10 | B15: analytics | C15: Расчёт на команду | D15: если работаете не одни | E15: да | F15: иконка переиспользована
A17: КАК РАБОТАЕТ
A18: Показываются все 4 варианта пула — без случайной выборки, порядок фиксирован.
A19: Пользователь отмечает сердечком те, что ему нужны, и нажимает «Отправить».
A21: ВАЖНО ПРО СТАТИСТИКУ: считаем не только лайки, но и показы.
A22: Метрика = лайки / показы. Иначе сравнение нечестное: у вариантов разное число показов.
A23: Показы = число расчётов: каждый вариант видят все, кто дошёл до отчёта.
A25: Добавить вариант: впишите строку выше, продублируйте в POOL внутри HTML и добавьте иконку в ICONS.
A27: ЦЕЛИ В ЯНДЕКС.МЕТРИКЕ
A28: № | B28: Цель | C28: Когда срабатывает | D28: Параметры
A29: 1 | B29: poll_show | C29: при отрисовке блока опроса | D29: shown — какие 4 варианта показаны
A30: 2 | B30: poll_vote | C30: при нажатии «Отправить» | D30: liked — отмеченные, other — своя идея, shown
A31: 3 | B31: buy_click | C31: клик по ценнику или кнопке оплаты | D31: —
A32: 4 | B32: paid | C32: возврат на страницу с ?paid=1 | D32: —
A34: Номер счётчика пропишите в HTML: var YM_ID=0; → var YM_ID=ваш_номер;
A35: Отчёт в Метрике: «Отчёты → Конверсии → Цели», параметры видны в «Содержание → Параметры визитов».
A37: ЕСЛИ НУЖНО СОБИРАТЬ ОТВЕТЫ В TILDA
A38: Вариант 1. Метрика — уже настроено, ничего не нужно. Смотрите статистику в отчётах.
A39: Вариант 2. Форма Tilda — добавить скрытое поле и отправлять ответы в Заявки.
A40: В HTML заменить отправку в ym() на fetch к форме Tilda с полями liked и other.
A41: Вариант 3. Google-таблица через Tilda — заявки автоматически падают в таблицу.
A43: Для теста хватит Метрики: она уже стоит и не требует бэкенда.

Sheet 28_Журнал_изменений
A1: Дата | B1: Что изменили | C1: Как считается теперь | D1: Почему | E1: Где отражено | F1: Статус
A2: 18.08.2026 | B2: Окупаемость камеры | C2: Цена камеры ÷ ((доход на руки за год + амортизация камеры) ÷ проектов за год) = 166 999 ÷ 6 363 = 26,2 съёмки (1,5 мес) | D2: Раньше делили цену камеры на выручку за съёмку (17,7) — это не окупаемость: из выручки ещё уходят налог, комиссия, реклама, аренда. Срок окупаемости считают по денежному потоку; амортизацию в поток возвращают, иначе камера оплачивается дважды | E2: Детализация, таблица 03; справочник — статьи «Окупаемость», «Денежный поток» | F2: в книгу не внесено
A3: 18.08.2026 | B3: Цена камеры / выручка за съёмку | C3: Цена камеры ÷ (выручка ÷ проектов за год) = 17,7 съёмки | D3: Оставлена как отдельная строка под честным названием: так фотографы говорят «окупил камеру», и человек должен видеть разницу с настоящей окупаемостью | E3: Детализация, таблица 03 | F3: в книгу не внесено
A4: 18.08.2026 | B4: Срабатываний затвора за 1 час | C4: Новое поле анкеты, по умолчанию 350 (Canon EOS R6 Mark II) | D4: Позволяет считать износ камеры и выработку ресурса затвора | E4: Анкета блок 04; детализация, таблицы 01 и 03 | F4: в анкету не внесено
A5: 18.08.2026 | B5: Ресурс затвора | C5: Новое поле анкеты, по умолчанию 300 000 срабатываний | D5: Заявленный ресурс у каждой камеры свой, зашивать в код нельзя | E5: Анкета блок 04; детализация, таблицы 01 и 03 | F5: в анкету не внесено
A6: 18.08.2026 | B6: Износ камеры | C6: Амортизация тушки за год ÷ срабатываний за год = 55 666 ÷ 75 810 = 0,73 ₽ за срабатывание; 257 ₽ за съёмку | D6: Показывает износ в деньгах на одну съёмку | E6: Детализация, таблица 03 | F6: в книгу не внесено
A7: 18.08.2026 | B7: Выработка ресурса затвора | C7: Срабатываний за год ÷ ресурс = 75 810 ÷ 300 000 = 25,3 % в год, ресурса хватит на 4 года | D7: Проверка срока амортизации камеры: разносим на 3 года, ресурс кончится через 4 — срок взят осторожно | E7: Детализация, таблица 03 | F7: в книгу не внесено
A8: 18.08.2026 | B8: Себестоимость часа съёмки | C8: (расходы дела + налог + комиссия) ÷ съёмочных часов = 3 324 ₽ | D8: Нужна, чтобы показать наценку и границу цены | E8: Детализация, таблица 08 | F8: в книгу не внесено
A9: 18.08.2026 | B9: Наценка к себестоимости | C9: Ставка ÷ себестоимость − 1 = 183,7 % | D9: — | E9: Детализация, таблица 08 | F9: в книгу не внесено
A10: 18.08.2026 | B10: Запас прочности | C10: 1 − выручка в ноль ÷ выручка = 70,2 % | D10: На столько может упасть выручка, прежде чем доход станет нулевым | E10: Детализация, таблица 08 | F10: в книгу не внесено
A11: 18.08.2026 | B11: Съёмок / выход в ноль | C11: Выручка в ноль ÷ цена проекта. При текущей ставке 101,6; при желаемой 64,6 | D11: Понятнее, чем проценты: сколько съёмок уходит только на покрытие расходов | E11: Детализация, таблица 08 | F11: в книгу не внесено
A12: 18.08.2026 | B12: Календарь года развёрнут | C12: 365 календарных = 104 выходных + 14 праздничных + 247 рабочих; 247 − 20 (отпуск) − 8 (больничные) = 219 | D12: Раньше в отчёте было только 247/20/8, и цепочка не сходилась на глаз. Отпуск 28 календарных дней = 20 рабочих, больничные 10 = 8 рабочих | E12: Детализация, таблица 02 | F12: в книгу не внесено
... A14: 18.08.2026 | B14: Налоги внутри расходов | C14: Всего расходов = расходы дела + налог + взносы + комиссия = 719 943 ₽ | D14: Налог и комиссия — такие же траты; выручка − расходы = доход на руки одной строкой | E14: Детализация, таблицы 04 и 05 | F14: в книгу не внесено

Sheet 06b_Отчёт_полный
A1: 06b · ПОЛНЫЙ ОТЧЁТ В КНИГЕ — то же, что видит человек в отчёте
A2: Формулы ссылаются на листы и параметры книги. Столбец «Калькулятор» — значение из настоящего расчёта сайта, для сверки. Пустая формула значит: параметра в книге ещё нет, смотрите описание.
A4: № | B4: Блок | C4: Показатель | D4: Значение | E4: Ед. | F4: Описание алгоритма | G4: Калькулятор | H4: Сходится
A6: ШАПКА И ПЕРВЫЙ ЭКРАН
A7: 1 | B7: Первый экран | C7: Желаемая ставка | D7: ='04_Итог'!B5 -> 9429.986 | E7: ₽/ч | F7: Выручка за год делится на Съёмочное время. Это рассчитанная стоимость часа съёмки, которая позволяет специалисту получать Желаемый доход. | G7: 9429.99 | H7: =IF(D7="","—",IF(ABS(D7-G7)<1,"да","НЕТ")) -> да
A8: 2 | B8: Первый экран | C8: Доход в час на руки | D8: =(target_income*11/12)/(net_days*8) -> 691.99543 | E8: ₽/ч | F8: Желаемый доход за 11 месяцев делится на рабочее время (рабочие дни × 8). Отпускной месяц — дополнительная оплата, не плата за рабочий месяц. | G8: 692 | H8: =IF(D8="","—",IF(ABS(D8-G8)<1,"да","НЕТ")) -> да
A9: 3 | B9: Первый экран | C9: Базовая ставка | D9: =base_rate -> 1332.3777 | E9: ₽/ч | F9: Вся выручка за год делится на эффективное рабочее время. Ставка выгодности для услуг вне съёмочной площадки: покрывает доход (включая отпускной месяц), расходы и налоги, без повышающего коэффициента съёмочного часа. | G9: 1332.38 | H9: =IF(D9="","—",IF(ABS(D9-G9)<1,"да","НЕТ")) -> да
A10: 4 | B10: Первый экран | C10: Доход на руки | D10: =target_income -> 1322592 | E10: ₽/год | F10: Желаемый доход в месяц × 12. Точка отсчёта всего расчёта. | G10: 1322592 | H10: =IF(D10="","—",IF(ABS(D10-G10)<1,"да","НЕТ")) -> да
A11: 5 | B11: Первый экран | C11: Доход на руки | D11: =target_income/months -> 110216 | E11: ₽/мес | F11: Сумма, которую человек указал в анкете. | G11: 110216 | H11: =IF(D11="","—",IF(ABS(D11-G11)<1,"да","НЕТ")) -> да
A12: 6 | B12: Первый экран | C12: Выручка | D12: ='04_Итог'!B8 -> 2042535 | E12: ₽/год | F12: Сколько нужно выставить клиентам, чтобы после расходов, налогов и эквайринга остался желаемый доход. | G12: 2042535 | H12: =IF(D12="","—",IF(ABS(D12-G12)<1,"да","НЕТ")) -> да
A13: 7 | B13: Первый экран | C13: Выручка | D13: ='04_Итог'!B9 -> 170211.25 | E13: ₽/мес | F13: Выручка за год ÷ 12. | G13: 170211.25 | H13: =IF(D13="","—",IF(ABS(D13-G13)<1,"да","НЕТ")) -> да
A14: 8 | B14: Первый экран | C14: Всего расходов | D14: =total_costs+CHOOSE(regime_no,'05_Расчёт'!B15,'05_Расчёт'!C15,'05_Расчёт'!D15,'05_Расчёт'!E15,'05_Расчёт'!F15,'05_Расчёт'!G15,'05_Расчёт'!H15)+'04_Итог'!B8*acquiring -> 719942.97 | E14: ₽/год | F14: Финансовые расходы плюс Налоги и Эквайринг. Резервный фонд и компенсация Инвестиционного времени не входят. calc() передаёт готовое поле totalExpenses; главный экран и детализация используют одно значение. | G14: 719942.97 | H14: =IF(D14="","—",IF(ABS(D14-G14)<1,"да","НЕТ")) -> да
A16: ВРЕМЯ
A17: 9 | B17: Время | C17: Рабочее время | D17: =work_days*nominal_hours -> 1976 | E17: ч/год | F17: Рабочие дни производственного календаря × 8 часов. Верхняя граница: всё время, которое человек проводит в работе. | G17: 1752 | H17: =IF(D17="","—",IF(ABS(D17-G17)<1,"да","НЕТ")) -> НЕТ
A18: 10 | B18: Время | C18: Эффективное рабочее время | D18: =net_time -> 1533 | E18: ч/год | F18: Рабочие дни минус отпуск и больничный, умноженные на 7 эффективных часов. | G18: 1533 | H18: =IF(D18="","—",IF(ABS(D18-G18)<1,"да","НЕТ")) -> да
A19: 11 | B19: Время | C19: Съёмочное время | D19: =shooting_time -> 216.6 | E19: ч/год | F19: Общее время непосредственной съёмки на съёмочной площадке. | G19: 216.6 | H19: =IF(D19="","—",IF(ABS(D19-G19)<1,"да","НЕТ")) -> да
