Workbook

Sheet Условные обозначения
A1: УСЛОВНЫЕ ОБОЗНАЧЕНИЯ — единый реестр понятий
A2: Тип: const — фиксированная аксиома из достоверного источника | calc — вычисляется формулой | default — предзаполнено, пользователь меняет | meta — служебное понятие реестра | ui — тип поля интерфейса
A4: A. МАРКЕРЫ ТИПОВ — служебные обозначения реестра
A5: № | B5: Наименование | C5: ID | D5: Тип | E5: Описание | F5: Формула / значение
A6: 1 | B6: Константа | C6: const | D6: meta | E6: Фиксированное значение-аксиома из достоверного источника (закон, производственный календарь, статистика). Пользователь не меняет | F6: 247 рабочих дня, 57 390 ₽
A7: 2 | B7: Формула | C7: calc | D7: meta | E7: Поле вычисляется из других значений. Пользователю показывается результат, ввод недоступен | F7: чистое время = (247−20−8)×7
A8: 3 | B8: Значение по умолчанию | C8: default | D8: meta | E8: Предзаполнено нашим значением (в т.ч. расчётным), пользователь может скорректировать | F8: желаемый доход 108 999 ₽
A9: 4 | B9: Служебное понятие | C9: meta | D9: meta | E9: Термин, описывающий устройство самого реестра, а не предметную область | F9: block, section, form
A10: 5 | B10: Тип поля интерфейса | C10: ui | D10: meta | E10: Обозначение способа ввода данных в калькуляторе | F10: input_number, dropdown
A11: 6 | B11: Скрытое поле | C11: hidden_field | D11: meta | E11: Считается автоматически, пользователю не показывается | F11: пересчёт покупки в ₽/год
A12: 7 | B12: Галочка «Не учитывать» | C12: exclude_flag | D12: meta | E12: Переключатель, исключающий блок или его часть из расчёта | F12: Block6–Block15
A13: B. ТИПЫ ПОЛЕЙ ИНТЕРФЕЙСА (значения столбца «Тип» на листе «Блоки»)
A14: № | B14: Наименование | C14: ID | D14: Тип | E14: Описание | F14: Формула / значение
A15: 8 | B15: Числовое поле | C15: input_number | D15: ui | E15: Одно поле для ввода числа | F15: Block1, Block3, Block13
A16: 9 | B16: Выпадающий список | C16: dropdown | D16: ui | E16: Готовый набор вариантов, выбирается один | F16: Block4, Block14
A17: 10 | B17: Расширенный ввод | C17: input_extended | D17: ui | E17: Несколько связанных полей, дающих один итог | F17: Block10 обучение
A18: 11 | B18: Переключатель + поле | C18: radio + input | D18: ui | E18: Выбор варианта и числовое поле, меняющее смысл | F18: Block12 сайт
A19: 12 | B19: Динамическая таблица | C19: dynamic_table | D19: ui | E19: Пользователь добавляет и удаляет строки | F19: Block6, Block7
A20: 13 | B20: Несколько таблиц | C20: dynamic_tables | D20: ui | E20: Блок содержит несколько независимых таблиц | F20: Block8 ПО
A21: 14 | B21: Список + таблица | C21: dropdown + dynamic_table | D21: ui | E21: Выбор варианта, под него появляется таблица | F21: Block9 рабочее место
A22: 15 | B22: Составной блок | C22: 2 parts | D22: ui | E22: Две разные формы в одном блоке: время и деньги | F22: Block11, Block15
A23: 16 | B23: Информационный блок | C23: info_block | D23: ui | E23: Только поясняющий текст, полей ввода нет | F23: Block5
A24: 17 | B24: Блок вывода | C24: report | D24: ui | E24: Итоговая страница с результатами, без формул | F24: Block16–Block18
A25: C. СТРУКТУРА РЕЕСТРА
A26: № | B26: Наименование | C26: ID | D26: Тип | E26: Описание | F26: Формула / значение
A27: 18 | B27: Реестр данных | C27: registry | D27: meta | E27: Рабочая книга со всеми параметрами, формулами и формами. Редактируется, видна изнутри | F27: эта книга
A28: 19 | B28: Калькулятор | C28: calculator | D28: meta | E28: Конечный продукт: тот же реестр в интерфейсе, формулы скрыты
A29: 20 | B29: Раздел | C29: section | D29: meta | E29: Логическое объединение блоков. Соответствует шагу интерфейса | F29: Section1–Section5
A30: 21 | B30: Блок | C30: block | D30: meta | E30: Совокупность данных, объединённых логически. Экран или его часть | F30: Block1–Block18
A31: 22 | B31: Форма | C31: form | D31: meta | E31: Таблица с данными для формы калькулятора. В блоке может быть несколько | F31: Form001–Form016
A32: 23 | B32: Поле | C32: item | D32: meta | E32: Поле для ввода данных пользователем
A33: 24 | B33: Вопрос | C33: question | D33: meta | E33: Формулировка рядом с полем — объясняет, что вписать
A34: 25 | B34: Отчёт | C34: report | D34: meta | E34: Итоговая страница с результатами для пользователя | F34: Section5
A35: 26 | B35: Пользователь | C35: user | D35: meta | E35: Человек, использующий калькулятор по назначению
A36: D. ВРЕМЯ — иерархия сверху вниз
A37: № | B37: Наименование | C37: ID | D37: Тип | E37: Описание | F37: Формула / значение
A38: 27 | B38: Рабочее время | C38: work_time | D38: const | E38: Время без выходных и праздников по производственному календарю РФ 2026 | F38: 247 дней × 8 ч = 1 976 ч
A39: 28 | B39: Чистое (эффективное) время | C39: net_time | D39: calc | E39: Рабочее время минус отпуск, больничный и 1 час в день на перерывы и второстепенные дела. ВЕРХНИЙ УРОВЕНЬ | F39: (247−20−8) × 7 = 1 533 ч/год
A40: 29 | B40: Операционное время | C40: side_time | D40: calc | E40: Обязанности вне проектов: продвижение и учёт. Клиенту напрямую не продаётся | F40: 438 + 12 = 450 ч/год
A41: 30 | B41: Профильное время | C41: core_time | D41: calc | E41: Работа по специальности: съёмка, постпродакшн, работа с клиентом | F41: 1 533 − 450 = 1 083 ч/год
A42: 31 | B42: Проектное время | C42: project_time | D42: calc | E42: Время на один законченный проект | F42: S×(1+K) + client_time = 29 ч
A43: 32 | B43: Съёмочное время | C43: shooting_time | D43: calc | E43: Часы на площадке. ИМЕННО ОНИ ПРОДАЮТСЯ и стоят в знаменателе ставки | F43: 37,34 × 7 = 261 ч/год
A44: 33 | B44: Постпродакшн | C44: post_time | D44: calc | E44: Обработка материала. Задаётся коэффициентом обработки | F44: 261 × 3 = 784 ч/год
A45: 34 | B45: Продолжительность съёмки | C45: shoot_duration | D45: default | E45: Средняя длительность одной съёмки. Ключевой ввод пользователя | F45: S = 7 ч
A46: 35 | B46: Коэффициент обработки | C46: post_ratio | D46: default | E46: Часов обработки на 1 час съёмки | F46: K = 3
A47: 36 | B47: Работа с клиентом | C47: client_time | D47: default | E47: Административное общение по проекту. Входит в проектное время | F47: 1 ч/проект → 37 ч/год
A48: 37 | B48: Продвижение | C48: promo_time | D48: default | E48: Собственные часы на поиск заказов: соцсети, отклики | F48: 2 ч/день × 219 = 438 ч/год
A49: 38 | B49: Учёт и планирование (время) | C49: accounting_time | D49: default | E49: Часы на бухгалтерию, если ведёте сами. Альтернатива accounting_money | F49: 3 ч/квартал × 4 = 12 ч/год
... A53: 42 | B53: Больничный | C53: sick_leave | D53: const | E53: Средний показатель нетрудоспособности за год | F53: 10 календарных = 8 рабочих
A54: E. ДЕНЬГИ — доходы и расходы
A55: № | B55: Наименование | C55: ID | D55: Тип | E55: Описание | F55: Формула / значение
A56: 43 | B56: Желаемый доход | C56: target_income | D56: default | E56: Сумма на руки ежемесячно. Точка отсчёта всего расчёта | F56: N = 108 999 × 12 = 1 307 988 ₽
A57: 44 | B57: Выручка | C57: revenue | D57: calc | E57: Сколько нужно выставить клиентам за год. ГЛАВНЫЙ РЕЗУЛЬТАТ | F57: R = 2 293 553 ₽ (УСН 6%)
A58: 45 | B58: Всего расходов | C58: total_costs | D58: calc | E58: Амортизация плюс переменные расходы за год. Без эквайринга | F58: C = 786 026 ₽/год
A59: 46 | B59: Инвестиции в бизнес | C59: investment | D59: calc | E59: Деньги, вложенные заранее ради возможности работать: оборудование, ПО, место, обучение | F59: 308 126 ₽/год после амортизации
A60: 47 | B60: Амортизация | C60: depreciation | D60: calc | E60: Распределение стоимости разовой покупки на срок службы | F60: стоимость / срок службы
A61: 48 | B61: Срок полезного использования | C61: useful_life | D61: default | E61: За сколько лет списывается покупка. Задаётся по каждой позиции | F61: камера 3 года, рюкзак 7 лет
A62: 49 | B62: Переменные расходы | C62: variable_costs | D62: calc | E62: Регулярные платежи за год: подписки, реклама, банк, бухгалтер, рабочее место | F62: 477 900 ₽/год
A63: 50 | B63: Съёмочное оборудование | C63: shoot_gear | D63: default | E63: Только обязательное для базовой съёмки | F63: 137 893 ₽/год
A64: 51 | B64: Офисное оборудование | C64: office_gear | D64: default | E64: Только обязательное для обработки и операционных задач | F64: 65 733 ₽/год
A65: 52 | B65: Программное обеспечение | C65: software | D65: default | E65: Подписки (переменные) и разовые покупки (амортизация) | F65: 27 000 + 11 500 ₽/год
A66: 53 | B66: Рабочее место | C66: workspace | D66: meta | E66: Пространство для работы вне площадки: дом или помещение
A67: 54 | B67: Обустройство рабочего места | C67: workspace_setup | D67: default | E67: Разовые вложения: мебель, ремонт. Амортизируются | F67: 9 286 ₽/год
A68: 55 | B68: Содержание рабочего места | C68: workspace_upkeep | D68: calc | E68: Аренда и коммунальные. Берутся ПО ДОЛЕ площади кабинета | F68: (40 000+7 000) × 12% × 12
A69: 56 | B69: Доля кабинета | C69: room_share | D69: calc | E69: Площадь кабинета к общей площади жилья | F69: 6 / 50 = 12%
A70: 57 | B70: Обучение | C70: education | D70: default | E70: Курс плюс упущенный доход за месяцы учёбы | F70: (80 000 + 4×108 999) / 7
A71: 58 | B71: Упущенная выгода | C71: opportunity_cost | D71: calc | E71: Доход, не полученный за время учёбы. Можно отключить флагом | F71: 4 мес × 108 999 = 435 996 ₽
A72: 59 | B72: Реклама | C72: ads_money | D72: default | E72: Деньги за привлечение клиентов: таргет, контекст, размещения | F72: 187 500 ₽/год
A73: 60 | B73: Учёт и планирование (деньги) | C73: accounting_money | D73: default | E73: Нанятый бухгалтер. Взаимоисключающе с accounting_time | F73: 120 000 ₽/год
A74: 61 | B74: Банковские расходы (фикс.) | C74: bank_fixed | D74: default | E74: РКО и СМС. Обычный расход, входит в C | F74: 1 800 ₽/год
A75: 62 | B75: Эквайринг | C75: acquiring | D75: default | E75: Процент С ОБОРОТА. НЕ расход — идёт в знаменатель формулы выручки | F75: 2,7% от выручки
A76: F. НАЛОГИ И ВЗНОСЫ 2026 (в исходном глоссарии отсутствовали полностью)
A77: № | B77: Наименование | C77: ID | D77: Тип | E77: Описание | F77: Формула / значение
A78: 63 | B78: НПД (самозанятость) | C78: npd | D78: const | E78: Налог на профессиональный доход. Взносов нет, расходы не вычитаются, лимит 2,4 млн ₽/год | F78: 4% с физлиц, 6% с юрлиц
A79: 64 | B79: УСН «Доходы» | C79: usn_income | D79: const | E79: Налог с полной выручки. Взносы ВЫЧИТАЮТСЯ из налога до нуля | F79: 6% (регион может снизить до 1%)
A80: 65 | B80: УСН «Доходы минус расходы» | C80: usn_profit | D80: const | E80: Налог с прибыли. Взносы уменьшают базу | F80: 15% (регион может снизить до 5%)
A81: 66 | B81: АУСН «Доходы» | C81: ausn_income | D81: const | E81: Автоматизированная УСН. Взносы ИП за себя НЕ платятся, лимит 60 млн ₽ | F81: 8%
A82: 67 | B82: АУСН «Доходы минус расходы» | C82: ausn_profit | D82: const | E82: То же с учётом расходов. Минимальный налог 3% | F82: 20%
A83: 68 | B83: Фиксированные страховые взносы | C83: fixed_contrib | D83: const | E83: Платит каждый ИП независимо от дохода. Срок — 28 декабря | F83: 57 390 ₽ за 2026 год
A84: 69 | B84: Дополнительный взнос | C84: extra_contrib | D84: const | E84: 1% с дохода сверх порога. Срок — 1 июля следующего года | F84: 1% × (база − 300 000)
A85: 70 | B85: Предельная величина дохода | C85: contrib_threshold | D85: const | E85: Порог, свыше которого начисляется допвзнос. ЗА ГОД, не за месяц | F85: 300 000 ₽/год
A86: 71 | B86: Максимум допвзноса | C86: contrib_cap | D86: const | E86: Потолок дополнительного взноса за год | F86: 321 818 ₽ (достигается ~32,5 млн)
A87: 72 | B87: Вычет взносов из налога | C87: contrib_deduction | D87: calc | E87: На УСН «Доходы» без сотрудников взносы уменьшают налог ДО НУЛЯ. Поэтому платёж = MAX(налог; взносы), а НЕ их сумма | F87: ключевая механика расчёта
A88: 73 | B88: Минимальный налог | C88: min_tax | D88: const | E88: Нижняя граница на режимах «доходы минус расходы» | F88: УСН 1% от выручки, АУСН 3%
A89: 74 | B89: Взнос на травматизм | C89: injury_contrib | D89: const | E89: Только на АУСН и только при наличии сотрудников | F89: 2 959 ₽/год, для соло — 0
... A95: 80 | B95: Общая процентная ставка | C95: effective_rate | D95: calc | E95: Эффективная нагрузка: все платежи к выручке. РАСЧЁТНАЯ, не сумма ставок | F95: 137 613 / 2 293 553 = 6,0%
A96: G. СТАВКИ ЧАСА — лестница от наивной к полной (все на съёмочный час)
A97: № | B97: Наименование | C97: ID | D97: Тип | E97: Описание | F97: Формула / значение
A98: 81 | B98: Наивная ставка | C98: naive_rate | D98: calc | E98: Доход делить на съёмочные часы. Без расходов и налогов. Демонстрация типичной ошибки | F98: 1 307 988 / 261 = 5 004 ₽/ч
A99: 82 | B99: Базовая ставка часа | C99: base_rate | D99: calc | E99: Доход, делённый на чистое время. Справочно «сколько стоит час моего времени вообще» | F99: 1 307 988 / 1 533 = 853 ₽/ч
A100: 83 | B100: Ставка найма | C100: hire_rate | D100: default | E100: Ставка «как в найме» для сравнения. 8 номинальных часов. Только ориентир | F100: 6 000 ₽/ч
A101: 84 | B101: Текущая ставка часа | C101: current_rate | D101: default | E101: По которой работаете сейчас. Для блока «Сколько вы теряете» | F101: вводится пользователем
A102: 85 | B102: Операционная ставка часа | C102: ops_rate | D102: calc | E102: Покрывает доход и все расходы, но БЕЗ налога и эквайринга | F102: (N + C) / 261 = 8 011 ₽/ч
A103: 86 | B103: Полная (реальная) ставка часа | C103: real_rate | D103: calc | E103: Покрывает доход, расходы, налог и эквайринг. ЦЕНА ЧАСА ДЛЯ КЛИЕНТА | F103: НПД 4% — 8 586 ₽, УСН 6% — 8 774 ₽
A104: 87 | B104: Ставка непроданного времени | C104: tax_rate_hour | D104: calc | E104: Синоним real_rate. Для оценки часов, не продаваемых клиенту (обучение, своя бухгалтерия) | F104: =real_rate
A105: 88 | B105: Стоимость проекта | C105: project_price | D105: calc | E105: Цена одного законченного заказа | F105: R / 37,34 = 61 416 ₽
A106: 89 | B106: Точка безубыточности | C106: breakeven | D106: calc | E106: Минимальная выручка при нулевом личном доходе | F106: подставить N = 0
A107: H. МЕТОДОЛОГИЯ РАСЧЁТА
A108: № | B108: Наименование | C108: ID | D108: Тип | E108: Описание | F108: Формула / значение
A109: 90 | B109: Обратный расчёт (gross-up) | C109: gross_up | D109: meta | E109: Идём от желаемого «на руки» к выручке, а не наоборот. Ставки применяются к выручке, поэтому делим, а не умножаем | F109: R = (N + C) / (1 − ставка)
...

Sheet Блоки
A1: СПЕЦИФИКАЦИЯ БЛОКОВ ИНТЕРФЕЙСА
A3: SECTION 1 — О ВАС И ВАШЕЙ РАБОТЕ
A4: ID | B4: Раздел | C4: H2 (Заголовок) | D4: H3 (Подзаголовок) | E4: Тип | F4: Формы_ID | G4: Описание под полем | H4: Исключаемый | I4: По умолч. | J4: Куда идёт в расчёт
A5: Block1 | B5: Section1 | C5: Желаемый доход | D5: Сколько хотите получать на руки ежемесячно | E5: input_number | F5: — | G5: По умолчанию — средняя номинальная зарплата по РФ, Росстат 2026 | H5: Нет | I5: 108 999 | J5: target_income → N
A6: Block2 | B6: Section1 | C6: Текущая стоимость часа | D6: Ваша текущая ставка — для сравнения | E6: input_number | F6: — | G6: Необязательное. Нужно для блока «Сколько вы теряете» | H6: Да | I6: 6 000 | J6: current_rate, в расчёт НЕ идёт
A7: Block3 | B7: Section1 | C7: Продолжительность съёмки | D7: Средняя длительность одной съёмки, часов | E7: input_number | F7: — | G7: Сложите часы съёмок за период и разделите на число съёмок | H7: Нет | I7: 7 ← было 0 | J7: S → проектное время
A8: Block3a | B8: Section1 | C8: Коэффициент обработки | D8: Сколько часов обработки на 1 час съёмки | E8: input_number | F8: — | G8: НОВЫЙ БЛОК. Без него проектное время не считается | H8: Нет | I8: 3 | J8: K → проектное время
A9: Block4 | B9: Section1 | C9: Ваш режим налогообложения | D9: — | E9: dropdown | F9: Form015, Form016 | G9: Если работаете и с юрлицами, и с физлицами — укажите доли выручки | H9: Нет | I9: УСН 6% | J9: ставка налога
A10: Block5 | B10: Section1 | C10: Как мы считаем | D10: Мы опираемся на нормы трудового законодательства РФ | E10: info_block | F10: — | G10: Про отпуск, больничный, эффективные часы. Ссылку на ст. 152 ТК убрать | H10: Нет | I10: — | J10: —
A12: SECTION 2 — ВАШИ ИНВЕСТИЦИИ В СВОЁ ДЕЛО (амортизируются)
A13: ID | B13: Раздел | C13: H2 (Заголовок) | D13: H3 (Подзаголовок) | E13: Тип | F13: Формы_ID | G13: Описание под полем | H13: Исключаемый | I13: По умолч. | J13: Куда идёт в расчёт
A14: Block6 | B14: Section2 | C14: Съёмочное оборудование | D14: Базовый комплект для каждой съёмки | E14: dynamic_table | F14: Form001 | G14: Актуальная рыночная стоимость; для снятых с производства — аналог. Разовую аренду не включать | H14: Да | I14: — | J14: investment → амортизация
A15: Block7 | B15: Section2 | C15: Офисное оборудование | D15: Для работы вне съёмочной площадки | E15: dynamic_table | F15: Form002 | G15: Аналогично Block6 | H15: Да | I15: — | J15: investment → амортизация
A16: Block8 | B16: Section2 | C16: Программное обеспечение | D16: Программы и сервисы | E16: dynamic_tables | F16: Form003, Form004 | G16: Form003 — подписки (переменные). Form004 — разовые покупки (амортизация) | H16: Да | I16: — | J16: Form003 → переменные, Form004 → амортизация
A17: Block9 | B17: Section2 | C17: Рабочее место | D17: Работаете из дома или арендуете? | E17: dropdown + dynamic_table | F17: Form005, Form013 | G17: Form013 — обустройство (амортизация). Form005 — содержание (переменные, по доле площади) | H17: Да | I17: — | J17: Form013 → амортизация, Form005 → переменные
A18: Block10 | B18: Section2 | C18: Проф. обучение | D18: — | E18: input_extended | F18: Form006 | G18: Стоимость курса, месяцев без дохода, срок амортизации. Упущенную выгоду можно отключить | H18: Да | I18: — | J18: investment → амортизация
A19: Block12 | B19: Section2 | C19: Создание сайта | D19: Сами делали (часы) или нанимали (₽)? | E19: radio + input | F19: Form014 | G19: ВНИМАНИЕ: вариант «сам» создаёт цикл. Формула ниже, в блоке «Особые случаи» | H19: Да | I19: нанимал, 70 000 | J19: investment → амортизация
A21: SECTION 3 — РЕГУЛЯРНЫЕ РАСХОДЫ
A22: ID | B22: Раздел | C22: H2 (Заголовок) | D22: H3 (Подзаголовок) | E22: Тип | F22: Формы_ID | G22: Описание под полем | H22: Исключаемый | I22: По умолч. | J22: Куда идёт в расчёт
A23: Block11 | B23: Section3 | C23: Поиск заказов (продвижение и реклама) | D23: — | E23: 2 parts | F23: Form009, Form010 | G23: Form009 — время (часов/день). Form010 — деньги (реклама, домен, хостинг). ПЕРЕНЕСЁН из Section2 | H23: Да | I23: 2 ч/день | J23: Form009 → promo_time, Form010 → переменные
A24: Block14 | B24: Section3 | C24: Учёт и планирование | D24: Сами ведёте или нанимаете бухгалтера? | E24: dropdown | F24: Form011 | G24: Взаимоисключающий выбор: либо часы, либо рубли. Оба сразу не учитываются | H24: Да | I24: бухгалтер 10 000/мес | J24: время ИЛИ переменные
A25: Block15 | B25: Section3 | C25: Банковские расходы | D25: — | E25: 2 parts | F25: Form007, Form008 | G25: Form007 — РКО и СМС (расход). Form008 — эквайринг (% с оборота, в знаменатель) | H25: Да | I25: 2,7% | J25: Form007 → переменные, Form008 → знаменатель
A27: SECTION 4 — ВРЕМЯ НА ПРОЕКТ (новый раздел)
A28: ID | B28: Раздел | C28: H2 (Заголовок) | D28: H3 (Подзаголовок) | E28: Тип | F28: Формы_ID | G28: Описание под полем | H28: Исключаемый | I28: По умолч. | J28: Куда идёт в расчёт
A29: Block13 | B29: Section4 | C29: Работа с клиентом | D29: Время на административную работу по одному проекту | E29: input_number | F29: Form012 | G29: ПЕРЕНЕСЁН из Section3: это время, а не расход | H29: Да | I29: 1 ч/проект | J29: client_time → проектное время
A31: SECTION 5 — РЕЗУЛЬТАТ (отсутствовал в спецификации)
A32: ID | B32: Раздел | C32: H2 (Заголовок) | D32: H3 (Подзаголовок) | E32: Тип | F32: Формы_ID | G32: Описание под полем | H32: Исключаемый | I32: По умолч. | J32: Куда идёт в расчёт
A33: Block16 | B33: Section5 | C33: Ваша ставка часа | D33: Сколько должен стоить час вашей съёмки | E33: report | F33: — | G33: real_rate по выбранному режиму + стоимость проекта | H33: Нет | I33: — | J33: вывод
A34: Block17 | B34: Section5 | C34: Сколько вы теряете | D34: Сравнение с текущей ставкой | E34: report | F34: — | G34: Работает только если заполнен Block2. Наивная vs полная ставка | H34: Да | I34: — | J34: вывод
A35: Block18 | B35: Section5 | C35: Сравнение режимов | D35: Какой режим выгоднее | E35: report | F35: — | G35: Шесть колонок, подсветка минимума. Предупреждения о лимитах НПД / НДС | H35: Нет | I35: — | J35: вывод
A38: СПИСОК ФОРМ (ошибки #ИМЯ? устранены — связи проставлены явно)
A39: Form_ID | B39: Блок_ID | C39: Наименование | D39: Что содержит | E39: Куда попадает
A40: Form001 | B40: Block6 | C40: Съёмочное оборудование | D40: позиция, стоимость, срок | E40: амортизация
A41: Form002 | B41: Block7 | C41: Офисное оборудование | D41: позиция, стоимость, срок | E41: амортизация
A42: Form003 | B42: Block8 | C42: ПО — подписки | D42: позиция, стоимость, период | E42: переменные
A43: Form004 | B43: Block8 | C43: ПО — разовые покупки | D43: позиция, стоимость, срок | E43: амортизация
A44: Form005 | B44: Block9 | C44: Рабочее место — содержание | D44: аренда, коммуналка, площади | E44: переменные (по доле)
A45: Form006 | B45: Block10 | C45: Проф. обучение | D45: курс, месяцев, срок, флаг упущенной выгоды | E45: амортизация
A46: Form007 | B46: Block15 | C46: Банк — регулярные | D46: РКО, СМС | E46: переменные
A47: Form008 | B47: Block15 | C47: Банк — эквайринг | D47: % и доля безнала | E47: знаменатель формулы
A48: Form009 | B48: Block11 | C48: Продвижение — время | D48: часов/день | E48: promo_time
A49: Form010 | B49: Block11 | C49: Продвижение — деньги | D49: реклама, домен, хостинг | E49: переменные
A50: Form011 | B50: Block14 | C50: Учёт и планирование | D50: радио: сам / бухгалтер | E50: время ИЛИ переменные
... A55: Form016 | B55: Block4 | C55: Режим — структура клиентов | D55: доля физлиц и юрлиц | E55: ставка НПД
A57: ОСОБЫЕ СЛУЧАИ И ЗАМЕЧАНИЯ
A58: BLOCK12 «САЙТ СВОИМИ РУКАМИ» — НАСТОЯЩАЯ ЦИКЛИЧЕСКАЯ ЗАВИСИМОСТЬ.
A59: В описании сказано «Часы переводятся в ₽ через Ф-11», то есть через ставку часа. Но ставка зависит от расходов,
A60: а стоимость сайта входит в расходы. Замкнутый круг: C → R → ставка → сайт → C.
A61: Решается аналитически, итерации не нужны:
A63: R = (N + C_без_сайта) / ( (1 − ставка_налога − эквайринг) − H / (срок_лет × съёмочных_часов) )
A65: где H — часы, потраченные на сайт. Проверка при H = 80 ч, срок 7 лет: ставка 8 965 ₽/ч, сайт 717 211 ₽,
A66: амортизация 102 459 ₽/год. Формула расходится при H ≥ 1 707 ч — поставьте валидацию.
A67: Тот же приём применим к любому «сделал сам» блоку.
A68: ПРАКТИЧЕСКИ: оценивать свой сайт в 717 тысяч методологически спорно. Рекомендую оценивать часы
A69: по РЫНОЧНОЙ цене подрядчика, а не по своей ставке — это и честнее, и убирает цикл полностью.
A71: BLOCK10 «ОБУЧЕНИЕ» — цикла НЕТ: упущенная выгода привязана к желаемому доходу (вводу), а не к расчётной ставке.
... A96: ОПЕЧАТКА: «Офисноге оборудование» → «Офисное» (Block7), «умрлчанию» → «умолчанию» (заголовок столбца).

Sheet Формы
A1: ФОРМЫ — источники расходов
A3: Съёмочное оборудование, амортизация
A4: Позиция | B4: Стоимость, ₽ | C4: Срок, лет | D4: Амортизация ₽/год
A5: Canon EOS R6 Mark II | B5: 239999 | C5: 3 | D5: =IF(C5=0,0,B5/C5)
A6: Canon RF 24–105mm F4 L | B6: 159999 | C6: 5 | D6: =IF(C6=0,0,B6/C6)
A7: Godox V1Pro C | B7: 36990 | C7: 5 | D7: =IF(C7=0,0,B7/C7)
A8: Godox XPro II C | B8: 9355 | C8: 5 | D8: =IF(C8=0,0,B8/C8)
A9: Аккумулятор LP-E6NH | B9: 12978 | C9: 3 | D9: =IF(C9=0,0,B9/C9)
A10: SanDisk Extreme PRO 256 ГБ #1 | B10: 6990 | C10: 2 | D10: =IF(C10=0,0,B10/C10)
A11: SanDisk Extreme PRO 256 ГБ #2 | B11: 6990 | C11: 2 | D11: =IF(C11=0,0,B11/C11)
A12: Рюкзак Lowepro ProTactic | B12: 27962 | C12: 7 | D12: =IF(C12=0,0,B12/C12)
A13: Godox RFT-05 отражатель | B13: 3000 | C13: 5 | D13: =IF(C13=0,0,B13/C13)
A14: X-Rite ColorChecker | B14: 5000 | C14: 7 | D14: =IF(C14=0,0,B14/C14)
A15: ИТОГО, амортизация ₽/год | D15: =SUM(D5:D14)
A17: Офисное оборудование, амортизация
A18: Позиция | B18: Стоимость, ₽ | C18: Срок, лет | D18: Амортизация ₽/год
A19: Системный блок | B19: 180000 | C19: 5 | D19: =IF(C19=0,0,B19/C19)
A20: Монитор ASUS ProArt | B20: 55000 | C20: 5 | D20: =IF(C20=0,0,B20/C20)
A21: Calibrite ColorChecker | B21: 30000 | C21: 5 | D21: =IF(C21=0,0,B21/C21)
A22: Колонки Logitech Z207 | B22: 5000 | C22: 5 | D22: =IF(C22=0,0,B22/C22)
A23: Клавиатура Logitech K380 | B23: 3500 | C23: 7 | D23: =IF(C23=0,0,B23/C23)
A24: Мышь Logitech M650 | B24: 4000 | C24: 3 | D24: =IF(C24=0,0,B24/C24)
A25: Веб-камера Logitech Brio | B25: 15999 | C25: 5 | D25: =IF(C25=0,0,B25/C25)
A26: Микрофон FIFINE K669B | B26: 3500 | C26: 5 | D26: =IF(C26=0,0,B26/C26)
A27: Принтер Canon PIXMA G640 | B27: 29999 | C27: 5 | D27: =IF(C27=0,0,B27/C27)
A28: ИТОГО, амортизация ₽/год | D28: =SUM(D19:D27)
A30: ПО разовая покупка + рабочее место + обучение + сайт (амортизация)
A31: Позиция | B31: Стоимость, ₽ | C31: Срок, лет | D31: Амортизация ₽/год
A32: Retouch4me Heal | B32: 6900 | C32: 3 | D32: =IF(C32=0,0,B32/C32)
A33: Retouch4me Dodge & Burn | B33: 6900 | C33: 3 | D33: =IF(C33=0,0,B33/C33)
A34: Retouch4me Fabric | B34: 6900 | C34: 3 | D34: =IF(C34=0,0,B34/C34)
A35: Retouch4me Clean Backdrop | B35: 6900 | C35: 3 | D35: =IF(C35=0,0,B35/C35)
A36: Retouch4me Dust | B36: 6900 | C36: 3 | D36: =IF(C36=0,0,B36/C36)
A37: Мебель | B37: 35000 | C37: 7 | D37: =IF(C37=0,0,B37/C37)
A38: Косметический ремонт | B38: 30000 | C38: 7 | D38: =IF(C38=0,0,B38/C38)
A39: Создание сайта (нанимал специалиста) | B39: 70000 | C39: 7 | D39: =IF(C39=0,0,B39/C39)
A40: Курс по фотографии (стоимость) | B40: 80000 | C40: 7 | D40: =(B40+B42*B41*Расчёт!$C$47)/C40 | E40: упущенная выгода = мес × желаемый доход/мес
A41: └ месяцев обучения (упущенная выгода) | B41: 4
A42: └ учитывать упущенную выгоду (1/0) | B42: 1
A43: ИТОГО, амортизация ₽/год | D43: =SUM(D32:D42)
A44: ВСЕГО АМОРТИЗАЦИЯ, ₽/год | D44: =Формы!$D$15+Формы!$D$28+Формы!$D$43
A46: ПЕРЕМЕННЫЕ РАСХОДЫ, ₽/год
A47: Позиция | B47: Стоимость, ₽ | C47: Период (12=мес, 1=год) | D47: ₽/год
A48: Adobe CC Photography | B48: 2000 | C48: 12 | D48: =B48*C48 | E48: период исправлен на месячный
A49: Яндекс Диск 1 ТБ | B49: 250 | C49: 12 | D49: =B49*C49
A50: Обслуживание счёта (РКО) | B50: 0 | C50: 12 | D50: =B50*C50
A51: СМС-уведомления | B51: 150 | C51: 12 | D51: =B51*C51
A52: Домен сайта | B52: 1500 | C52: 1 | D52: =B52*C52
A53: Хостинг сайта | B53: 6000 | C53: 1 | D53: =B53*C53
A54: Яндекс Директ | B54: 15000 | C54: 12 | D54: =B54*C54
A55: Авито | B55: 0 | C55: 12 | D55: =B55*C55
A56: Таргетированная реклама | B56: 0 | C56: 12 | D56: =B56*C56
A57: Платные размещения у блогеров | B57: 0 | C57: 12 | D57: =B57*C57
A58: Отклики на Profi.ru | B58: 0 | C58: 12 | D58: =B58*C58
A59: Бухгалтер | B59: 10000 | C59: 12 | D59: =B59*C59 | E59: << был потерян в прошлой версии
A60: Рабочее место — доля под кабинет
A61: Аренда / ипотека, ₽/мес | B61: 40000
A62: Коммунальные и связь, ₽/мес | B62: 7000
A63: Общая площадь жилья, м² | B63: 50
A64: Площадь под кабинет, м² | B64: 6
A65: Доля кабинета | B65: =IF(B63=0,0,B64/B63)
A66: Рабочее место, ₽/год | D66: =(B61+B62)*IF(B63=0,0,B64/B63)*12 | E66: коммуналка тоже по доле, а не целиком
A67: ВСЕГО ПЕРЕМЕННЫЕ, ₽/год | D67: =SUM(D48:D59)+Формы!$D$66
A69: Комиссии с оборота
A70: Эквайринг, % | B70: 0.027 | C70: считается ОТ ВЫРУЧКИ, не фикс. сумма
A71: Доля оплат через эквайринг, % | B71: 1
A73: Временные затраты (переносятся в лист Расчёт)
A74: Ведение соцсетей, час/день | B74: 2
A75: Учёт и планирование, час/квартал | B75: 3
A76: Работа с клиентом, час/проект | B76: 1

Sheet Данные из форм
A1: ДАННЫЕ ИЗ ФОРМ — сводка (всё тянется ссылками, вручную не вводить)
A3: 1. ИНВЕСТИЦИИ (амортизация), ₽/год
A4: Источник | B4: ₽/год
A5: Съёмочное оборудование | B5: =Формы!D15
A6: Офисное оборудование | B6: =Формы!D28
A7: ПО, рабочее место, обучение, сайт | B7: =Формы!D43
A8: ИТОГО инвестиции, ₽/год | B8: =SUM(B5:B7)
A10: 2. ПЕРЕМЕННЫЕ РАСХОДЫ, ₽/год
A11: Источник | B11: ₽/год | C11: Примечание
A12: Все регулярные платежи (ПО, банк, реклама, бухгалтер) | B12: =Формы!D67-Формы!D66 | C12: включая бухгалтера 120 000
A13: Рабочее место (доля кабинета) | B13: =Формы!D66
A14: ИТОГО переменные, ₽/год | B14: =SUM(B12:B13)
A15: ВСЕГО РАСХОДОВ (C), ₽/год | B15: ='Данные из форм'!$B$8+'Данные из форм'!$B$14
A17: 3. ВРЕМЕННЫЕ ЗАТРАТЫ, часов/год
A18: Источник | B18: Часов/год | C18: Примечание
A19: Продвижение (соцсети и пр.) | B19: =Формы!B74*Расчёт!$C$13 | C19: час/день × чистых рабочих дней
A20: Учёт и планирование | B20: =Формы!B75*Расчёт!$C$7 | C20: был потерян в исходной сводке
A21: ИТОГО операционное время, час/год | B21: =SUM(B19:B20)
A22: Работа с клиентом, час/проект | B22: =Формы!B76 | C22: НЕ суммируется сюда — входит в проектное время
A24: 4. СТАВКИ ОТ ОБОРОТА, %
A25: Источник | B25: Ставка | C25: Идёт в знаменатель?
A26: Эквайринг (комиссия с оборота) | B26: =Формы!B70*Формы!B71 | C26: ДА — общая для всех режимов
A27: Ставка налогового режима | B27: — | C27: НЕ сводится сюда — своя в каждой колонке
A29: 5. ПОЧЕМУ «ОБЩАЯ ПРОЦЕНТНАЯ СТАВКА 7,70» БЫЛА НЕВЕРНОЙ
A30: В исходной сводке столбец «% ставка (от оборота)» содержал 2,70 и 5,00, а итог 7,70 = их сумма.
A31: 2,70 — эквайринг. 5,00 — «Самозанятый (НПД), средняя ставка». Отсюда и бралась «Общая процентная ставка».
A33: Три проблемы:
A35: а) Ставки 5% в НПД не существует. Есть 4% (с физлицами) и 6% (с юрлицами). «Средняя» — выдуманная величина:
A36: при реальной структуре клиентов нужно считать взвешенно, а лучше — двумя отдельными колонками.
A38: б) Смешаны разные сущности. Эквайринг — комиссия банка, она есть на ЛЮБОМ режиме. Налог — своя ставка
A39: в каждой колонке. Их нельзя схлопывать в одно число: получается «ставка», которая не соответствует
A40: ни одному реальному режиму.
A42: в) Для ИП сложение вообще не работает. Складывать проценты допустимо, только когда ОБЕ величины —
A43: чистый процент от оборота. Это верно для НПД (нет взносов). Но на УСН есть фикс. взнос 57 390 ₽,
A44: который ВЫЧИТАЕТСЯ из налога, и допвзнос 1% с базы сверх 300 000 — это не процент от оборота.
... A57: (меньший доход, где фикс. взнос доминирует) ошибка вырастает в разы.

Sheet Расчёт
A1: КАЛЬКУЛЯТОР СТОИМОСТИ ЧАСА — соло-специалист, 2026
A3: 1. КАЛЕНДАРЬ
A4: const | B4: Рабочих дней в году (произв. календарь РФ 2026) | C4: 247
A5: const | B5: Рабочих дней в неделю | C5: 5
A6: const | B6: Месяцев в году | C6: 12
A7: const | B7: Кварталов в году | C7: 4
A8: const | B8: Отпуск, рабочих дней | C8: 20
A9: const | B9: Больничный, рабочих дней | C9: 8
A10: const | B10: Чистых (эффективных) часов в день | C10: 7
A12: 2. ЧИСТОЕ РАБОЧЕЕ ВРЕМЯ
A13: calc | B13: Чистое рабочее время, дней/год | C13: =$C$4-$C$8-$C$9
A14: calc | B14: Чистое рабочее время, часов/год | C14: =$C$13*$C$10
A15: calc | B15: Чистое рабочее время, недель/год | C15: =$C$13/$C$5
A16: calc | B16: Чистое рабочее время, часов/месяц | C16: =$C$14/$C$6
A17: calc | B17: Чистое рабочее время, часов/неделю | C17: =$C$14/$C$15
A19: 3. СТРУКТУРА ВРЕМЕНИ
A20: calc | B20: Время на продвижение, час/год | C20: ='Данные из форм'!$B$21-Расчёт!$C$22
A21: calc | B21: Время на продвижение, час/мес | C21: =$C$20/$C$6
A22: calc | B22: Учёт и планирование, час/год | C22: =Формы!$B$75*$C$7
A23: calc | B23: Операционное время, час/год (из сводки) | C23: ='Данные из форм'!$B$21 | E23: продвижение + учёт
A24: calc | B24: Операционное время, час/мес | C24: =$C$23/$C$6
A25: calc | B25: Операционное время, час/неделю | C25: =$C$23/$C$15
A26: calc | B26: Профильное время, час/год | C26: =$C$14-$C$23
A27: calc | B27: Профильное время, час/мес | C27: =$C$26/$C$6
A28: calc | B28: Профильное время, час/неделю | C28: =$C$26/$C$15
A30: 4. ПРОЕКТ
A31: default | B31: Съёмочных часов на 1 проект | C31: 7
A32: default | B32: Коэффициент обработки (ч обработки на 1 ч съёмки) | C32: 3
A33: calc | B33: Проектное время, час/проект | C33: =$C$31*(1+$C$32)+'Данные из форм'!$B$22
A34: calc | B34: Проектов в год | C34: =IF($C$33=0,0,$C$26/$C$33)
A35: calc | B35: Проектов в месяц | C35: =$C$34/$C$6
A36: calc | B36: Проектов в неделю | C36: =$C$34/$C$15
A37: calc | B37: Съёмочное время, час/год | C37: =$C$34*$C$31
A38: calc | B38: Съёмочное время, час/мес | C38: =$C$37/$C$6
A39: calc | B39: Съёмочное время, час/неделю | C39: =$C$37/$C$15
A40: calc | B40: Операционное время на час съёмки | C40: =IF($C$37=0,0,$C$23/$C$37)
A42: 5. ДОХОД И РАСХОДЫ (из листа «Формы»)
A43: calc | B43: Амортизация, ₽/год (из сводки) | C43: ='Данные из форм'!$B$8
A44: calc | B44: Переменные расходы, ₽/год (из сводки) | C44: ='Данные из форм'!$B$14
A45: calc | B45: Всего расходов (без эквайринга), ₽/год | C45: =$C$43+$C$44
A46: calc | B46: Эквайринг, эффективная ставка от выручки (из сводки) | C46: ='Данные из форм'!$B$26
A47: default | B47: Желаемый доход на руки, ₽/мес | C47: 108999
A48: calc | B48: Желаемый доход на руки, ₽/год | C48: =$C$47*$C$6
A49: calc | B49: Базовая ставка часа (только время специалиста) | C49: =$C$48/$C$14 | E49: справочно
A51: 6. КОНСТАНТЫ НАЛОГОВ 2026
A52: default | B52: Страховые взносы ИП за себя (фикс.), ₽/год | C52: 57390
A53: default | B53: Дополнительный взнос, % | C53: 0.01
A54: default | B54: Предельная величина дохода, ₽/год | C54: 300000
A55: default | B55: Максимум допвзноса, ₽/год | C55: 321818
A56: default | B56: Минимальный налог УСН Д−Р, % | C56: 0.01
A57: default | B57: Минимальный налог АУСН Д−Р, % | C57: 0.03
A58: default | B58: Взнос на травматизм АУСН, ₽/год | C58: 0
A59: default | B59: НПД, физлица, % | C59: 0.04
A60: default | B60: НПД, юрлица, % | C60: 0.06
A61: default | B61: УСН доходы, % | C61: 0.06
A62: default | B62: УСН доходы минус расходы, % | C62: 0.15
A63: default | B63: АУСН доходы, % | C63: 0.08
A64: default | B64: АУСН доходы минус расходы, % | C64: 0.2
A66: 7. РАСЧЁТ ПО РЕЖИМАМ
B67: Показатель | C67: НПД 4% физлица | D67: НПД 6% юрлица | E67: УСН Доходы 6% | F67: УСН Д−Р 15% | G67: АУСН Доходы 8% | H67: АУСН Д−Р 20%
B68: Планируемый доход до вычета общей проц. ставки, ₽/год | C68: =$C$48+$C$45 | D68: =$C$48+$C$45 | E68: =$C$48+$C$45 | F68: =$C$48+$C$45 | G68: =$C$48+$C$45 | H68: =$C$48+$C$45
B69: Планируемый доход, ₽/год ← ВЫРУЧКА | C69: =($C$48+$C$45)/(1-$C$59-$C$46) | D69: =($C$48+$C$45)/(1-$C$60-$C$46) | E69: =MAX(($C$48+$C$45+$C$52-($C$54*$C$53))/(1-$C$53-$C$46),($C$48+$C$45)/(1-$C$61-$C$46)) | F69: =(($C$48/(1-$C$62))+($C$52-($C$54*$C$53)+$C$53*($C$48/(1-$C$62)))+$C$45)/(1-$C$46) | G69: =($C$48+$C$45+$C$58)/(1-$C$63-$C$46) | H69: =(($C$48/(1-$C$64))+$C$45+$C$58)/(1-$C$46)
B70: Планируемый доход, ₽/месяц | C70: =C69/$C$6 | D70: =D69/$C$6 | E70: =E69/$C$6 | F70: =F69/$C$6 | G70: =G69/$C$6 | H70: =H69/$C$6
B71: Планируемая стоимость одного проекта, ₽ | C71: =IF($C$34=0,0,C69/$C$34) | D71: =IF($C$34=0,0,D69/$C$34) | E71: =IF($C$34=0,0,E69/$C$34) | F71: =IF($C$34=0,0,F69/$C$34) | G71: =IF($C$34=0,0,G69/$C$34) | H71: =IF($C$34=0,0,H69/$C$34)
B72: Планируемая стоимость съёмочного часа, ₽ | C72: =IF($C$37=0,0,C69/$C$37) | D72: =IF($C$37=0,0,D69/$C$37) | E72: =IF($C$37=0,0,E69/$C$37) | F72: =IF($C$37=0,0,F69/$C$37) | G72: =IF($C$37=0,0,G69/$C$37) | H72: =IF($C$37=0,0,H69/$C$37)
B74: Эквайринг, ₽/год | C74: =C69*$C$46 | D74: =D69*$C$46 | E74: =E69*$C$46 | F74: =F69*$C$46 | G74: =G69*$C$46 | H74: =H69*$C$46
B75: База для доначисления взносов, ₽/год | C75: =0 | D75: =0 | E75: =MAX(0,E69-$C$54) | F75: =MAX(0,($C$48/(1-$C$62))-$C$54) | G75: =0 | H75: =0
B76: Сумма для уплаты страховых взносов, ₽/год | C76: =0 | D76: =0 | E76: =$C$52 | F76: =$C$52 | G76: =0 | H76: =0
B77: Доначисление страховых взносов ИП, ₽/год | C77: =0 | D77: =0 | E77: =MIN(E75*$C$53,$C$55) | F77: =MIN(F75*$C$53,$C$55) | G77: =0 | H77: =0
B78: Сумма для уплаты налога, ₽/год | C78: =C69*$C$59 | D78: =D69*$C$60 | E78: =MAX(0,E69*$C$61-(E76+E77)) | F78: =MAX(($C$48/(1-$C$62))*$C$62,F69*$C$56) | G78: =G69*$C$63 | H78: =MAX(($C$48/(1-$C$64))*$C$64,H69*$C$57)
B79: Взнос на травматизм (АУСН), ₽/год | C79: =0 | D79: =0 | E79: =0 | F79: =0 | G79: =$C$58 | H79: =$C$58
B81: Всего налогов и взносов, ₽/год | C81: =C76+C77+C78+C79 | D81: =D76+D77+D78+D79 | E81: =E76+E77+E78+E79 | F81: =F76+F77+F78+F79 | G81: =G76+G77+G78+G79 | H81: =H76+H77+H78+H79
B82: Всего налогов и взносов, ₽/месяц | C82: =C81/$C$6 | D82: =D81/$C$6 | E82: =E81/$C$6 | F82: =F81/$C$6 | G82: =G81/$C$6 | H82: =H81/$C$6
B83: Всего налогов и взносов, ₽/проект | C83: =IF($C$34=0,0,C81/$C$34) | D83: =IF($C$34=0,0,D81/$C$34) | E83: =IF($C$34=0,0,E81/$C$34) | F83: =IF($C$34=0,0,F81/$C$34) | G83: =IF($C$34=0,0,G81/$C$34) | H83: =IF($C$34=0,0,H81/$C$34)
B84: Всего налогов и взносов, ₽/час (съёмочный) | C84: =IF($C$37=0,0,C81/$C$37) | D84: =IF($C$37=0,0,D81/$C$37) | E84: =IF($C$37=0,0,E81/$C$37) | F84: =IF($C$37=0,0,F81/$C$37) | G84: =IF($C$37=0,0,G81/$C$37) | H84: =IF($C$37=0,0,H81/$C$37)
B85: Общая процентная ставка (эфф. нагрузка), % | C85: =IF(C69=0,0,C81/C69) | D85: =IF(D69=0,0,D81/D69) | E85: =IF(E69=0,0,E81/E69) | F85: =IF(F69=0,0,F81/F69) | G85: =IF(G69=0,0,G81/G69) | H85: =IF(H69=0,0,H81/H69)
B87: Точка безубыточности, ₽/год | C87: =$C$45/(1-$C$59-$C$46) | D87: =$C$45/(1-$C$60-$C$46) | E87: =MAX(($C$45+$C$52-($C$54*$C$53))/(1-$C$53-$C$46),$C$45/(1-$C$61-$C$46)) | F87: =($C$45+$C$52)/(1-$C$46) | G87: =($C$45+$C$58)/(1-$C$63-$C$46) | H87: =($C$45+$C$58)/(1-$C$46)
B88: Точка безубыточности, ₽/час (съёмочный) | C88: =IF($C$37=0,0,C87/$C$37) | D88: =IF($C$37=0,0,D87/$C$37) | E88: =IF($C$37=0,0,E87/$C$37) | F88: =IF($C$37=0,0,F87/$C$37) | G88: =IF($C$37=0,0,G87/$C$37) | H88: =IF($C$37=0,0,H87/$C$37)
B90: ПРОВЕРКА: остаётся на руки (должно = C48) | C90: =C69-$C$45-C74-C81 | D90: =D69-$C$45-D74-D81 | E90: =E69-$C$45-E74-E81 | F90: =F69-$C$45-F74-F81 | G90: =G69-$C$45-G74-G81 | H90: =H69-$C$45-H74-H81
B91: Контроль лимитов | C91: =IF(C69>2400000,"! лимит НПД","ок") | D91: =IF(D69>2400000,"! лимит НПД","ок") | E91: =IF(E69>20000000,"! НДС","ок") | F91: =IF(F69>20000000,"! НДС","ок") | G91: =IF(G69>60000000,"! лимит АУСН","ок") | H91: =IF(H69>60000000,"! лимит АУСН","ок")
A93: 8. ЧТО ИСПРАВЛЕНО В ЛИСТЕ «ФОРМЫ»
B94: 1. БУХГАЛТЕР 120 000 ₽/год не попал в «Переменные расходы». 27 000 + 1 800 + 187 500 + 141 600 = 357 900 —
B95: ровно ваша цифра, бухгалтера в ней нет. Это занижало себестоимость на 120 000 ₽, т.е. ~460 ₽ на съёмочный час.
B97: 2. ЭКВАЙРИНГ 2,7% нигде не учитывался. Это процент ОТ ВЫРУЧКИ, и он попадает в знаменатель формулы,
B98: а не в расходы фиксированной суммой: R = (N + C) / (1 − ставка налога − эквайринг).
B99: Добавлено поле «доля оплат через эквайринг» — если часть клиентов платит переводом, поставьте < 100%.
B101: 3. Adobe CC: 2 000 ₽ помечено периодом «Год», но посчитано как 24 000 (то есть по 2 000 в месяц).
B102: Период приведён к месячному. Проверьте, что верно: 2 000/мес или 2 000/год.
B104: 4. Рабочее место: аренда бралась по доле кабинета (40 000 × 6/50 = 4 800), а коммуналка 7 000 — ЦЕЛИКОМ.
B105: Непоследовательно: либо всё по доле, либо всё целиком. Сделано по доле: (40 000 + 7 000) × 12% = 5 640 ₽/мес.
B106: Если считаете, что интернет и связь нужны бизнесу полностью — вынесите их отдельной строкой в переменные.
B108: 5. «Упущенная выгода» 435 996 ₽ = 108 999 × 4 мес теперь пересчитывается автоматически от желаемого дохода,
B109: а не зашита числом. Есть флаг 1/0 — её можно выключить.
... B118: на проект и входит в «Проектное время», а годовая сумма выводится как производная.
